Workbook

Sheet Objectifs Maths 2023-2024
B2: Objectifs d'apprentissage du tronc commun de la formation en mathématiques au sein de l'Ecole d'Ingénieurs CESI
B3: A - Fondamentaux en mathématiques (notions de prérequis) | C3: 1 | D3: Cycle préparatoire (CPI)
B4: A.1 Connaître les grandes notions d'algèbre, d'analyse, de géomètrie, de probabilité statiques
B5: A.2 Mobiliser les 6 compétences élémentaires dans des exercices d'application (Modéliser, Calculer, Représenter, Chercher, Communiquer, Raisonner)
B6: B - Calcul numérique et analytique
B7: B.1 Faire preuve d'autonomie, d'initiative dans la démarche de résolution d'un problème
B8: B.2 Savoir employer une démarche de résolution analytico-numérique (du modèle physique ou des hypothèses jusqu'à l'implémentation)
B9: B.3 Savoir lire, comprendre, concevoir des algorithmes (sans langage spécifique, en privilégiant le pseudo-code)
B10: B.4 Savoir analyser et interpréter un résultat, avoir un point de vue critique et l'exprimer
B11: C - Sciences des données | C11: 2 | D11: Cycle ingénieur (CI)
B12: C.1 Savoir gérer des jeux de données (choix des modèles discrets, continus ; des conditions)
B13: C.2 Savoir traiter les jeux de données, y compris de grand volume (décrire, visualiser, explorer, analyser, modéliser)
B14: C.3 Connaître les tests permettant une analyse décisionnelle
B15: D - Sciences de la modélisation
B16: D.1 Savoir identifier les outils utiles pour la résolution du problème
B17: D.2 Connaître, comprendre et savoir faire usage des outils de la modélisation numérique (MEF, VF, DF)
B18: D.3 Être capable d'analyse de critique des modèles, des résultats

Sheet Items sous domaines Maths 
A1: Objectifs d'apprentissage des Mathématiques | L1: Remédiation
A2: Propositions d'Items pour les Objectifs d'apprentissage | H2: nv | I2: nv rétention A4 | J2: nv rétention A2 | K2: A3 | L2: lien Unisciel ou livre scolaire
B7: Algèbre | D7: Arithmétique
B8: Algèbre | C8: Arithmétique | D8: Divisibilité | E8: Critères de divisibilité | H8: 1 | I8: 7 | K8: 5 | L8: https://uel.unisciel.fr/mathematiques/arithmetique/arithmetique/co/arithmetique.html | M8: lien1
B9: Algèbre | C9: Arithmétique | E9: Division euclidienne | F9: Algorithme d'Euclide. | H9: 1 | I9: 7 | K9: 5
B10: Algèbre | C10: Arithmétique | E10: Congruences | H10: 1 | I10: 7 | K10: 5 | L10: 22
B11: Algèbre | C11: Arithmétique | D11: Factorisation | E11: Nombres premiers, Crible d'Eratosthène | H11: 1 | I11: 7 | K11: 5
B12: Algèbre | C12: Arithmétique | E12: Lemme d'Euclide | H12: 1 | I12: 7 | K12: 5
B13: Algèbre | C13: Arithmétique | E13: Petit théorème de Fermat | H13: 1 | I13: 7 | K13: 5
B14: Algèbre | C14: Arithmétique | E14: Décomposition en facteurs premiers / Théorème fondamental de l'arithmétique | H14: 1 | I14: 7 | K14: 5
B15: Algèbre | C15: Arithmétique | D15: PGCD | E15: PGCD de 2 entiers, lien avec la décomposition en facteurs premiers | H15: 1 | I15: 7 | K15: 5
B16: Algèbre | C16: Arithmétique | E16: Théorème de Bezout | H16: 1 | I16: 7 | K16: 5
B17: Algèbre | C17: Arithmétique | E17: Nombres premiers entre eux, caractérisation via Bezout, Lemme de Gauss | H17: 1 | I17: 7 | K17: 5
B18: Algèbre | C18: Arithmétique | E18: PPCM | H18: 1 | I18: 7 | K18: 5
B19: Algèbre | C19: Arithmétique | D19: Équations dophantiennes | H19: 1 | I19: 7 | K19: 5
B20: Algèbre | C20: Arithmétique | D20: Chiffrage | E20: Chiffrement simple | F20: rot, César, Vigenère... | H20: 1 | I20: 7 | K20: 5
B21: Algèbre | C21: Arithmétique | E21: Chiffrement symétrique | F21: Verman | H21: 1 | I21: 7 | K21: 5
B22: Algèbre | C22: Arithmétique | E22: Division euclidienne de polynômes | F22: Lien avec les CRC | H22: 1 | I22: 7 | K22: 5
B23: Algèbre | C23: Arithmétique | E23: Chiffrement asymétrique | F23: RSA, PGP (hybride) | H23: 1 | I23: 7 | K23: 5
B24: Algèbre | C24: Arithmétique
B25: Algèbre | D25: Logique
B26: Algèbre | C26: Logique | D26: Logique et raisonnements | E26: Rudiments de logique | F26: Opérations : négation, conjonction, disjonction, implication, équivalence. | H26: 1 | K26: 5 | L26: https://uel.unisciel.fr/mathematiques/logique1/logique1/co/logique1.html
B27: Algèbre | C27: Logique | F27: Tables de vérité | H27: 1 | K27: 5
B28: Algèbre | C28: Logique | F28: Quantificateurs . | H28: 1 | K28: 5
B29: Algèbre | C29: Logique | F29: Négations | H29: 1 | K29: 5 | M29: lien Moodle
B30: Algèbre | C30: Logique | E30: Propriétés de N | F30: Définitions générales . | H30: 1 | K30: 5
B31: Algèbre | C31: Logique | F31: Parties de N . | H31: 1 | K31: 5
B32: Algèbre | C32: Logique | E32: Autres types de raisonnements | F32: Raisonnement par récurrence | H32: 1 | K32: 5
B33: Algèbre | C33: Logique | F33: Raisonnement par contraposition | H33: 1 | K33: 5
B34: Algèbre | C34: Logique | F34: Raisonnement par l’absurde | H34: 1 | K34: 5
B35: Algèbre | C35: Logique | D35: Logique booléenne | E35: Fonctions Booléennes | F35: Fonction NOT, NOR, AND, OR | H35: 1 | I35: 7 | K35: 5
B36: Algèbre | C36: Logique | F36: Tables de verité | H36: 1 | I36: 7 | K36: 5
B37: Algèbre | C37: Logique | E37: Représentations graphiques des fonctions booléennes | F37: Connaissance des symboles de représentation | H37: 1 | I37: 7 | K37: 5
B38: Algèbre | C38: Logique | F38: Utilisation dans la description des circuits logiques. | H38: 1 | I38: 7 | K38: 5
B39: Algèbre | D39: Les nombres complexes
B40: Algèbre | C40: Les nombres complexes | D40: Définition et écriture algébrique des nombres complexes | E40: Définition | F40: Connaître l'écriture algébrique, la partie réelle et imaginaire d'un nombre complexe | H40: 2 | I40: 7 | J40: 3 | K40: 5 | L40: https://uel.unisciel.fr/physique/outils_nancy/outils_nancy_ch04/co/apprendre_ch04.html | M40: lien1
B41: Algèbre | C41: Les nombres complexes | F41: Savoir faire des opérations sur les nombres complexes. | H41: 2 | I41: 7 | J41: 3 | K41: 5
B42: Algèbre | C42: Les nombres complexes | F42: Connaître et savoir calculer le conjugué d'un nombre complexe. Connaître les propriétés du conjugué et son utilité dans l'écriture des fractions complexes sous forme algébrique. | H42: 2 | I42: 7 | J42: 3 | K42: 5
B43: Algèbre | C43: Les nombres complexes | F43: Savoir associer un point du plan à un nombre complexe, affixe d’un point du plan, affixe d’un vecteur du plan (dentifier C au plan usuel muni d’un repère orthonormé direct) | H43: 2 | I43: 7 | J43: 3 | K43: 5
B44: Algèbre | C44: Les nombres complexes | E44: Module d’un nombre complexe | F44: Savoir calculer un module d'un nombre complexe. | H44: 2 | I44: 7 | J44: 3 | K44: 5
B45: Algèbre | C45: Les nombres complexes | F45: Connaître l'interprétation géométrique d'un module et repérer les images des affixes de même module. | H45: 2 | I45: 7 | J45: 3 | K45: 5
B46: Algèbre | C46: Les nombres complexes | F46: Savoir calculer le module d’un produit, d’un quotient. | H46: 2 | I46: 7 | J46: 3 | K46: 5
B47: Algèbre | C47: Les nombres complexes | F47: Savoir résoudre des équations du type |z-zA|=|z-zB| et |z-zA|=R > 0 | H47: 2 | I47: 7 | J47: 3 | K47: 5
B48: Algèbre | C48: Les nombres complexes | D48: Forme trigonométrique et exponentielle d'un nombre complexe | E48: Argument d'un nombre complexe et forme trigonometrique | F48: Connaître le cercle trigonométrique. Savoir repérer un point du cercle avec les fonctions circulaires sinus et cosinus. Connaître les formules des angles associés, cos(a±b), sin(a±b), cos(2a), sin(2a), | H48: 2 | I48: 7 | J48: 3 | K48: 5
B49: Algèbre | C49: Les nombres complexes | F49: Savoir calculer l'argument d'un nombre complexe à partir de sa forme algébrique et connaître l'interprétation géométrique de l'argument. | H49: 2 | I49: 7 | J49: 3 | K49: 5
B50: Algèbre | C50: Les nombres complexes | F50: Savoir calculer l'argument d’un produit, d’un quotient. | H50: 2 | I50: 7 | J50: 3 | K50: 5
B51: Algèbre | C51: Les nombres complexes | F51: Savoir passer de la forme algébrique à la forme trigonométrique d'un nombre complexe. | H51: 2 | I51: 7 | J51: 3 | K51: 5
B52: Algèbre | C52: Les nombres complexes | E52: Complexes de module 1 et forme exponentielle d'un nombre complexe | F52: Définition de exp(it) pour t réel. | H52: 2 | I52: 7 | J52: 3 | K52: 5
B53: Algèbre | C53: Les nombres complexes | F53: Savoir réaliser des opérations avec les nombres complexes. | H53: 2 | I53: 7 | J53: 3 | K53: 5
B54: Algèbre | C54: Les nombres complexes | F54: Connaître l'écriture exponentielle d'un nombre complexe sous la forme r.exp(it). | H54: 2 | I54: 7 | J54: 3 | K54: 5
B55: Algèbre | C55: Les nombres complexes | F55: Connaître les formules de Moivre et d'Euler. Savoir factoriser 1±exp(it) | G55: savoir effectuer une linearisation, polynomes de Tchebychev, somme de cosinus et sunis | H55: 2 | I55: 7 | J55: 3 | K55: 5
B56: Algèbre | C56: Les nombres complexes | D56: Solutions complexes d'équations polynomiales | E56: Equations du second degré | F56: Connaître la méthode permettant de calculer les racines carrées d’un nombre complexe. | H56: 2 | I56: 7 | J56: 3 | K56: 5
B57: Algèbre | C57: Les nombres complexes | F57: Savoir résudre les équations du second degré à coefficients complexes (discriminant complexe) | H57: 2 | I57: 7 | J57: 3 | K57: 6
B58: Algèbre | C58: Les nombres complexes | E58: Racines n-ièmes | F58: Connaître la description des racines n-ièmes de l’unité et la représentation géometrique des solutions. | H58: 2 | I58: 7 | J58: 3 | K58: 6
B59: Algèbre | C59: Les nombres complexes | F59: Savoir résoudre les équations du type quation z ^n = a avec a complexe. | H59: 2 | I59: 7 | J59: 3 | K59: 6
B60: Algèbre | C60: Les nombres complexes | D60: Nombre complexes et géometrie plane | E60: Traduction de l'aligenment et de l'orthogonlité. Transformations z→ ̅z et interpretation géometrique. | F60: Savoir traduite l'alignement et l'orthogonalité à l'aide de l'argument | H60: 2 | I60: 7 | J60: 3 | K60: 6
B61: Algèbre | C61: Les nombres complexes | E61: Transformations classiques du plan : translation, rotation homothetie, similitude. | F61: Savoir résoudre les équations du type quation z ^n = a avec a complexe. | H61: 2 | I61: 7 | J61: 3 | K61: 6
B62: Algèbre | D62: Les polynômes
B63: Algèbre | C63: Les polynômes | D63: Présentation de l'ensemble IK[X] | E63: Degré | F63: Savoir repérer le coefficient dominant, terme de plus haurt degré, polynôme nul, polynôme unitaire. | H63: 1 | I63: 7 | J63: 3 | K63: 5 | L63: Développements limités (unisciel.fr)
B64: Algèbre | C64: Les polynômes | F64: Savoir trouver le degré d'une somme, d'un produit, d'une composée. | H64: 1 | I64: 7 | J64: 3 | K64: 5
B65: Algèbre | C65: Les polynômes | E65: Opérations | F65: Savoir effectuer la somme, produit, composée de deux polynômes. | H65: 1 | I65: 7 | J65: 3 | K65: 5
B66: Algèbre | C66: Les polynômes | E66: Divisibilité et division euclidienne dans IK[X] | F66: Savoir effectuer une division posée suivant les puissances décroissantes, polynômes premiers entre eux. | H66: 1 | I66: 7 | J66: 3 | K66: 5
B67: Algèbre | C67: Les polynômes | D67: Dérivation des polynomes | E67: Polynôme dérivé et degré | F67: Connaître l'écriture du polynôme dérivé d'ordre 1 et d'ordres supérieurs. Connaître la formule de la dérivée du monôme de degré n pour tout n. | H67: 1 | I67: 7 | J67: 3 | K67: 5
B68: Algèbre | C68: Les polynômes | F68: Connaître la formule de Leibniz : savoir l'appliquer à la dérivation d'un produit de polynômes. | H68: 1 | I68: 7 | J68: 3 | K68: 5
B69: Algèbre | C69: Les polynômes | E69: Formules de Taylor | F69: Savoir établir la formules de Taylor d'un polynôme, à un ordre n, en 0 et en a réel donné. | H69: 1 | I69: 7 | J69: 3 | K69: 5
B70: Algèbre | C70: Les polynômes | D70: Décomposition en facteurs irreductibles | E70: Racines (ou zéros) d’un polynôme. | F70: Connaître les techniques de détermination des racines d'un polynôme et les factorisations qui en découlent (polynômes d'ordre 2, 3 et plus). | H70: 1 | I70: 7 | J70: 3 | K70: 5
B71: Algèbre | C71: Les polynômes | E71: Multiplicité d’une racine. | F71: Savoir caractériser l'ordre de multiplicité d'une racine par l'annulation des dérivées successives. | H71: 1 | I71: 7 | J71: 3 | K71: 5
B72: Algèbre | C72: Les polynômes | F72: Savoir que le nombre de racines d’un polynôme P non nul est majoré par le degré de P. | H72: 1 | I72: 7 | J72: 3 | K72: 5
B73: Algèbre | C73: Les polynômes | E73: Décomposition dans C[X] et R[X] | F73: Polynôme scindé sur K. Théorie de la décomposition dans l'ensemble des complexes. | H73: 7 | I73: 7 | J73: 3
B74: Algèbre | C74: Les polynômes | F74: Savoir décomposer un polynôme en facteurs irreductibles. Savoir passer de la décomposition dans C à celle dans R. | H74: 7 | I74: 7 | J74: 3
B75: Algèbre | C75: Les polynômes | F75: Somme et produit des racines. Cas des polynômes de degré deux. | H75: 7 | I75: 7
B76: Algèbre | D76: Les Fractions rationnelles
B77: Algèbre | C77: Les Fractions rationnelles | D77: Présentation de l'ensemble des fractions rationnelles | E77: Opération dans l'ensemble des fractions rationnelles | F77: Savoir calculer la somme, le produit de fractions rationnelles. | H77: 7
B78: Algèbre | C78: Les Fractions rationnelles | E78: Dérivation dans l'ensemble des fractions rationnelles | F78: Connaître la formule de dérivation. | H78: 7
B79: Algèbre | C79: Les Fractions rationnelles | E79: Zéros et Pôles d'une fraction rationnelle | F79: Connaître la différence entre zeros et pôles d'une fraction rationnelle et définir leur ordre de multiplicité. | H79: 7
B80: Algèbre | C80: Les Fractions rationnelles | F80: Savoir mettre une fraction rationnelle sous forme irréductibles. | H80: 7
B81: Algèbre | C81: Les Fractions rationnelles | E81: Partie entière d'une fraction rationnelle | F81: Savoir analyser des degrés des polynômes de la fraction rationnelle et obtenir la partie entierre à l'aide de la division éuclidienne des polynômes. | H81: 7
B82: Algèbre | C82: Les Fractions rationnelles | D82: Décomposition en élement simple | E82: Théorie de la décomposition | F82: Connaître l'écriture/la forme théorique d'une décomposition en élements simples de première et de seconde espèce dans C et dans R. | H82: 7
B83: Algèbre | C83: Les Fractions rationnelles | F83: Savoir effectuer une recherche de pôles. | H83: 7
B84: Algèbre | C84: Les Fractions rationnelles | E84: Méthodologie de la décomposition | F84: Connaître la décomposition en élements simples de première espèce : pôles simples, pôles doubles, pôles d'ordre supérieur ou égal à 3. | H84: 7
B85: Algèbre | C85: Les Fractions rationnelles | F85: Connaître la décomposition en élements simples de seconde espèce. | H85: 7
B86: Algèbre | C86: Les Fractions rationnelles | F86: Connaître les techniques de calculs des coefficients de la décomposition (multiplication-évaluation, dérivation, limites, parité/imparité,passage dans C). | H86: 7
B87: Algèbre | D87: Les Matrices
B88: Algèbre | C88: Les Matrices | D88: Ensembles de matrices | E88: Ensemble Mn,p (K) des matrices à n lignes et p colonnes à coefficients dans K. | J88: 3
B89: Algèbre | C89: Les Matrices | E89: Propriétés des opérations matricielles. | F89: Savoir effectuer des opérations de type somme, produit par un scalaire produit de deux matrices. Savoir transposer un système en écriture matricielle. Savoir qu'il existe des matrices non nulles dont le produit est nul. | H89: 2 | J89: 3 | K89: 5 | L89: Calcul matriciel (unisciel.fr)
B90: Algèbre | C90: Les Matrices | D90: Ensemble des matrices carrées Mn(K). | E90: Définition, notation | F90: Définition, vocabulaire. Trace d'une matrice. Savoir calculer les premières puissances d’une matrice carrée. Exemple de matrices nilpotentes. | H90: 3 | J90: 3 | K90: 6
B91: Algèbre | C91: Les Matrices | E91: Matrices diagonales, triangulaires | F91: Connaître la dénomination de matrices triangulaires supérieures et inférieures. Notation In pour la matrice identité. Exemple de matrices nilpotentes. | H91: 3 | J91: 3 | K91: 6
B92: Algèbre | C92: Les Matrices | E92: Opérations sur les matrices carrées | F92: Commutativité des matrices. Formule du Binôme. | H92: 3 | J92: 3 | K92: 6
B93: Algèbre | C93: Les Matrices | E93: Transposée | F93: Notations, Matrices symétriques et antisymétriques.Transposée d’une somme, d’un produit de matrices. | H93: 3 | J93: 3 | K93: 6
B94: Algèbre | C94: Les Matrices | E94: Trace d'une matrice | F94: Définition et exemple de calcul. | H94: 3 | J94: 3 | K94: 6
B95: Algèbre | C95: Les Matrices | D95: Determinant d'une matrice carrée | E95: Définition, notation | F95: Exemple de calcul du déterminant sur des matrices 2X2 et 3X3. Formule de calcul et Methodes de Sarrus. | H95: 2 | J95: 3 | K95: 5
B96: Algèbre | C96: Les Matrices | E96: Propriétés | F96: Effet de la combinaison linéaire de deux lignes ou deux colones sur le calcul du déterminant. | H96: 2 | J96: 3 | K96: 5
B97: Algèbre | C97: Les Matrices | F97: Déterminant de la transposée. | G97: Nullité du determinant d'une matricelorsque deux lignes ou deux colonnes sont identiques | H97: 2 | J97: 3 | K97: 6
B98: Algèbre | C98: Les Matrices | D98: Matrices carrées inversibles | E98: Définition, notation | F98: Unicité de l'inverse quand elle existe. | H98: 2 | J98: 3 | K98: 5
B99: Algèbre | C99: Les Matrices | E99: Propriétés | F99: Inverses du produit, d'une puissance et de la transposée de matrices inversibles. | H99: 2 | J99: 3 | K99: 5
B100: Algèbre | C100: Les Matrices | F100: Critère d'existence de l'inverse à l'aide du déterminant. | H100: 2 | J100: 3 | K100: 5
B101: Algèbre | C101: Les Matrices | F101: Méthodes de calcul de l'inverse d'une matrice. | G101: algotithme de Gauss Jordan. Calcul à l'aide de la transposée de la comatrice. | H101: 2 | J101: 3 | K101: 5 | M101: lien1
B102: Algèbre | D102: Les Systèmes
B103: Algèbre | C103: Les Systèmes | D103: Définitions | E103: Définition d'une équation linéaire | F103: Savoir ce qu'est une équation linéaire et une combinaison linéaire. | H103: 2 | K103: 5
B104: Algèbre | C104: Les Systèmes | E104: Définition d'un système linéaire | F104: Connaître l'interprétation géometrique : intersections de droites, de plans et les differents cas de figures possibles. | H104: 2 | K104: 5 | M104: lien2
...

Sheet Remédiation
A1: Aide :
A2: Vous trouverez votre cursus dans les onglets
A3: Vous trouverez les éléments évaluables de votre dossier de synthèse avec les chapitres et thèmes sur lesquels vous serez interrogé
A4: Vos révisions sont donc ciblées sur la base de ce référentiel
A5: Pour les A1 et A3 vous pouvez renseigner vos scores et voir votre progression par rapport au positionnement
A8: 1) Donner le numéro de votre année | B8: 1
A10: 2) Insérer vos résultats (nombre de bonnes réponses) dans les cases blanches :
A12: =IF(OR($B$8=1,$B$8=3), "Positionnement", "Pas de Positionnement en A2-A4") -> Positionnement
A13: Compétences | B13: Calculer | C13: Raisonner | D13: Représenter | E13: Communiquer | F13: Chercher | G13: Modéliser | H13: % Réussite
A14: Chapitre/Capacités
A15: =IF(OR($B$8=1,$B$8=3),IF($B$8=1,Aide1!A4,Aide3!A4), ) -> Analyse : Suites | B15: 1 | C15: 1 | D15: 1 | E15: 1 | F15: 0 | G15: 1 | H15: =SUM(B15:G15)*100/5 -> 100
A16: =IF(OR($B$8=1,$B$8=3),IF($B$8=1,Aide1!A5,Aide3!A5), ) -> Analyse : Équations différentielles | B16: 0.5 | C16: 0 | D16: 0 | E16: 1 | F16: 0 | G16: 0 | H16: =SUM(B16:G16)*100/5 -> 30
A17: =IF(OR($B$8=1,$B$8=3),IF($B$8=1,Aide1!A6,Aide3!A6), ) -> Analyse : Intégration 1D | B17: 1 | C17: 1 | D17: 1 | E17: 0 | F17: 1 | G17: 1 | H17: =SUM(B17:G17)*100/5 -> 100
A18: =IF(OR($B$8=1,$B$8=3),IF($B$8=1,Aide1!A7,Aide3!A7), ) -> Analyse : Fonctions 1D | B18: 0 | C18: 1 | D18: 1 | H18: =SUM(B18:G18)*100/5 -> 40
A19: =IF(OR($B$8=1,$B$8=3),IF($B$8=1,Aide1!A8,Aide3!A8), ) -> Probabilités | B19: 1 | C19: 0 | D19: 1 | E19: 1 | F19: 1 | G19: 0 | H19: =SUM(B19:G19)*100/5 -> 80
A20: =IF(OR($B$8=1,$B$8=3),IF($B$8=1,Aide1!A9,Aide3!A9), ) -> Statistiques | B20: 1 | C20: 0 | D20: 1 | H20: =SUM(B20:G20)*100/5 -> 40
A21: =IF(OR($B$8=1,$B$8=3),IF($B$8=1,Aide1!A10,Aide3!A10), ) -> Algèbre : Nombres complexes | B21: 0 | C21: 0 | D21: 0 | F21: 0 | G21: 0 | H21: =SUM(B21:G21)*100/5 -> 0
A22: =IF(OR($B$8=1,$B$8=3),IF($B$8=1,Aide1!A11,Aide3!A11), ) -> Algèbre : Arithmétique | B22: 1 | C22: 0 | D22: 0 | E22: 1 | G22: 1 | H22: =SUM(B22:G22)*100/5 -> 60
A23: =IF(OR($B$8=1,$B$8=3),IF($B$8=1,Aide1!A12,Aide3!A12), ) -> Algèbre : Graphes et matrice | B23: 1 | C23: 1 | D23: 1 | E23: 0 | F23: 1 | G23: 1 | H23: =SUM(B23:G23)*100/5 -> 100
A24: =IF(OR($B$8=1,$B$8=3),IF($B$8=1,Aide1!A13,Aide3!A13), ) -> Géomètrie analytique et plane | B24: 1 | C24: 0 | D24: 1 | E24: 0.5 | G24: 1 | H24: =SUM(B24:G24)*100/5 -> 70
A25: =IF(OR($B$8=1,$B$8=3),IF($B$8=1,Aide1!A14,Aide3!A14), ) -> Algèbre : Polynômes | B25: 2 | C25: 0 | D25: 0 | E25: 1 | F25: 0 | H25: =SUM(B25:G25)*100/5 -> 60
A26: % Réussite | B26: =SUM(B15:B25)*100/17 -> 55.882353 | C26: =SUM(C15:C25)*100/8 -> 50 | D26: =SUM(D15:D25)*100/8 -> 87.5 | E26: =SUM(E15:E25)*100/8 -> 68.75 | F26: =SUM(F15:F25)*100/6 -> 50 | G26: =SUM(G15:G25)*100/8 -> 62.5
A29: Semestre impair
A30: Compétences | B30: Calculer | C30: Raisonner | D30: Représenter | E30: Communiquer | F30: Chercher | G30: Modéliser | H30: % Réussite
A31: Chapitre/Capacités
A32: =IF(OR($B$8=1,$B$8=3),IF($B$8=1,Aide1!A20,Aide3!A19),Aide2!A4) -> Géométrie | H32: =SUM(B32:G32)*100/(IF($B$8=1,Aide1!H20,Aide3!H19)) -> 0
A33: =IF(OR($B$8=1,$B$8=3),IF($B$8=1,Aide1!A21,Aide3!A20),Aide2!A5) -> Probabilités- Statistique | H33: =SUM(B33:G33)*100/(IF($B$8=1,Aide1!H21,Aide3!H20)) -> 0
A34: =IF(OR($B$8=1,$B$8=3),IF($B$8=1,Aide1!A22,Aide3!A21),Aide2!A6) -> Analyse : Suites et Séries | H34: =SUM(B34:G34)*100/(IF($B$8=1,Aide1!H22,Aide3!H21)) -> 0
A35: =IF(OR($B$8=1,$B$8=3),IF($B$8=1,Aide1!A23,Aide3!A22),Aide2!#REF!) -> Analyse : Primitives-Intégrations 0 | H35: =SUM(B35:G35)*100/(IF($B$8=1,Aide1!H23,Aide3!H22)) -> 0
A36: =IF(OR($B$8=1,$B$8=3),IF($B$8=1,Aide1!A24,Aide3!A23),Aide2!A7) -> Analyse : Interpolation, développement limité 0 | H36: =SUM(B36:G36)*100/(IF($B$8=1,Aide1!H24,Aide3!H23)) -> 0
A37: =IF(OR($B$8=1,$B$8=3),IF($B$8=1,Aide1!A25,Aide3!A24),Aide2!A8) -> Analyse : Equations différentielles 0 | H37: =SUM(B37:G37)*100/(IF($B$8=1,Aide1!H25,Aide3!H24)) -> 0
A38: =IF(OR($B$8=1,$B$8=3),IF($B$8=1,Aide1!A26,Aide3!A25),Aide2!A9) -> Algèbre : Arithmétique | H38: =SUM(B38:G38)*100/(IF($B$8=1,Aide1!H26,Aide3!H25)) -> 0
A39: =IF(OR($B$8=1,$B$8=3),IF($B$8=1,Aide1!A27,Aide3!A26),Aide2!A10) -> 0 | H39: =SUM(B39:G39)*100/(IF($B$8=1,Aide1!H27,Aide3!H26)) -> #DIV/0!
A40: =IF(OR($B$8=1,$B$8=3),IF($B$8=1,Aide1!A28,Aide3!A27),Aide2!A11) -> 0 | H40: =SUM(B40:G40)*100/(IF($B$8=1,Aide1!H28,Aide3!H27)) -> #DIV/0!
A41: =IF(OR($B$8=1,$B$8=3),IF($B$8=1,Aide1!A29,Aide3!A28),Aide2!A12) -> 0 | H41: =SUM(B41:G41)*100/(IF($B$8=1,Aide1!H29,Aide3!H28)) -> #DIV/0!
A42: % Réussite | B42: =SUM(B32:B41)*100/(IF($B$8=1,Aide1!B34,Aide3!B33)) -> 0 | C42: =SUM(C32:C41)*100/(IF($B$8=1,Aide1!C34,Aide3!C33)) -> 0 | D42: =SUM(D32:D41)*100/(IF($B$8=1,Aide1!D34,Aide3!D33)) -> 0 | E42: =SUM(E32:E41)*100/(IF($B$8=1,Aide1!E34,Aide3!E33)) -> 0 | F42: =SUM(F32:F41)*100/(IF($B$8=1,Aide1!F34,Aide3!F33)) -> 0 | G42: =SUM(G32:G41)*100/(IF($B$8=1,Aide1!G34,Aide3!G33)) -> 0
A47: Semestre pair
A48: Compétences | B48: Calculer | C48: Raisonner | D48: Représenter | E48: Communiquer | F48: Chercher | G48: Modéliser | H48: % Réussite
A49: Chapitre/Capacités
A50: =IF(OR($B$8=1,$B$8=3),IF($B$8=1,Aide1!A39,Aide3!A37),) -> Algèbre : Nombres complexes | H50: =SUM(B50:G50)*100/(IF($B$8=1,Aide1!H39,Aide3!H37)) -> 0
A51: =IF(OR($B$8=1,$B$8=3),IF($B$8=1,Aide1!A40,Aide3!A38),) -> Analyse : Etude 1D | H51: =SUM(B51:G51)*100/(IF($B$8=1,Aide1!H40,Aide3!H38)) -> 0
A52: =IF(OR($B$8=1,$B$8=3),IF($B$8=1,Aide1!A41,Aide3!A39),) -> Analyse : fonctions de plx variables | H52: =SUM(B52:G52)*100/(IF($B$8=1,Aide1!H41,Aide3!H39)) -> 0
A53: =IF(OR($B$8=1,$B$8=3),IF($B$8=1,Aide1!A42,Aide3!A40),) -> Graphes | H53: =SUM(B53:G53)*100/(IF($B$8=1,Aide1!H42,Aide3!H40)) -> 0
A54: =IF(OR($B$8=1,$B$8=3),IF($B$8=1,Aide1!A43,Aide3!A41),) -> Matrices et systèmes | H54: =SUM(B54:G54)*100/(IF($B$8=1,Aide1!H43,Aide3!H41)) -> 0
A55: =IF(OR($B$8=1,$B$8=3),IF($B$8=1,Aide1!A44,Aide3!A42),) -> Probabilités | H55: =SUM(B55:G55)*100/(IF($B$8=1,Aide1!H44,Aide3!#REF!)) -> 0
A56: =IF(OR($B$8=1,$B$8=3),IF($B$8=1,Aide1!A45,Aide3!A43),) -> Statistiques descriptives | H56: =SUM(B56:G56)*100/(IF($B$8=1,Aide1!H45,Aide3!#REF!)) -> 0
A57: =IF(OR($B$8=1,$B$8=3),IF($B$8=1,Aide1!A46,Aide3!A44),) -> 0 | H57: =SUM(B57:G57)*100/(IF($B$8=1,Aide1!H46,Aide3!H42)) -> #DIV/0!
A58: =IF(OR($B$8=1,$B$8=3),IF($B$8=1,Aide1!A47,Aide3!A45),) -> 0 | H58: =SUM(B58:G58)*100/(IF($B$8=1,Aide1!H47,Aide3!H43)) -> #DIV/0!
A59: % Réussite | B59: =SUM(B50:B58)*100/(IF($B$8=1,Aide1!B51,Aide3!B51)) -> 0 | C59: =SUM(C50:C58)*100/(IF($B$8=1,Aide1!C51,Aide3!C51)) -> 0 | D59: =SUM(D50:D58)*100/(IF($B$8=1,Aide1!D51,Aide3!D51)) -> 0 | E59: =SUM(E50:E58)*100/(IF($B$8=1,Aide1!E51,Aide3!E51)) -> 0 | F59: =SUM(F50:F58)*100/(IF($B$8=1,Aide1!F51,Aide3!F51)) -> 0 | G59: =SUM(G50:G58)*100/(IF($B$8=1,Aide1!G51,Aide3!G51)) -> 0

Sheet Aide1
A1: Le test de positionnement est constitué de :
A2: Compétences | B2: Calculer | C2: Raisonner | D2: Représenter | E2: Communiquer | F2: Chercher | G2: Modéliser
A3: Chapitre/Capacités
A4: Analyse : Suites | B4: 1 | C4: 1 | D4: 1 | E4: 1 | F4: 0 | G4: 1 | H4: =SUM(B4:G4) -> 5
A5: Analyse : Équations différentielles | B5: 2 | C5: 1 | D5: 0 | E5: 0 | F5: 1 | G5: 1 | H5: =SUM(B5:G5) -> 5
A6: Analyse : Intégration 1D | B6: 2 | C6: 0 | D6: 1 | E6: 1 | F6: 0 | G6: 1 | H6: =SUM(B6:G6) -> 5
A7: Analyse : Fonctions 1D | B7: 1 | C7: 1 | D7: 1 | E7: 1 | F7: 1 | G7: 0 | H7: =SUM(B7:G7) -> 5
A8: Probabilités | B8: 1 | C8: 0 | D8: 1 | E8: 1 | F8: 1 | G8: 1 | H8: =SUM(B8:G8) -> 5
A9: Statistiques | B9: 2 | C9: 1 | D9: 1 | E9: 1 | F9: 0 | G9: 0 | H9: =SUM(B9:G9) -> 5
A10: Algèbre : Nombres complexes | B10: 1 | C10: 1 | D10: 1 | E10: 0 | F10: 1 | G10: 1 | H10: =SUM(B10:G10) -> 5
A11: Algèbre : Arithmétique | B11: 2 | C11: 1 | D11: 0 | E11: 1 | F11: 0 | G11: 1 | H11: =SUM(B11:G11) -> 5
A12: Algèbre : Graphes et matrice | B12: 2 | C12: 0 | D12: 1 | E12: 0 | F12: 1 | G12: 1 | H12: =SUM(B12:G12) -> 5
A13: Géomètrie analytique et plane | B13: 1 | C13: 1 | D13: 1 | E13: 1 | F13: 0 | G13: 1 | H13: =SUM(B13:G13) -> 5
A14: Algèbre : Polynômes | B14: 2 | C14: 1 | D14: 0 | E14: 1 | F14: 1 | G14: 0 | H14: =SUM(B14:G14) -> 5
A15: nombre de questions | B15: =SUM(B4:B14) -> 17 | C15: =SUM(C4:C14) -> 8 | D15: =SUM(D4:D14) -> 8 | E15: =SUM(E4:E14) -> 8 | F15: =SUM(F4:F14) -> 6 | G15: =SUM(G4:G14) -> 8 | H15: =SUM(B15:G15) -> 55
A18: Compétences | B18: Calculer | C18: Raisonner | D18: Représenter | E18: Communiquer | F18: Chercher | G18: Modéliser
A19: Chapitre/Capacités
A20: Géométrie | B20: 1 | C20: 1 | D20: 1 | E20: 1 | F20: 1 | G20: 1 | H20: =SUM(B20:G20) -> 6
A21: Probabilités- Statistique | B21: 1 | C21: 1 | D21: 1 | E21: 1 | F21: 1 | G21: 1 | H21: =SUM(B21:G21) -> 6
A22: Analyse : Suites et Séries | B22: 1 | C22: 1 | D22: 1 | E22: 1 | F22: 1 | G22: 1 | H22: =SUM(B22:G22) -> 6
A23: Analyse : Primitives-Intégrations 0 | B23: 1 | C23: 1 | D23: 1 | E23: 1 | F23: 1 | G23: 1 | H23: =SUM(B23:G23) -> 6
A24: Analyse : Interpolation, développement limité 0 | B24: 1 | C24: 1 | D24: 1 | E24: 1 | F24: 1 | G24: 1 | H24: =SUM(B24:G24) -> 6
A25: Analyse : Equations différentielles 0 | B25: 1 | C25: 1 | D25: 1 | E25: 1 | F25: 1 | G25: 1 | H25: =SUM(B25:G25) -> 6
A26: Algèbre : Arithmétique | B26: 1 | C26: 1 | D26: 1 | E26: 1 | F26: 1 | G26: 1 | H26: =SUM(B26:G26) -> 6
H27: =SUM(B27:G27) -> 0
H28: =SUM(B28:G28) -> 0
H29: =SUM(B29:G29) -> 0
H30: =SUM(B30:G30) -> 0
H31: =SUM(B31:G31) -> 0
H32: =SUM(B32:G32) -> 0
H33: =SUM(B33:G33) -> 0
A34: nombre de questions | B34: =SUM(B20:B33) -> 7 | C34: =SUM(C20:C33) -> 7 | D34: =SUM(D20:D33) -> 7 | E34: =SUM(E20:E33) -> 7 | F34: =SUM(F20:F33) -> 7 | G34: =SUM(G20:G33) -> 7 | H34: =SUM(B34:G34) -> 42
A37: Compétences | B37: Calculer | C37: Raisonner | D37: Représenter | E37: Communiquer | F37: Chercher | G37: Modéliser
A38: Chapitre/Capacités
A39: Algèbre : Nombres complexes | B39: 1 | C39: 1 | D39: 1 | E39: 1 | F39: 1 | G39: 1 | H39: =SUM(B39:G39) -> 6
A40: Analyse : Etude 1D | B40: 1 | C40: 1 | D40: 1 | E40: 1 | F40: 1 | G40: 1 | H40: =SUM(B40:G40) -> 6
A41: Analyse : fonctions de plx variables | B41: 1 | C41: 1 | D41: 1 | E41: 1 | F41: 1 | G41: 1 | H41: =SUM(B44:G44) -> 6
A42: Graphes | B42: 1 | C42: 1 | D42: 1 | E42: 1 | F42: 1 | G42: 1 | H42: =SUM(B42:G42) -> 6
A43: Matrices et systèmes | B43: 1 | C43: 1 | D43: 1 | E43: 1 | F43: 1 | G43: 1 | H43: =SUM(B43:G43) -> 6
A44: Probabilités | B44: 1 | C44: 1 | D44: 1 | E44: 1 | F44: 1 | G44: 1 | H44: =SUM(B44:G44) -> 6
A45: Statistiques descriptives | B45: 1 | C45: 1 | D45: 1 | E45: 1 | F45: 1 | G45: 1 | H45: =SUM(B45:G45) -> 6
H46: =SUM(B46:G46) -> 0
H47: =SUM(B47:G47) -> 0
H48: =SUM(B48:G48) -> 0
H49: =SUM(B48:G48) -> 0
H50: =SUM(B41:G41) -> 6
B51: =SUM(B39:B50) -> 7 | C51: =SUM(C39:C50) -> 7 | D51: =SUM(D39:D50) -> 7 | E51: =SUM(E39:E50) -> 7 | F51: =SUM(F39:F50) -> 7 | G51: =SUM(G39:G50) -> 7 | H51: =SUM(B51:G51) -> 42

Sheet Aide2
A2: Compétences | B2: Calculer | C2: Raisonner | D2: Représenter | E2: Communiquer | F2: Chercher | G2: Modéliser
A3: Chapitre/Capacités
A4: QCM : Analyse : Etude de plusieurs variables, suites et série | B4: 6
A5: QCM : Géométrie | B5: 6
A6: QCM : Algèbre : nombres complexes, matrices et systèmes | B6: 6
A7: Epreuve rédactionnelle - Etude de fonctions 1D | B7: 6
A8: Epreuve rédactionnelle :Maths spé G/BTP : fonctions de plusieurs variables // Info/S3E Complexité Algo | B8: 6
A9: Epreuve rédactionnelle : Statistique et probabilités | B9: 6
A10: Epreuve rédactionnelle : Equations différentielles | B10: 6

Sheet Aide3
A1: Le test de positionnement est constitué de :
A2: Compétences | B2: Calculer | C2: Raisonner | D2: Représenter | E2: Communiquer | F2: Chercher | G2: Modéliser
A3: Chapitre/Capacités
A4: Analyse : Suites et Séries numériques | B4: 1 | C4: 1 | D4: 1 | E4: 1 | F4: 0 | G4: 1 | H4: =SUM(B4:G4) -> 5
A5: Analyse : Équations différentielles | B5: 2 | C5: 1 | D5: 0 | E5: 0 | F5: 1 | G5: 1 | H5: =SUM(B5:G5) -> 5
A6: Analyse : Intégration 1-2-3 D | B6: 2 | C6: 0 | D6: 1 | E6: 1 | F6: 0 | G6: 1 | H6: =SUM(B6:G6) -> 5
A7: Analyse : Fonctions 1-2-3 D | B7: 1 | C7: 1 | D7: 1 | E7: 1 | F7: 1 | G7: 0 | H7: =SUM(B7:G7) -> 5
A8: Probabilités | B8: 1 | C8: 0 | D8: 1 | E8: 1 | F8: 1 | G8: 1 | H8: =SUM(B8:G8) -> 5
A9: Statistiques | B9: 2 | C9: 1 | D9: 1 | E9: 1 | F9: 0 | G9: 0 | H9: =SUM(B9:G9) -> 5
A10: Algèbre : Nombres complexes | B10: 1 | C10: 1 | D10: 1 | E10: 0 | F10: 1 | G10: 1 | H10: =SUM(B10:G10) -> 5
A11: Algèbre : Arithmétique | B11: 2 | C11: 1 | D11: 0 | E11: 1 | F11: 0 | G11: 1 | H11: =SUM(B11:G11) -> 5
A12: Algèbre : Graphes et matrice | B12: 2 | C12: 0 | D12: 1 | E12: 0 | F12: 1 | G12: 1 | H12: =SUM(B12:G12) -> 5
A13: Géomètrie analytique et plane | B13: 1 | C13: 1 | D13: 1 | E13: 1 | F13: 0 | G13: 1 | H13: =SUM(B13:G13) -> 5
A14: Algèbre : Polynômes | B14: 2 | C14: 1 | D14: 0 | E14: 1 | F14: 1 | G14: 0 | H14: =SUM(B14:G14) -> 5
A15: nombre de questions | B15: =SUM(B4:B14) -> 17 | C15: =SUM(C4:C14) -> 8 | D15: =SUM(D4:D14) -> 8 | E15: =SUM(E4:E14) -> 8 | F15: =SUM(F4:F14) -> 6 | G15: =SUM(G4:G14) -> 8 | H15: =SUM(H4:H14) -> 55
A17: Compétences | B17: Calculer | C17: Raisonner | D17: Représenter | E17: Communiquer | F17: Chercher | G17: Modéliser
A18: Chapitre/Capacités
A19: QCM : Analyse : Equations différentielles 1 | B19: 2 | C19: 1 | D19: 0 | E19: 1 | F19: 1 | G19: 1 | H19: =SUM(B19:G19) -> 6
A20: QCM : Analyse : fonctions multivariées, opérateurs et développements limités | B20: 2 | C20: 1 | D20: 1 | E20: 0 | F20: 1 | G20: 1 | H20: =SUM(B20:G20) -> 6
A21: QCM : Probabilités continues et discrètes | B21: 2 | C21: 1 | D21: 1 | E21: 1 | F21: 1 | G21: 1 | H21: =SUM(B21:G21) -> 7
A22: QCM : Statistiques univariés et bivariés | B22: 2 | C22: 1 | D22: 1 | E22: 1 | F22: 1 | G22: 1 | H22: =SUM(B22:G22) -> 7
A23: QCM : Géomètrie | B23: 2 | C23: 1 | D23: 1 | E23: 1 | F23: 1 | G23: 1 | H23: =SUM(B23:G23) -> 7
A24: QCM : Analyse : suites, série 1 | B24: 2 | C24: 1 | D24: 1 | E24: 1 | F24: 1 | G24: 1 | H24: =SUM(B24:G24) -> 7
A25: QCM : Algèbre : Nombres complexes | B25: 2 | C25: 0 | D25: 1 | E25: 1 | F25: 0 | G25: 1 | H25: =SUM(B25:G25) -> 5
A26: QCM : Algèbre : Arithmétique | B26: 2 | C26: 0 | D26: 0 | E26: 1 | F26: 1 | G26: 1 | H26: =SUM(B26:G26) -> 5
A27: QCM : Algèbre : Matrice et système | B27: 2 | C27: 0 | D27: 1 | E27: 1 | F27: 1 | G27: 0 | H27: =SUM(B27:G27) -> 5
A28: QCM : Analyse : fonctiosn, developpement limités | B28: 2 | C28: 1 | D28: 0 | E28: 0 | F28: 1 | G28: 1 | H28: =SUM(B28:G28) -> 5
H29: =SUM(B29:G29) -> 0
H30: =SUM(B30:G30) -> 0
H31: =SUM(B31:G31) -> 0
H32: =SUM(B32:G32) -> 0
A33: nombre de questions | B33: =SUM(B19:B32) -> 20 | C33: =SUM(C19:C32) -> 7 | D33: =SUM(D19:D32) -> 7 | E33: =SUM(E19:E32) -> 8 | F33: =SUM(F19:F32) -> 9 | G33: =SUM(G19:G32) -> 9 | H33: =SUM(H27:H32) -> 10
A35: Compétences | B35: Calculer | C35: Raisonner | D35: Représenter | E35: Communiquer | F35: Chercher | G35: Modéliser
A36: Chapitre/Capacités
A37: QCM : Géométrie | B37: 1 | C37: 1 | D37: 1 | E37: 1 | F37: 1 | G37: 1 | H37: =SUM(B37:G37) -> 6
A38: QCM : Analyse : suites, série 1 | B38: 1 | C38: 1 | D38: 1 | E38: 1 | F38: 1 | G38: 1 | H38: =SUM(B38:G38) -> 6
A39: QCM : Algèbre : Nombres complexes | B39: 1 | C39: 1 | D39: 1 | E39: 1 | F39: 1 | G39: 1 | H39: =SUM(B39:G39) -> 6
A40: QCM : Analyse : Etude nD | B40: 1 | C40: 1 | D40: 1 | E40: 1 | F40: 1 | G40: 1 | H40: =SUM(B40:G40) -> 6
A41: QCM : Algèbre : Matrice et système | B41: 1 | C41: 1 | D41: 1 | E41: 1 | F41: 1 | G41: 1 | H41: =SUM(B41:G41) -> 6
A42: Rédactionnel : Démarche : Transformées de Laplace et Equa Diff, fonctions NV 1 et 2 | B42: 1 | C42: 1 | D42: 1 | E42: 1 | F42: 1 | G42: 1 | H42: =SUM(B42:G42) -> 6
A43: Rédactionnel :Modéliser/Représenter des données : Statistiques inférentielles | B43: 1 | C43: 1 | D43: 1 | E43: 1 | F43: 1 | G43: 1 | H43: =SUM(B43:G43) -> 6
A44: Rédactionnel :Modéliser/Représenter des données : Statistiques descriptives | B44: 1 | C44: 1 | D44: 1 | E44: 1 | F44: 1 | G44: 1 | H44: =SUM(B44:G44) -> 6
H45: =SUM(B45:G45) -> 0
H46: =SUM(B46:G46) -> 0
H47: =SUM(B47:G47) -> 0
H48: =SUM(B48:G48) -> 0
A51: nombre de questions | B51: =SUM(B37:B48) -> 8 | C51: =SUM(C37:C48) -> 8 | D51: =SUM(D37:D48) -> 8 | E51: =SUM(E37:E48) -> 8 | F51: =SUM(F37:F48) -> 8 | G51: =SUM(G37:G48) -> 8 | H51: =SUM(H43:H48) -> 12

Sheet A1 CPI S1
A1: Objectifs d'apprentissage des Mathématiques | H1: Remédiation
A2: Notions à maîtriser en CPI A1 S1 | H2: lien Unisciel ou livre scolaire
A3: EE du DS | B3: Domaine | C3: Discipline | D3: Chapitres | E3: Thèmes | F3: Détail des chapitres | G3: Utilisation
A4: Algèbre : Arithmétique | B4: =IF('Items sous domaines Maths '!H8=1,'Items sous domaines Maths '!B8,0) -> Algèbre | C4: =IF('Items sous domaines Maths '!H8=1,'Items sous domaines Maths '!C8) -> Arithmétique | D4: =IF('Items sous domaines Maths '!H8=1,'Items sous domaines Maths '!D8,0) -> Divisibilité | E4: =IF('Items sous domaines Maths '!H8=1,'Items sous domaines Maths '!E8,0) -> Critères de divisibilité | F4: =IF('Items sous domaines Maths '!H8=1,'Items sous domaines Maths '!F8,0) -> 0 | G4: ETS | H4: https://uel.unisciel.fr/mathematiques/arithmetique/arithmetique/co/arithmetique.html | I4: lien1
B5: =IF('Items sous domaines Maths '!H9=1,'Items sous domaines Maths '!B9,0) -> Algèbre | C5: =IF('Items sous domaines Maths '!H9=1,'Items sous domaines Maths '!C9,0) -> Arithmétique | D5: =IF('Items sous domaines Maths '!H9=1,'Items sous domaines Maths '!D9,0) -> 0 | E5: =IF('Items sous domaines Maths '!H9=1,'Items sous domaines Maths '!E9,0) -> Division euclidienne | F5: =IF('Items sous domaines Maths '!H9=1,'Items sous domaines Maths '!F9,0) -> Algorithme d'Euclide.
B6: =IF('Items sous domaines Maths '!H10=1,'Items sous domaines Maths '!B10,0) -> Algèbre | C6: =IF('Items sous domaines Maths '!H10=1,'Items sous domaines Maths '!C10,0) -> Arithmétique | D6: =IF('Items sous domaines Maths '!H10=1,'Items sous domaines Maths '!D10,0) -> 0 | E6: =IF('Items sous domaines Maths '!H10=1,'Items sous domaines Maths '!E10,0) -> Congruences | F6: =IF('Items sous domaines Maths '!H10=1,'Items sous domaines Maths '!F10,0) -> 0
B7: =IF('Items sous domaines Maths '!H11=1,'Items sous domaines Maths '!B11,0) -> Algèbre | C7: =IF('Items sous domaines Maths '!H11=1,'Items sous domaines Maths '!C11,0) -> Arithmétique | D7: =IF('Items sous domaines Maths '!H11=1,'Items sous domaines Maths '!D11,0) -> Factorisation | E7: =IF('Items sous domaines Maths '!H11=1,'Items sous domaines Maths '!E11,0) -> Nombres premiers, Crible d'Eratosthène | F7: =IF('Items sous domaines Maths '!H11=1,'Items sous domaines Maths '!F11,0) -> 0
B8: =IF('Items sous domaines Maths '!H12=1,'Items sous domaines Maths '!B12,0) -> Algèbre | C8: =IF('Items sous domaines Maths '!H12=1,'Items sous domaines Maths '!C12,0) -> Arithmétique | D8: =IF('Items sous domaines Maths '!H12=1,'Items sous domaines Maths '!D12,0) -> 0 | E8: =IF('Items sous domaines Maths '!H12=1,'Items sous domaines Maths '!E12,0) -> Lemme d'Euclide | F8: =IF('Items sous domaines Maths '!H12=1,'Items sous domaines Maths '!F12,0) -> 0
B9: =IF('Items sous domaines Maths '!H13=1,'Items sous domaines Maths '!B13,0) -> Algèbre | C9: =IF('Items sous domaines Maths '!H13=1,'Items sous domaines Maths '!C13,0) -> Arithmétique | D9: =IF('Items sous domaines Maths '!H13=1,'Items sous domaines Maths '!D13,0) -> 0 | E9: =IF('Items sous domaines Maths '!H13=1,'Items sous domaines Maths '!E13,0) -> Petit théorème de Fermat | F9: =IF('Items sous domaines Maths '!H13=1,'Items sous domaines Maths '!F13,0) -> 0
B10: =IF('Items sous domaines Maths '!H14=1,'Items sous domaines Maths '!B14,0) -> Algèbre | C10: =IF('Items sous domaines Maths '!H14=1,'Items sous domaines Maths '!C14,0) -> Arithmétique | D10: =IF('Items sous domaines Maths '!H14=1,'Items sous domaines Maths '!D14,0) -> 0 | E10: =IF('Items sous domaines Maths '!H14=1,'Items sous domaines Maths '!E14,0) -> Décomposition en facteurs premiers / Théorème fondamental de l'arithmétique | F10: =IF('Items sous domaines Maths '!H14=1,'Items sous domaines Maths '!F14,0) -> 0
B11: =IF('Items sous domaines Maths '!H15=1,'Items sous domaines Maths '!B15,0) -> Algèbre | C11: =IF('Items sous domaines Maths '!H15=1,'Items sous domaines Maths '!C15,0) -> Arithmétique | D11: =IF('Items sous domaines Maths '!H15=1,'Items sous domaines Maths '!D15,0) -> PGCD | E11: =IF('Items sous domaines Maths '!H15=1,'Items sous domaines Maths '!E15,0) -> PGCD de 2 entiers, lien avec la décomposition en facteurs premiers | F11: =IF('Items sous domaines Maths '!H15=1,'Items sous domaines Maths '!F15,0) -> 0
B12: =IF('Items sous domaines Maths '!H16=1,'Items sous domaines Maths '!B16,0) -> Algèbre | C12: =IF('Items sous domaines Maths '!H16=1,'Items sous domaines Maths '!C16,0) -> Arithmétique | D12: =IF('Items sous domaines Maths '!H16=1,'Items sous domaines Maths '!D16,0) -> 0 | E12: =IF('Items sous domaines Maths '!H16=1,'Items sous domaines Maths '!E16,0) -> Théorème de Bezout | F12: =IF('Items sous domaines Maths '!H16=1,'Items sous domaines Maths '!F16,0) -> 0
B13: =IF('Items sous domaines Maths '!H17=1,'Items sous domaines Maths '!B17,0) -> Algèbre | C13: =IF('Items sous domaines Maths '!H17=1,'Items sous domaines Maths '!C17,0) -> Arithmétique | D13: =IF('Items sous domaines Maths '!H17=1,'Items sous domaines Maths '!D17,0) -> 0 | E13: =IF('Items sous domaines Maths '!H17=1,'Items sous domaines Maths '!E17,0) -> Nombres premiers entre eux, caractérisation via Bezout, Lemme de Gauss | F13: =IF('Items sous domaines Maths '!H17=1,'Items sous domaines Maths '!F17,0) -> 0
B14: =IF('Items sous domaines Maths '!H18=1,'Items sous domaines Maths '!B18,0) -> Algèbre | C14: =IF('Items sous domaines Maths '!H18=1,'Items sous domaines Maths '!C18,0) -> Arithmétique | D14: =IF('Items sous domaines Maths '!H18=1,'Items sous domaines Maths '!D18,0) -> 0 | E14: =IF('Items sous domaines Maths '!H18=1,'Items sous domaines Maths '!E18,0) -> PPCM | F14: =IF('Items sous domaines Maths '!H18=1,'Items sous domaines Maths '!F18,0) -> 0
B15: =IF('Items sous domaines Maths '!H19=1,'Items sous domaines Maths '!B19,0) -> Algèbre | C15: =IF('Items sous domaines Maths '!H19=1,'Items sous domaines Maths '!C19,0) -> Arithmétique | D15: =IF('Items sous domaines Maths '!H19=1,'Items sous domaines Maths '!D19,0) -> Équations dophantiennes | E15: =IF('Items sous domaines Maths '!H19=1,'Items sous domaines Maths '!E19,0) -> 0 | F15: =IF('Items sous domaines Maths '!H19=1,'Items sous domaines Maths '!F19,0) -> 0
B16: =IF('Items sous domaines Maths '!H20=1,'Items sous domaines Maths '!B20,0) -> Algèbre | C16: =IF('Items sous domaines Maths '!H20=1,'Items sous domaines Maths '!C20,0) -> Arithmétique | D16: =IF('Items sous domaines Maths '!H20=1,'Items sous domaines Maths '!D20,0) -> Chiffrage | E16: =IF('Items sous domaines Maths '!H20=1,'Items sous domaines Maths '!E20,0) -> Chiffrement simple | F16: =IF('Items sous domaines Maths '!H20=1,'Items sous domaines Maths '!F20,0) -> rot, César, Vigenère...
... B19: =IF('Items sous domaines Maths '!H23=1,'Items sous domaines Maths '!B23,0) -> Algèbre | C19: =IF('Items sous domaines Maths '!H23=1,'Items sous domaines Maths '!C23,0) -> Arithmétique | D19: =IF('Items sous domaines Maths '!H23=1,'Items sous domaines Maths '!D23,0) -> 0 | E19: =IF('Items sous domaines Maths '!H23=1,'Items sous domaines Maths '!E23,0) -> Chiffrement asymétrique | F19: =IF('Items sous domaines Maths '!H23=1,'Items sous domaines Maths '!F23,0) -> RSA, PGP (hybride)
B20: =IF('Items sous domaines Maths '!H24=1,'Items sous domaines Maths '!B24,0) -> 0 | C20: =IF('Items sous domaines Maths '!H24=1,'Items sous domaines Maths '!C24,0) -> 0 | D20: =IF('Items sous domaines Maths '!H24=1,'Items sous domaines Maths '!D24,0) -> 0 | E20: =IF('Items sous domaines Maths '!H24=1,'Items sous domaines Maths '!E24,0) -> 0 | F20: =IF('Items sous domaines Maths '!H24=1,'Items sous domaines Maths '!F24,0) -> 0 | G20: =IF('Items sous domaines Maths '!H24=1,'Items sous domaines Maths '!G24,0) -> 0
B21: =IF('Items sous domaines Maths '!H25=1,'Items sous domaines Maths '!B25,0) -> 0 | C21: =IF('Items sous domaines Maths '!H25=1,'Items sous domaines Maths '!C25,0) -> 0 | D21: =IF('Items sous domaines Maths '!H25=1,'Items sous domaines Maths '!D25,0) -> 0 | E21: =IF('Items sous domaines Maths '!H25=1,'Items sous domaines Maths '!E25,0) -> 0 | F21: =IF('Items sous domaines Maths '!H25=1,'Items sous domaines Maths '!F25,0) -> 0 | G21: =IF('Items sous domaines Maths '!H25=1,'Items sous domaines Maths '!G25,0) -> 0
A22: Algèbre de Boole (hors TOMIC) | B22: =IF('Items sous domaines Maths '!H26=1,'Items sous domaines Maths '!B26,0) -> Algèbre | C22: =IF('Items sous domaines Maths '!H26=1,'Items sous domaines Maths '!C26,0) -> Logique | D22: =IF('Items sous domaines Maths '!H26=1,'Items sous domaines Maths '!D26,0) -> Logique et raisonnements | E22: =IF('Items sous domaines Maths '!H26=1,'Items sous domaines Maths '!E26,0) -> Rudiments de logique | F22: =IF('Items sous domaines Maths '!H26=1,'Items sous domaines Maths '!F26,0) -> Opérations : négation, conjonction, disjonction, implication, équivalence. | G22: Projet Strongbox-Electronique | H22: https://uel.unisciel.fr/mathematiques/logique1/logique1/co/logique1.html
B23: =IF('Items sous domaines Maths '!H27=1,'Items sous domaines Maths '!B27,0) -> Algèbre | C23: =IF('Items sous domaines Maths '!H27=1,'Items sous domaines Maths '!C27,0) -> Logique | D23: =IF('Items sous domaines Maths '!H27=1,'Items sous domaines Maths '!D27,0) -> 0 | E23: =IF('Items sous domaines Maths '!H27=1,'Items sous domaines Maths '!E27,0) -> 0 | F23: =IF('Items sous domaines Maths '!H27=1,'Items sous domaines Maths '!F27,0) -> Tables de vérité
B24: =IF('Items sous domaines Maths '!H28=1,'Items sous domaines Maths '!B28,0) -> Algèbre | C24: =IF('Items sous domaines Maths '!H28=1,'Items sous domaines Maths '!C28,0) -> Logique | D24: =IF('Items sous domaines Maths '!H28=1,'Items sous domaines Maths '!D28,0) -> 0 | E24: =IF('Items sous domaines Maths '!H28=1,'Items sous domaines Maths '!E28,0) -> 0 | F24: =IF('Items sous domaines Maths '!H28=1,'Items sous domaines Maths '!F28,0) -> Quantificateurs .
B25: =IF('Items sous domaines Maths '!H29=1,'Items sous domaines Maths '!B29,0) -> Algèbre | C25: =IF('Items sous domaines Maths '!H29=1,'Items sous domaines Maths '!C29,0) -> Logique | D25: =IF('Items sous domaines Maths '!H29=1,'Items sous domaines Maths '!D29,0) -> 0 | E25: =IF('Items sous domaines Maths '!H29=1,'Items sous domaines Maths '!E29,0) -> 0 | F25: =IF('Items sous domaines Maths '!H29=1,'Items sous domaines Maths '!F29,0) -> Négations | I25: lien Moodle
B26: =IF('Items sous domaines Maths '!H30=1,'Items sous domaines Maths '!B30,0) -> Algèbre | C26: =IF('Items sous domaines Maths '!H30=1,'Items sous domaines Maths '!C30,0) -> Logique | D26: =IF('Items sous domaines Maths '!H30=1,'Items sous domaines Maths '!D30,0) -> 0 | E26: =IF('Items sous domaines Maths '!H30=1,'Items sous domaines Maths '!E30,0) -> Propriétés de N | F26: =IF('Items sous domaines Maths '!H30=1,'Items sous domaines Maths '!F30,0) -> Définitions générales .
B27: =IF('Items sous domaines Maths '!H31=1,'Items sous domaines Maths '!B31,0) -> Algèbre | C27: =IF('Items sous domaines Maths '!H31=1,'Items sous domaines Maths '!C31,0) -> Logique | D27: =IF('Items sous domaines Maths '!H31=1,'Items sous domaines Maths '!D31,0) -> 0 | E27: =IF('Items sous domaines Maths '!H31=1,'Items sous domaines Maths '!E31,0) -> 0 | F27: =IF('Items sous domaines Maths '!H31=1,'Items sous domaines Maths '!F31,0) -> Parties de N .
B28: =IF('Items sous domaines Maths '!H32=1,'Items sous domaines Maths '!B32,0) -> Algèbre | C28: =IF('Items sous domaines Maths '!H32=1,'Items sous domaines Maths '!C32,0) -> Logique | D28: =IF('Items sous domaines Maths '!H32=1,'Items sous domaines Maths '!D32,0) -> 0 | E28: =IF('Items sous domaines Maths '!H32=1,'Items sous domaines Maths '!E32,0) -> Autres types de raisonnements | F28: =IF('Items sous domaines Maths '!H32=1,'Items sous domaines Maths '!F32,0) -> Raisonnement par récurrence
B29: =IF('Items sous domaines Maths '!H33=1,'Items sous domaines Maths '!B33,0) -> Algèbre | C29: =IF('Items sous domaines Maths '!H33=1,'Items sous domaines Maths '!C33,0) -> Logique | D29: =IF('Items sous domaines Maths '!H33=1,'Items sous domaines Maths '!D33,0) -> 0 | E29: =IF('Items sous domaines Maths '!H33=1,'Items sous domaines Maths '!E33,0) -> 0 | F29: =IF('Items sous domaines Maths '!H33=1,'Items sous domaines Maths '!F33,0) -> Raisonnement par contraposition
B30: =IF('Items sous domaines Maths '!H34=1,'Items sous domaines Maths '!B34,0) -> Algèbre | C30: =IF('Items sous domaines Maths '!H34=1,'Items sous domaines Maths '!C34,0) -> Logique | D30: =IF('Items sous domaines Maths '!H34=1,'Items sous domaines Maths '!D34,0) -> 0 | E30: =IF('Items sous domaines Maths '!H34=1,'Items sous domaines Maths '!E34,0) -> 0 | F30: =IF('Items sous domaines Maths '!H34=1,'Items sous domaines Maths '!F34,0) -> Raisonnement par l’absurde
B31: =IF('Items sous domaines Maths '!H35=1,'Items sous domaines Maths '!B35,0) -> Algèbre | C31: =IF('Items sous domaines Maths '!H35=1,'Items sous domaines Maths '!C35,0) -> Logique | D31: =IF('Items sous domaines Maths '!H35=1,'Items sous domaines Maths '!D35,0) -> Logique booléenne | E31: =IF('Items sous domaines Maths '!H35=1,'Items sous domaines Maths '!E35,0) -> Fonctions Booléennes | F31: =IF('Items sous domaines Maths '!H35=1,'Items sous domaines Maths '!F35,0) -> Fonction NOT, NOR, AND, OR
B32: =IF('Items sous domaines Maths '!H36=1,'Items sous domaines Maths '!B36,0) -> Algèbre | C32: =IF('Items sous domaines Maths '!H36=1,'Items sous domaines Maths '!C36,0) -> Logique | D32: =IF('Items sous domaines Maths '!H36=1,'Items sous domaines Maths '!D36,0) -> 0 | E32: =IF('Items sous domaines Maths '!H36=1,'Items sous domaines Maths '!E36,0) -> 0 | F32: =IF('Items sous domaines Maths '!H36=1,'Items sous domaines Maths '!F36,0) -> Tables de verité
B33: =IF('Items sous domaines Maths '!H37=1,'Items sous domaines Maths '!B37,0) -> Algèbre | C33: =IF('Items sous domaines Maths '!H37=1,'Items sous domaines Maths '!C37,0) -> Logique | D33: =IF('Items sous domaines Maths '!H37=1,'Items sous domaines Maths '!D37,0) -> 0 | E33: =IF('Items sous domaines Maths '!H37=1,'Items sous domaines Maths '!E37,0) -> Représentations graphiques des fonctions booléennes | F33: =IF('Items sous domaines Maths '!H37=1,'Items sous domaines Maths '!F37,0) -> Connaissance des symboles de représentation
B34: =IF('Items sous domaines Maths '!H38=1,'Items sous domaines Maths '!B38,0) -> Algèbre | C34: =IF('Items sous domaines Maths '!H38=1,'Items sous domaines Maths '!C38,0) -> Logique | D34: =IF('Items sous domaines Maths '!H38=1,'Items sous domaines Maths '!D38,0) -> 0 | E34: =IF('Items sous domaines Maths '!H38=1,'Items sous domaines Maths '!E38,0) -> 0 | F34: =IF('Items sous domaines Maths '!H38=1,'Items sous domaines Maths '!F38,0) -> Utilisation dans la description des circuits logiques.
B35: =IF('Items sous domaines Maths '!H39=1,'Items sous domaines Maths '!B39,0) -> 0 | C35: =IF('Items sous domaines Maths '!H39=1,'Items sous domaines Maths '!C39,0) -> 0 | D35: =IF('Items sous domaines Maths '!H39=1,'Items sous domaines Maths '!D39,0) -> 0 | E35: =IF('Items sous domaines Maths '!H39=1,'Items sous domaines Maths '!E39,0) -> 0 | F35: =IF('Items sous domaines Maths '!H39=1,'Items sous domaines Maths '!F39,0) -> 0 | G35: =IF('Items sous domaines Maths '!H39=1,'Items sous domaines Maths '!G39,0) -> 0
B36: =IF('Items sous domaines Maths '!H40=1,'Items sous domaines Maths '!B40,0) -> 0 | C36: =IF('Items sous domaines Maths '!H40=1,'Items sous domaines Maths '!C40,0) -> 0 | D36: =IF('Items sous domaines Maths '!H40=1,'Items sous domaines Maths '!D40,0) -> 0 | E36: =IF('Items sous domaines Maths '!H40=1,'Items sous domaines Maths '!E40,0) -> 0 | F36: =IF('Items sous domaines Maths '!H40=1,'Items sous domaines Maths '!F40,0) -> 0 | G36: Projet Strongbox-Electronique et ETS | H36: https://uel.unisciel.fr/physique/outils_nancy/outils_nancy_ch04/co/apprendre_ch04.html | I36: lien1
B37: =IF('Items sous domaines Maths '!H41=1,'Items sous domaines Maths '!B41,0) -> 0 | C37: =IF('Items sous domaines Maths '!H41=1,'Items sous domaines Maths '!C41,0) -> 0 | D37: =IF('Items sous domaines Maths '!H41=1,'Items sous domaines Maths '!D41,0) -> 0 | E37: =IF('Items sous domaines Maths '!H41=1,'Items sous domaines Maths '!E41,0) -> 0 | F37: =IF('Items sous domaines Maths '!H41=1,'Items sous domaines Maths '!F41,0) -> 0
B38: =IF('Items sous domaines Maths '!H42=1,'Items sous domaines Maths '!B42,0) -> 0 | C38: =IF('Items sous domaines Maths '!H42=1,'Items sous domaines Maths '!C42,0) -> 0 | D38: =IF('Items sous domaines Maths '!H42=1,'Items sous domaines Maths '!D42,0) -> 0 | E38: =IF('Items sous domaines Maths '!H42=1,'Items sous domaines Maths '!E42,0) -> 0 | F38: =IF('Items sous domaines Maths '!H42=1,'Items sous domaines Maths '!F42,0) -> 0
B39: =IF('Items sous domaines Maths '!H43=1,'Items sous domaines Maths '!B43,0) -> 0 | C39: =IF('Items sous domaines Maths '!H43=1,'Items sous domaines Maths '!C43,0) -> 0 | D39: =IF('Items sous domaines Maths '!H43=1,'Items sous domaines Maths '!D43,0) -> 0 | E39: =IF('Items sous domaines Maths '!H43=1,'Items sous domaines Maths '!E43,0) -> 0 | F39: =IF('Items sous domaines Maths '!H43=1,'Items sous domaines Maths '!F43,0) -> 0
B40: =IF('Items sous domaines Maths '!H44=1,'Items sous domaines Maths '!B44,0) -> 0 | C40: =IF('Items sous domaines Maths '!H44=1,'Items sous domaines Maths '!C44,0) -> 0 | D40: =IF('Items sous domaines Maths '!H44=1,'Items sous domaines Maths '!D44,0) -> 0 | E40: =IF('Items sous domaines Maths '!H44=1,'Items sous domaines Maths '!E44,0) -> 0 | F40: =IF('Items sous domaines Maths '!H44=1,'Items sous domaines Maths '!F44,0) -> 0
B41: =IF('Items sous domaines Maths '!H45=1,'Items sous domaines Maths '!B45,0) -> 0 | C41: =IF('Items sous domaines Maths '!H45=1,'Items sous domaines Maths '!C45,0) -> 0 | D41: =IF('Items sous domaines Maths '!H45=1,'Items sous domaines Maths '!D45,0) -> 0 | E41: =IF('Items sous domaines Maths '!H45=1,'Items sous domaines Maths '!E45,0) -> 0 | F41: =IF('Items sous domaines Maths '!H45=1,'Items sous domaines Maths '!F45,0) -> 0
B42: =IF('Items sous domaines Maths '!H46=1,'Items sous domaines Maths '!B46,0) -> 0 | C42: =IF('Items sous domaines Maths '!H46=1,'Items sous domaines Maths '!C46,0) -> 0 | D42: =IF('Items sous domaines Maths '!H46=1,'Items sous domaines Maths '!D46,0) -> 0 | E42: =IF('Items sous domaines Maths '!H46=1,'Items sous domaines Maths '!E46,0) -> 0 | F42: =IF('Items sous domaines Maths '!H46=1,'Items sous domaines Maths '!F46,0) -> 0
B43: =IF('Items sous domaines Maths '!H47=1,'Items sous domaines Maths '!B47,0) -> 0 | C43: =IF('Items sous domaines Maths '!H47=1,'Items sous domaines Maths '!C47,0) -> 0 | D43: =IF('Items sous domaines Maths '!H47=1,'Items sous domaines Maths '!D47,0) -> 0 | E43: =IF('Items sous domaines Maths '!H47=1,'Items sous domaines Maths '!E47,0) -> 0 | F43: =IF('Items sous domaines Maths '!H47=1,'Items sous domaines Maths '!F47,0) -> 0
B44: =IF('Items sous domaines Maths '!H48=1,'Items sous domaines Maths '!B48,0) -> 0 | C44: =IF('Items sous domaines Maths '!H48=1,'Items sous domaines Maths '!C48,0) -> 0 | D44: =IF('Items sous domaines Maths '!H48=1,'Items sous domaines Maths '!D48,0) -> 0 | E44: =IF('Items sous domaines Maths '!H48=1,'Items sous domaines Maths '!E48,0) -> 0 | F44: =IF('Items sous domaines Maths '!H48=1,'Items sous domaines Maths '!F48,0) -> 0
B45: =IF('Items sous domaines Maths '!H49=1,'Items sous domaines Maths '!B49,0) -> 0 | C45: =IF('Items sous domaines Maths '!H49=1,'Items sous domaines Maths '!C49,0) -> 0 | D45: =IF('Items sous domaines Maths '!H49=1,'Items sous domaines Maths '!D49,0) -> 0 | E45: =IF('Items sous domaines Maths '!H49=1,'Items sous domaines Maths '!E49,0) -> 0 | F45: =IF('Items sous domaines Maths '!H49=1,'Items sous domaines Maths '!F49,0) -> 0
B46: =IF('Items sous domaines Maths '!H50=1,'Items sous domaines Maths '!B50,0) -> 0 | C46: =IF('Items sous domaines Maths '!H50=1,'Items sous domaines Maths '!C50,0) -> 0 | D46: =IF('Items sous domaines Maths '!H50=1,'Items sous domaines Maths '!D50,0) -> 0 | E46: =IF('Items sous domaines Maths '!H50=1,'Items sous domaines Maths '!E50,0) -> 0 | F46: =IF('Items sous domaines Maths '!H50=1,'Items sous domaines Maths '!F50,0) -> 0
B47: =IF('Items sous domaines Maths '!H51=1,'Items sous domaines Maths '!B51,0) -> 0 | C47: =IF('Items sous domaines Maths '!H51=1,'Items sous domaines Maths '!C51,0) -> 0 | D47: =IF('Items sous domaines Maths '!H51=1,'Items sous domaines Maths '!D51,0) -> 0 | E47: =IF('Items sous domaines Maths '!H51=1,'Items sous domaines Maths '!E51,0) -> 0 | F47: =IF('Items sous domaines Maths '!H51=1,'Items sous domaines Maths '!F51,0) -> 0
B48: =IF('Items sous domaines Maths '!H52=1,'Items sous domaines Maths '!B52,0) -> 0 | C48: =IF('Items sous domaines Maths '!H52=1,'Items sous domaines Maths '!C52,0) -> 0 | D48: =IF('Items sous domaines Maths '!H52=1,'Items sous domaines Maths '!D52,0) -> 0 | E48: =IF('Items sous domaines Maths '!H52=1,'Items sous domaines Maths '!E52,0) -> 0 | F48: =IF('Items sous domaines Maths '!H52=1,'Items sous domaines Maths '!F52,0) -> 0
... B52: =IF('Items sous domaines Maths '!H56=1,'Items sous domaines Maths '!B56,0) -> 0 | C52: =IF('Items sous domaines Maths '!H56=1,'Items sous domaines Maths '!C56,0) -> 0 | D52: =IF('Items sous domaines Maths '!H56=1,'Items sous domaines Maths '!D56,0) -> 0 | E52: =IF('Items sous domaines Maths '!H56=1,'Items sous domaines Maths '!E56,0) -> 0 | F52: =IF('Items sous domaines Maths '!H56=1,'Items sous domaines Maths '!F56,0) -> 0
B53: =IF('Items sous domaines Maths '!H57=1,'Items sous domaines Maths '!B57,0) -> 0 | C53: =IF('Items sous domaines Maths '!H57=1,'Items sous domaines Maths '!C57,0) -> 0 | D53: =IF('Items sous domaines Maths '!H57=1,'Items sous domaines Maths '!D57,0) -> 0 | E53: =IF('Items sous domaines Maths '!H57=1,'Items sous domaines Maths '!E57,0) -> 0 | F53: =IF('Items sous domaines Maths '!H57=1,'Items sous domaines Maths '!F57,0) -> 0 | G53: =IF('Items sous domaines Maths '!H57=1,'Items sous domaines Maths '!G57,0) -> 0
B54: =IF('Items sous domaines Maths '!H58=1,'Items sous domaines Maths '!B58,0) -> 0 | C54: =IF('Items sous domaines Maths '!H58=1,'Items sous domaines Maths '!C58,0) -> 0 | D54: =IF('Items sous domaines Maths '!H58=1,'Items sous domaines Maths '!D58,0) -> 0 | E54: =IF('Items sous domaines Maths '!H58=1,'Items sous domaines Maths '!E58,0) -> 0 | F54: =IF('Items sous domaines Maths '!H58=1,'Items sous domaines Maths '!F58,0) -> 0 | G54: =IF('Items sous domaines Maths '!H58=1,'Items sous domaines Maths '!G58,0) -> 0
B55: =IF('Items sous domaines Maths '!H59=1,'Items sous domaines Maths '!B59,0) -> 0 | C55: =IF('Items sous domaines Maths '!H59=1,'Items sous domaines Maths '!C59,0) -> 0 | D55: =IF('Items sous domaines Maths '!H59=1,'Items sous domaines Maths '!D59,0) -> 0 | E55: =IF('Items sous domaines Maths '!H59=1,'Items sous domaines Maths '!E59,0) -> 0 | F55: =IF('Items sous domaines Maths '!H59=1,'Items sous domaines Maths '!F59,0) -> 0 | G55: =IF('Items sous domaines Maths '!H59=1,'Items sous domaines Maths '!G59,0) -> 0
B56: =IF('Items sous domaines Maths '!H60=1,'Items sous domaines Maths '!B60,0) -> 0 | C56: =IF('Items sous domaines Maths '!H60=1,'Items sous domaines Maths '!C60,0) -> 0 | D56: =IF('Items sous domaines Maths '!H60=1,'Items sous domaines Maths '!D60,0) -> 0 | E56: =IF('Items sous domaines Maths '!H60=1,'Items sous domaines Maths '!E60,0) -> 0 | F56: =IF('Items sous domaines Maths '!H60=1,'Items sous domaines Maths '!F60,0) -> 0 | G56: =IF('Items sous domaines Maths '!H60=1,'Items sous domaines Maths '!G60,0) -> 0
B57: =IF('Items sous domaines Maths '!H61=1,'Items sous domaines Maths '!B61,0) -> 0 | C57: =IF('Items sous domaines Maths '!H61=1,'Items sous domaines Maths '!C61,0) -> 0 | D57: =IF('Items sous domaines Maths '!H61=1,'Items sous domaines Maths '!D61,0) -> 0 | E57: =IF('Items sous domaines Maths '!H61=1,'Items sous domaines Maths '!E61,0) -> 0 | F57: =IF('Items sous domaines Maths '!H61=1,'Items sous domaines Maths '!F61,0) -> 0 | G57: =IF('Items sous domaines Maths '!H61=1,'Items sous domaines Maths '!G61,0) -> 0
B58: =IF('Items sous domaines Maths '!H62=1,'Items sous domaines Maths '!B62,0) -> 0 | C58: =IF('Items sous domaines Maths '!H62=1,'Items sous domaines Maths '!C62,0) -> 0 | D58: =IF('Items sous domaines Maths '!H62=1,'Items sous domaines Maths '!D62,0) -> 0 | E58: =IF('Items sous domaines Maths '!H62=1,'Items sous domaines Maths '!E62,0) -> 0 | F58: =IF('Items sous domaines Maths '!H62=1,'Items sous domaines Maths '!F62,0) -> 0 | G58: =IF('Items sous domaines Maths '!H62=1,'Items sous domaines Maths '!G62,0) -> 0
A59: Analyse : Interpolation, développement limité 0 | B59: =IF('Items sous domaines Maths '!H63=1,'Items sous domaines Maths '!B63,0) -> Algèbre | C59: =IF('Items sous domaines Maths '!H63=1,'Items sous domaines Maths '!C63,0) -> Les polynômes | D59: =IF('Items sous domaines Maths '!H63=1,'Items sous domaines Maths '!D63,0) -> Présentation de l'ensemble IK[X] | E59: =IF('Items sous domaines Maths '!H63=1,'Items sous domaines Maths '!E63,0) -> Degré | F59: =IF('Items sous domaines Maths '!H63=1,'Items sous domaines Maths '!F63,0) -> Savoir repérer le coefficient dominant, terme de plus haurt degré, polynôme nul, polynôme unitaire. | G59: ETS | H59: Développements limités (unisciel.fr)
B60: =IF('Items sous domaines Maths '!H64=1,'Items sous domaines Maths '!B64,0) -> Algèbre | C60: =IF('Items sous domaines Maths '!H64=1,'Items sous domaines Maths '!C64,0) -> Les polynômes | D60: =IF('Items sous domaines Maths '!H64=1,'Items sous domaines Maths '!D64,0) -> 0 | E60: =IF('Items sous domaines Maths '!H64=1,'Items sous domaines Maths '!E64,0) -> 0 | F60: =IF('Items sous domaines Maths '!H64=1,'Items sous domaines Maths '!F64,0) -> Savoir trouver le degré d'une somme, d'un produit, d'une composée.
B61: =IF('Items sous domaines Maths '!H65=1,'Items sous domaines Maths '!B65,0) -> Algèbre | C61: =IF('Items sous domaines Maths '!H65=1,'Items sous domaines Maths '!C65,0) -> Les polynômes | D61: =IF('Items sous domaines Maths '!H65=1,'Items sous domaines Maths '!D65,0) -> 0 | E61: =IF('Items sous domaines Maths '!H65=1,'Items sous domaines Maths '!E65,0) -> Opérations | F61: =IF('Items sous domaines Maths '!H65=1,'Items sous domaines Maths '!F65,0) -> Savoir effectuer la somme, produit, composée de deux polynômes.
B62: =IF('Items sous domaines Maths '!H66=1,'Items sous domaines Maths '!B66,0) -> Algèbre | C62: =IF('Items sous domaines Maths '!H66=1,'Items sous domaines Maths '!C66,0) -> Les polynômes | D62: =IF('Items sous domaines Maths '!H66=1,'Items sous domaines Maths '!D66,0) -> 0 | E62: =IF('Items sous domaines Maths '!H66=1,'Items sous domaines Maths '!E66,0) -> Divisibilité et division euclidienne dans IK[X] | F62: =IF('Items sous domaines Maths '!H66=1,'Items sous domaines Maths '!F66,0) -> Savoir effectuer une division posée suivant les puissances décroissantes, polynômes premiers entre eux.
B63: =IF('Items sous domaines Maths '!H67=1,'Items sous domaines Maths '!B67,0) -> Algèbre | C63: =IF('Items sous domaines Maths '!H67=1,'Items sous domaines Maths '!C67,0) -> Les polynômes | D63: =IF('Items sous domaines Maths '!H67=1,'Items sous domaines Maths '!D67,0) -> Dérivation des polynomes | E63: =IF('Items sous domaines Maths '!H67=1,'Items sous domaines Maths '!E67,0) -> Polynôme dérivé et degré | F63: =IF('Items sous domaines Maths '!H67=1,'Items sous domaines Maths '!F67,0) -> Connaître l'écriture du polynôme dérivé d'ordre 1 et d'ordres supérieurs. Connaître la formule de la dérivée du monôme de degré n pour tout n.
B64: =IF('Items sous domaines Maths '!H68=1,'Items sous domaines Maths '!B68,0) -> Algèbre | C64: =IF('Items sous domaines Maths '!H68=1,'Items sous domaines Maths '!C68,0) -> Les polynômes | D64: =IF('Items sous domaines Maths '!H68=1,'Items sous domaines Maths '!D68,0) -> 0 | E64: =IF('Items sous domaines Maths '!H68=1,'Items sous domaines Maths '!E68,0) -> 0 | F64: =IF('Items sous domaines Maths '!H68=1,'Items sous domaines Maths '!F68,0) -> Connaître la formule de Leibniz : savoir l'appliquer à la dérivation d'un produit de polynômes.
B65: =IF('Items sous domaines Maths '!H69=1,'Items sous domaines Maths '!B69,0) -> Algèbre | C65: =IF('Items sous domaines Maths '!H69=1,'Items sous domaines Maths '!C69,0) -> Les polynômes | D65: =IF('Items sous domaines Maths '!H69=1,'Items sous domaines Maths '!D69,0) -> 0 | E65: =IF('Items sous domaines Maths '!H69=1,'Items sous domaines Maths '!E69,0) -> Formules de Taylor | F65: =IF('Items sous domaines Maths '!H69=1,'Items sous domaines Maths '!F69,0) -> Savoir établir la formules de Taylor d'un polynôme, à un ordre n, en 0 et en a réel donné.
B66: =IF('Items sous domaines Maths '!H70=1,'Items sous domaines Maths '!B70,0) -> Algèbre | C66: =IF('Items sous domaines Maths '!H70=1,'Items sous domaines Maths '!C70,0) -> Les polynômes | D66: =IF('Items sous domaines Maths '!H70=1,'Items sous domaines Maths '!D70,0) -> Décomposition en facteurs irreductibles | E66: =IF('Items sous domaines Maths '!H70=1,'Items sous domaines Maths '!E70,0) -> Racines (ou zéros) d’un polynôme. | F66: =IF('Items sous domaines Maths '!H70=1,'Items sous domaines Maths '!F70,0) -> Connaître les techniques de détermination des racines d'un polynôme et les factorisations qui en découlent (polynômes d'ordre 2, 3 et plus).
B67: =IF('Items sous domaines Maths '!H71=1,'Items sous domaines Maths '!B71,0) -> Algèbre | C67: =IF('Items sous domaines Maths '!H71=1,'Items sous domaines Maths '!C71,0) -> Les polynômes | D67: =IF('Items sous domaines Maths '!H71=1,'Items sous domaines Maths '!D71,0) -> 0 | E67: =IF('Items sous domaines Maths '!H71=1,'Items sous domaines Maths '!E71,0) -> Multiplicité d’une racine. | F67: =IF('Items sous domaines Maths '!H71=1,'Items sous domaines Maths '!F71,0) -> Savoir caractériser l'ordre de multiplicité d'une racine par l'annulation des dérivées successives.
B68: =IF('Items sous domaines Maths '!H72=1,'Items sous domaines Maths '!B72,0) -> Algèbre | C68: =IF('Items sous domaines Maths '!H72=1,'Items sous domaines Maths '!C72,0) -> Les polynômes | D68: =IF('Items sous domaines Maths '!H72=1,'Items sous domaines Maths '!D72,0) -> 0 | E68: =IF('Items sous domaines Maths '!H72=1,'Items sous domaines Maths '!E72,0) -> 0 | F68: =IF('Items sous domaines Maths '!H72=1,'Items sous domaines Maths '!F72,0) -> Savoir que le nombre de racines d’un polynôme P non nul est majoré par le degré de P.
B69: =IF('Items sous domaines Maths '!H73=1,'Items sous domaines Maths '!B73,0) -> 0 | C69: =IF('Items sous domaines Maths '!H73=1,'Items sous domaines Maths '!C73,0) -> 0 | D69: =IF('Items sous domaines Maths '!H73=1,'Items sous domaines Maths '!D73,0) -> 0 | E69: =IF('Items sous domaines Maths '!H73=1,'Items sous domaines Maths '!E73,0) -> 0 | F69: =IF('Items sous domaines Maths '!H73=1,'Items sous domaines Maths '!F73,0) -> 0 | G69: =IF('Items sous domaines Maths '!H73=1,'Items sous domaines Maths '!G73,0) -> 0
B70: =IF('Items sous domaines Maths '!H74=1,'Items sous domaines Maths '!B74,0) -> 0 | C70: =IF('Items sous domaines Maths '!H74=1,'Items sous domaines Maths '!C74,0) -> 0 | D70: =IF('Items sous domaines Maths '!H74=1,'Items sous domaines Maths '!D74,0) -> 0 | E70: =IF('Items sous domaines Maths '!H74=1,'Items sous domaines Maths '!E74,0) -> 0 | F70: =IF('Items sous domaines Maths '!H74=1,'Items sous domaines Maths '!F74,0) -> 0 | G70: =IF('Items sous domaines Maths '!H74=1,'Items sous domaines Maths '!G74,0) -> 0
B71: =IF('Items sous domaines Maths '!H75=1,'Items sous domaines Maths '!B75,0) -> 0 | C71: =IF('Items sous domaines Maths '!H75=1,'Items sous domaines Maths '!C75,0) -> 0 | D71: =IF('Items sous domaines Maths '!H75=1,'Items sous domaines Maths '!D75,0) -> 0 | E71: =IF('Items sous domaines Maths '!H75=1,'Items sous domaines Maths '!E75,0) -> 0 | F71: =IF('Items sous domaines Maths '!H75=1,'Items sous domaines Maths '!F75,0) -> 0 | G71: =IF('Items sous domaines Maths '!H75=1,'Items sous domaines Maths '!G75,0) -> 0
B72: =IF('Items sous domaines Maths '!H76=1,'Items sous domaines Maths '!B76,0) -> 0 | C72: =IF('Items sous domaines Maths '!H76=1,'Items sous domaines Maths '!C76,0) -> 0 | D72: =IF('Items sous domaines Maths '!H76=1,'Items sous domaines Maths '!D76,0) -> 0 | E72: =IF('Items sous domaines Maths '!H76=1,'Items sous domaines Maths '!E76,0) -> 0 | F72: =IF('Items sous domaines Maths '!H76=1,'Items sous domaines Maths '!F76,0) -> 0 | G72: =IF('Items sous domaines Maths '!H76=1,'Items sous domaines Maths '!G76,0) -> 0
B73: =IF('Items sous domaines Maths '!H77=1,'Items sous domaines Maths '!B77,0) -> 0 | C73: =IF('Items sous domaines Maths '!H77=1,'Items sous domaines Maths '!C77,0) -> 0 | D73: =IF('Items sous domaines Maths '!H77=1,'Items sous domaines Maths '!D77,0) -> 0 | E73: =IF('Items sous domaines Maths '!H77=1,'Items sous domaines Maths '!E77,0) -> 0 | F73: =IF('Items sous domaines Maths '!H77=1,'Items sous domaines Maths '!F77,0) -> 0 | G73: =IF('Items sous domaines Maths '!H77=1,'Items sous domaines Maths '!G77,0) -> 0
B74: =IF('Items sous domaines Maths '!H78=1,'Items sous domaines Maths '!B78,0) -> 0 | C74: =IF('Items sous domaines Maths '!H78=1,'Items sous domaines Maths '!C78,0) -> 0 | D74: =IF('Items sous domaines Maths '!H78=1,'Items sous domaines Maths '!D78,0) -> 0 | E74: =IF('Items sous domaines Maths '!H78=1,'Items sous domaines Maths '!E78,0) -> 0 | F74: =IF('Items sous domaines Maths '!H78=1,'Items sous domaines Maths '!F78,0) -> 0 | G74: =IF('Items sous domaines Maths '!H78=1,'Items sous domaines Maths '!G78,0) -> 0
B75: =IF('Items sous domaines Maths '!H79=1,'Items sous domaines Maths '!B79,0) -> 0 | C75: =IF('Items sous domaines Maths '!H79=1,'Items sous domaines Maths '!C79,0) -> 0 | D75: =IF('Items sous domaines Maths '!H79=1,'Items sous domaines Maths '!D79,0) -> 0 | E75: =IF('Items sous domaines Maths '!H79=1,'Items sous domaines Maths '!E79,0) -> 0 | F75: =IF('Items sous domaines Maths '!H79=1,'Items sous domaines Maths '!F79,0) -> 0 | G75: =IF('Items sous domaines Maths '!H79=1,'Items sous domaines Maths '!G79,0) -> 0
B76: =IF('Items sous domaines Maths '!H80=1,'Items sous domaines Maths '!B80,0) -> 0 | C76: =IF('Items sous domaines Maths '!H80=1,'Items sous domaines Maths '!C80,0) -> 0 | D76: =IF('Items sous domaines Maths '!H80=1,'Items sous domaines Maths '!D80,0) -> 0 | E76: =IF('Items sous domaines Maths '!H80=1,'Items sous domaines Maths '!E80,0) -> 0 | F76: =IF('Items sous domaines Maths '!H80=1,'Items sous domaines Maths '!F80,0) -> 0 | G76: =IF('Items sous domaines Maths '!H80=1,'Items sous domaines Maths '!G80,0) -> 0
B77: =IF('Items sous domaines Maths '!H81=1,'Items sous domaines Maths '!B81,0) -> 0 | C77: =IF('Items sous domaines Maths '!H81=1,'Items sous domaines Maths '!C81,0) -> 0 | D77: =IF('Items sous domaines Maths '!H81=1,'Items sous domaines Maths '!D81,0) -> 0 | E77: =IF('Items sous domaines Maths '!H81=1,'Items sous domaines Maths '!E81,0) -> 0 | F77: =IF('Items sous domaines Maths '!H81=1,'Items sous domaines Maths '!F81,0) -> 0 | G77: =IF('Items sous domaines Maths '!H81=1,'Items sous domaines Maths '!G81,0) -> 0
B78: =IF('Items sous domaines Maths '!H82=1,'Items sous domaines Maths '!B82,0) -> 0 | C78: =IF('Items sous domaines Maths '!H82=1,'Items sous domaines Maths '!C82,0) -> 0 | D78: =IF('Items sous domaines Maths '!H82=1,'Items sous domaines Maths '!D82,0) -> 0 | E78: =IF('Items sous domaines Maths '!H82=1,'Items sous domaines Maths '!E82,0) -> 0 | F78: =IF('Items sous domaines Maths '!H82=1,'Items sous domaines Maths '!F82,0) -> 0 | G78: =IF('Items sous domaines Maths '!H82=1,'Items sous domaines Maths '!G82,0) -> 0
B79: =IF('Items sous domaines Maths '!H83=1,'Items sous domaines Maths '!B83,0) -> 0 | C79: =IF('Items sous domaines Maths '!H83=1,'Items sous domaines Maths '!C83,0) -> 0 | D79: =IF('Items sous domaines Maths '!H83=1,'Items sous domaines Maths '!D83,0) -> 0 | E79: =IF('Items sous domaines Maths '!H83=1,'Items sous domaines Maths '!E83,0) -> 0 | F79: =IF('Items sous domaines Maths '!H83=1,'Items sous domaines Maths '!F83,0) -> 0 | G79: =IF('Items sous domaines Maths '!H83=1,'Items sous domaines Maths '!G83,0) -> 0
B80: =IF('Items sous domaines Maths '!H84=1,'Items sous domaines Maths '!B84,0) -> 0 | C80: =IF('Items sous domaines Maths '!H84=1,'Items sous domaines Maths '!C84,0) -> 0 | D80: =IF('Items sous domaines Maths '!H84=1,'Items sous domaines Maths '!D84,0) -> 0 | E80: =IF('Items sous domaines Maths '!H84=1,'Items sous domaines Maths '!E84,0) -> 0 | F80: =IF('Items sous domaines Maths '!H84=1,'Items sous domaines Maths '!F84,0) -> 0 | G80: =IF('Items sous domaines Maths '!H84=1,'Items sous domaines Maths '!G84,0) -> 0
... B84: =IF('Items sous domaines Maths '!H88=1,'Items sous domaines Maths '!B88,0) -> 0 | C84: =IF('Items sous domaines Maths '!H88=1,'Items sous domaines Maths '!C88,0) -> 0 | D84: =IF('Items sous domaines Maths '!H88=1,'Items sous domaines Maths '!D88,0) -> 0 | E84: =IF('Items sous domaines Maths '!H88=1,'Items sous domaines Maths '!E88,0) -> 0 | F84: =IF('Items sous domaines Maths '!H88=1,'Items sous domaines Maths '!F88,0) -> 0 | G84: =IF('Items sous domaines Maths '!H88=1,'Items sous domaines Maths '!G88,0) -> 0
A85: Algèbre : Matrices et système | B85: =IF('Items sous domaines Maths '!H89=1,'Items sous domaines Maths '!B89,0) -> 0 | C85: =IF('Items sous domaines Maths '!H89=1,'Items sous domaines Maths '!C89,0) -> 0 | D85: =IF('Items sous domaines Maths '!H89=1,'Items sous domaines Maths '!D89,0) -> 0 | E85: =IF('Items sous domaines Maths '!H89=1,'Items sous domaines Maths '!E89,0) -> 0 | F85: =IF('Items sous domaines Maths '!H89=1,'Items sous domaines Maths '!F89,0) -> 0 | G85: ETS | H85: Calcul matriciel (unisciel.fr)
B86: =IF('Items sous domaines Maths '!H90=1,'Items sous domaines Maths '!B90,0) -> 0 | C86: =IF('Items sous domaines Maths '!H90=1,'Items sous domaines Maths '!C90,0) -> 0 | D86: =IF('Items sous domaines Maths '!H90=1,'Items sous domaines Maths '!D90,0) -> 0 | E86: =IF('Items sous domaines Maths '!H90=1,'Items sous domaines Maths '!E90,0) -> 0 | F86: =IF('Items sous domaines Maths '!H90=1,'Items sous domaines Maths '!F90,0) -> 0
B87: =IF('Items sous domaines Maths '!H91=1,'Items sous domaines Maths '!B91,0) -> 0 | C87: =IF('Items sous domaines Maths '!H91=1,'Items sous domaines Maths '!C91,0) -> 0 | D87: =IF('Items sous domaines Maths '!H91=1,'Items sous domaines Maths '!D91,0) -> 0 | E87: =IF('Items sous domaines Maths '!H91=1,'Items sous domaines Maths '!E91,0) -> 0 | F87: =IF('Items sous domaines Maths '!H91=1,'Items sous domaines Maths '!F91,0) -> 0
B88: =IF('Items sous domaines Maths '!H92=1,'Items sous domaines Maths '!B92,0) -> 0 | C88: =IF('Items sous domaines Maths '!H92=1,'Items sous domaines Maths '!C92,0) -> 0 | D88: =IF('Items sous domaines Maths '!H92=1,'Items sous domaines Maths '!D92,0) -> 0 | E88: =IF('Items sous domaines Maths '!H92=1,'Items sous domaines Maths '!E92,0) -> 0 | F88: =IF('Items sous domaines Maths '!H92=1,'Items sous domaines Maths '!F92,0) -> 0
B89: =IF('Items sous domaines Maths '!H93=1,'Items sous domaines Maths '!B93,0) -> 0 | C89: =IF('Items sous domaines Maths '!H93=1,'Items sous domaines Maths '!C93,0) -> 0 | D89: =IF('Items sous domaines Maths '!H93=1,'Items sous domaines Maths '!D93,0) -> 0 | E89: =IF('Items sous domaines Maths '!H93=1,'Items sous domaines Maths '!E93,0) -> 0 | F89: =IF('Items sous domaines Maths '!H93=1,'Items sous domaines Maths '!F93,0) -> 0
B90: =IF('Items sous domaines Maths '!H94=1,'Items sous domaines Maths '!B94,0) -> 0 | C90: =IF('Items sous domaines Maths '!H94=1,'Items sous domaines Maths '!C94,0) -> 0 | D90: =IF('Items sous domaines Maths '!H94=1,'Items sous domaines Maths '!D94,0) -> 0 | E90: =IF('Items sous domaines Maths '!H94=1,'Items sous domaines Maths '!E94,0) -> 0 | F90: =IF('Items sous domaines Maths '!H94=1,'Items sous domaines Maths '!F94,0) -> 0
B91: =IF('Items sous domaines Maths '!H95=1,'Items sous domaines Maths '!B95,0) -> 0 | C91: =IF('Items sous domaines Maths '!H95=1,'Items sous domaines Maths '!C95,0) -> 0 | D91: =IF('Items sous domaines Maths '!H95=1,'Items sous domaines Maths '!D95,0) -> 0 | E91: =IF('Items sous domaines Maths '!H95=1,'Items sous domaines Maths '!E95,0) -> 0 | F91: =IF('Items sous domaines Maths '!H95=1,'Items sous domaines Maths '!F95,0) -> 0
B92: =IF('Items sous domaines Maths '!H96=1,'Items sous domaines Maths '!B96,0) -> 0 | C92: =IF('Items sous domaines Maths '!H96=1,'Items sous domaines Maths '!C96,0) -> 0 | D92: =IF('Items sous domaines Maths '!H96=1,'Items sous domaines Maths '!D96,0) -> 0 | E92: =IF('Items sous domaines Maths '!H96=1,'Items sous domaines Maths '!E96,0) -> 0 | F92: =IF('Items sous domaines Maths '!H96=1,'Items sous domaines Maths '!F96,0) -> 0
B93: =IF('Items sous domaines Maths '!H97=1,'Items sous domaines Maths '!B97,0) -> 0 | C93: =IF('Items sous domaines Maths '!H97=1,'Items sous domaines Maths '!C97,0) -> 0 | D93: =IF('Items sous domaines Maths '!H97=1,'Items sous domaines Maths '!D97,0) -> 0 | E93: =IF('Items sous domaines Maths '!H97=1,'Items sous domaines Maths '!E97,0) -> 0 | F93: =IF('Items sous domaines Maths '!H97=1,'Items sous domaines Maths '!F97,0) -> 0
B94: =IF('Items sous domaines Maths '!H98=1,'Items sous domaines Maths '!B98,0) -> 0 | C94: =IF('Items sous domaines Maths '!H98=1,'Items sous domaines Maths '!C98,0) -> 0 | D94: =IF('Items sous domaines Maths '!H98=1,'Items sous domaines Maths '!D98,0) -> 0 | E94: =IF('Items sous domaines Maths '!H98=1,'Items sous domaines Maths '!E98,0) -> 0 | F94: =IF('Items sous domaines Maths '!H98=1,'Items sous domaines Maths '!F98,0) -> 0
B95: =IF('Items sous domaines Maths '!H99=1,'Items sous domaines Maths '!B99,0) -> 0 | C95: =IF('Items sous domaines Maths '!H99=1,'Items sous domaines Maths '!C99,0) -> 0 | D95: =IF('Items sous domaines Maths '!H99=1,'Items sous domaines Maths '!D99,0) -> 0 | E95: =IF('Items sous domaines Maths '!H99=1,'Items sous domaines Maths '!E99,0) -> 0 | F95: =IF('Items sous domaines Maths '!H99=1,'Items sous domaines Maths '!F99,0) -> 0
B96: =IF('Items sous domaines Maths '!H100=1,'Items sous domaines Maths '!B100,0) -> 0 | C96: =IF('Items sous domaines Maths '!H100=1,'Items sous domaines Maths '!C100,0) -> 0 | D96: =IF('Items sous domaines Maths '!H100=1,'Items sous domaines Maths '!D100,0) -> 0 | E96: =IF('Items sous domaines Maths '!H100=1,'Items sous domaines Maths '!E100,0) -> 0 | F96: =IF('Items sous domaines Maths '!H100=1,'Items sous domaines Maths '!F100,0) -> 0
B97: =IF('Items sous domaines Maths '!H101=1,'Items sous domaines Maths '!B101,0) -> 0 | C97: =IF('Items sous domaines Maths '!H101=1,'Items sous domaines Maths '!C101,0) -> 0 | D97: =IF('Items sous domaines Maths '!H101=1,'Items sous domaines Maths '!D101,0) -> 0 | E97: =IF('Items sous domaines Maths '!H101=1,'Items sous domaines Maths '!E101,0) -> 0 | F97: =IF('Items sous domaines Maths '!H101=1,'Items sous domaines Maths '!F101,0) -> 0 | I97: lien1
B98: =IF('Items sous domaines Maths '!H102=1,'Items sous domaines Maths '!B102,0) -> 0 | C98: =IF('Items sous domaines Maths '!H102=1,'Items sous domaines Maths '!C102,0) -> 0 | D98: =IF('Items sous domaines Maths '!H102=1,'Items sous domaines Maths '!D102,0) -> 0 | E98: =IF('Items sous domaines Maths '!H102=1,'Items sous domaines Maths '!E102,0) -> 0 | F98: =IF('Items sous domaines Maths '!H102=1,'Items sous domaines Maths '!F102,0) -> 0
B99: =IF('Items sous domaines Maths '!H103=1,'Items sous domaines Maths '!B103,0) -> 0 | C99: =IF('Items sous domaines Maths '!H103=1,'Items sous domaines Maths '!C103,0) -> 0 | D99: =IF('Items sous domaines Maths '!H103=1,'Items sous domaines Maths '!D103,0) -> 0 | E99: =IF('Items sous domaines Maths '!H103=1,'Items sous domaines Maths '!E103,0) -> 0 | F99: =IF('Items sous domaines Maths '!H103=1,'Items sous domaines Maths '!F103,0) -> 0
B100: =IF('Items sous domaines Maths '!H104=1,'Items sous domaines Maths '!B104,0) -> 0 | C100: =IF('Items sous domaines Maths '!H104=1,'Items sous domaines Maths '!C104,0) -> 0 | D100: =IF('Items sous domaines Maths '!H104=1,'Items sous domaines Maths '!D104,0) -> 0 | E100: =IF('Items sous domaines Maths '!H104=1,'Items sous domaines Maths '!E104,0) -> 0 | F100: =IF('Items sous domaines Maths '!H104=1,'Items sous domaines Maths '!F104,0) -> 0 | I100: lien2
B101: =IF('Items sous domaines Maths '!H105=1,'Items sous domaines Maths '!B105,0) -> 0 | C101: =IF('Items sous domaines Maths '!H105=1,'Items sous domaines Maths '!C105,0) -> 0 | D101: =IF('Items sous domaines Maths '!H105=1,'Items sous domaines Maths '!D105,0) -> 0 | E101: =IF('Items sous domaines Maths '!H105=1,'Items sous domaines Maths '!E105,0) -> 0 | F101: =IF('Items sous domaines Maths '!H105=1,'Items sous domaines Maths '!F105,0) -> 0
B102: =IF('Items sous domaines Maths '!H106=1,'Items sous domaines Maths '!B106,0) -> 0 | C102: =IF('Items sous domaines Maths '!H106=1,'Items sous domaines Maths '!C106,0) -> 0 | D102: =IF('Items sous domaines Maths '!H106=1,'Items sous domaines Maths '!D106,0) -> 0 | E102: =IF('Items sous domaines Maths '!H106=1,'Items sous domaines Maths '!E106,0) -> 0 | F102: =IF('Items sous domaines Maths '!H106=1,'Items sous domaines Maths '!F106,0) -> 0
B103: =IF('Items sous domaines Maths '!H107=1,'Items sous domaines Maths '!B107,0) -> 0 | C103: =IF('Items sous domaines Maths '!H107=1,'Items sous domaines Maths '!C107,0) -> 0 | D103: =IF('Items sous domaines Maths '!H107=1,'Items sous domaines Maths '!D107,0) -> 0 | E103: =IF('Items sous domaines Maths '!H107=1,'Items sous domaines Maths '!E107,0) -> 0 | F103: =IF('Items sous domaines Maths '!H107=1,'Items sous domaines Maths '!F107,0) -> 0
B104: =IF('Items sous domaines Maths '!H108=1,'Items sous domaines Maths '!B108,0) -> 0 | C104: =IF('Items sous domaines Maths '!H108=1,'Items sous domaines Maths '!C108,0) -> 0 | D104: =IF('Items sous domaines Maths '!H108=1,'Items sous domaines Maths '!D108,0) -> 0 | E104: =IF('Items sous domaines Maths '!H108=1,'Items sous domaines Maths '!E108,0) -> 0 | F104: =IF('Items sous domaines Maths '!H108=1,'Items sous domaines Maths '!F108,0) -> 0
B105: =IF('Items sous domaines Maths '!H109=1,'Items sous domaines Maths '!B109,0) -> 0 | C105: =IF('Items sous domaines Maths '!H109=1,'Items sous domaines Maths '!C109,0) -> 0 | D105: =IF('Items sous domaines Maths '!H109=1,'Items sous domaines Maths '!D109,0) -> 0 | E105: =IF('Items sous domaines Maths '!H109=1,'Items sous domaines Maths '!E109,0) -> 0 | F105: =IF('Items sous domaines Maths '!H109=1,'Items sous domaines Maths '!F109,0) -> 0 | G105: =IF('Items sous domaines Maths '!H109=1,'Items sous domaines Maths '!G109,0) -> 0
B106: =IF('Items sous domaines Maths '!H110=1,'Items sous domaines Maths '!B110,0) -> 0 | C106: =IF('Items sous domaines Maths '!H110=1,'Items sous domaines Maths '!C110,0) -> 0 | D106: =IF('Items sous domaines Maths '!H110=1,'Items sous domaines Maths '!D110,0) -> 0 | E106: =IF('Items sous domaines Maths '!H110=1,'Items sous domaines Maths '!E110,0) -> 0 | F106: =IF('Items sous domaines Maths '!H110=1,'Items sous domaines Maths '!F110,0) -> 0 | G106: =IF('Items sous domaines Maths '!H110=1,'Items sous domaines Maths '!G110,0) -> 0
B107: =IF('Items sous domaines Maths '!H111=1,'Items sous domaines Maths '!B111,0) -> 0 | C107: =IF('Items sous domaines Maths '!H111=1,'Items sous domaines Maths '!C111,0) -> 0 | D107: =IF('Items sous domaines Maths '!H111=1,'Items sous domaines Maths '!D111,0) -> 0 | E107: =IF('Items sous domaines Maths '!H111=1,'Items sous domaines Maths '!E111,0) -> 0 | F107: =IF('Items sous domaines Maths '!H111=1,'Items sous domaines Maths '!F111,0) -> 0 | G107: =IF('Items sous domaines Maths '!H111=1,'Items sous domaines Maths '!G111,0) -> 0
B108: =IF('Items sous domaines Maths '!H112=1,'Items sous domaines Maths '!B112,0) -> 0 | C108: =IF('Items sous domaines Maths '!H112=1,'Items sous domaines Maths '!C112,0) -> 0 | D108: =IF('Items sous domaines Maths '!H112=1,'Items sous domaines Maths '!D112,0) -> 0 | E108: =IF('Items sous domaines Maths '!H112=1,'Items sous domaines Maths '!E112,0) -> 0 | F108: =IF('Items sous domaines Maths '!H112=1,'Items sous domaines Maths '!F112,0) -> 0 | G108: =IF('Items sous domaines Maths '!H112=1,'Items sous domaines Maths '!G112,0) -> 0
...

Sheet A1 CPI S2
A1: Objectifs d'apprentissage des Mathématiques
A2: Notions à maîtriser en CPI A1 S2 (+onglet A1 CPI S1)
A3: ='A1 CPI S1'!A3 -> EE du DS | B3: ='A1 CPI S1'!B3 -> Domaine | C3: ='A1 CPI S1'!C3 -> Discipline | D3: ='A1 CPI S1'!D3 -> Chapitres | E3: ='A1 CPI S1'!E3 -> Thèmes | F3: ='A1 CPI S1'!F3 -> Détail des chapitres | G3: Utilisation
A4: Algèbre : Nombres complexes, arithmétique | B4: =IF('Items sous domaines Maths '!H8=2,'Items sous domaines Maths '!B8,0) -> 0 | C4: =IF('Items sous domaines Maths '!H8=2,'Items sous domaines Maths '!C8) -> FALSE | D4: =IF('Items sous domaines Maths '!H8=2,'Items sous domaines Maths '!D8,0) -> 0 | E4: =IF('Items sous domaines Maths '!H8=2,'Items sous domaines Maths '!E8,0) -> 0 | F4: =IF('Items sous domaines Maths '!H8=2,'Items sous domaines Maths '!F8,0) -> 0 | G4: =IF('Items sous domaines Maths '!H8=2,'Items sous domaines Maths '!G8,0) -> 0
B5: =IF('Items sous domaines Maths '!H9=2,'Items sous domaines Maths '!B9,0) -> 0 | C5: =IF('Items sous domaines Maths '!H9=2,'Items sous domaines Maths '!C9) -> FALSE | D5: =IF('Items sous domaines Maths '!H9=2,'Items sous domaines Maths '!D9,0) -> 0 | E5: =IF('Items sous domaines Maths '!H9=2,'Items sous domaines Maths '!E9,0) -> 0 | F5: =IF('Items sous domaines Maths '!H9=2,'Items sous domaines Maths '!F9,0) -> 0 | G5: =IF('Items sous domaines Maths '!H9=2,'Items sous domaines Maths '!G9,0) -> 0
B6: =IF('Items sous domaines Maths '!H10=2,'Items sous domaines Maths '!B10,0) -> 0 | C6: =IF('Items sous domaines Maths '!H10=2,'Items sous domaines Maths '!C10) -> FALSE | D6: =IF('Items sous domaines Maths '!H10=2,'Items sous domaines Maths '!D10,0) -> 0 | E6: =IF('Items sous domaines Maths '!H10=2,'Items sous domaines Maths '!E10,0) -> 0 | F6: =IF('Items sous domaines Maths '!H10=2,'Items sous domaines Maths '!F10,0) -> 0 | G6: =IF('Items sous domaines Maths '!H10=2,'Items sous domaines Maths '!G10,0) -> 0
A7: Algèbre : arithmétique | B7: =IF('Items sous domaines Maths '!H11=2,'Items sous domaines Maths '!B11,0) -> 0 | C7: =IF('Items sous domaines Maths '!H11=2,'Items sous domaines Maths '!C11) -> FALSE | D7: =IF('Items sous domaines Maths '!H11=2,'Items sous domaines Maths '!D11,0) -> 0 | E7: =IF('Items sous domaines Maths '!H11=2,'Items sous domaines Maths '!E11,0) -> 0 | F7: =IF('Items sous domaines Maths '!H11=2,'Items sous domaines Maths '!F11,0) -> 0 | G7: ETS | H7: https://uel.unisciel.fr/mathematiques/arithmetique/arithmetique/co/arithmetique.html | I7: lien1
B8: =IF('Items sous domaines Maths '!H12=2,'Items sous domaines Maths '!B12,0) -> 0 | C8: =IF('Items sous domaines Maths '!H12=2,'Items sous domaines Maths '!C12) -> FALSE | D8: =IF('Items sous domaines Maths '!H12=2,'Items sous domaines Maths '!D12,0) -> 0 | E8: =IF('Items sous domaines Maths '!H12=2,'Items sous domaines Maths '!E12,0) -> 0 | F8: =IF('Items sous domaines Maths '!H12=2,'Items sous domaines Maths '!F12,0) -> 0 | I8: lien2
B9: =IF('Items sous domaines Maths '!H13=2,'Items sous domaines Maths '!B13,0) -> 0 | C9: =IF('Items sous domaines Maths '!H13=2,'Items sous domaines Maths '!C13) -> FALSE | D9: =IF('Items sous domaines Maths '!H13=2,'Items sous domaines Maths '!D13,0) -> 0 | E9: =IF('Items sous domaines Maths '!H13=2,'Items sous domaines Maths '!E13,0) -> 0 | F9: =IF('Items sous domaines Maths '!H13=2,'Items sous domaines Maths '!F13,0) -> 0 | I9: lien 3
B10: =IF('Items sous domaines Maths '!H14=2,'Items sous domaines Maths '!B14,0) -> 0 | C10: =IF('Items sous domaines Maths '!H14=2,'Items sous domaines Maths '!C14) -> FALSE | D10: =IF('Items sous domaines Maths '!H14=2,'Items sous domaines Maths '!D14,0) -> 0 | E10: =IF('Items sous domaines Maths '!H14=2,'Items sous domaines Maths '!E14,0) -> 0 | F10: =IF('Items sous domaines Maths '!H14=2,'Items sous domaines Maths '!F14,0) -> 0
B11: =IF('Items sous domaines Maths '!H15=2,'Items sous domaines Maths '!B15,0) -> 0 | C11: =IF('Items sous domaines Maths '!H15=2,'Items sous domaines Maths '!C15) -> FALSE | D11: =IF('Items sous domaines Maths '!H15=2,'Items sous domaines Maths '!D15,0) -> 0 | E11: =IF('Items sous domaines Maths '!H15=2,'Items sous domaines Maths '!E15,0) -> 0 | F11: =IF('Items sous domaines Maths '!H15=2,'Items sous domaines Maths '!F15,0) -> 0 | G11: =IF('Items sous domaines Maths '!H15=2,'Items sous domaines Maths '!G15,0) -> 0
B12: =IF('Items sous domaines Maths '!H16=2,'Items sous domaines Maths '!B16,0) -> 0 | C12: =IF('Items sous domaines Maths '!H16=2,'Items sous domaines Maths '!C16) -> FALSE | D12: =IF('Items sous domaines Maths '!H16=2,'Items sous domaines Maths '!D16,0) -> 0 | E12: =IF('Items sous domaines Maths '!H16=2,'Items sous domaines Maths '!E16,0) -> 0 | F12: =IF('Items sous domaines Maths '!H16=2,'Items sous domaines Maths '!F16,0) -> 0 | G12: =IF('Items sous domaines Maths '!H16=2,'Items sous domaines Maths '!G16,0) -> 0
B13: =IF('Items sous domaines Maths '!H17=2,'Items sous domaines Maths '!B17,0) -> 0 | C13: =IF('Items sous domaines Maths '!H17=2,'Items sous domaines Maths '!C17) -> FALSE | D13: =IF('Items sous domaines Maths '!H17=2,'Items sous domaines Maths '!D17,0) -> 0 | E13: =IF('Items sous domaines Maths '!H17=2,'Items sous domaines Maths '!E17,0) -> 0 | F13: =IF('Items sous domaines Maths '!H17=2,'Items sous domaines Maths '!F17,0) -> 0 | G13: =IF('Items sous domaines Maths '!H17=2,'Items sous domaines Maths '!G17,0) -> 0
B14: =IF('Items sous domaines Maths '!H18=2,'Items sous domaines Maths '!B18,0) -> 0 | C14: =IF('Items sous domaines Maths '!H18=2,'Items sous domaines Maths '!C18) -> FALSE | D14: =IF('Items sous domaines Maths '!H18=2,'Items sous domaines Maths '!D18,0) -> 0 | E14: =IF('Items sous domaines Maths '!H18=2,'Items sous domaines Maths '!E18,0) -> 0 | F14: =IF('Items sous domaines Maths '!H18=2,'Items sous domaines Maths '!F18,0) -> 0 | G14: =IF('Items sous domaines Maths '!H18=2,'Items sous domaines Maths '!G18,0) -> 0
B15: =IF('Items sous domaines Maths '!H19=2,'Items sous domaines Maths '!B19,0) -> 0 | C15: =IF('Items sous domaines Maths '!H19=2,'Items sous domaines Maths '!C19) -> FALSE | D15: =IF('Items sous domaines Maths '!H19=2,'Items sous domaines Maths '!D19,0) -> 0 | E15: =IF('Items sous domaines Maths '!H19=2,'Items sous domaines Maths '!E19,0) -> 0 | F15: =IF('Items sous domaines Maths '!H19=2,'Items sous domaines Maths '!F19,0) -> 0 | G15: =IF('Items sous domaines Maths '!H19=2,'Items sous domaines Maths '!G19,0) -> 0
B16: =IF('Items sous domaines Maths '!H20=2,'Items sous domaines Maths '!B20,0) -> 0 | C16: =IF('Items sous domaines Maths '!H20=2,'Items sous domaines Maths '!C20) -> FALSE | D16: =IF('Items sous domaines Maths '!H20=2,'Items sous domaines Maths '!D20,0) -> 0 | E16: =IF('Items sous domaines Maths '!H20=2,'Items sous domaines Maths '!E20,0) -> 0 | F16: =IF('Items sous domaines Maths '!H20=2,'Items sous domaines Maths '!F20,0) -> 0 | G16: =IF('Items sous domaines Maths '!H20=2,'Items sous domaines Maths '!G20,0) -> 0
B17: =IF('Items sous domaines Maths '!H21=2,'Items sous domaines Maths '!B21,0) -> 0 | C17: =IF('Items sous domaines Maths '!H21=2,'Items sous domaines Maths '!C21) -> FALSE | D17: =IF('Items sous domaines Maths '!H21=2,'Items sous domaines Maths '!D21,0) -> 0 | E17: =IF('Items sous domaines Maths '!H21=2,'Items sous domaines Maths '!E21,0) -> 0 | F17: =IF('Items sous domaines Maths '!H21=2,'Items sous domaines Maths '!F21,0) -> 0 | G17: =IF('Items sous domaines Maths '!H21=2,'Items sous domaines Maths '!G21,0) -> 0
B18: =IF('Items sous domaines Maths '!H22=2,'Items sous domaines Maths '!B22,0) -> 0 | C18: =IF('Items sous domaines Maths '!H22=2,'Items sous domaines Maths '!C22) -> FALSE | D18: =IF('Items sous domaines Maths '!H22=2,'Items sous domaines Maths '!D22,0) -> 0 | E18: =IF('Items sous domaines Maths '!H22=2,'Items sous domaines Maths '!E22,0) -> 0 | F18: =IF('Items sous domaines Maths '!H22=2,'Items sous domaines Maths '!F22,0) -> 0 | G18: =IF('Items sous domaines Maths '!H22=2,'Items sous domaines Maths '!G22,0) -> 0
B19: =IF('Items sous domaines Maths '!H23=2,'Items sous domaines Maths '!B23,0) -> 0 | C19: =IF('Items sous domaines Maths '!H23=2,'Items sous domaines Maths '!C23) -> FALSE | D19: =IF('Items sous domaines Maths '!H23=2,'Items sous domaines Maths '!D23,0) -> 0 | E19: =IF('Items sous domaines Maths '!H23=2,'Items sous domaines Maths '!E23,0) -> 0 | F19: =IF('Items sous domaines Maths '!H23=2,'Items sous domaines Maths '!F23,0) -> 0 | G19: =IF('Items sous domaines Maths '!H23=2,'Items sous domaines Maths '!G23,0) -> 0
B20: =IF('Items sous domaines Maths '!H24=2,'Items sous domaines Maths '!B24,0) -> 0 | C20: =IF('Items sous domaines Maths '!H24=2,'Items sous domaines Maths '!C24) -> FALSE | D20: =IF('Items sous domaines Maths '!H24=2,'Items sous domaines Maths '!D24,0) -> 0 | E20: =IF('Items sous domaines Maths '!H24=2,'Items sous domaines Maths '!E24,0) -> 0 | F20: =IF('Items sous domaines Maths '!H24=2,'Items sous domaines Maths '!F24,0) -> 0 | G20: =IF('Items sous domaines Maths '!H24=2,'Items sous domaines Maths '!G24,0) -> 0
B21: =IF('Items sous domaines Maths '!H25=2,'Items sous domaines Maths '!B25,0) -> 0 | C21: =IF('Items sous domaines Maths '!H25=2,'Items sous domaines Maths '!C25) -> FALSE | D21: =IF('Items sous domaines Maths '!H25=2,'Items sous domaines Maths '!D25,0) -> 0 | E21: =IF('Items sous domaines Maths '!H25=2,'Items sous domaines Maths '!E25,0) -> 0 | F21: =IF('Items sous domaines Maths '!H25=2,'Items sous domaines Maths '!F25,0) -> 0 | G21: =IF('Items sous domaines Maths '!H25=2,'Items sous domaines Maths '!G25,0) -> 0
B22: =IF('Items sous domaines Maths '!H26=2,'Items sous domaines Maths '!B26,0) -> 0 | C22: =IF('Items sous domaines Maths '!H26=2,'Items sous domaines Maths '!C26) -> FALSE | D22: =IF('Items sous domaines Maths '!H26=2,'Items sous domaines Maths '!D26,0) -> 0 | E22: =IF('Items sous domaines Maths '!H26=2,'Items sous domaines Maths '!E26,0) -> 0 | F22: =IF('Items sous domaines Maths '!H26=2,'Items sous domaines Maths '!F26,0) -> 0 | G22: =IF('Items sous domaines Maths '!H26=2,'Items sous domaines Maths '!G26,0) -> 0
... B25: =IF('Items sous domaines Maths '!H29=2,'Items sous domaines Maths '!B29,0) -> 0 | C25: =IF('Items sous domaines Maths '!H29=2,'Items sous domaines Maths '!C29) -> FALSE | D25: =IF('Items sous domaines Maths '!H29=2,'Items sous domaines Maths '!D29,0) -> 0 | E25: =IF('Items sous domaines Maths '!H29=2,'Items sous domaines Maths '!E29,0) -> 0 | F25: =IF('Items sous domaines Maths '!H29=2,'Items sous domaines Maths '!F29,0) -> 0 | G25: =IF('Items sous domaines Maths '!H29=2,'Items sous domaines Maths '!G29,0) -> 0
A26: Théorie des ensembles | B26: =IF('Items sous domaines Maths '!H30=2,'Items sous domaines Maths '!B30,0) -> 0 | C26: =IF('Items sous domaines Maths '!H30=2,'Items sous domaines Maths '!C30) -> FALSE | D26: =IF('Items sous domaines Maths '!H30=2,'Items sous domaines Maths '!D30,0) -> 0 | E26: =IF('Items sous domaines Maths '!H30=2,'Items sous domaines Maths '!E30,0) -> 0 | F26: =IF('Items sous domaines Maths '!H30=2,'Items sous domaines Maths '!F30,0) -> 0 | G26: Projet BDD
B27: =IF('Items sous domaines Maths '!H31=2,'Items sous domaines Maths '!B31,0) -> 0 | C27: =IF('Items sous domaines Maths '!H31=2,'Items sous domaines Maths '!C31) -> FALSE | D27: =IF('Items sous domaines Maths '!H31=2,'Items sous domaines Maths '!D31,0) -> 0 | E27: =IF('Items sous domaines Maths '!H31=2,'Items sous domaines Maths '!E31,0) -> 0 | F27: =IF('Items sous domaines Maths '!H31=2,'Items sous domaines Maths '!F31,0) -> 0
B28: =IF('Items sous domaines Maths '!H32=2,'Items sous domaines Maths '!B32,0) -> 0 | C28: =IF('Items sous domaines Maths '!H32=2,'Items sous domaines Maths '!C32) -> FALSE | D28: =IF('Items sous domaines Maths '!H32=2,'Items sous domaines Maths '!D32,0) -> 0 | E28: =IF('Items sous domaines Maths '!H32=2,'Items sous domaines Maths '!E32,0) -> 0 | F28: =IF('Items sous domaines Maths '!H32=2,'Items sous domaines Maths '!F32,0) -> 0 | G28: =IF('Items sous domaines Maths '!H32=2,'Items sous domaines Maths '!G32,0) -> 0
B29: =IF('Items sous domaines Maths '!H33=2,'Items sous domaines Maths '!B33,0) -> 0 | C29: =IF('Items sous domaines Maths '!H33=2,'Items sous domaines Maths '!C33) -> FALSE | D29: =IF('Items sous domaines Maths '!H33=2,'Items sous domaines Maths '!D33,0) -> 0 | E29: =IF('Items sous domaines Maths '!H33=2,'Items sous domaines Maths '!E33,0) -> 0 | F29: =IF('Items sous domaines Maths '!H33=2,'Items sous domaines Maths '!F33,0) -> 0 | G29: =IF('Items sous domaines Maths '!H33=2,'Items sous domaines Maths '!G33,0) -> 0
B30: =IF('Items sous domaines Maths '!H34=2,'Items sous domaines Maths '!B34,0) -> 0 | C30: =IF('Items sous domaines Maths '!H34=2,'Items sous domaines Maths '!C34) -> FALSE | D30: =IF('Items sous domaines Maths '!H34=2,'Items sous domaines Maths '!D34,0) -> 0 | E30: =IF('Items sous domaines Maths '!H34=2,'Items sous domaines Maths '!E34,0) -> 0 | F30: =IF('Items sous domaines Maths '!H34=2,'Items sous domaines Maths '!F34,0) -> 0 | G30: =IF('Items sous domaines Maths '!H34=2,'Items sous domaines Maths '!G34,0) -> 0
B31: =IF('Items sous domaines Maths '!H35=2,'Items sous domaines Maths '!B35,0) -> 0 | C31: =IF('Items sous domaines Maths '!H35=2,'Items sous domaines Maths '!C35) -> FALSE | D31: =IF('Items sous domaines Maths '!H35=2,'Items sous domaines Maths '!D35,0) -> 0 | E31: =IF('Items sous domaines Maths '!H35=2,'Items sous domaines Maths '!E35,0) -> 0 | F31: =IF('Items sous domaines Maths '!H35=2,'Items sous domaines Maths '!F35,0) -> 0 | G31: =IF('Items sous domaines Maths '!H35=2,'Items sous domaines Maths '!G35,0) -> 0
B32: =IF('Items sous domaines Maths '!H36=2,'Items sous domaines Maths '!B36,0) -> 0 | C32: =IF('Items sous domaines Maths '!H36=2,'Items sous domaines Maths '!C36) -> FALSE | D32: =IF('Items sous domaines Maths '!H36=2,'Items sous domaines Maths '!D36,0) -> 0 | E32: =IF('Items sous domaines Maths '!H36=2,'Items sous domaines Maths '!E36,0) -> 0 | F32: =IF('Items sous domaines Maths '!H36=2,'Items sous domaines Maths '!F36,0) -> 0 | G32: =IF('Items sous domaines Maths '!H36=2,'Items sous domaines Maths '!G36,0) -> 0
B33: =IF('Items sous domaines Maths '!H37=2,'Items sous domaines Maths '!B37,0) -> 0 | C33: =IF('Items sous domaines Maths '!H37=2,'Items sous domaines Maths '!C37) -> FALSE | D33: =IF('Items sous domaines Maths '!H37=2,'Items sous domaines Maths '!D37,0) -> 0 | E33: =IF('Items sous domaines Maths '!H37=2,'Items sous domaines Maths '!E37,0) -> 0 | F33: =IF('Items sous domaines Maths '!H37=2,'Items sous domaines Maths '!F37,0) -> 0 | G33: =IF('Items sous domaines Maths '!H37=2,'Items sous domaines Maths '!G37,0) -> 0
B34: =IF('Items sous domaines Maths '!H38=2,'Items sous domaines Maths '!B38,0) -> 0 | C34: =IF('Items sous domaines Maths '!H38=2,'Items sous domaines Maths '!C38) -> FALSE | D34: =IF('Items sous domaines Maths '!H38=2,'Items sous domaines Maths '!D38,0) -> 0 | E34: =IF('Items sous domaines Maths '!H38=2,'Items sous domaines Maths '!E38,0) -> 0 | F34: =IF('Items sous domaines Maths '!H38=2,'Items sous domaines Maths '!F38,0) -> 0 | G34: =IF('Items sous domaines Maths '!H38=2,'Items sous domaines Maths '!G38,0) -> 0
B35: =IF('Items sous domaines Maths '!H39=2,'Items sous domaines Maths '!B39,0) -> 0 | C35: =IF('Items sous domaines Maths '!H39=2,'Items sous domaines Maths '!C39) -> FALSE | D35: =IF('Items sous domaines Maths '!H39=2,'Items sous domaines Maths '!D39,0) -> 0 | E35: =IF('Items sous domaines Maths '!H39=2,'Items sous domaines Maths '!E39,0) -> 0 | F35: =IF('Items sous domaines Maths '!H39=2,'Items sous domaines Maths '!F39,0) -> 0 | G35: =IF('Items sous domaines Maths '!H39=2,'Items sous domaines Maths '!G39,0) -> 0
A36: Algèbre : Nombres complexes | B36: =IF('Items sous domaines Maths '!H40=2,'Items sous domaines Maths '!B40,0) -> Algèbre | C36: =IF('Items sous domaines Maths '!H40=2,'Items sous domaines Maths '!C40) -> Les nombres complexes | D36: =IF('Items sous domaines Maths '!H40=2,'Items sous domaines Maths '!D40,0) -> Définition et écriture algébrique des nombres complexes | E36: =IF('Items sous domaines Maths '!H40=2,'Items sous domaines Maths '!E40,0) -> Définition | F36: =IF('Items sous domaines Maths '!H40=2,'Items sous domaines Maths '!F40,0) -> Connaître l'écriture algébrique, la partie réelle et imaginaire d'un nombre complexe | G36: =IF('Items sous domaines Maths '!H40=2,'Items sous domaines Maths '!G40,0) -> 0
B37: =IF('Items sous domaines Maths '!H41=2,'Items sous domaines Maths '!B41,0) -> Algèbre | C37: =IF('Items sous domaines Maths '!H41=2,'Items sous domaines Maths '!C41) -> Les nombres complexes | D37: =IF('Items sous domaines Maths '!H41=2,'Items sous domaines Maths '!D41,0) -> 0 | E37: =IF('Items sous domaines Maths '!H41=2,'Items sous domaines Maths '!E41,0) -> 0 | F37: =IF('Items sous domaines Maths '!H41=2,'Items sous domaines Maths '!F41,0) -> Savoir faire des opérations sur les nombres complexes. | G37: =IF('Items sous domaines Maths '!H41=2,'Items sous domaines Maths '!G41,0) -> 0
B38: =IF('Items sous domaines Maths '!H42=2,'Items sous domaines Maths '!B42,0) -> Algèbre | C38: =IF('Items sous domaines Maths '!H42=2,'Items sous domaines Maths '!C42) -> Les nombres complexes | D38: =IF('Items sous domaines Maths '!H42=2,'Items sous domaines Maths '!D42,0) -> 0 | E38: =IF('Items sous domaines Maths '!H42=2,'Items sous domaines Maths '!E42,0) -> 0 | F38: =IF('Items sous domaines Maths '!H42=2,'Items sous domaines Maths '!F42,0) -> Connaître et savoir calculer le conjugué d'un nombre complexe. Connaître les propriétés du conjugué et son utilité dans l'écriture des fractions complexes sous forme algébrique. | G38: =IF('Items sous domaines Maths '!H42=2,'Items sous domaines Maths '!G42,0) -> 0
B39: =IF('Items sous domaines Maths '!H43=2,'Items sous domaines Maths '!B43,0) -> Algèbre | C39: =IF('Items sous domaines Maths '!H43=2,'Items sous domaines Maths '!C43) -> Les nombres complexes | D39: =IF('Items sous domaines Maths '!H43=2,'Items sous domaines Maths '!D43,0) -> 0 | E39: =IF('Items sous domaines Maths '!H43=2,'Items sous domaines Maths '!E43,0) -> 0 | F39: =IF('Items sous domaines Maths '!H43=2,'Items sous domaines Maths '!F43,0) -> Savoir associer un point du plan à un nombre complexe, affixe d’un point du plan, affixe d’un vecteur du plan (dentifier C au plan usuel muni d’un repère orthonormé direct) | G39: =IF('Items sous domaines Maths '!H43=2,'Items sous domaines Maths '!G43,0) -> 0
B40: =IF('Items sous domaines Maths '!H44=2,'Items sous domaines Maths '!B44,0) -> Algèbre | C40: =IF('Items sous domaines Maths '!H44=2,'Items sous domaines Maths '!C44) -> Les nombres complexes | D40: =IF('Items sous domaines Maths '!H44=2,'Items sous domaines Maths '!D44,0) -> 0 | E40: =IF('Items sous domaines Maths '!H44=2,'Items sous domaines Maths '!E44,0) -> Module d’un nombre complexe | F40: =IF('Items sous domaines Maths '!H44=2,'Items sous domaines Maths '!F44,0) -> Savoir calculer un module d'un nombre complexe. | G40: =IF('Items sous domaines Maths '!H44=2,'Items sous domaines Maths '!G44,0) -> 0
B41: =IF('Items sous domaines Maths '!H45=2,'Items sous domaines Maths '!B45,0) -> Algèbre | C41: =IF('Items sous domaines Maths '!H45=2,'Items sous domaines Maths '!C45) -> Les nombres complexes | D41: =IF('Items sous domaines Maths '!H45=2,'Items sous domaines Maths '!D45,0) -> 0 | E41: =IF('Items sous domaines Maths '!H45=2,'Items sous domaines Maths '!E45,0) -> 0 | F41: =IF('Items sous domaines Maths '!H45=2,'Items sous domaines Maths '!F45,0) -> Connaître l'interprétation géométrique d'un module et repérer les images des affixes de même module. | G41: =IF('Items sous domaines Maths '!H45=2,'Items sous domaines Maths '!G45,0) -> 0
B42: =IF('Items sous domaines Maths '!H46=2,'Items sous domaines Maths '!B46,0) -> Algèbre | C42: =IF('Items sous domaines Maths '!H46=2,'Items sous domaines Maths '!C46) -> Les nombres complexes | D42: =IF('Items sous domaines Maths '!H46=2,'Items sous domaines Maths '!D46,0) -> 0 | E42: =IF('Items sous domaines Maths '!H46=2,'Items sous domaines Maths '!E46,0) -> 0 | F42: =IF('Items sous domaines Maths '!H46=2,'Items sous domaines Maths '!F46,0) -> Savoir calculer le module d’un produit, d’un quotient. | G42: =IF('Items sous domaines Maths '!H46=2,'Items sous domaines Maths '!G46,0) -> 0
B43: =IF('Items sous domaines Maths '!H47=2,'Items sous domaines Maths '!B47,0) -> Algèbre | C43: =IF('Items sous domaines Maths '!H47=2,'Items sous domaines Maths '!C47) -> Les nombres complexes | D43: =IF('Items sous domaines Maths '!H47=2,'Items sous domaines Maths '!D47,0) -> 0 | E43: =IF('Items sous domaines Maths '!H47=2,'Items sous domaines Maths '!E47,0) -> 0 | F43: =IF('Items sous domaines Maths '!H47=2,'Items sous domaines Maths '!F47,0) -> Savoir résoudre des équations du type |z-zA|=|z-zB| et |z-zA|=R > 0 | G43: =IF('Items sous domaines Maths '!H47=2,'Items sous domaines Maths '!G47,0) -> 0
B44: =IF('Items sous domaines Maths '!H48=2,'Items sous domaines Maths '!B48,0) -> Algèbre | C44: =IF('Items sous domaines Maths '!H48=2,'Items sous domaines Maths '!C48) -> Les nombres complexes | D44: =IF('Items sous domaines Maths '!H48=2,'Items sous domaines Maths '!D48,0) -> Forme trigonométrique et exponentielle d'un nombre complexe | E44: =IF('Items sous domaines Maths '!H48=2,'Items sous domaines Maths '!E48,0) -> Argument d'un nombre complexe et forme trigonometrique | F44: =IF('Items sous domaines Maths '!H48=2,'Items sous domaines Maths '!F48,0) -> Connaître le cercle trigonométrique. Savoir repérer un point du cercle avec les fonctions circulaires sinus et cosinus. Connaître les formules des angles associés, cos(a±b), sin(a±b), cos(2a), sin(2a), | G44: =IF('Items sous domaines Maths '!H48=2,'Items sous domaines Maths '!G48,0) -> 0
B45: =IF('Items sous domaines Maths '!H49=2,'Items sous domaines Maths '!B49,0) -> Algèbre | C45: =IF('Items sous domaines Maths '!H49=2,'Items sous domaines Maths '!C49) -> Les nombres complexes | D45: =IF('Items sous domaines Maths '!H49=2,'Items sous domaines Maths '!D49,0) -> 0 | E45: =IF('Items sous domaines Maths '!H49=2,'Items sous domaines Maths '!E49,0) -> 0 | F45: =IF('Items sous domaines Maths '!H49=2,'Items sous domaines Maths '!F49,0) -> Savoir calculer l'argument d'un nombre complexe à partir de sa forme algébrique et connaître l'interprétation géométrique de l'argument. | G45: =IF('Items sous domaines Maths '!H49=2,'Items sous domaines Maths '!G49,0) -> 0
B46: =IF('Items sous domaines Maths '!H50=2,'Items sous domaines Maths '!B50,0) -> Algèbre | C46: =IF('Items sous domaines Maths '!H50=2,'Items sous domaines Maths '!C50) -> Les nombres complexes | D46: =IF('Items sous domaines Maths '!H50=2,'Items sous domaines Maths '!D50,0) -> 0 | E46: =IF('Items sous domaines Maths '!H50=2,'Items sous domaines Maths '!E50,0) -> 0 | F46: =IF('Items sous domaines Maths '!H50=2,'Items sous domaines Maths '!F50,0) -> Savoir calculer l'argument d’un produit, d’un quotient. | G46: =IF('Items sous domaines Maths '!H50=2,'Items sous domaines Maths '!G50,0) -> 0
B47: =IF('Items sous domaines Maths '!H51=2,'Items sous domaines Maths '!B51,0) -> Algèbre | C47: =IF('Items sous domaines Maths '!H51=2,'Items sous domaines Maths '!C51) -> Les nombres complexes | D47: =IF('Items sous domaines Maths '!H51=2,'Items sous domaines Maths '!D51,0) -> 0 | E47: =IF('Items sous domaines Maths '!H51=2,'Items sous domaines Maths '!E51,0) -> 0 | F47: =IF('Items sous domaines Maths '!H51=2,'Items sous domaines Maths '!F51,0) -> Savoir passer de la forme algébrique à la forme trigonométrique d'un nombre complexe. | G47: =IF('Items sous domaines Maths '!H51=2,'Items sous domaines Maths '!G51,0) -> 0
B48: =IF('Items sous domaines Maths '!H52=2,'Items sous domaines Maths '!B52,0) -> Algèbre | C48: =IF('Items sous domaines Maths '!H52=2,'Items sous domaines Maths '!C52) -> Les nombres complexes | D48: =IF('Items sous domaines Maths '!H52=2,'Items sous domaines Maths '!D52,0) -> 0 | E48: =IF('Items sous domaines Maths '!H52=2,'Items sous domaines Maths '!E52,0) -> Complexes de module 1 et forme exponentielle d'un nombre complexe | F48: =IF('Items sous domaines Maths '!H52=2,'Items sous domaines Maths '!F52,0) -> Définition de exp(it) pour t réel. | G48: =IF('Items sous domaines Maths '!H52=2,'Items sous domaines Maths '!G52,0) -> 0
... B52: =IF('Items sous domaines Maths '!H56=2,'Items sous domaines Maths '!B56,0) -> Algèbre | C52: =IF('Items sous domaines Maths '!H56=2,'Items sous domaines Maths '!C56) -> Les nombres complexes | D52: =IF('Items sous domaines Maths '!H56=2,'Items sous domaines Maths '!D56,0) -> Solutions complexes d'équations polynomiales | E52: =IF('Items sous domaines Maths '!H56=2,'Items sous domaines Maths '!E56,0) -> Equations du second degré | F52: =IF('Items sous domaines Maths '!H56=2,'Items sous domaines Maths '!F56,0) -> Connaître la méthode permettant de calculer les racines carrées d’un nombre complexe. | G52: =IF('Items sous domaines Maths '!H56=2,'Items sous domaines Maths '!G56,0) -> 0
B53: =IF('Items sous domaines Maths '!H57=2,'Items sous domaines Maths '!B57,0) -> Algèbre | C53: =IF('Items sous domaines Maths '!H57=2,'Items sous domaines Maths '!C57) -> Les nombres complexes | D53: =IF('Items sous domaines Maths '!H57=2,'Items sous domaines Maths '!D57,0) -> 0 | E53: =IF('Items sous domaines Maths '!H57=2,'Items sous domaines Maths '!E57,0) -> 0 | F53: =IF('Items sous domaines Maths '!H57=2,'Items sous domaines Maths '!F57,0) -> Savoir résudre les équations du second degré à coefficients complexes (discriminant complexe) | G53: ETS | H53: https://uel.unisciel.fr/physique/outils_nancy/outils_nancy_ch04/co/apprendre_ch04.html | I53: lien1 | J53: lien2
B54: =IF('Items sous domaines Maths '!H58=2,'Items sous domaines Maths '!B58,0) -> Algèbre | C54: =IF('Items sous domaines Maths '!H58=2,'Items sous domaines Maths '!C58) -> Les nombres complexes | D54: =IF('Items sous domaines Maths '!H58=2,'Items sous domaines Maths '!D58,0) -> 0 | E54: =IF('Items sous domaines Maths '!H58=2,'Items sous domaines Maths '!E58,0) -> Racines n-ièmes | F54: =IF('Items sous domaines Maths '!H58=2,'Items sous domaines Maths '!F58,0) -> Connaître la description des racines n-ièmes de l’unité et la représentation géometrique des solutions. | J54: lien 3
B55: =IF('Items sous domaines Maths '!H59=2,'Items sous domaines Maths '!B59,0) -> Algèbre | C55: =IF('Items sous domaines Maths '!H59=2,'Items sous domaines Maths '!C59) -> Les nombres complexes | D55: =IF('Items sous domaines Maths '!H59=2,'Items sous domaines Maths '!D59,0) -> 0 | E55: =IF('Items sous domaines Maths '!H59=2,'Items sous domaines Maths '!E59,0) -> 0 | F55: =IF('Items sous domaines Maths '!H59=2,'Items sous domaines Maths '!F59,0) -> Savoir résoudre les équations du type quation z ^n = a avec a complexe. | J55: lien 4
B56: =IF('Items sous domaines Maths '!H60=2,'Items sous domaines Maths '!B60,0) -> Algèbre | C56: =IF('Items sous domaines Maths '!H60=2,'Items sous domaines Maths '!C60) -> Les nombres complexes | D56: =IF('Items sous domaines Maths '!H60=2,'Items sous domaines Maths '!D60,0) -> Nombre complexes et géometrie plane | E56: =IF('Items sous domaines Maths '!H60=2,'Items sous domaines Maths '!E60,0) -> Traduction de l'aligenment et de l'orthogonlité. Transformations z→ ̅z et interpretation géometrique. | F56: =IF('Items sous domaines Maths '!H60=2,'Items sous domaines Maths '!F60,0) -> Savoir traduite l'alignement et l'orthogonalité à l'aide de l'argument
B57: =IF('Items sous domaines Maths '!H61=2,'Items sous domaines Maths '!B61,0) -> Algèbre | C57: =IF('Items sous domaines Maths '!H61=2,'Items sous domaines Maths '!C61) -> Les nombres complexes | D57: =IF('Items sous domaines Maths '!H61=2,'Items sous domaines Maths '!D61,0) -> 0 | E57: =IF('Items sous domaines Maths '!H61=2,'Items sous domaines Maths '!E61,0) -> Transformations classiques du plan : translation, rotation homothetie, similitude. | F57: =IF('Items sous domaines Maths '!H61=2,'Items sous domaines Maths '!F61,0) -> Savoir résoudre les équations du type quation z ^n = a avec a complexe.
B58: =IF('Items sous domaines Maths '!H62=2,'Items sous domaines Maths '!B62,0) -> 0 | C58: =IF('Items sous domaines Maths '!H62=2,'Items sous domaines Maths '!C62) -> FALSE | D58: =IF('Items sous domaines Maths '!H62=2,'Items sous domaines Maths '!D62,0) -> 0 | E58: =IF('Items sous domaines Maths '!H62=2,'Items sous domaines Maths '!E62,0) -> 0 | F58: =IF('Items sous domaines Maths '!H62=2,'Items sous domaines Maths '!F62,0) -> 0 | G58: =IF('Items sous domaines Maths '!H62=2,'Items sous domaines Maths '!G62,0) -> 0
A59: Analyse : Interpolation, développement limité 0 | B59: =IF('Items sous domaines Maths '!H63=2,'Items sous domaines Maths '!B63,0) -> 0 | C59: =IF('Items sous domaines Maths '!H63=2,'Items sous domaines Maths '!C63) -> FALSE | D59: =IF('Items sous domaines Maths '!H63=2,'Items sous domaines Maths '!D63,0) -> 0 | E59: =IF('Items sous domaines Maths '!H63=2,'Items sous domaines Maths '!E63,0) -> 0 | F59: =IF('Items sous domaines Maths '!H63=2,'Items sous domaines Maths '!F63,0) -> 0 | G59: =IF('Items sous domaines Maths '!H63=2,'Items sous domaines Maths '!G63,0) -> 0
B60: =IF('Items sous domaines Maths '!H64=2,'Items sous domaines Maths '!B64,0) -> 0 | C60: =IF('Items sous domaines Maths '!H64=2,'Items sous domaines Maths '!C64) -> FALSE | D60: =IF('Items sous domaines Maths '!H64=2,'Items sous domaines Maths '!D64,0) -> 0 | E60: =IF('Items sous domaines Maths '!H64=2,'Items sous domaines Maths '!E64,0) -> 0 | F60: =IF('Items sous domaines Maths '!H64=2,'Items sous domaines Maths '!F64,0) -> 0 | G60: =IF('Items sous domaines Maths '!H64=2,'Items sous domaines Maths '!G64,0) -> 0
B61: =IF('Items sous domaines Maths '!H65=2,'Items sous domaines Maths '!B65,0) -> 0 | C61: =IF('Items sous domaines Maths '!H65=2,'Items sous domaines Maths '!C65) -> FALSE | D61: =IF('Items sous domaines Maths '!H65=2,'Items sous domaines Maths '!D65,0) -> 0 | E61: =IF('Items sous domaines Maths '!H65=2,'Items sous domaines Maths '!E65,0) -> 0 | F61: =IF('Items sous domaines Maths '!H65=2,'Items sous domaines Maths '!F65,0) -> 0 | G61: =IF('Items sous domaines Maths '!H65=2,'Items sous domaines Maths '!G65,0) -> 0
B62: =IF('Items sous domaines Maths '!H66=2,'Items sous domaines Maths '!B66,0) -> 0 | C62: =IF('Items sous domaines Maths '!H66=2,'Items sous domaines Maths '!C66) -> FALSE | D62: =IF('Items sous domaines Maths '!H66=2,'Items sous domaines Maths '!D66,0) -> 0 | E62: =IF('Items sous domaines Maths '!H66=2,'Items sous domaines Maths '!E66,0) -> 0 | F62: =IF('Items sous domaines Maths '!H66=2,'Items sous domaines Maths '!F66,0) -> 0 | G62: =IF('Items sous domaines Maths '!H66=2,'Items sous domaines Maths '!G66,0) -> 0
B63: =IF('Items sous domaines Maths '!H67=2,'Items sous domaines Maths '!B67,0) -> 0 | C63: =IF('Items sous domaines Maths '!H67=2,'Items sous domaines Maths '!C67) -> FALSE | D63: =IF('Items sous domaines Maths '!H67=2,'Items sous domaines Maths '!D67,0) -> 0 | E63: =IF('Items sous domaines Maths '!H67=2,'Items sous domaines Maths '!E67,0) -> 0 | F63: =IF('Items sous domaines Maths '!H67=2,'Items sous domaines Maths '!F67,0) -> 0 | G63: =IF('Items sous domaines Maths '!H67=2,'Items sous domaines Maths '!G67,0) -> 0
B64: =IF('Items sous domaines Maths '!H68=2,'Items sous domaines Maths '!B68,0) -> 0 | C64: =IF('Items sous domaines Maths '!H68=2,'Items sous domaines Maths '!C68) -> FALSE | D64: =IF('Items sous domaines Maths '!H68=2,'Items sous domaines Maths '!D68,0) -> 0 | E64: =IF('Items sous domaines Maths '!H68=2,'Items sous domaines Maths '!E68,0) -> 0 | F64: =IF('Items sous domaines Maths '!H68=2,'Items sous domaines Maths '!F68,0) -> 0 | G64: =IF('Items sous domaines Maths '!H68=2,'Items sous domaines Maths '!G68,0) -> 0
B65: =IF('Items sous domaines Maths '!H69=2,'Items sous domaines Maths '!B69,0) -> 0 | C65: =IF('Items sous domaines Maths '!H69=2,'Items sous domaines Maths '!C69) -> FALSE | D65: =IF('Items sous domaines Maths '!H69=2,'Items sous domaines Maths '!D69,0) -> 0 | E65: =IF('Items sous domaines Maths '!H69=2,'Items sous domaines Maths '!E69,0) -> 0 | F65: =IF('Items sous domaines Maths '!H69=2,'Items sous domaines Maths '!F69,0) -> 0 | G65: =IF('Items sous domaines Maths '!H69=2,'Items sous domaines Maths '!G69,0) -> 0
B66: =IF('Items sous domaines Maths '!H70=2,'Items sous domaines Maths '!B70,0) -> 0 | C66: =IF('Items sous domaines Maths '!H70=2,'Items sous domaines Maths '!C70) -> FALSE | D66: =IF('Items sous domaines Maths '!H70=2,'Items sous domaines Maths '!D70,0) -> 0 | E66: =IF('Items sous domaines Maths '!H70=2,'Items sous domaines Maths '!E70,0) -> 0 | F66: =IF('Items sous domaines Maths '!H70=2,'Items sous domaines Maths '!F70,0) -> 0 | G66: =IF('Items sous domaines Maths '!H70=2,'Items sous domaines Maths '!G70,0) -> 0
B67: =IF('Items sous domaines Maths '!H71=2,'Items sous domaines Maths '!B71,0) -> 0 | C67: =IF('Items sous domaines Maths '!H71=2,'Items sous domaines Maths '!C71) -> FALSE | D67: =IF('Items sous domaines Maths '!H71=2,'Items sous domaines Maths '!D71,0) -> 0 | E67: =IF('Items sous domaines Maths '!H71=2,'Items sous domaines Maths '!E71,0) -> 0 | F67: =IF('Items sous domaines Maths '!H71=2,'Items sous domaines Maths '!F71,0) -> 0 | G67: =IF('Items sous domaines Maths '!H71=2,'Items sous domaines Maths '!G71,0) -> 0
B68: =IF('Items sous domaines Maths '!H72=2,'Items sous domaines Maths '!B72,0) -> 0 | C68: =IF('Items sous domaines Maths '!H72=2,'Items sous domaines Maths '!C72) -> FALSE | D68: =IF('Items sous domaines Maths '!H72=2,'Items sous domaines Maths '!D72,0) -> 0 | E68: =IF('Items sous domaines Maths '!H72=2,'Items sous domaines Maths '!E72,0) -> 0 | F68: =IF('Items sous domaines Maths '!H72=2,'Items sous domaines Maths '!F72,0) -> 0 | G68: =IF('Items sous domaines Maths '!H72=2,'Items sous domaines Maths '!G72,0) -> 0
B69: =IF('Items sous domaines Maths '!H73=2,'Items sous domaines Maths '!B73,0) -> 0 | C69: =IF('Items sous domaines Maths '!H73=2,'Items sous domaines Maths '!C73) -> FALSE | D69: =IF('Items sous domaines Maths '!H73=2,'Items sous domaines Maths '!D73,0) -> 0 | E69: =IF('Items sous domaines Maths '!H73=2,'Items sous domaines Maths '!E73,0) -> 0 | F69: =IF('Items sous domaines Maths '!H73=2,'Items sous domaines Maths '!F73,0) -> 0 | G69: =IF('Items sous domaines Maths '!H73=2,'Items sous domaines Maths '!G73,0) -> 0
B70: =IF('Items sous domaines Maths '!H74=2,'Items sous domaines Maths '!B74,0) -> 0 | C70: =IF('Items sous domaines Maths '!H74=2,'Items sous domaines Maths '!C74) -> FALSE | D70: =IF('Items sous domaines Maths '!H74=2,'Items sous domaines Maths '!D74,0) -> 0 | E70: =IF('Items sous domaines Maths '!H74=2,'Items sous domaines Maths '!E74,0) -> 0 | F70: =IF('Items sous domaines Maths '!H74=2,'Items sous domaines Maths '!F74,0) -> 0 | G70: =IF('Items sous domaines Maths '!H74=2,'Items sous domaines Maths '!G74,0) -> 0
B71: =IF('Items sous domaines Maths '!H75=2,'Items sous domaines Maths '!B75,0) -> 0 | C71: =IF('Items sous domaines Maths '!H75=2,'Items sous domaines Maths '!C75) -> FALSE | D71: =IF('Items sous domaines Maths '!H75=2,'Items sous domaines Maths '!D75,0) -> 0 | E71: =IF('Items sous domaines Maths '!H75=2,'Items sous domaines Maths '!E75,0) -> 0 | F71: =IF('Items sous domaines Maths '!H75=2,'Items sous domaines Maths '!F75,0) -> 0 | G71: =IF('Items sous domaines Maths '!H75=2,'Items sous domaines Maths '!G75,0) -> 0
... B84: =IF('Items sous domaines Maths '!H88=2,'Items sous domaines Maths '!B88,0) -> 0 | C84: =IF('Items sous domaines Maths '!H88=2,'Items sous domaines Maths '!C88) -> FALSE | D84: =IF('Items sous domaines Maths '!H88=2,'Items sous domaines Maths '!D88,0) -> 0 | E84: =IF('Items sous domaines Maths '!H88=2,'Items sous domaines Maths '!E88,0) -> 0 | F84: =IF('Items sous domaines Maths '!H88=2,'Items sous domaines Maths '!F88,0) -> 0 | G84: =IF('Items sous domaines Maths '!H88=2,'Items sous domaines Maths '!G88,0) -> 0
A85: Algèbre : Matrices et système | B85: =IF('Items sous domaines Maths '!H89=2,'Items sous domaines Maths '!B89,0) -> Algèbre | C85: =IF('Items sous domaines Maths '!H89=2,'Items sous domaines Maths '!C89) -> Les Matrices | D85: =IF('Items sous domaines Maths '!H89=2,'Items sous domaines Maths '!D89,0) -> 0 | E85: =IF('Items sous domaines Maths '!H89=2,'Items sous domaines Maths '!E89,0) -> Propriétés des opérations matricielles. | F85: =IF('Items sous domaines Maths '!H89=2,'Items sous domaines Maths '!F89,0) -> Savoir effectuer des opérations de type somme, produit par un scalaire produit de deux matrices. Savoir transposer un système en écriture matricielle. Savoir qu'il existe des matrices non nulles dont le produit est nul. | G85: =IF('Items sous domaines Maths '!H89=2,'Items sous domaines Maths '!G89,0) -> 0
B86: =IF('Items sous domaines Maths '!H90=2,'Items sous domaines Maths '!B90,0) -> 0 | C86: =IF('Items sous domaines Maths '!H90=2,'Items sous domaines Maths '!C90) -> FALSE | D86: =IF('Items sous domaines Maths '!H90=2,'Items sous domaines Maths '!D90,0) -> 0 | E86: =IF('Items sous domaines Maths '!H90=2,'Items sous domaines Maths '!E90,0) -> 0 | F86: =IF('Items sous domaines Maths '!H90=2,'Items sous domaines Maths '!F90,0) -> 0 | G86: =IF('Items sous domaines Maths '!H90=2,'Items sous domaines Maths '!G90,0) -> 0
B87: =IF('Items sous domaines Maths '!H91=2,'Items sous domaines Maths '!B91,0) -> 0 | C87: =IF('Items sous domaines Maths '!H91=2,'Items sous domaines Maths '!C91) -> FALSE | D87: =IF('Items sous domaines Maths '!H91=2,'Items sous domaines Maths '!D91,0) -> 0 | E87: =IF('Items sous domaines Maths '!H91=2,'Items sous domaines Maths '!E91,0) -> 0 | F87: =IF('Items sous domaines Maths '!H91=2,'Items sous domaines Maths '!F91,0) -> 0 | G87: =IF('Items sous domaines Maths '!H91=2,'Items sous domaines Maths '!G91,0) -> 0
B88: =IF('Items sous domaines Maths '!H92=2,'Items sous domaines Maths '!B92,0) -> 0 | C88: =IF('Items sous domaines Maths '!H92=2,'Items sous domaines Maths '!C92) -> FALSE | D88: =IF('Items sous domaines Maths '!H92=2,'Items sous domaines Maths '!D92,0) -> 0 | E88: =IF('Items sous domaines Maths '!H92=2,'Items sous domaines Maths '!E92,0) -> 0 | F88: =IF('Items sous domaines Maths '!H92=2,'Items sous domaines Maths '!F92,0) -> 0 | G88: =IF('Items sous domaines Maths '!H92=2,'Items sous domaines Maths '!G92,0) -> 0
B89: =IF('Items sous domaines Maths '!H93=2,'Items sous domaines Maths '!B93,0) -> 0 | C89: =IF('Items sous domaines Maths '!H93=2,'Items sous domaines Maths '!C93) -> FALSE | D89: =IF('Items sous domaines Maths '!H93=2,'Items sous domaines Maths '!D93,0) -> 0 | E89: =IF('Items sous domaines Maths '!H93=2,'Items sous domaines Maths '!E93,0) -> 0 | F89: =IF('Items sous domaines Maths '!H93=2,'Items sous domaines Maths '!F93,0) -> 0 | G89: =IF('Items sous domaines Maths '!H93=2,'Items sous domaines Maths '!G93,0) -> 0
B90: =IF('Items sous domaines Maths '!H94=2,'Items sous domaines Maths '!B94,0) -> 0 | C90: =IF('Items sous domaines Maths '!H94=2,'Items sous domaines Maths '!C94) -> FALSE | D90: =IF('Items sous domaines Maths '!H94=2,'Items sous domaines Maths '!D94,0) -> 0 | E90: =IF('Items sous domaines Maths '!H94=2,'Items sous domaines Maths '!E94,0) -> 0 | F90: =IF('Items sous domaines Maths '!H94=2,'Items sous domaines Maths '!F94,0) -> 0 | G90: =IF('Items sous domaines Maths '!H94=2,'Items sous domaines Maths '!G94,0) -> 0
B91: =IF('Items sous domaines Maths '!H95=2,'Items sous domaines Maths '!B95,0) -> Algèbre | C91: =IF('Items sous domaines Maths '!H95=2,'Items sous domaines Maths '!C95) -> Les Matrices | D91: =IF('Items sous domaines Maths '!H95=2,'Items sous domaines Maths '!D95,0) -> Determinant d'une matrice carrée | E91: =IF('Items sous domaines Maths '!H95=2,'Items sous domaines Maths '!E95,0) -> Définition, notation | F91: =IF('Items sous domaines Maths '!H95=2,'Items sous domaines Maths '!F95,0) -> Exemple de calcul du déterminant sur des matrices 2X2 et 3X3. Formule de calcul et Methodes de Sarrus. | G91: ETS | H91: Cours [Calcul matriciel] (unisciel.fr)
B92: =IF('Items sous domaines Maths '!H96=2,'Items sous domaines Maths '!B96,0) -> Algèbre | C92: =IF('Items sous domaines Maths '!H96=2,'Items sous domaines Maths '!C96) -> Les Matrices | D92: =IF('Items sous domaines Maths '!H96=2,'Items sous domaines Maths '!D96,0) -> 0 | E92: =IF('Items sous domaines Maths '!H96=2,'Items sous domaines Maths '!E96,0) -> Propriétés | F92: =IF('Items sous domaines Maths '!H96=2,'Items sous domaines Maths '!F96,0) -> Effet de la combinaison linéaire de deux lignes ou deux colones sur le calcul du déterminant. | I92: lien1
B93: =IF('Items sous domaines Maths '!H97=2,'Items sous domaines Maths '!B97,0) -> Algèbre | C93: =IF('Items sous domaines Maths '!H97=2,'Items sous domaines Maths '!C97) -> Les Matrices | D93: =IF('Items sous domaines Maths '!H97=2,'Items sous domaines Maths '!D97,0) -> 0 | E93: =IF('Items sous domaines Maths '!H97=2,'Items sous domaines Maths '!E97,0) -> 0 | F93: =IF('Items sous domaines Maths '!H97=2,'Items sous domaines Maths '!F97,0) -> Déterminant de la transposée.
B94: =IF('Items sous domaines Maths '!H98=2,'Items sous domaines Maths '!B98,0) -> Algèbre | C94: =IF('Items sous domaines Maths '!H98=2,'Items sous domaines Maths '!C98) -> Les Matrices | D94: =IF('Items sous domaines Maths '!H98=2,'Items sous domaines Maths '!D98,0) -> Matrices carrées inversibles | E94: =IF('Items sous domaines Maths '!H98=2,'Items sous domaines Maths '!E98,0) -> Définition, notation | F94: =IF('Items sous domaines Maths '!H98=2,'Items sous domaines Maths '!F98,0) -> Unicité de l'inverse quand elle existe.
B95: =IF('Items sous domaines Maths '!H99=2,'Items sous domaines Maths '!B99,0) -> Algèbre | C95: =IF('Items sous domaines Maths '!H99=2,'Items sous domaines Maths '!C99) -> Les Matrices | D95: =IF('Items sous domaines Maths '!H99=2,'Items sous domaines Maths '!D99,0) -> 0 | E95: =IF('Items sous domaines Maths '!H99=2,'Items sous domaines Maths '!E99,0) -> Propriétés | F95: =IF('Items sous domaines Maths '!H99=2,'Items sous domaines Maths '!F99,0) -> Inverses du produit, d'une puissance et de la transposée de matrices inversibles.
B96: =IF('Items sous domaines Maths '!H100=2,'Items sous domaines Maths '!B100,0) -> Algèbre | C96: =IF('Items sous domaines Maths '!H100=2,'Items sous domaines Maths '!C100) -> Les Matrices | D96: =IF('Items sous domaines Maths '!H100=2,'Items sous domaines Maths '!D100,0) -> 0 | E96: =IF('Items sous domaines Maths '!H100=2,'Items sous domaines Maths '!E100,0) -> 0 | F96: =IF('Items sous domaines Maths '!H100=2,'Items sous domaines Maths '!F100,0) -> Critère d'existence de l'inverse à l'aide du déterminant.
B97: =IF('Items sous domaines Maths '!H101=2,'Items sous domaines Maths '!B101,0) -> Algèbre | C97: =IF('Items sous domaines Maths '!H101=2,'Items sous domaines Maths '!C101) -> Les Matrices | D97: =IF('Items sous domaines Maths '!H101=2,'Items sous domaines Maths '!D101,0) -> 0 | E97: =IF('Items sous domaines Maths '!H101=2,'Items sous domaines Maths '!E101,0) -> 0 | F97: =IF('Items sous domaines Maths '!H101=2,'Items sous domaines Maths '!F101,0) -> Méthodes de calcul de l'inverse d'une matrice.
B98: =IF('Items sous domaines Maths '!H102=2,'Items sous domaines Maths '!B102,0) -> 0 | C98: =IF('Items sous domaines Maths '!H102=2,'Items sous domaines Maths '!C102) -> FALSE | D98: =IF('Items sous domaines Maths '!H102=2,'Items sous domaines Maths '!D102,0) -> 0 | E98: =IF('Items sous domaines Maths '!H102=2,'Items sous domaines Maths '!E102,0) -> 0 | F98: =IF('Items sous domaines Maths '!H102=2,'Items sous domaines Maths '!F102,0) -> 0
B99: =IF('Items sous domaines Maths '!H103=2,'Items sous domaines Maths '!B103,0) -> Algèbre | C99: =IF('Items sous domaines Maths '!H103=2,'Items sous domaines Maths '!C103) -> Les Systèmes | D99: =IF('Items sous domaines Maths '!H103=2,'Items sous domaines Maths '!D103,0) -> Définitions | E99: =IF('Items sous domaines Maths '!H103=2,'Items sous domaines Maths '!E103,0) -> Définition d'une équation linéaire | F99: =IF('Items sous domaines Maths '!H103=2,'Items sous domaines Maths '!F103,0) -> Savoir ce qu'est une équation linéaire et une combinaison linéaire.
B100: =IF('Items sous domaines Maths '!H104=2,'Items sous domaines Maths '!B104,0) -> Algèbre | C100: =IF('Items sous domaines Maths '!H104=2,'Items sous domaines Maths '!C104) -> Les Systèmes | D100: =IF('Items sous domaines Maths '!H104=2,'Items sous domaines Maths '!D104,0) -> 0 | E100: =IF('Items sous domaines Maths '!H104=2,'Items sous domaines Maths '!E104,0) -> Définition d'un système linéaire | F100: =IF('Items sous domaines Maths '!H104=2,'Items sous domaines Maths '!F104,0) -> Connaître l'interprétation géometrique : intersections de droites, de plans et les differents cas de figures possibles.
B101: =IF('Items sous domaines Maths '!H105=2,'Items sous domaines Maths '!B105,0) -> Algèbre | C101: =IF('Items sous domaines Maths '!H105=2,'Items sous domaines Maths '!C105) -> Les Systèmes | D101: =IF('Items sous domaines Maths '!H105=2,'Items sous domaines Maths '!D105,0) -> 0 | E101: =IF('Items sous domaines Maths '!H105=2,'Items sous domaines Maths '!E105,0) -> Matrice associée à un système | F101: =IF('Items sous domaines Maths '!H105=2,'Items sous domaines Maths '!F105,0) -> Savoir transposer un système en écriture matricielle.
B102: =IF('Items sous domaines Maths '!H106=2,'Items sous domaines Maths '!B106,0) -> Algèbre | C102: =IF('Items sous domaines Maths '!H106=2,'Items sous domaines Maths '!C106) -> Les Systèmes | D102: =IF('Items sous domaines Maths '!H106=2,'Items sous domaines Maths '!D106,0) -> 0 | E102: =IF('Items sous domaines Maths '!H106=2,'Items sous domaines Maths '!E106,0) -> Systèmes équivalents | F102: =IF('Items sous domaines Maths '!H106=2,'Items sous domaines Maths '!F106,0) -> Connaître les opérations élémentaires sur les lignes qui ne changent pas les solutions.
B103: =IF('Items sous domaines Maths '!H107=2,'Items sous domaines Maths '!B107,0) -> Algèbre | C103: =IF('Items sous domaines Maths '!H107=2,'Items sous domaines Maths '!C107) -> Les Systèmes | D103: =IF('Items sous domaines Maths '!H107=2,'Items sous domaines Maths '!D107,0) -> 0 | E103: =IF('Items sous domaines Maths '!H107=2,'Items sous domaines Maths '!E107,0) -> Algorithme de Gauss | F103: =IF('Items sous domaines Maths '!H107=2,'Items sous domaines Maths '!F107,0) -> Savoir ce qu'est un pivot.
B104: =IF('Items sous domaines Maths '!H108=2,'Items sous domaines Maths '!B108,0) -> Algèbre | C104: =IF('Items sous domaines Maths '!H108=2,'Items sous domaines Maths '!C108) -> Les Systèmes | D104: =IF('Items sous domaines Maths '!H108=2,'Items sous domaines Maths '!D108,0) -> Résolution d’un système linéaire | E104: =IF('Items sous domaines Maths '!H108=2,'Items sous domaines Maths '!E108,0) -> Résolution | F104: =IF('Items sous domaines Maths '!H108=2,'Items sous domaines Maths '!F108,0) -> Savoir appliquer l'algorithme de Gauss au système ainsi qu'en échelonnant la matrice.
... B107: =IF('Items sous domaines Maths '!H111=2,'Items sous domaines Maths '!B111,0) -> Algèbre | C107: =IF('Items sous domaines Maths '!H111=2,'Items sous domaines Maths '!C111) -> Les Systèmes | D107: =IF('Items sous domaines Maths '!H111=2,'Items sous domaines Maths '!D111,0) -> 0 | E107: =IF('Items sous domaines Maths '!H111=2,'Items sous domaines Maths '!E111,0) -> 0 | F107: =IF('Items sous domaines Maths '!H111=2,'Items sous domaines Maths '!F111,0) -> Savoir résoudre un système à l'aide de la matrice inverse.
B108: =IF('Items sous domaines Maths '!H112=2,'Items sous domaines Maths '!B112,0) -> 0 | C108: =IF('Items sous domaines Maths '!H112=2,'Items sous domaines Maths '!C112) -> FALSE | D108: =IF('Items sous domaines Maths '!H112=2,'Items sous domaines Maths '!D112,0) -> 0 | E108: =IF('Items sous domaines Maths '!H112=2,'Items sous domaines Maths '!E112,0) -> 0 | F108: =IF('Items sous domaines Maths '!H112=2,'Items sous domaines Maths '!F112,0) -> 0 | G108: =IF('Items sous domaines Maths '!H112=2,'Items sous domaines Maths '!G112,0) -> 0
A109: Algèbre : Graphes | B109: =IF('Items sous domaines Maths '!H113=2,'Items sous domaines Maths '!B113,0) -> Algèbre | C109: =IF('Items sous domaines Maths '!H113=2,'Items sous domaines Maths '!C113) -> La Théorie des graphes | D109: =IF('Items sous domaines Maths '!H113=2,'Items sous domaines Maths '!D113,0) -> Terminologie et définitions | E109: =IF('Items sous domaines Maths '!H113=2,'Items sous domaines Maths '!E113,0) -> Sommet, ordre, arete, graphe orienté, aretes adjacentes, degré d'un sommet | F109: =IF('Items sous domaines Maths '!H113=2,'Items sous domaines Maths '!F113,0) -> Connaître le vocabulaire spécifique à la théorie des graphes. | G109: =IF('Items sous domaines Maths '!H113=2,'Items sous domaines Maths '!G113,0) -> 0
B110: =IF('Items sous domaines Maths '!H114=2,'Items sous domaines Maths '!B114,0) -> Algèbre | C110: =IF('Items sous domaines Maths '!H114=2,'Items sous domaines Maths '!C114) -> La Théorie des graphes | D110: =IF('Items sous domaines Maths '!H114=2,'Items sous domaines Maths '!D114,0) -> 0 | E110: =IF('Items sous domaines Maths '!H114=2,'Items sous domaines Maths '!E114,0) -> Graphe complet | F110: =IF('Items sous domaines Maths '!H114=2,'Items sous domaines Maths '!F114,0) -> Savoir que la somme des degrés de tous les sommets d’un graphe est égal au double du nombre total d’arêtes. Savoir qu'un graphe complet est un graphe simple dont tous les sommets sont adjacents les uns avec les autres. | G110: =IF('Items sous domaines Maths '!H114=2,'Items sous domaines Maths '!G114,0) -> 0
B111: =IF('Items sous domaines Maths '!H115=2,'Items sous domaines Maths '!B115,0) -> Algèbre | C111: =IF('Items sous domaines Maths '!H115=2,'Items sous domaines Maths '!C115) -> La Théorie des graphes | D111: =IF('Items sous domaines Maths '!H115=2,'Items sous domaines Maths '!D115,0) -> 0 | E111: =IF('Items sous domaines Maths '!H115=2,'Items sous domaines Maths '!E115,0) -> Graphe orienté | F111: =IF('Items sous domaines Maths '!H115=2,'Items sous domaines Maths '!F115,0) -> 0 | G111: =IF('Items sous domaines Maths '!H115=2,'Items sous domaines Maths '!G115,0) -> 0
B112: =IF('Items sous domaines Maths '!H116=2,'Items sous domaines Maths '!B116,0) -> Algèbre | C112: =IF('Items sous domaines Maths '!H116=2,'Items sous domaines Maths '!C116) -> La Théorie des graphes | D112: =IF('Items sous domaines Maths '!H116=2,'Items sous domaines Maths '!D116,0) -> 0 | E112: =IF('Items sous domaines Maths '!H116=2,'Items sous domaines Maths '!E116,0) -> Matrice d'adjacence d'un graphe | F112: =IF('Items sous domaines Maths '!H116=2,'Items sous domaines Maths '!F116,0) -> Savoir établir la matrice d'adjacence d'un graphe dans le cas d'un graphe orienté et non orienté. | G112: =IF('Items sous domaines Maths '!H116=2,'Items sous domaines Maths '!G116,0) -> 0
B113: =IF('Items sous domaines Maths '!H117=2,'Items sous domaines Maths '!B117,0) -> Algèbre | C113: =IF('Items sous domaines Maths '!H117=2,'Items sous domaines Maths '!C117) -> La Théorie des graphes | D113: =IF('Items sous domaines Maths '!H117=2,'Items sous domaines Maths '!D117,0) -> Chaines et cycles | E113: =IF('Items sous domaines Maths '!H117=2,'Items sous domaines Maths '!E117,0) -> Terminologie | F113: =IF('Items sous domaines Maths '!H117=2,'Items sous domaines Maths '!F117,0) -> Connaître la caractérisation d'une chaîne, d'une chaîne orientée, ainsi que des cycles et graphes connexes. | G113: =IF('Items sous domaines Maths '!H117=2,'Items sous domaines Maths '!G117,0) -> 0
B114: =IF('Items sous domaines Maths '!H118=2,'Items sous domaines Maths '!B118,0) -> Algèbre | C114: =IF('Items sous domaines Maths '!H118=2,'Items sous domaines Maths '!C118) -> La Théorie des graphes | D114: =IF('Items sous domaines Maths '!H118=2,'Items sous domaines Maths '!D118,0) -> 0 | E114: =IF('Items sous domaines Maths '!H118=2,'Items sous domaines Maths '!E118,0) -> Chaines et Cycles eulériens | F114: =IF('Items sous domaines Maths '!H118=2,'Items sous domaines Maths '!F118,0) -> Savoir qu'un graphe connexe admet une chaîne eulérienne entre les sommets A et B si et seulement si A et B sont les seuls sommets de degré impair. Savoir qu'un graphe connexe admet un cycle eulérien si et seulement si tous les sommets sont de degré pair. Application à la "promenade de Königsberg" | G114: =IF('Items sous domaines Maths '!H118=2,'Items sous domaines Maths '!G118,0) -> 0
B115: =IF('Items sous domaines Maths '!H119=2,'Items sous domaines Maths '!B119,0) -> Algèbre | C115: =IF('Items sous domaines Maths '!H119=2,'Items sous domaines Maths '!C119) -> La Théorie des graphes | D115: =IF('Items sous domaines Maths '!H119=2,'Items sous domaines Maths '!D119,0) -> 0 | E115: =IF('Items sous domaines Maths '!H119=2,'Items sous domaines Maths '!E119,0) -> 0 | F115: =IF('Items sous domaines Maths '!H119=2,'Items sous domaines Maths '!F119,0) -> Savoir trouver le nombre de chaînes de longueur k entre 2 sommets on regarde M^k où M est la matrice d'adjacence du graphe. | G115: =IF('Items sous domaines Maths '!H119=2,'Items sous domaines Maths '!G119,0) -> 0
B116: =IF('Items sous domaines Maths '!H120=2,'Items sous domaines Maths '!B120,0) -> Algèbre | C116: =IF('Items sous domaines Maths '!H120=2,'Items sous domaines Maths '!C120) -> La Théorie des graphes | D116: =IF('Items sous domaines Maths '!H120=2,'Items sous domaines Maths '!D120,0) -> 0 | E116: =IF('Items sous domaines Maths '!H120=2,'Items sous domaines Maths '!E120,0) -> Chaines et Cycles hamiltoniens | F116: =IF('Items sous domaines Maths '!H120=2,'Items sous domaines Maths '!F120,0) -> Savoir qu'un chemin hamiltonien d'un graphe orienté ou non orienté est un chemin qui passe par tous les sommets une fois et une seule. Un cycle hamiltonien est un chemin hamiltonien qui est un cycle. Un graphe hamiltonien est un graphe qui possède un cycle hamiltonien. | G116: =IF('Items sous domaines Maths '!H120=2,'Items sous domaines Maths '!G120,0) -> 0
B117: =IF('Items sous domaines Maths '!H121=2,'Items sous domaines Maths '!B121,0) -> Algèbre | C117: =IF('Items sous domaines Maths '!H121=2,'Items sous domaines Maths '!C121) -> La Théorie des graphes | D117: =IF('Items sous domaines Maths '!H121=2,'Items sous domaines Maths '!D121,0) -> Application | E117: =IF('Items sous domaines Maths '!H121=2,'Items sous domaines Maths '!E121,0) -> Coloration d'un graphe | F117: =IF('Items sous domaines Maths '!H121=2,'Items sous domaines Maths '!F121,0) -> Comprendre le principe de coloration des graphes dans le but d'utiliser le nombre minimal de couleurs (coloration minimale). Comprendre le champ d'applications de la coloration de graphe. | G117: =IF('Items sous domaines Maths '!H121=2,'Items sous domaines Maths '!G121,0) -> 0
B118: =IF('Items sous domaines Maths '!H122=2,'Items sous domaines Maths '!B122,0) -> Algèbre | C118: =IF('Items sous domaines Maths '!H122=2,'Items sous domaines Maths '!C122) -> La Théorie des graphes | D118: =IF('Items sous domaines Maths '!H122=2,'Items sous domaines Maths '!D122,0) -> 0 | E118: =IF('Items sous domaines Maths '!H122=2,'Items sous domaines Maths '!E122,0) -> 0 | F118: =IF('Items sous domaines Maths '!H122=2,'Items sous domaines Maths '!F122,0) -> Savoir appliquer l'algorithme de coloration de Welsh et Powell. | G118: =IF('Items sous domaines Maths '!H122=2,'Items sous domaines Maths '!G122,0) -> 0
B119: =IF('Items sous domaines Maths '!H123=2,'Items sous domaines Maths '!B123,0) -> Algèbre | C119: =IF('Items sous domaines Maths '!H123=2,'Items sous domaines Maths '!C123) -> La Théorie des graphes | D119: =IF('Items sous domaines Maths '!H123=2,'Items sous domaines Maths '!D123,0) -> 0 | E119: =IF('Items sous domaines Maths '!H123=2,'Items sous domaines Maths '!E123,0) -> Graphes pondérés/valués | F119: =IF('Items sous domaines Maths '!H123=2,'Items sous domaines Maths '!F123,0) -> Savoir ce qu'est un graphe pondéré et être capable de modélier un énoncé avec cette représentation. | G119: =IF('Items sous domaines Maths '!H123=2,'Items sous domaines Maths '!G123,0) -> 0
...

Sheet A2 CPI S3 
A1: Objectifs d'apprentissage des Mathématiques
A2: Notions à maîtriser en A2 (en révisant le socle A1)
A3: ='A1 CPI S1'!A3 -> EE du DS | B3: ='A1 CPI S1'!B3 -> Domaine | C3: ='A1 CPI S1'!C3 -> Discipline | D3: ='A1 CPI S1'!D3 -> Chapitres | E3: ='A1 CPI S1'!E3 -> Thèmes | F3: ='A1 CPI S1'!F3 -> Détail des chapitres | G3: ='A1 CPI S1'!G3 -> Utilisation
A4: Mathématiques élémentaires | B4: =IF(OR('Items sous domaines Maths '!H8=3,'Items sous domaines Maths '!J8=3 ),'Items sous domaines Maths '!B8,0) -> 0 | C4: =IF(OR('Items sous domaines Maths '!H8=3,'Items sous domaines Maths '!J8=3 ),'Items sous domaines Maths '!C8) -> FALSE | D4: =IF(OR('Items sous domaines Maths '!H8=3,'Items sous domaines Maths '!J8=3 ),'Items sous domaines Maths '!D8,0) -> 0 | E4: =IF(OR('Items sous domaines Maths '!H8=3,'Items sous domaines Maths '!J8=3 ),'Items sous domaines Maths '!E8,0) -> 0 | F4: =IF(OR('Items sous domaines Maths '!H8=3,'Items sous domaines Maths '!J8=3 ),'Items sous domaines Maths '!F8,0) -> 0 | G4: =IF('Items sous domaines Maths '!H8=1,'Items sous domaines Maths '!G8,0) -> 0
B5: =IF(OR('Items sous domaines Maths '!H9=3,'Items sous domaines Maths '!J9=3 ),'Items sous domaines Maths '!B9,0) -> 0 | C5: =IF(OR('Items sous domaines Maths '!H9=3,'Items sous domaines Maths '!J9=3 ),'Items sous domaines Maths '!C9) -> FALSE | D5: =IF(OR('Items sous domaines Maths '!H9=3,'Items sous domaines Maths '!J9=3 ),'Items sous domaines Maths '!D9,0) -> 0 | E5: =IF(OR('Items sous domaines Maths '!H9=3,'Items sous domaines Maths '!J9=3 ),'Items sous domaines Maths '!E9,0) -> 0 | F5: =IF(OR('Items sous domaines Maths '!H9=3,'Items sous domaines Maths '!J9=3 ),'Items sous domaines Maths '!F9,0) -> 0 | G5: =IF('Items sous domaines Maths '!H9=1,'Items sous domaines Maths '!G9,0) -> 0
B6: =IF(OR('Items sous domaines Maths '!H10=3,'Items sous domaines Maths '!J10=3 ),'Items sous domaines Maths '!B10,0) -> 0 | C6: =IF(OR('Items sous domaines Maths '!H10=3,'Items sous domaines Maths '!J10=3 ),'Items sous domaines Maths '!C10) -> FALSE | D6: =IF(OR('Items sous domaines Maths '!H10=3,'Items sous domaines Maths '!J10=3 ),'Items sous domaines Maths '!D10,0) -> 0 | E6: =IF(OR('Items sous domaines Maths '!H10=3,'Items sous domaines Maths '!J10=3 ),'Items sous domaines Maths '!E10,0) -> 0 | F6: =IF(OR('Items sous domaines Maths '!H10=3,'Items sous domaines Maths '!J10=3 ),'Items sous domaines Maths '!F10,0) -> 0 | G6: =IF('Items sous domaines Maths '!H10=1,'Items sous domaines Maths '!G10,0) -> 0
B7: =IF(OR('Items sous domaines Maths '!H11=3,'Items sous domaines Maths '!J11=3 ),'Items sous domaines Maths '!B11,0) -> 0 | C7: =IF(OR('Items sous domaines Maths '!H11=3,'Items sous domaines Maths '!J11=3 ),'Items sous domaines Maths '!C11) -> FALSE | D7: =IF(OR('Items sous domaines Maths '!H11=3,'Items sous domaines Maths '!J11=3 ),'Items sous domaines Maths '!D11,0) -> 0 | E7: =IF(OR('Items sous domaines Maths '!H11=3,'Items sous domaines Maths '!J11=3 ),'Items sous domaines Maths '!E11,0) -> 0 | F7: =IF(OR('Items sous domaines Maths '!H11=3,'Items sous domaines Maths '!J11=3 ),'Items sous domaines Maths '!F11,0) -> 0 | G7: =IF('Items sous domaines Maths '!H11=1,'Items sous domaines Maths '!G11,0) -> 0
B8: =IF(OR('Items sous domaines Maths '!H12=3,'Items sous domaines Maths '!J12=3 ),'Items sous domaines Maths '!B12,0) -> 0 | C8: =IF(OR('Items sous domaines Maths '!H12=3,'Items sous domaines Maths '!J12=3 ),'Items sous domaines Maths '!C12) -> FALSE | D8: =IF(OR('Items sous domaines Maths '!H12=3,'Items sous domaines Maths '!J12=3 ),'Items sous domaines Maths '!D12,0) -> 0 | E8: =IF(OR('Items sous domaines Maths '!H12=3,'Items sous domaines Maths '!J12=3 ),'Items sous domaines Maths '!E12,0) -> 0 | F8: =IF(OR('Items sous domaines Maths '!H12=3,'Items sous domaines Maths '!J12=3 ),'Items sous domaines Maths '!F12,0) -> 0 | G8: =IF('Items sous domaines Maths '!H12=1,'Items sous domaines Maths '!G12,0) -> 0
B9: =IF(OR('Items sous domaines Maths '!H13=3,'Items sous domaines Maths '!J13=3 ),'Items sous domaines Maths '!B13,0) -> 0 | C9: =IF(OR('Items sous domaines Maths '!H13=3,'Items sous domaines Maths '!J13=3 ),'Items sous domaines Maths '!C13) -> FALSE | D9: =IF(OR('Items sous domaines Maths '!H13=3,'Items sous domaines Maths '!J13=3 ),'Items sous domaines Maths '!D13,0) -> 0 | E9: =IF(OR('Items sous domaines Maths '!H13=3,'Items sous domaines Maths '!J13=3 ),'Items sous domaines Maths '!E13,0) -> 0 | F9: =IF(OR('Items sous domaines Maths '!H13=3,'Items sous domaines Maths '!J13=3 ),'Items sous domaines Maths '!F13,0) -> 0 | G9: =IF('Items sous domaines Maths '!H13=1,'Items sous domaines Maths '!G13,0) -> 0
B10: =IF(OR('Items sous domaines Maths '!H14=3,'Items sous domaines Maths '!J14=3 ),'Items sous domaines Maths '!B14,0) -> 0 | C10: =IF(OR('Items sous domaines Maths '!H14=3,'Items sous domaines Maths '!J14=3 ),'Items sous domaines Maths '!C14) -> FALSE | D10: =IF(OR('Items sous domaines Maths '!H14=3,'Items sous domaines Maths '!J14=3 ),'Items sous domaines Maths '!D14,0) -> 0 | E10: =IF(OR('Items sous domaines Maths '!H14=3,'Items sous domaines Maths '!J14=3 ),'Items sous domaines Maths '!E14,0) -> 0 | F10: =IF(OR('Items sous domaines Maths '!H14=3,'Items sous domaines Maths '!J14=3 ),'Items sous domaines Maths '!F14,0) -> 0 | G10: =IF('Items sous domaines Maths '!H14=1,'Items sous domaines Maths '!G14,0) -> 0
B11: =IF(OR('Items sous domaines Maths '!H15=3,'Items sous domaines Maths '!J15=3 ),'Items sous domaines Maths '!B15,0) -> 0 | C11: =IF(OR('Items sous domaines Maths '!H15=3,'Items sous domaines Maths '!J15=3 ),'Items sous domaines Maths '!C15) -> FALSE | D11: =IF(OR('Items sous domaines Maths '!H15=3,'Items sous domaines Maths '!J15=3 ),'Items sous domaines Maths '!D15,0) -> 0 | E11: =IF(OR('Items sous domaines Maths '!H15=3,'Items sous domaines Maths '!J15=3 ),'Items sous domaines Maths '!E15,0) -> 0 | F11: =IF(OR('Items sous domaines Maths '!H15=3,'Items sous domaines Maths '!J15=3 ),'Items sous domaines Maths '!F15,0) -> 0 | G11: =IF('Items sous domaines Maths '!H15=1,'Items sous domaines Maths '!G15,0) -> 0
B12: =IF(OR('Items sous domaines Maths '!H16=3,'Items sous domaines Maths '!J16=3 ),'Items sous domaines Maths '!B16,0) -> 0 | C12: =IF(OR('Items sous domaines Maths '!H16=3,'Items sous domaines Maths '!J16=3 ),'Items sous domaines Maths '!C16) -> FALSE | D12: =IF(OR('Items sous domaines Maths '!H16=3,'Items sous domaines Maths '!J16=3 ),'Items sous domaines Maths '!D16,0) -> 0 | E12: =IF(OR('Items sous domaines Maths '!H16=3,'Items sous domaines Maths '!J16=3 ),'Items sous domaines Maths '!E16,0) -> 0 | F12: =IF(OR('Items sous domaines Maths '!H16=3,'Items sous domaines Maths '!J16=3 ),'Items sous domaines Maths '!F16,0) -> 0 | G12: =IF('Items sous domaines Maths '!H16=1,'Items sous domaines Maths '!G16,0) -> 0
B13: =IF(OR('Items sous domaines Maths '!H17=3,'Items sous domaines Maths '!J17=3 ),'Items sous domaines Maths '!B17,0) -> 0 | C13: =IF(OR('Items sous domaines Maths '!H17=3,'Items sous domaines Maths '!J17=3 ),'Items sous domaines Maths '!C17) -> FALSE | D13: =IF(OR('Items sous domaines Maths '!H17=3,'Items sous domaines Maths '!J17=3 ),'Items sous domaines Maths '!D17,0) -> 0 | E13: =IF(OR('Items sous domaines Maths '!H17=3,'Items sous domaines Maths '!J17=3 ),'Items sous domaines Maths '!E17,0) -> 0 | F13: =IF(OR('Items sous domaines Maths '!H17=3,'Items sous domaines Maths '!J17=3 ),'Items sous domaines Maths '!F17,0) -> 0 | G13: =IF('Items sous domaines Maths '!H17=1,'Items sous domaines Maths '!G17,0) -> 0
B14: =IF(OR('Items sous domaines Maths '!H18=3,'Items sous domaines Maths '!J18=3 ),'Items sous domaines Maths '!B18,0) -> 0 | C14: =IF(OR('Items sous domaines Maths '!H18=3,'Items sous domaines Maths '!J18=3 ),'Items sous domaines Maths '!C18) -> FALSE | D14: =IF(OR('Items sous domaines Maths '!H18=3,'Items sous domaines Maths '!J18=3 ),'Items sous domaines Maths '!D18,0) -> 0 | E14: =IF(OR('Items sous domaines Maths '!H18=3,'Items sous domaines Maths '!J18=3 ),'Items sous domaines Maths '!E18,0) -> 0 | F14: =IF(OR('Items sous domaines Maths '!H18=3,'Items sous domaines Maths '!J18=3 ),'Items sous domaines Maths '!F18,0) -> 0 | G14: =IF('Items sous domaines Maths '!H18=1,'Items sous domaines Maths '!G18,0) -> 0
B15: =IF(OR('Items sous domaines Maths '!H19=3,'Items sous domaines Maths '!J19=3 ),'Items sous domaines Maths '!B19,0) -> 0 | C15: =IF(OR('Items sous domaines Maths '!H19=3,'Items sous domaines Maths '!J19=3 ),'Items sous domaines Maths '!C19) -> FALSE | D15: =IF(OR('Items sous domaines Maths '!H19=3,'Items sous domaines Maths '!J19=3 ),'Items sous domaines Maths '!D19,0) -> 0 | E15: =IF(OR('Items sous domaines Maths '!H19=3,'Items sous domaines Maths '!J19=3 ),'Items sous domaines Maths '!E19,0) -> 0 | F15: =IF(OR('Items sous domaines Maths '!H19=3,'Items sous domaines Maths '!J19=3 ),'Items sous domaines Maths '!F19,0) -> 0 | G15: =IF('Items sous domaines Maths '!H19=1,'Items sous domaines Maths '!G19,0) -> 0
B16: =IF(OR('Items sous domaines Maths '!H20=3,'Items sous domaines Maths '!J20=3 ),'Items sous domaines Maths '!B20,0) -> 0 | C16: =IF(OR('Items sous domaines Maths '!H20=3,'Items sous domaines Maths '!J20=3 ),'Items sous domaines Maths '!C20) -> FALSE | D16: =IF(OR('Items sous domaines Maths '!H20=3,'Items sous domaines Maths '!J20=3 ),'Items sous domaines Maths '!D20,0) -> 0 | E16: =IF(OR('Items sous domaines Maths '!H20=3,'Items sous domaines Maths '!J20=3 ),'Items sous domaines Maths '!E20,0) -> 0 | F16: =IF(OR('Items sous domaines Maths '!H20=3,'Items sous domaines Maths '!J20=3 ),'Items sous domaines Maths '!F20,0) -> 0 | G16: =IF('Items sous domaines Maths '!H20=1,'Items sous domaines Maths '!G20,0) -> 0
... B35: =IF(OR('Items sous domaines Maths '!H39=3,'Items sous domaines Maths '!J39=3 ),'Items sous domaines Maths '!B39,0) -> 0 | C35: =IF(OR('Items sous domaines Maths '!H39=3,'Items sous domaines Maths '!J39=3 ),'Items sous domaines Maths '!C39) -> FALSE | D35: =IF(OR('Items sous domaines Maths '!H39=3,'Items sous domaines Maths '!J39=3 ),'Items sous domaines Maths '!D39,0) -> 0 | E35: =IF(OR('Items sous domaines Maths '!H39=3,'Items sous domaines Maths '!J39=3 ),'Items sous domaines Maths '!E39,0) -> 0 | F35: =IF(OR('Items sous domaines Maths '!H39=3,'Items sous domaines Maths '!J39=3 ),'Items sous domaines Maths '!F39,0) -> 0 | G35: =IF('Items sous domaines Maths '!H39=1,'Items sous domaines Maths '!G39,0) -> 0
B36: =IF(OR('Items sous domaines Maths '!H40=3,'Items sous domaines Maths '!J40=3 ),'Items sous domaines Maths '!B40,0) -> Algèbre | C36: =IF(OR('Items sous domaines Maths '!H40=3,'Items sous domaines Maths '!J40=3 ),'Items sous domaines Maths '!C40) -> Les nombres complexes | D36: =IF(OR('Items sous domaines Maths '!H40=3,'Items sous domaines Maths '!J40=3 ),'Items sous domaines Maths '!D40,0) -> Définition et écriture algébrique des nombres complexes | E36: =IF(OR('Items sous domaines Maths '!H40=3,'Items sous domaines Maths '!J40=3 ),'Items sous domaines Maths '!E40,0) -> Définition | F36: =IF(OR('Items sous domaines Maths '!H40=3,'Items sous domaines Maths '!J40=3 ),'Items sous domaines Maths '!F40,0) -> Connaître l'écriture algébrique, la partie réelle et imaginaire d'un nombre complexe | G36: ETS et projet PBL | H36: voir onglet CPI S1 et S2
B37: =IF(OR('Items sous domaines Maths '!H41=3,'Items sous domaines Maths '!J41=3 ),'Items sous domaines Maths '!B41,0) -> Algèbre | C37: =IF(OR('Items sous domaines Maths '!H41=3,'Items sous domaines Maths '!J41=3 ),'Items sous domaines Maths '!C41) -> Les nombres complexes | D37: =IF(OR('Items sous domaines Maths '!H41=3,'Items sous domaines Maths '!J41=3 ),'Items sous domaines Maths '!D41,0) -> 0 | E37: =IF(OR('Items sous domaines Maths '!H41=3,'Items sous domaines Maths '!J41=3 ),'Items sous domaines Maths '!E41,0) -> 0 | F37: =IF(OR('Items sous domaines Maths '!H41=3,'Items sous domaines Maths '!J41=3 ),'Items sous domaines Maths '!F41,0) -> Savoir faire des opérations sur les nombres complexes.
B38: =IF(OR('Items sous domaines Maths '!H42=3,'Items sous domaines Maths '!J42=3 ),'Items sous domaines Maths '!B42,0) -> Algèbre | C38: =IF(OR('Items sous domaines Maths '!H42=3,'Items sous domaines Maths '!J42=3 ),'Items sous domaines Maths '!C42) -> Les nombres complexes | D38: =IF(OR('Items sous domaines Maths '!H42=3,'Items sous domaines Maths '!J42=3 ),'Items sous domaines Maths '!D42,0) -> 0 | E38: =IF(OR('Items sous domaines Maths '!H42=3,'Items sous domaines Maths '!J42=3 ),'Items sous domaines Maths '!E42,0) -> 0 | F38: =IF(OR('Items sous domaines Maths '!H42=3,'Items sous domaines Maths '!J42=3 ),'Items sous domaines Maths '!F42,0) -> Connaître et savoir calculer le conjugué d'un nombre complexe. Connaître les propriétés du conjugué et son utilité dans l'écriture des fractions complexes sous forme algébrique.
B39: =IF(OR('Items sous domaines Maths '!H43=3,'Items sous domaines Maths '!J43=3 ),'Items sous domaines Maths '!B43,0) -> Algèbre | C39: =IF(OR('Items sous domaines Maths '!H43=3,'Items sous domaines Maths '!J43=3 ),'Items sous domaines Maths '!C43) -> Les nombres complexes | D39: =IF(OR('Items sous domaines Maths '!H43=3,'Items sous domaines Maths '!J43=3 ),'Items sous domaines Maths '!D43,0) -> 0 | E39: =IF(OR('Items sous domaines Maths '!H43=3,'Items sous domaines Maths '!J43=3 ),'Items sous domaines Maths '!E43,0) -> 0 | F39: =IF(OR('Items sous domaines Maths '!H43=3,'Items sous domaines Maths '!J43=3 ),'Items sous domaines Maths '!F43,0) -> Savoir associer un point du plan à un nombre complexe, affixe d’un point du plan, affixe d’un vecteur du plan (dentifier C au plan usuel muni d’un repère orthonormé direct)
B40: =IF(OR('Items sous domaines Maths '!H44=3,'Items sous domaines Maths '!J44=3 ),'Items sous domaines Maths '!B44,0) -> Algèbre | C40: =IF(OR('Items sous domaines Maths '!H44=3,'Items sous domaines Maths '!J44=3 ),'Items sous domaines Maths '!C44) -> Les nombres complexes | D40: =IF(OR('Items sous domaines Maths '!H44=3,'Items sous domaines Maths '!J44=3 ),'Items sous domaines Maths '!D44,0) -> 0 | E40: =IF(OR('Items sous domaines Maths '!H44=3,'Items sous domaines Maths '!J44=3 ),'Items sous domaines Maths '!E44,0) -> Module d’un nombre complexe | F40: =IF(OR('Items sous domaines Maths '!H44=3,'Items sous domaines Maths '!J44=3 ),'Items sous domaines Maths '!F44,0) -> Savoir calculer un module d'un nombre complexe.
B41: =IF(OR('Items sous domaines Maths '!H45=3,'Items sous domaines Maths '!J45=3 ),'Items sous domaines Maths '!B45,0) -> Algèbre | C41: =IF(OR('Items sous domaines Maths '!H45=3,'Items sous domaines Maths '!J45=3 ),'Items sous domaines Maths '!C45) -> Les nombres complexes | D41: =IF(OR('Items sous domaines Maths '!H45=3,'Items sous domaines Maths '!J45=3 ),'Items sous domaines Maths '!D45,0) -> 0 | E41: =IF(OR('Items sous domaines Maths '!H45=3,'Items sous domaines Maths '!J45=3 ),'Items sous domaines Maths '!E45,0) -> 0 | F41: =IF(OR('Items sous domaines Maths '!H45=3,'Items sous domaines Maths '!J45=3 ),'Items sous domaines Maths '!F45,0) -> Connaître l'interprétation géométrique d'un module et repérer les images des affixes de même module.
B42: =IF(OR('Items sous domaines Maths '!H46=3,'Items sous domaines Maths '!J46=3 ),'Items sous domaines Maths '!B46,0) -> Algèbre | C42: =IF(OR('Items sous domaines Maths '!H46=3,'Items sous domaines Maths '!J46=3 ),'Items sous domaines Maths '!C46) -> Les nombres complexes | D42: =IF(OR('Items sous domaines Maths '!H46=3,'Items sous domaines Maths '!J46=3 ),'Items sous domaines Maths '!D46,0) -> 0 | E42: =IF(OR('Items sous domaines Maths '!H46=3,'Items sous domaines Maths '!J46=3 ),'Items sous domaines Maths '!E46,0) -> 0 | F42: =IF(OR('Items sous domaines Maths '!H46=3,'Items sous domaines Maths '!J46=3 ),'Items sous domaines Maths '!F46,0) -> Savoir calculer le module d’un produit, d’un quotient.
B43: =IF(OR('Items sous domaines Maths '!H47=3,'Items sous domaines Maths '!J47=3 ),'Items sous domaines Maths '!B47,0) -> Algèbre | C43: =IF(OR('Items sous domaines Maths '!H47=3,'Items sous domaines Maths '!J47=3 ),'Items sous domaines Maths '!C47) -> Les nombres complexes | D43: =IF(OR('Items sous domaines Maths '!H47=3,'Items sous domaines Maths '!J47=3 ),'Items sous domaines Maths '!D47,0) -> 0 | E43: =IF(OR('Items sous domaines Maths '!H47=3,'Items sous domaines Maths '!J47=3 ),'Items sous domaines Maths '!E47,0) -> 0 | F43: =IF(OR('Items sous domaines Maths '!H47=3,'Items sous domaines Maths '!J47=3 ),'Items sous domaines Maths '!F47,0) -> Savoir résoudre des équations du type |z-zA|=|z-zB| et |z-zA|=R > 0
B44: =IF(OR('Items sous domaines Maths '!H48=3,'Items sous domaines Maths '!J48=3 ),'Items sous domaines Maths '!B48,0) -> Algèbre | C44: =IF(OR('Items sous domaines Maths '!H48=3,'Items sous domaines Maths '!J48=3 ),'Items sous domaines Maths '!C48) -> Les nombres complexes | D44: =IF(OR('Items sous domaines Maths '!H48=3,'Items sous domaines Maths '!J48=3 ),'Items sous domaines Maths '!D48,0) -> Forme trigonométrique et exponentielle d'un nombre complexe | E44: =IF(OR('Items sous domaines Maths '!H48=3,'Items sous domaines Maths '!J48=3 ),'Items sous domaines Maths '!E48,0) -> Argument d'un nombre complexe et forme trigonometrique | F44: =IF(OR('Items sous domaines Maths '!H48=3,'Items sous domaines Maths '!J48=3 ),'Items sous domaines Maths '!F48,0) -> Connaître le cercle trigonométrique. Savoir repérer un point du cercle avec les fonctions circulaires sinus et cosinus. Connaître les formules des angles associés, cos(a±b), sin(a±b), cos(2a), sin(2a),
B45: =IF(OR('Items sous domaines Maths '!H49=3,'Items sous domaines Maths '!J49=3 ),'Items sous domaines Maths '!B49,0) -> Algèbre | C45: =IF(OR('Items sous domaines Maths '!H49=3,'Items sous domaines Maths '!J49=3 ),'Items sous domaines Maths '!C49) -> Les nombres complexes | D45: =IF(OR('Items sous domaines Maths '!H49=3,'Items sous domaines Maths '!J49=3 ),'Items sous domaines Maths '!D49,0) -> 0 | E45: =IF(OR('Items sous domaines Maths '!H49=3,'Items sous domaines Maths '!J49=3 ),'Items sous domaines Maths '!E49,0) -> 0 | F45: =IF(OR('Items sous domaines Maths '!H49=3,'Items sous domaines Maths '!J49=3 ),'Items sous domaines Maths '!F49,0) -> Savoir calculer l'argument d'un nombre complexe à partir de sa forme algébrique et connaître l'interprétation géométrique de l'argument.
B46: =IF(OR('Items sous domaines Maths '!H50=3,'Items sous domaines Maths '!J50=3 ),'Items sous domaines Maths '!B50,0) -> Algèbre | C46: =IF(OR('Items sous domaines Maths '!H50=3,'Items sous domaines Maths '!J50=3 ),'Items sous domaines Maths '!C50) -> Les nombres complexes | D46: =IF(OR('Items sous domaines Maths '!H50=3,'Items sous domaines Maths '!J50=3 ),'Items sous domaines Maths '!D50,0) -> 0 | E46: =IF(OR('Items sous domaines Maths '!H50=3,'Items sous domaines Maths '!J50=3 ),'Items sous domaines Maths '!E50,0) -> 0 | F46: =IF(OR('Items sous domaines Maths '!H50=3,'Items sous domaines Maths '!J50=3 ),'Items sous domaines Maths '!F50,0) -> Savoir calculer l'argument d’un produit, d’un quotient.
B47: =IF(OR('Items sous domaines Maths '!H51=3,'Items sous domaines Maths '!J51=3 ),'Items sous domaines Maths '!B51,0) -> Algèbre | C47: =IF(OR('Items sous domaines Maths '!H51=3,'Items sous domaines Maths '!J51=3 ),'Items sous domaines Maths '!C51) -> Les nombres complexes | D47: =IF(OR('Items sous domaines Maths '!H51=3,'Items sous domaines Maths '!J51=3 ),'Items sous domaines Maths '!D51,0) -> 0 | E47: =IF(OR('Items sous domaines Maths '!H51=3,'Items sous domaines Maths '!J51=3 ),'Items sous domaines Maths '!E51,0) -> 0 | F47: =IF(OR('Items sous domaines Maths '!H51=3,'Items sous domaines Maths '!J51=3 ),'Items sous domaines Maths '!F51,0) -> Savoir passer de la forme algébrique à la forme trigonométrique d'un nombre complexe.
B48: =IF(OR('Items sous domaines Maths '!H52=3,'Items sous domaines Maths '!J52=3 ),'Items sous domaines Maths '!B52,0) -> Algèbre | C48: =IF(OR('Items sous domaines Maths '!H52=3,'Items sous domaines Maths '!J52=3 ),'Items sous domaines Maths '!C52) -> Les nombres complexes | D48: =IF(OR('Items sous domaines Maths '!H52=3,'Items sous domaines Maths '!J52=3 ),'Items sous domaines Maths '!D52,0) -> 0 | E48: =IF(OR('Items sous domaines Maths '!H52=3,'Items sous domaines Maths '!J52=3 ),'Items sous domaines Maths '!E52,0) -> Complexes de module 1 et forme exponentielle d'un nombre complexe | F48: =IF(OR('Items sous domaines Maths '!H52=3,'Items sous domaines Maths '!J52=3 ),'Items sous domaines Maths '!F52,0) -> Définition de exp(it) pour t réel.
... B97: =IF(OR('Items sous domaines Maths '!H101=3,'Items sous domaines Maths '!J101=3 ),'Items sous domaines Maths '!B101,0) -> Algèbre | C97: =IF(OR('Items sous domaines Maths '!H101=3,'Items sous domaines Maths '!J101=3 ),'Items sous domaines Maths '!C101) -> Les Matrices | D97: =IF(OR('Items sous domaines Maths '!H101=3,'Items sous domaines Maths '!J101=3 ),'Items sous domaines Maths '!D101,0) -> 0 | E97: =IF(OR('Items sous domaines Maths '!H101=3,'Items sous domaines Maths '!J101=3 ),'Items sous domaines Maths '!E101,0) -> 0 | F97: =IF(OR('Items sous domaines Maths '!H101=3,'Items sous domaines Maths '!J101=3 ),'Items sous domaines Maths '!F101,0) -> Méthodes de calcul de l'inverse d'une matrice.
B98: =IF(OR('Items sous domaines Maths '!H102=3,'Items sous domaines Maths '!J102=3 ),'Items sous domaines Maths '!B102,0) -> 0 | C98: =IF(OR('Items sous domaines Maths '!H102=3,'Items sous domaines Maths '!J102=3 ),'Items sous domaines Maths '!C102) -> FALSE | D98: =IF(OR('Items sous domaines Maths '!H102=3,'Items sous domaines Maths '!J102=3 ),'Items sous domaines Maths '!D102,0) -> 0 | E98: =IF(OR('Items sous domaines Maths '!H102=3,'Items sous domaines Maths '!J102=3 ),'Items sous domaines Maths '!E102,0) -> 0 | F98: =IF(OR('Items sous domaines Maths '!H102=3,'Items sous domaines Maths '!J102=3 ),'Items sous domaines Maths '!F102,0) -> 0 | G98: =IF('Items sous domaines Maths '!H102=1,'Items sous domaines Maths '!G102,0) -> 0
B99: =IF(OR('Items sous domaines Maths '!H103=3,'Items sous domaines Maths '!J103=3 ),'Items sous domaines Maths '!B103,0) -> 0 | C99: =IF(OR('Items sous domaines Maths '!H103=3,'Items sous domaines Maths '!J103=3 ),'Items sous domaines Maths '!C103) -> FALSE | D99: =IF(OR('Items sous domaines Maths '!H103=3,'Items sous domaines Maths '!J103=3 ),'Items sous domaines Maths '!D103,0) -> 0 | E99: =IF(OR('Items sous domaines Maths '!H103=3,'Items sous domaines Maths '!J103=3 ),'Items sous domaines Maths '!E103,0) -> 0 | F99: =IF(OR('Items sous domaines Maths '!H103=3,'Items sous domaines Maths '!J103=3 ),'Items sous domaines Maths '!F103,0) -> 0 | G99: =IF('Items sous domaines Maths '!H103=1,'Items sous domaines Maths '!G103,0) -> 0
B100: =IF(OR('Items sous domaines Maths '!H104=3,'Items sous domaines Maths '!J104=3 ),'Items sous domaines Maths '!B104,0) -> 0 | C100: =IF(OR('Items sous domaines Maths '!H104=3,'Items sous domaines Maths '!J104=3 ),'Items sous domaines Maths '!C104) -> FALSE | D100: =IF(OR('Items sous domaines Maths '!H104=3,'Items sous domaines Maths '!J104=3 ),'Items sous domaines Maths '!D104,0) -> 0 | E100: =IF(OR('Items sous domaines Maths '!H104=3,'Items sous domaines Maths '!J104=3 ),'Items sous domaines Maths '!E104,0) -> 0 | F100: =IF(OR('Items sous domaines Maths '!H104=3,'Items sous domaines Maths '!J104=3 ),'Items sous domaines Maths '!F104,0) -> 0 | G100: =IF('Items sous domaines Maths '!H104=1,'Items sous domaines Maths '!G104,0) -> 0
B101: =IF(OR('Items sous domaines Maths '!H105=3,'Items sous domaines Maths '!J105=3 ),'Items sous domaines Maths '!B105,0) -> 0 | C101: =IF(OR('Items sous domaines Maths '!H105=3,'Items sous domaines Maths '!J105=3 ),'Items sous domaines Maths '!C105) -> FALSE | D101: =IF(OR('Items sous domaines Maths '!H105=3,'Items sous domaines Maths '!J105=3 ),'Items sous domaines Maths '!D105,0) -> 0 | E101: =IF(OR('Items sous domaines Maths '!H105=3,'Items sous domaines Maths '!J105=3 ),'Items sous domaines Maths '!E105,0) -> 0 | F101: =IF(OR('Items sous domaines Maths '!H105=3,'Items sous domaines Maths '!J105=3 ),'Items sous domaines Maths '!F105,0) -> 0 | G101: =IF('Items sous domaines Maths '!H105=1,'Items sous domaines Maths '!G105,0) -> 0
B102: =IF(OR('Items sous domaines Maths '!H106=3,'Items sous domaines Maths '!J106=3 ),'Items sous domaines Maths '!B106,0) -> 0 | C102: =IF(OR('Items sous domaines Maths '!H106=3,'Items sous domaines Maths '!J106=3 ),'Items sous domaines Maths '!C106) -> FALSE | D102: =IF(OR('Items sous domaines Maths '!H106=3,'Items sous domaines Maths '!J106=3 ),'Items sous domaines Maths '!D106,0) -> 0 | E102: =IF(OR('Items sous domaines Maths '!H106=3,'Items sous domaines Maths '!J106=3 ),'Items sous domaines Maths '!E106,0) -> 0 | F102: =IF(OR('Items sous domaines Maths '!H106=3,'Items sous domaines Maths '!J106=3 ),'Items sous domaines Maths '!F106,0) -> 0 | G102: =IF('Items sous domaines Maths '!H106=1,'Items sous domaines Maths '!G106,0) -> 0
B103: =IF(OR('Items sous domaines Maths '!H107=3,'Items sous domaines Maths '!J107=3 ),'Items sous domaines Maths '!B107,0) -> 0 | C103: =IF(OR('Items sous domaines Maths '!H107=3,'Items sous domaines Maths '!J107=3 ),'Items sous domaines Maths '!C107) -> FALSE | D103: =IF(OR('Items sous domaines Maths '!H107=3,'Items sous domaines Maths '!J107=3 ),'Items sous domaines Maths '!D107,0) -> 0 | E103: =IF(OR('Items sous domaines Maths '!H107=3,'Items sous domaines Maths '!J107=3 ),'Items sous domaines Maths '!E107,0) -> 0 | F103: =IF(OR('Items sous domaines Maths '!H107=3,'Items sous domaines Maths '!J107=3 ),'Items sous domaines Maths '!F107,0) -> 0 | G103: =IF('Items sous domaines Maths '!H107=1,'Items sous domaines Maths '!G107,0) -> 0
B104: =IF(OR('Items sous domaines Maths '!H108=3,'Items sous domaines Maths '!J108=3 ),'Items sous domaines Maths '!B108,0) -> 0 | C104: =IF(OR('Items sous domaines Maths '!H108=3,'Items sous domaines Maths '!J108=3 ),'Items sous domaines Maths '!C108) -> FALSE | D104: =IF(OR('Items sous domaines Maths '!H108=3,'Items sous domaines Maths '!J108=3 ),'Items sous domaines Maths '!D108,0) -> 0 | E104: =IF(OR('Items sous domaines Maths '!H108=3,'Items sous domaines Maths '!J108=3 ),'Items sous domaines Maths '!E108,0) -> 0 | F104: =IF(OR('Items sous domaines Maths '!H108=3,'Items sous domaines Maths '!J108=3 ),'Items sous domaines Maths '!F108,0) -> 0 | G104: =IF('Items sous domaines Maths '!H108=1,'Items sous domaines Maths '!G108,0) -> 0
B105: =IF(OR('Items sous domaines Maths '!H109=3,'Items sous domaines Maths '!J109=3 ),'Items sous domaines Maths '!B109,0) -> 0 | C105: =IF(OR('Items sous domaines Maths '!H109=3,'Items sous domaines Maths '!J109=3 ),'Items sous domaines Maths '!C109) -> FALSE | D105: =IF(OR('Items sous domaines Maths '!H109=3,'Items sous domaines Maths '!J109=3 ),'Items sous domaines Maths '!D109,0) -> 0 | E105: =IF(OR('Items sous domaines Maths '!H109=3,'Items sous domaines Maths '!J109=3 ),'Items sous domaines Maths '!E109,0) -> 0 | F105: =IF(OR('Items sous domaines Maths '!H109=3,'Items sous domaines Maths '!J109=3 ),'Items sous domaines Maths '!F109,0) -> 0 | G105: =IF('Items sous domaines Maths '!H109=1,'Items sous domaines Maths '!G109,0) -> 0
B106: =IF(OR('Items sous domaines Maths '!H110=3,'Items sous domaines Maths '!J110=3 ),'Items sous domaines Maths '!B110,0) -> 0 | C106: =IF(OR('Items sous domaines Maths '!H110=3,'Items sous domaines Maths '!J110=3 ),'Items sous domaines Maths '!C110) -> FALSE | D106: =IF(OR('Items sous domaines Maths '!H110=3,'Items sous domaines Maths '!J110=3 ),'Items sous domaines Maths '!D110,0) -> 0 | E106: =IF(OR('Items sous domaines Maths '!H110=3,'Items sous domaines Maths '!J110=3 ),'Items sous domaines Maths '!E110,0) -> 0 | F106: =IF(OR('Items sous domaines Maths '!H110=3,'Items sous domaines Maths '!J110=3 ),'Items sous domaines Maths '!F110,0) -> 0 | G106: =IF('Items sous domaines Maths '!H110=1,'Items sous domaines Maths '!G110,0) -> 0
B107: =IF(OR('Items sous domaines Maths '!H111=3,'Items sous domaines Maths '!J111=3 ),'Items sous domaines Maths '!B111,0) -> 0 | C107: =IF(OR('Items sous domaines Maths '!H111=3,'Items sous domaines Maths '!J111=3 ),'Items sous domaines Maths '!C111) -> FALSE | D107: =IF(OR('Items sous domaines Maths '!H111=3,'Items sous domaines Maths '!J111=3 ),'Items sous domaines Maths '!D111,0) -> 0 | E107: =IF(OR('Items sous domaines Maths '!H111=3,'Items sous domaines Maths '!J111=3 ),'Items sous domaines Maths '!E111,0) -> 0 | F107: =IF(OR('Items sous domaines Maths '!H111=3,'Items sous domaines Maths '!J111=3 ),'Items sous domaines Maths '!F111,0) -> 0 | G107: =IF('Items sous domaines Maths '!H111=1,'Items sous domaines Maths '!G111,0) -> 0
B108: =IF(OR('Items sous domaines Maths '!H112=3,'Items sous domaines Maths '!J112=3 ),'Items sous domaines Maths '!B112,0) -> 0 | C108: =IF(OR('Items sous domaines Maths '!H112=3,'Items sous domaines Maths '!J112=3 ),'Items sous domaines Maths '!C112) -> FALSE | D108: =IF(OR('Items sous domaines Maths '!H112=3,'Items sous domaines Maths '!J112=3 ),'Items sous domaines Maths '!D112,0) -> 0 | E108: =IF(OR('Items sous domaines Maths '!H112=3,'Items sous domaines Maths '!J112=3 ),'Items sous domaines Maths '!E112,0) -> 0 | F108: =IF(OR('Items sous domaines Maths '!H112=3,'Items sous domaines Maths '!J112=3 ),'Items sous domaines Maths '!F112,0) -> 0 | G108: =IF('Items sous domaines Maths '!H112=1,'Items sous domaines Maths '!G112,0) -> 0
A109: Maths spécialité : graphes en FISE info FISA info | B109: =IF(OR('Items sous domaines Maths '!H113=3,'Items sous domaines Maths '!J113=3 ),'Items sous domaines Maths '!B113,0) -> 0 | C109: =IF(OR('Items sous domaines Maths '!H113=3,'Items sous domaines Maths '!J113=3 ),'Items sous domaines Maths '!C113) -> FALSE | D109: =IF(OR('Items sous domaines Maths '!H113=3,'Items sous domaines Maths '!J113=3 ),'Items sous domaines Maths '!D113,0) -> 0 | E109: =IF(OR('Items sous domaines Maths '!H113=3,'Items sous domaines Maths '!J113=3 ),'Items sous domaines Maths '!E113,0) -> 0 | F109: =IF(OR('Items sous domaines Maths '!H113=3,'Items sous domaines Maths '!J113=3 ),'Items sous domaines Maths '!F113,0) -> 0 | G109: =IF('Items sous domaines Maths '!H113=1,'Items sous domaines Maths '!G113,0) -> 0
B110: =IF(OR('Items sous domaines Maths '!H114=3,'Items sous domaines Maths '!J114=3 ),'Items sous domaines Maths '!B114,0) -> 0 | C110: =IF(OR('Items sous domaines Maths '!H114=3,'Items sous domaines Maths '!J114=3 ),'Items sous domaines Maths '!C114) -> FALSE | D110: =IF(OR('Items sous domaines Maths '!H114=3,'Items sous domaines Maths '!J114=3 ),'Items sous domaines Maths '!D114,0) -> 0 | E110: =IF(OR('Items sous domaines Maths '!H114=3,'Items sous domaines Maths '!J114=3 ),'Items sous domaines Maths '!E114,0) -> 0 | F110: =IF(OR('Items sous domaines Maths '!H114=3,'Items sous domaines Maths '!J114=3 ),'Items sous domaines Maths '!F114,0) -> 0 | G110: =IF('Items sous domaines Maths '!H114=1,'Items sous domaines Maths '!G114,0) -> 0
B111: =IF(OR('Items sous domaines Maths '!H115=3,'Items sous domaines Maths '!J115=3 ),'Items sous domaines Maths '!B115,0) -> 0 | C111: =IF(OR('Items sous domaines Maths '!H115=3,'Items sous domaines Maths '!J115=3 ),'Items sous domaines Maths '!C115) -> FALSE | D111: =IF(OR('Items sous domaines Maths '!H115=3,'Items sous domaines Maths '!J115=3 ),'Items sous domaines Maths '!D115,0) -> 0 | E111: =IF(OR('Items sous domaines Maths '!H115=3,'Items sous domaines Maths '!J115=3 ),'Items sous domaines Maths '!E115,0) -> 0 | F111: =IF(OR('Items sous domaines Maths '!H115=3,'Items sous domaines Maths '!J115=3 ),'Items sous domaines Maths '!F115,0) -> 0 | G111: =IF('Items sous domaines Maths '!H115=1,'Items sous domaines Maths '!G115,0) -> 0
B112: =IF(OR('Items sous domaines Maths '!H116=3,'Items sous domaines Maths '!J116=3 ),'Items sous domaines Maths '!B116,0) -> 0 | C112: =IF(OR('Items sous domaines Maths '!H116=3,'Items sous domaines Maths '!J116=3 ),'Items sous domaines Maths '!C116) -> FALSE | D112: =IF(OR('Items sous domaines Maths '!H116=3,'Items sous domaines Maths '!J116=3 ),'Items sous domaines Maths '!D116,0) -> 0 | E112: =IF(OR('Items sous domaines Maths '!H116=3,'Items sous domaines Maths '!J116=3 ),'Items sous domaines Maths '!E116,0) -> 0 | F112: =IF(OR('Items sous domaines Maths '!H116=3,'Items sous domaines Maths '!J116=3 ),'Items sous domaines Maths '!F116,0) -> 0 | G112: =IF('Items sous domaines Maths '!H116=1,'Items sous domaines Maths '!G116,0) -> 0
B113: =IF(OR('Items sous domaines Maths '!H117=3,'Items sous domaines Maths '!J117=3 ),'Items sous domaines Maths '!B117,0) -> 0 | C113: =IF(OR('Items sous domaines Maths '!H117=3,'Items sous domaines Maths '!J117=3 ),'Items sous domaines Maths '!C117) -> FALSE | D113: =IF(OR('Items sous domaines Maths '!H117=3,'Items sous domaines Maths '!J117=3 ),'Items sous domaines Maths '!D117,0) -> 0 | E113: =IF(OR('Items sous domaines Maths '!H117=3,'Items sous domaines Maths '!J117=3 ),'Items sous domaines Maths '!E117,0) -> 0 | F113: =IF(OR('Items sous domaines Maths '!H117=3,'Items sous domaines Maths '!J117=3 ),'Items sous domaines Maths '!F117,0) -> 0 | G113: =IF('Items sous domaines Maths '!H117=1,'Items sous domaines Maths '!G117,0) -> 0
B114: =IF(OR('Items sous domaines Maths '!H118=3,'Items sous domaines Maths '!J118=3 ),'Items sous domaines Maths '!B118,0) -> 0 | C114: =IF(OR('Items sous domaines Maths '!H118=3,'Items sous domaines Maths '!J118=3 ),'Items sous domaines Maths '!C118) -> FALSE | D114: =IF(OR('Items sous domaines Maths '!H118=3,'Items sous domaines Maths '!J118=3 ),'Items sous domaines Maths '!D118,0) -> 0 | E114: =IF(OR('Items sous domaines Maths '!H118=3,'Items sous domaines Maths '!J118=3 ),'Items sous domaines Maths '!E118,0) -> 0 | F114: =IF(OR('Items sous domaines Maths '!H118=3,'Items sous domaines Maths '!J118=3 ),'Items sous domaines Maths '!F118,0) -> 0 | G114: =IF('Items sous domaines Maths '!H118=1,'Items sous domaines Maths '!G118,0) -> 0
B115: =IF(OR('Items sous domaines Maths '!H119=3,'Items sous domaines Maths '!J119=3 ),'Items sous domaines Maths '!B119,0) -> 0 | C115: =IF(OR('Items sous domaines Maths '!H119=3,'Items sous domaines Maths '!J119=3 ),'Items sous domaines Maths '!C119) -> FALSE | D115: =IF(OR('Items sous domaines Maths '!H119=3,'Items sous domaines Maths '!J119=3 ),'Items sous domaines Maths '!D119,0) -> 0 | E115: =IF(OR('Items sous domaines Maths '!H119=3,'Items sous domaines Maths '!J119=3 ),'Items sous domaines Maths '!E119,0) -> 0 | F115: =IF(OR('Items sous domaines Maths '!H119=3,'Items sous domaines Maths '!J119=3 ),'Items sous domaines Maths '!F119,0) -> 0 | G115: =IF('Items sous domaines Maths '!H119=1,'Items sous domaines Maths '!G119,0) -> 0
B116: =IF(OR('Items sous domaines Maths '!H120=3,'Items sous domaines Maths '!J120=3 ),'Items sous domaines Maths '!B120,0) -> 0 | C116: =IF(OR('Items sous domaines Maths '!H120=3,'Items sous domaines Maths '!J120=3 ),'Items sous domaines Maths '!C120) -> FALSE | D116: =IF(OR('Items sous domaines Maths '!H120=3,'Items sous domaines Maths '!J120=3 ),'Items sous domaines Maths '!D120,0) -> 0 | E116: =IF(OR('Items sous domaines Maths '!H120=3,'Items sous domaines Maths '!J120=3 ),'Items sous domaines Maths '!E120,0) -> 0 | F116: =IF(OR('Items sous domaines Maths '!H120=3,'Items sous domaines Maths '!J120=3 ),'Items sous domaines Maths '!F120,0) -> 0 | G116: =IF('Items sous domaines Maths '!H120=1,'Items sous domaines Maths '!G120,0) -> 0
B117: =IF(OR('Items sous domaines Maths '!H121=3,'Items sous domaines Maths '!J121=3 ),'Items sous domaines Maths '!B121,0) -> 0 | C117: =IF(OR('Items sous domaines Maths '!H121=3,'Items sous domaines Maths '!J121=3 ),'Items sous domaines Maths '!C121) -> FALSE | D117: =IF(OR('Items sous domaines Maths '!H121=3,'Items sous domaines Maths '!J121=3 ),'Items sous domaines Maths '!D121,0) -> 0 | E117: =IF(OR('Items sous domaines Maths '!H121=3,'Items sous domaines Maths '!J121=3 ),'Items sous domaines Maths '!E121,0) -> 0 | F117: =IF(OR('Items sous domaines Maths '!H121=3,'Items sous domaines Maths '!J121=3 ),'Items sous domaines Maths '!F121,0) -> 0 | G117: =IF('Items sous domaines Maths '!H121=1,'Items sous domaines Maths '!G121,0) -> 0
B118: =IF(OR('Items sous domaines Maths '!H122=3,'Items sous domaines Maths '!J122=3 ),'Items sous domaines Maths '!B122,0) -> 0 | C118: =IF(OR('Items sous domaines Maths '!H122=3,'Items sous domaines Maths '!J122=3 ),'Items sous domaines Maths '!C122) -> FALSE | D118: =IF(OR('Items sous domaines Maths '!H122=3,'Items sous domaines Maths '!J122=3 ),'Items sous domaines Maths '!D122,0) -> 0 | E118: =IF(OR('Items sous domaines Maths '!H122=3,'Items sous domaines Maths '!J122=3 ),'Items sous domaines Maths '!E122,0) -> 0 | F118: =IF(OR('Items sous domaines Maths '!H122=3,'Items sous domaines Maths '!J122=3 ),'Items sous domaines Maths '!F122,0) -> 0 | G118: =IF('Items sous domaines Maths '!H122=1,'Items sous domaines Maths '!G122,0) -> 0
B119: =IF(OR('Items sous domaines Maths '!H123=3,'Items sous domaines Maths '!J123=3 ),'Items sous domaines Maths '!B123,0) -> 0 | C119: =IF(OR('Items sous domaines Maths '!H123=3,'Items sous domaines Maths '!J123=3 ),'Items sous domaines Maths '!C123) -> FALSE | D119: =IF(OR('Items sous domaines Maths '!H123=3,'Items sous domaines Maths '!J123=3 ),'Items sous domaines Maths '!D123,0) -> 0 | E119: =IF(OR('Items sous domaines Maths '!H123=3,'Items sous domaines Maths '!J123=3 ),'Items sous domaines Maths '!E123,0) -> 0 | F119: =IF(OR('Items sous domaines Maths '!H123=3,'Items sous domaines Maths '!J123=3 ),'Items sous domaines Maths '!F123,0) -> 0 | G119: =IF('Items sous domaines Maths '!H123=1,'Items sous domaines Maths '!G123,0) -> 0
B120: =IF(OR('Items sous domaines Maths '!H124=3,'Items sous domaines Maths '!J124=3 ),'Items sous domaines Maths '!B124,0) -> 0 | C120: =IF(OR('Items sous domaines Maths '!H124=3,'Items sous domaines Maths '!J124=3 ),'Items sous domaines Maths '!C124) -> FALSE | D120: =IF(OR('Items sous domaines Maths '!H124=3,'Items sous domaines Maths '!J124=3 ),'Items sous domaines Maths '!D124,0) -> 0 | E120: =IF(OR('Items sous domaines Maths '!H124=3,'Items sous domaines Maths '!J124=3 ),'Items sous domaines Maths '!E124,0) -> 0 | F120: =IF(OR('Items sous domaines Maths '!H124=3,'Items sous domaines Maths '!J124=3 ),'Items sous domaines Maths '!F124,0) -> 0 | G120: =IF('Items sous domaines Maths '!H124=1,'Items sous domaines Maths '!G124,0) -> 0
B121: =IF(OR('Items sous domaines Maths '!H125=3,'Items sous domaines Maths '!J125=3 ),'Items sous domaines Maths '!B125,0) -> 0 | C121: =IF(OR('Items sous domaines Maths '!H125=3,'Items sous domaines Maths '!J125=3 ),'Items sous domaines Maths '!C125) -> FALSE | D121: =IF(OR('Items sous domaines Maths '!H125=3,'Items sous domaines Maths '!J125=3 ),'Items sous domaines Maths '!D125,0) -> 0 | E121: =IF(OR('Items sous domaines Maths '!H125=3,'Items sous domaines Maths '!J125=3 ),'Items sous domaines Maths '!E125,0) -> 0 | F121: =IF(OR('Items sous domaines Maths '!H125=3,'Items sous domaines Maths '!J125=3 ),'Items sous domaines Maths '!F125,0) -> 0 | G121: =IF('Items sous domaines Maths '!H125=1,'Items sous domaines Maths '!G125,0) -> 0
... B124: =IF(OR('Items sous domaines Maths '!H128=3,'Items sous domaines Maths '!J128=3 ),'Items sous domaines Maths '!B128,0) -> 0 | C124: =IF(OR('Items sous domaines Maths '!H128=3,'Items sous domaines Maths '!J128=3 ),'Items sous domaines Maths '!C128) -> FALSE | D124: =IF(OR('Items sous domaines Maths '!H128=3,'Items sous domaines Maths '!J128=3 ),'Items sous domaines Maths '!D128,0) -> 0 | E124: =IF(OR('Items sous domaines Maths '!H128=3,'Items sous domaines Maths '!J128=3 ),'Items sous domaines Maths '!E128,0) -> 0 | F124: =IF(OR('Items sous domaines Maths '!H128=3,'Items sous domaines Maths '!J128=3 ),'Items sous domaines Maths '!F128,0) -> 0 | G124: =IF('Items sous domaines Maths '!H128=1,'Items sous domaines Maths '!G128,0) -> 0
A125: Maths élémentaires | B125: =IF(OR('Items sous domaines Maths '!H129=3,'Items sous domaines Maths '!J129=3 ),'Items sous domaines Maths '!B129,0) -> 0 | C125: =IF(OR('Items sous domaines Maths '!H129=3,'Items sous domaines Maths '!J129=3 ),'Items sous domaines Maths '!C129) -> FALSE | D125: =IF(OR('Items sous domaines Maths '!H129=3,'Items sous domaines Maths '!J129=3 ),'Items sous domaines Maths '!D129,0) -> 0 | E125: =IF(OR('Items sous domaines Maths '!H129=3,'Items sous domaines Maths '!J129=3 ),'Items sous domaines Maths '!E129,0) -> 0 | F125: =IF(OR('Items sous domaines Maths '!H129=3,'Items sous domaines Maths '!J129=3 ),'Items sous domaines Maths '!F129,0) -> 0 | G125: =IF('Items sous domaines Maths '!H129=1,'Items sous domaines Maths '!G129,0) -> 0
B126: =IF(OR('Items sous domaines Maths '!H130=3,'Items sous domaines Maths '!J130=3 ),'Items sous domaines Maths '!B130,0) -> 0 | C126: =IF(OR('Items sous domaines Maths '!H130=3,'Items sous domaines Maths '!J130=3 ),'Items sous domaines Maths '!C130) -> FALSE | D126: =IF(OR('Items sous domaines Maths '!H130=3,'Items sous domaines Maths '!J130=3 ),'Items sous domaines Maths '!D130,0) -> 0 | E126: =IF(OR('Items sous domaines Maths '!H130=3,'Items sous domaines Maths '!J130=3 ),'Items sous domaines Maths '!E130,0) -> 0 | F126: =IF(OR('Items sous domaines Maths '!H130=3,'Items sous domaines Maths '!J130=3 ),'Items sous domaines Maths '!F130,0) -> 0 | G126: =IF('Items sous domaines Maths '!H130=1,'Items sous domaines Maths '!G130,0) -> 0
B127: =IF(OR('Items sous domaines Maths '!H131=3,'Items sous domaines Maths '!J131=3 ),'Items sous domaines Maths '!B131,0) -> 0 | C127: =IF(OR('Items sous domaines Maths '!H131=3,'Items sous domaines Maths '!J131=3 ),'Items sous domaines Maths '!C131) -> FALSE | D127: =IF(OR('Items sous domaines Maths '!H131=3,'Items sous domaines Maths '!J131=3 ),'Items sous domaines Maths '!D131,0) -> 0 | E127: =IF(OR('Items sous domaines Maths '!H131=3,'Items sous domaines Maths '!J131=3 ),'Items sous domaines Maths '!E131,0) -> 0 | F127: =IF(OR('Items sous domaines Maths '!H131=3,'Items sous domaines Maths '!J131=3 ),'Items sous domaines Maths '!F131,0) -> 0 | G127: =IF('Items sous domaines Maths '!H131=1,'Items sous domaines Maths '!G131,0) -> 0
B128: =IF(OR('Items sous domaines Maths '!H132=3,'Items sous domaines Maths '!J132=3 ),'Items sous domaines Maths '!B132,0) -> 0 | C128: =IF(OR('Items sous domaines Maths '!H132=3,'Items sous domaines Maths '!J132=3 ),'Items sous domaines Maths '!C132) -> FALSE | D128: =IF(OR('Items sous domaines Maths '!H132=3,'Items sous domaines Maths '!J132=3 ),'Items sous domaines Maths '!D132,0) -> 0 | E128: =IF(OR('Items sous domaines Maths '!H132=3,'Items sous domaines Maths '!J132=3 ),'Items sous domaines Maths '!E132,0) -> 0 | F128: =IF(OR('Items sous domaines Maths '!H132=3,'Items sous domaines Maths '!J132=3 ),'Items sous domaines Maths '!F132,0) -> 0 | G128: =IF('Items sous domaines Maths '!H132=1,'Items sous domaines Maths '!G132,0) -> 0
B129: =IF(OR('Items sous domaines Maths '!H133=3,'Items sous domaines Maths '!J133=3 ),'Items sous domaines Maths '!B133,0) -> 0 | C129: =IF(OR('Items sous domaines Maths '!H133=3,'Items sous domaines Maths '!J133=3 ),'Items sous domaines Maths '!C133) -> FALSE | D129: =IF(OR('Items sous domaines Maths '!H133=3,'Items sous domaines Maths '!J133=3 ),'Items sous domaines Maths '!D133,0) -> 0 | E129: =IF(OR('Items sous domaines Maths '!H133=3,'Items sous domaines Maths '!J133=3 ),'Items sous domaines Maths '!E133,0) -> 0 | F129: =IF(OR('Items sous domaines Maths '!H133=3,'Items sous domaines Maths '!J133=3 ),'Items sous domaines Maths '!F133,0) -> 0 | G129: =IF('Items sous domaines Maths '!H133=1,'Items sous domaines Maths '!G133,0) -> 0
B130: =IF(OR('Items sous domaines Maths '!H134=3,'Items sous domaines Maths '!J134=3 ),'Items sous domaines Maths '!B134,0) -> 0 | C130: =IF(OR('Items sous domaines Maths '!H134=3,'Items sous domaines Maths '!J134=3 ),'Items sous domaines Maths '!C134) -> FALSE | D130: =IF(OR('Items sous domaines Maths '!H134=3,'Items sous domaines Maths '!J134=3 ),'Items sous domaines Maths '!D134,0) -> 0 | E130: =IF(OR('Items sous domaines Maths '!H134=3,'Items sous domaines Maths '!J134=3 ),'Items sous domaines Maths '!E134,0) -> 0 | F130: =IF(OR('Items sous domaines Maths '!H134=3,'Items sous domaines Maths '!J134=3 ),'Items sous domaines Maths '!F134,0) -> 0 | G130: =IF('Items sous domaines Maths '!H134=1,'Items sous domaines Maths '!G134,0) -> 0
B131: =IF(OR('Items sous domaines Maths '!H135=3,'Items sous domaines Maths '!J135=3 ),'Items sous domaines Maths '!B135,0) -> 0 | C131: =IF(OR('Items sous domaines Maths '!H135=3,'Items sous domaines Maths '!J135=3 ),'Items sous domaines Maths '!C135) -> FALSE | D131: =IF(OR('Items sous domaines Maths '!H135=3,'Items sous domaines Maths '!J135=3 ),'Items sous domaines Maths '!D135,0) -> 0 | E131: =IF(OR('Items sous domaines Maths '!H135=3,'Items sous domaines Maths '!J135=3 ),'Items sous domaines Maths '!E135,0) -> 0 | F131: =IF(OR('Items sous domaines Maths '!H135=3,'Items sous domaines Maths '!J135=3 ),'Items sous domaines Maths '!F135,0) -> 0 | G131: =IF('Items sous domaines Maths '!H135=1,'Items sous domaines Maths '!G135,0) -> 0
B132: =IF(OR('Items sous domaines Maths '!H136=3,'Items sous domaines Maths '!J136=3 ),'Items sous domaines Maths '!B136,0) -> 0 | C132: =IF(OR('Items sous domaines Maths '!H136=3,'Items sous domaines Maths '!J136=3 ),'Items sous domaines Maths '!C136) -> FALSE | D132: =IF(OR('Items sous domaines Maths '!H136=3,'Items sous domaines Maths '!J136=3 ),'Items sous domaines Maths '!D136,0) -> 0 | E132: =IF(OR('Items sous domaines Maths '!H136=3,'Items sous domaines Maths '!J136=3 ),'Items sous domaines Maths '!E136,0) -> 0 | F132: =IF(OR('Items sous domaines Maths '!H136=3,'Items sous domaines Maths '!J136=3 ),'Items sous domaines Maths '!F136,0) -> 0 | G132: =IF('Items sous domaines Maths '!H136=1,'Items sous domaines Maths '!G136,0) -> 0
B133: =IF(OR('Items sous domaines Maths '!H137=3,'Items sous domaines Maths '!J137=3 ),'Items sous domaines Maths '!B137,0) -> 0 | C133: =IF(OR('Items sous domaines Maths '!H137=3,'Items sous domaines Maths '!J137=3 ),'Items sous domaines Maths '!C137) -> FALSE | D133: =IF(OR('Items sous domaines Maths '!H137=3,'Items sous domaines Maths '!J137=3 ),'Items sous domaines Maths '!D137,0) -> 0 | E133: =IF(OR('Items sous domaines Maths '!H137=3,'Items sous domaines Maths '!J137=3 ),'Items sous domaines Maths '!E137,0) -> 0 | F133: =IF(OR('Items sous domaines Maths '!H137=3,'Items sous domaines Maths '!J137=3 ),'Items sous domaines Maths '!F137,0) -> 0 | G133: =IF('Items sous domaines Maths '!H137=1,'Items sous domaines Maths '!G137,0) -> 0
B134: =IF(OR('Items sous domaines Maths '!H138=3,'Items sous domaines Maths '!J138=3 ),'Items sous domaines Maths '!B138,0) -> 0 | C134: =IF(OR('Items sous domaines Maths '!H138=3,'Items sous domaines Maths '!J138=3 ),'Items sous domaines Maths '!C138) -> FALSE | D134: =IF(OR('Items sous domaines Maths '!H138=3,'Items sous domaines Maths '!J138=3 ),'Items sous domaines Maths '!D138,0) -> 0 | E134: =IF(OR('Items sous domaines Maths '!H138=3,'Items sous domaines Maths '!J138=3 ),'Items sous domaines Maths '!E138,0) -> 0 | F134: =IF(OR('Items sous domaines Maths '!H138=3,'Items sous domaines Maths '!J138=3 ),'Items sous domaines Maths '!F138,0) -> 0 | G134: =IF('Items sous domaines Maths '!H138=1,'Items sous domaines Maths '!G138,0) -> 0
B135: =IF(OR('Items sous domaines Maths '!H139=3,'Items sous domaines Maths '!J139=3 ),'Items sous domaines Maths '!B139,0) -> 0 | C135: =IF(OR('Items sous domaines Maths '!H139=3,'Items sous domaines Maths '!J139=3 ),'Items sous domaines Maths '!C139) -> FALSE | D135: =IF(OR('Items sous domaines Maths '!H139=3,'Items sous domaines Maths '!J139=3 ),'Items sous domaines Maths '!D139,0) -> 0 | E135: =IF(OR('Items sous domaines Maths '!H139=3,'Items sous domaines Maths '!J139=3 ),'Items sous domaines Maths '!E139,0) -> 0 | F135: =IF(OR('Items sous domaines Maths '!H139=3,'Items sous domaines Maths '!J139=3 ),'Items sous domaines Maths '!F139,0) -> 0 | G135: =IF('Items sous domaines Maths '!H139=1,'Items sous domaines Maths '!G139,0) -> 0
B136: =IF(OR('Items sous domaines Maths '!H140=3,'Items sous domaines Maths '!J140=3 ),'Items sous domaines Maths '!B140,0) -> 0 | C136: =IF(OR('Items sous domaines Maths '!H140=3,'Items sous domaines Maths '!J140=3 ),'Items sous domaines Maths '!C140) -> FALSE | D136: =IF(OR('Items sous domaines Maths '!H140=3,'Items sous domaines Maths '!J140=3 ),'Items sous domaines Maths '!D140,0) -> 0 | E136: =IF(OR('Items sous domaines Maths '!H140=3,'Items sous domaines Maths '!J140=3 ),'Items sous domaines Maths '!E140,0) -> 0 | F136: =IF(OR('Items sous domaines Maths '!H140=3,'Items sous domaines Maths '!J140=3 ),'Items sous domaines Maths '!F140,0) -> 0 | G136: =IF('Items sous domaines Maths '!H140=1,'Items sous domaines Maths '!G140,0) -> 0
B137: =IF(OR('Items sous domaines Maths '!H141=3,'Items sous domaines Maths '!J141=3 ),'Items sous domaines Maths '!B141,0) -> 0 | C137: =IF(OR('Items sous domaines Maths '!H141=3,'Items sous domaines Maths '!J141=3 ),'Items sous domaines Maths '!C141) -> FALSE | D137: =IF(OR('Items sous domaines Maths '!H141=3,'Items sous domaines Maths '!J141=3 ),'Items sous domaines Maths '!D141,0) -> 0 | E137: =IF(OR('Items sous domaines Maths '!H141=3,'Items sous domaines Maths '!J141=3 ),'Items sous domaines Maths '!E141,0) -> 0 | F137: =IF(OR('Items sous domaines Maths '!H141=3,'Items sous domaines Maths '!J141=3 ),'Items sous domaines Maths '!F141,0) -> 0 | G137: =IF('Items sous domaines Maths '!H141=1,'Items sous domaines Maths '!G141,0) -> 0
... B186: =IF(OR('Items sous domaines Maths '!H190=3,'Items sous domaines Maths '!J190=3 ),'Items sous domaines Maths '!B190,0) -> 0 | C186: =IF(OR('Items sous domaines Maths '!H190=3,'Items sous domaines Maths '!J190=3 ),'Items sous domaines Maths '!C190) -> FALSE | D186: =IF(OR('Items sous domaines Maths '!H190=3,'Items sous domaines Maths '!J190=3 ),'Items sous domaines Maths '!D190,0) -> 0 | E186: =IF(OR('Items sous domaines Maths '!H190=3,'Items sous domaines Maths '!J190=3 ),'Items sous domaines Maths '!E190,0) -> 0 | F186: =IF(OR('Items sous domaines Maths '!H190=3,'Items sous domaines Maths '!J190=3 ),'Items sous domaines Maths '!F190,0) -> 0 | G186: =IF('Items sous domaines Maths '!H190=1,'Items sous domaines Maths '!G190,0) -> 0
A187: Analyse : Etude de fonction 1D | B187: =IF(OR('Items sous domaines Maths '!H191=3,'Items sous domaines Maths '!J191=3 ),'Items sous domaines Maths '!B191,0) -> Analyse | C187: =IF(OR('Items sous domaines Maths '!H191=3,'Items sous domaines Maths '!J191=3 ),'Items sous domaines Maths '!C191) -> Fonctions d'une variable | D187: =IF(OR('Items sous domaines Maths '!H191=3,'Items sous domaines Maths '!J191=3 ),'Items sous domaines Maths '!D191,0) -> Géneralités sur les fonctions | E187: =IF(OR('Items sous domaines Maths '!H191=3,'Items sous domaines Maths '!J191=3 ),'Items sous domaines Maths '!E191,0) -> Définition | F187: =IF(OR('Items sous domaines Maths '!H191=3,'Items sous domaines Maths '!J191=3 ),'Items sous domaines Maths '!F191,0) -> Savoir les définitions d'antécédent, d'image. | G187: ETS | H187: https://uel.unisciel.fr/mathematiques/analyse1/analyse1_ch03/co/analyse1_ch03.html
B188: =IF(OR('Items sous domaines Maths '!H192=3,'Items sous domaines Maths '!J192=3 ),'Items sous domaines Maths '!B192,0) -> Analyse | C188: =IF(OR('Items sous domaines Maths '!H192=3,'Items sous domaines Maths '!J192=3 ),'Items sous domaines Maths '!C192) -> Fonctions d'une variable | D188: =IF(OR('Items sous domaines Maths '!H192=3,'Items sous domaines Maths '!J192=3 ),'Items sous domaines Maths '!D192,0) -> 0 | E188: =IF(OR('Items sous domaines Maths '!H192=3,'Items sous domaines Maths '!J192=3 ),'Items sous domaines Maths '!E192,0) -> Propriétés | F188: =IF(OR('Items sous domaines Maths '!H192=3,'Items sous domaines Maths '!J192=3 ),'Items sous domaines Maths '!F192,0) -> Etudier la parité, la périodicité, réduction d'intervalles d'étude et étudier une fonction.
B189: =IF(OR('Items sous domaines Maths '!H193=3,'Items sous domaines Maths '!J193=3 ),'Items sous domaines Maths '!B193,0) -> Analyse | C189: =IF(OR('Items sous domaines Maths '!H193=3,'Items sous domaines Maths '!J193=3 ),'Items sous domaines Maths '!C193) -> Fonctions d'une variable | D189: =IF(OR('Items sous domaines Maths '!H193=3,'Items sous domaines Maths '!J193=3 ),'Items sous domaines Maths '!D193,0) -> Limites | E189: =IF(OR('Items sous domaines Maths '!H193=3,'Items sous domaines Maths '!J193=3 ),'Items sous domaines Maths '!E193,0) -> Limites finies et infinies en un réel fini et en l'infini | F189: =IF(OR('Items sous domaines Maths '!H193=3,'Items sous domaines Maths '!J193=3 ),'Items sous domaines Maths '!F193,0) -> 0
B190: =IF(OR('Items sous domaines Maths '!H194=3,'Items sous domaines Maths '!J194=3 ),'Items sous domaines Maths '!B194,0) -> Analyse | C190: =IF(OR('Items sous domaines Maths '!H194=3,'Items sous domaines Maths '!J194=3 ),'Items sous domaines Maths '!C194) -> Fonctions d'une variable | D190: =IF(OR('Items sous domaines Maths '!H194=3,'Items sous domaines Maths '!J194=3 ),'Items sous domaines Maths '!D194,0) -> 0 | E190: =IF(OR('Items sous domaines Maths '!H194=3,'Items sous domaines Maths '!J194=3 ),'Items sous domaines Maths '!E194,0) -> Limites des fonctions usuelles | F190: =IF(OR('Items sous domaines Maths '!H194=3,'Items sous domaines Maths '!J194=3 ),'Items sous domaines Maths '!F194,0) -> 0
B191: =IF(OR('Items sous domaines Maths '!H195=3,'Items sous domaines Maths '!J195=3 ),'Items sous domaines Maths '!B195,0) -> Analyse | C191: =IF(OR('Items sous domaines Maths '!H195=3,'Items sous domaines Maths '!J195=3 ),'Items sous domaines Maths '!C195) -> Fonctions d'une variable | D191: =IF(OR('Items sous domaines Maths '!H195=3,'Items sous domaines Maths '!J195=3 ),'Items sous domaines Maths '!D195,0) -> 0 | E191: =IF(OR('Items sous domaines Maths '!H195=3,'Items sous domaines Maths '!J195=3 ),'Items sous domaines Maths '!E195,0) -> Opérations sur les limites et formes indéterminées | F191: =IF(OR('Items sous domaines Maths '!H195=3,'Items sous domaines Maths '!J195=3 ),'Items sous domaines Maths '!F195,0) -> 0
B192: =IF(OR('Items sous domaines Maths '!H196=3,'Items sous domaines Maths '!J196=3 ),'Items sous domaines Maths '!B196,0) -> Analyse | C192: =IF(OR('Items sous domaines Maths '!H196=3,'Items sous domaines Maths '!J196=3 ),'Items sous domaines Maths '!C196) -> Fonctions d'une variable | D192: =IF(OR('Items sous domaines Maths '!H196=3,'Items sous domaines Maths '!J196=3 ),'Items sous domaines Maths '!D196,0) -> 0 | E192: =IF(OR('Items sous domaines Maths '!H196=3,'Items sous domaines Maths '!J196=3 ),'Items sous domaines Maths '!E196,0) -> Techniques de calculs de limites | F192: =IF(OR('Items sous domaines Maths '!H196=3,'Items sous domaines Maths '!J196=3 ),'Items sous domaines Maths '!F196,0) -> Levées d'indeterminations.
B193: =IF(OR('Items sous domaines Maths '!H197=3,'Items sous domaines Maths '!J197=3 ),'Items sous domaines Maths '!B197,0) -> Analyse | C193: =IF(OR('Items sous domaines Maths '!H197=3,'Items sous domaines Maths '!J197=3 ),'Items sous domaines Maths '!C197) -> Fonctions d'une variable | D193: =IF(OR('Items sous domaines Maths '!H197=3,'Items sous domaines Maths '!J197=3 ),'Items sous domaines Maths '!D197,0) -> 0 | E193: =IF(OR('Items sous domaines Maths '!H197=3,'Items sous domaines Maths '!J197=3 ),'Items sous domaines Maths '!E197,0) -> Interprétation graphique et asymptotes | F193: =IF(OR('Items sous domaines Maths '!H197=3,'Items sous domaines Maths '!J197=3 ),'Items sous domaines Maths '!F197,0) -> 0
B194: =IF(OR('Items sous domaines Maths '!H198=3,'Items sous domaines Maths '!J198=3 ),'Items sous domaines Maths '!B198,0) -> Analyse | C194: =IF(OR('Items sous domaines Maths '!H198=3,'Items sous domaines Maths '!J198=3 ),'Items sous domaines Maths '!C198) -> Fonctions d'une variable | D194: =IF(OR('Items sous domaines Maths '!H198=3,'Items sous domaines Maths '!J198=3 ),'Items sous domaines Maths '!D198,0) -> Continuité | E194: =IF(OR('Items sous domaines Maths '!H198=3,'Items sous domaines Maths '!J198=3 ),'Items sous domaines Maths '!E198,0) -> Continuité en un point | F194: =IF(OR('Items sous domaines Maths '!H198=3,'Items sous domaines Maths '!J198=3 ),'Items sous domaines Maths '!F198,0) -> 0
B195: =IF(OR('Items sous domaines Maths '!H199=3,'Items sous domaines Maths '!J199=3 ),'Items sous domaines Maths '!B199,0) -> Analyse | C195: =IF(OR('Items sous domaines Maths '!H199=3,'Items sous domaines Maths '!J199=3 ),'Items sous domaines Maths '!C199) -> Fonctions d'une variable | D195: =IF(OR('Items sous domaines Maths '!H199=3,'Items sous domaines Maths '!J199=3 ),'Items sous domaines Maths '!D199,0) -> 0 | E195: =IF(OR('Items sous domaines Maths '!H199=3,'Items sous domaines Maths '!J199=3 ),'Items sous domaines Maths '!E199,0) -> Continuité sur un intervalle | F195: =IF(OR('Items sous domaines Maths '!H199=3,'Items sous domaines Maths '!J199=3 ),'Items sous domaines Maths '!F199,0) -> 0
B196: =IF(OR('Items sous domaines Maths '!H200=3,'Items sous domaines Maths '!J200=3 ),'Items sous domaines Maths '!B200,0) -> Analyse | C196: =IF(OR('Items sous domaines Maths '!H200=3,'Items sous domaines Maths '!J200=3 ),'Items sous domaines Maths '!C200) -> Fonctions d'une variable | D196: =IF(OR('Items sous domaines Maths '!H200=3,'Items sous domaines Maths '!J200=3 ),'Items sous domaines Maths '!D200,0) -> Derivation | E196: =IF(OR('Items sous domaines Maths '!H200=3,'Items sous domaines Maths '!J200=3 ),'Items sous domaines Maths '!E200,0) -> Dérivabilité en un point | F196: =IF(OR('Items sous domaines Maths '!H200=3,'Items sous domaines Maths '!J200=3 ),'Items sous domaines Maths '!F200,0) -> Notion de nombre dérivé et interprétation géométrique. Taux de variation.
B197: =IF(OR('Items sous domaines Maths '!H201=3,'Items sous domaines Maths '!J201=3 ),'Items sous domaines Maths '!B201,0) -> Analyse | C197: =IF(OR('Items sous domaines Maths '!H201=3,'Items sous domaines Maths '!J201=3 ),'Items sous domaines Maths '!C201) -> Fonctions d'une variable | D197: =IF(OR('Items sous domaines Maths '!H201=3,'Items sous domaines Maths '!J201=3 ),'Items sous domaines Maths '!D201,0) -> 0 | E197: =IF(OR('Items sous domaines Maths '!H201=3,'Items sous domaines Maths '!J201=3 ),'Items sous domaines Maths '!E201,0) -> 0 | F197: =IF(OR('Items sous domaines Maths '!H201=3,'Items sous domaines Maths '!J201=3 ),'Items sous domaines Maths '!F201,0) -> Existence et équation de la tangente en un point.
B198: =IF(OR('Items sous domaines Maths '!H202=3,'Items sous domaines Maths '!J202=3 ),'Items sous domaines Maths '!B202,0) -> Analyse | C198: =IF(OR('Items sous domaines Maths '!H202=3,'Items sous domaines Maths '!J202=3 ),'Items sous domaines Maths '!C202) -> Fonctions d'une variable | D198: =IF(OR('Items sous domaines Maths '!H202=3,'Items sous domaines Maths '!J202=3 ),'Items sous domaines Maths '!D202,0) -> 0 | E198: =IF(OR('Items sous domaines Maths '!H202=3,'Items sous domaines Maths '!J202=3 ),'Items sous domaines Maths '!E202,0) -> Dérivabilité sur un intervalle | F198: =IF(OR('Items sous domaines Maths '!H202=3,'Items sous domaines Maths '!J202=3 ),'Items sous domaines Maths '!F202,0) -> Formules des dérivées usuelles et domaines d'existence.
B199: =IF(OR('Items sous domaines Maths '!H203=3,'Items sous domaines Maths '!J203=3 ),'Items sous domaines Maths '!B203,0) -> Analyse | C199: =IF(OR('Items sous domaines Maths '!H203=3,'Items sous domaines Maths '!J203=3 ),'Items sous domaines Maths '!C203) -> Fonctions d'une variable | D199: =IF(OR('Items sous domaines Maths '!H203=3,'Items sous domaines Maths '!J203=3 ),'Items sous domaines Maths '!D203,0) -> 0 | E199: =IF(OR('Items sous domaines Maths '!H203=3,'Items sous domaines Maths '!J203=3 ),'Items sous domaines Maths '!E203,0) -> Application de la dérivée | F199: =IF(OR('Items sous domaines Maths '!H203=3,'Items sous domaines Maths '!J203=3 ),'Items sous domaines Maths '!F203,0) -> Signe de la dérivée d'ordre un et variation.
... B206: =IF(OR('Items sous domaines Maths '!H210=3,'Items sous domaines Maths '!J210=3 ),'Items sous domaines Maths '!B210,0) -> Analyse | C206: =IF(OR('Items sous domaines Maths '!H210=3,'Items sous domaines Maths '!J210=3 ),'Items sous domaines Maths '!C210) -> Fonctions d'une variable | D206: =IF(OR('Items sous domaines Maths '!H210=3,'Items sous domaines Maths '!J210=3 ),'Items sous domaines Maths '!D210,0) -> 0 | E206: =IF(OR('Items sous domaines Maths '!H210=3,'Items sous domaines Maths '!J210=3 ),'Items sous domaines Maths '!E210,0) -> 0 | F206: =IF(OR('Items sous domaines Maths '!H210=3,'Items sous domaines Maths '!J210=3 ),'Items sous domaines Maths '!F210,0) -> Théorème des valeurs intermédiaires, théorème de la bijection.
