Workbook

Sheet Objectifs Sciences 2022-2023
A1: Objectifs d'apprentissage du tronc commun de la formation en sciences au sein de l'Ecole d'Ingénieurs CESI
A2: A - Fondamentaux en sciences physiques (notions de prérequis) | B2: 1 | C2: Cycle préparatoire (CPI)
A3: A.1 Connaître les grandes notions de mécanique, d'électricité, de thermodynamique
A4: A.2 Mobiliser les 3 compétences élémentaires dans des exercices d'application (Modéliser, Calculer, Raisonner)
A5: B - Calcul numérique et analytique
A6: B.1 Faire preuve d'autonomie, d'initiative dans la démarche de résolution d'un problème
A7: B.2 Savoir employer une démarche de résolution analytico-numérique (du modèle physique ou des hypothèses jusqu'à l'implémentation)
A8: B.3 Savoir lire, comprendre, concevoir des algorithmes (sans langage spécifique, en privilégiant le pseudo-code)
A9: B.4 Savoir analyser et interpréter un résultat, avoir un point de vue critique et l'exprimer
A10: C - Sciences de la modélisation | B10: 2 | C10: CI
A11: C.1 Savoir identifier les outils utiles pour la résolution du problème
A12: C.2 Connaître, comprendre et savoir faire usage des outils de la modélisation numérique (MEF, VF, DF)
A13: C.3 Être capable d'analyse de critique des modèles, des résultats

Sheet Items sous domaines Sciences 
A1: Objectifs d'apprentissage des Sciences | H1: Remédiation
A4: Propositions d'Items pour les Objectifs d'apprentissage | G4: nv | H4: lien Unisciel ou livre scolaire
B7: Mécanique | D7: Mécanique
B10: Mécanique | C10: Point | D10: Mécanique du point | E10: Distinguer les différents types de force (poids, réaction, frottements (statique et cinétique), tension...). | F10: 1 | G10: =F10 -> 1
B11: Mécanique | C11: Point | E11: Appliquer le PFD avec et sans frottements à un mouvement plan. | F11: 1 | G11: =F11 -> 1
B12: Mécanique | C12: Point | E12: Calculer le travail d'une force. | F12: 1 | G12: =F12 -> 1
B13: Mécanique | C13: Point | E13: Distinguer une force conservative et non conservative. | F13: 1 | G13: =F13 -> 1
B14: Mécanique | C14: Point | E14: Calculer une énergie mécanique, cinétique, potentielle. | F14: 1 | G14: =F14 -> 1
B15: Mécanique | C15: Point | E15: Appliquer le théorème de conservation de l'énergie mécanique. | F15: 1 | G15: =F15 -> 1
B16: Mécanique | C16: Point | E16: Appliquer le théorème de l'énergie cinétique. | F16: 1 | G16: =F16 -> 1
B17: Mécanique | C17: Point | E17: Établir les équations horaires (sans et avec frottements). | F17: 1 | G17: =F17 -> 1
B18: Mécanique | C18: Point | E18: Calculer le moment d’une force. | F18: 1 | G18: =F18 -> 1
B19: Mécanique | C19: Point | E19: Appliquer le PFD avec et sans frottements à un mouvement circulaire. | F19: 1 | G19: =F19 -> 1
B20: Mécanique | C20: Point | E20: Établir une équation différentielle du 1er et 2ème ordre. | F20: 1 | G20: =F20 -> 1
B21: Mécanique | C21: Point | E21: Calculer une force. | F21: 5 | G21: =F21 -> 5
B22: Mécanique | C22: Point | E22: Calculer un moment. | F22: 5 | G22: =F22 -> 5
B23: Mécanique | C23: Point | E23: Calculer une énergie mécanique. | F23: 5 | G23: =F23 -> 5
B24: Mécanique | C24: Mécanisme | D24: Mécanique du solide | E24: Établir le schéma mécanique d'une structure. | F24: 5 | G24: =F24 -> 5
B25: Mécanique | C25: Solide | E25: Appliquer le principe fondamental de la statique. | F25: 5 | G25: =F25 -> 5
B26: Mécanique | C26: Solide | E26: Expliquer l'équilibre statique d'un solide ou d'un ensemble de solides. | F26: 5 | G26: =F26 -> 5
B27: Mécanique | C27: Solide | E27: Appliquer le torseur pour résoudre un problème de statique (PFS). | F27: 5 | G27: =F27 -> 5
B28: Mécanique | C28: Point | E28: Appliquer les lois de Coulomb. | F28: 5 | G28: =F28 -> 5
B29: Mécanique | C29: Solide | E29: Utiliser les liaisons mécaniques usuelles. | F29: 5 | G29: =F29 -> 5
B30: Mécanique | C30: Solide | E30: Résoudre un problème de statique graphique. | F30: 5 | G30: =F30 -> 5
B31: Mécanique | C31: Solide | E31: Appliquer le principe fondamental de la dynamique. | F31: 6 | G31: =F31 -> 6
B32: Mécanique | C32: Solide | E32: Schématiser les actions mécaniques. | F32: 6 | G32: =F32 -> 6
B33: Mécanique | C33: Solide | E33: Calculer une puissance mécanique. | F33: 6 | G33: =F33 -> 6
B34: Mécanique | C34: Solide | E34: Appliquer le théorème de l'énergie cinétique. | F34: 6 | G34: =F34 -> 6
B35: Mécanique | C35: Solide | E35: Utiliser les moments d'inertie équivalents. | F35: 6 | G35: =F35 -> 6
B36: Mécanique | C36: RDM | D36: RDM | E36: Expliquer les notions "contrainte" et "déformation". | F36: 2 | G36: =F36 -> 2
B37: Mécanique | C37: RDM | E37: Interpréter une courbe de traction (domaines élastique, plastique, striction, rupture) et ses données caractéristiques (résistance élastique, résistance max). | F37: 2 | G37: =F37 -> 2
B38: Mécanique | C38: RDM | E38: Calculer un module d’Young à partir d’une courbe de traction. | F38: 2 | G38: =F38 -> 2
B39: Mécanique | C39: RDM | E39: Calculer une contrainte et un allongement. | F39: 2 | G39: =F39 -> 2
B40: Mécanique | C40: RDM | E40: Utiliser la loi de Hooke. | F40: 2 | G40: =F40 -> 2
B41: Mécanique | C41: RDM | E41: Corréler les propriétés mécaniques et thermiques d’un matériau au type de liaison. | F41: 2 | G41: =F41 -> 2
B42: Mécanique | C42: RDM | E42: Discriminer un matériau pour une application. | F42: 2 | G42: =F42 -> 2
B43: Mécanique | C43: RDM | E43: Identifier les liaisons mécaniques (2D) entre solides, internes/externes (appui simple, articulation). | F43: 2 | G43: =F43 -> 2
B44: Mécanique | C44: RDM | E44: Identifier et appliquer les différents types de charges (force ponctuelle, charge linéique). | F44: 2 | G44: =F44 -> 2
B45: Mécanique | C45: RDM | E45: Déterminer le nombre de degrés de liberté d’un système articulé. | F45: 2 | G45: =F45 -> 2
B46: Mécanique | C46: RDM | E46: Utiliser le principe d’action/réaction pour appliquer le PFS. | F46: 2 | G46: =F46 -> 2
B47: Mécanique | C47: RDM | E47: Mettre en place une méthode de résolution d’un système isostatique. | F47: 2 | G47: =F47 -> 2
B48: Mécanique | C48: RDM | E48: Calculer une descente de charge. | F48: 2 | G48: =F48 -> 2
... B56: Mécanique | C56: RDM | E56: Sélectionner une poutre (forme, matériau) adaptée à un contexte de structure simple. | F56: 2 | G56: =F56 -> 2
B57: Mécanique | C57: Fluides | D57: Mécanique des fluides | E57: Établir l'équation locale de la statique des fluides à partir d'un bilan de forces. | F57: 3 | G57: =F57 -> 3
B58: Mécanique | C58: Fluides | E58: Déterminer un champ de pression. | F58: 3 | G58: =F58 -> 3
B59: Mécanique | C59: Fluides | E59: Calculer une intégrale multiple. | F59: 3 | G59: =F59 -> 3
B60: Mécanique | C60: Fluides | E60: Calculer la résultante des forces de pression sur une surface. | F60: 3 | G60: =F60 -> 3
B61: Mécanique | C61: Fluides | E61: Appliquer le théorème Bernoulli sur un fluide en mouvement. | F61: 3 | G61: =F61 -> 3
B62: Mécanique | C62: Fluides | E62: Distinguer un écoulement d'un fluide parfait d'un écoulement d'un fluide réel. | F62: 3 | G62: =F62 -> 3
B63: Mécanique | C63: Fluides | E63: Calculer les pertes de charges singulières ou régulières. | F63: 3 | G63: =F63 -> 3
B64: Mécanique | C64: Fluides | E64: Déterminer les différents types d'écoulements d'un fluide réel à l'aide de nombre adimensionnel. | F64: 3 | G64: =F64 -> 3
B65: Mécanique | C65: Fluides | E65: Comparer des circuits équipés de deux pompes centrifuges en série ou en parallèle. | F65: 3 | G65: =F65 -> 3
B66: Mécanique | C66: Fluides | E66: Différencier les types de pompes existantes. | F66: 3 | G66: =F66 -> 3
B67: Mécanique | C67: Fluides | E67: Sélectionner les organes hydrauliques adéquats. | F67: 3 | G67: =F67 -> 3
B68: Mécanique | C68: Fluides | E68: Sélectionner une pompe pour répondre à un réseau hydraulique particulier (HMT, NPSH). | F68: 3 | G68: =F68 -> 3
B69: Mécanique | C69: Solide | D69: Mécanique du solide | E69: Utiliser les matrices. | F69: 4 | G69: =F69 -> 4
B70: Mécanique | C70: Solide | E70: Déterminer le barycentre d'un solide. | F70: 4 | G70: =F70 -> 4
B71: Mécanique | C71: Solide | E71: Utiliser le repère adéquat au problème (cartésien, polaire, sphérique). | F71: 4 | G71: =F71 -> 4
B72: Mécanique | C72: Solide | E72: Résoudre un problème de mécanique du solide. | F72: 4 | G72: =F72 -> 4
B73: Mécanique | C73: Solide | E73: Calculer les matrices d'inertie et les opérateurs d'inertie d'un solide. | F73: 4 | G73: =F73 -> 4
B74: Mécanique | C74: Solide | E74: Utiliser le théorème de Huygens. | F74: 4 | G74: =F74 -> 4
B75: Mécanique | C75: Solide | E75: Représenter les liaisons mécaniques. | F75: 4 | G75: =F75 -> 4
B76: Mécanique | C76: Solide | E76: Établir les torseurs cinématiques et d'action mécanique. | F76: 4 | G76: =F76 -> 4
B77: Mécanique | C77: Solide | E77: Utiliser les engrenages. | F77: 4 | G77: =F77 -> 4
B78: Electricité - Electromagnétisme | D78: Electricité | G78: =F78 -> 0
B79: Electricité - Electromagnétisme | C79: Electricité | D79: Electricité - courant continu | E79: Identifier les différents composants d'un circuit électrique (générateur, résistance, diode, transistor…) (prérequis). | F79: 1 | G79: =F79 -> 1
B80: Electricité - Electromagnétisme | C80: Electricité | E80: Connaître les conventions (générateur et récepteur, sens du courant) (prérequis). | F80: 1 | G80: =F80 -> 1
B81: Electricité - Electromagnétisme | C81: Electricité | E81: Produire une mesure physique à l'aide de l'outil adapté (prérequis). | F81: 1 | G81: =F81 -> 1
B82: Electricité - Electromagnétisme | C82: Electricité | E82: Décrire la constitution et le fonctionnement d'une résistance. | F82: 1 | G82: =F82 -> 1
B83: Electricité - Electromagnétisme | C83: Electricité | E83: Expliquer la notion de différence de potentiel. | F83: 1 | G83: =F83 -> 1
B84: Electricité - Electromagnétisme | C84: Electricité | E84: Appliquer la loi d’Ohm. | F84: 1 | G84: =F84 -> 1
B85: Electricité - Electromagnétisme | C85: Electricité | E85: Appliquer les lois de Kirchhoff. | F85: 1 | G85: =F85 -> 1
B86: Electricité - Electromagnétisme | C86: Electricité | E86: Calculer une résistance équivalente. | F86: 1 | G86: =F86 -> 1
B87: Electricité - Electromagnétisme | C87: Electricité | E87: Appliquer le théorème de Thévenin. | F87: 1 | G87: =F87 -> 1
B88: Electricité - Electromagnétisme | C88: Electricité | E88: Appliquer le théorème du pont diviseur de tension. | F88: 1 | G88: =F88 -> 1
B89: Electricité - Electromagnétisme | C89: Electricité | E89: Décrire le fonctionnement d’une jonction PN. | F89: 1 | G89: =F89 -> 1
B90: Electricité - Electromagnétisme | C90: Electricité | E90: Décrire le fonctionnement d’une diode (caractéristique, polarisation directe et inverse). | F90: 1 | G90: =F90 -> 1
B91: Electricité - Electromagnétisme | C91: Electricité | E91: Décrire le fonctionnement d’un transistor (caractéristique, polarisations). | F91: 1 | G91: =F91 -> 1
... B95: Electricité - Electromagnétisme | C95: Electricité | E95: Appliquer le théorème de superposition. | F95: 1 | G95: =F95 -> 1
B96: Electricité - Electromagnétisme | C96: Electricité | D96: Electricité - courant alternatif | E96: Expliquer le mécanisme de transformation d'une onde en signal électrique et inversement (principe du micro et du haut-parleur). | F96: 1 | G96: =F96 -> 1
B97: Electricité - Electromagnétisme | C97: Electricité | E97: Décrire les caractéristiques physiques d'un circuit et de ses composants soumis à un courant alternatif (inductance, capacité, impédance, phase, admittance). | F97: 1 | G97: =F97 -> 1
B98: Electricité - Electromagnétisme | C98: Electricité | E98: Représenter et manipuler les grandeurs électriques à l'aide des nombres complexes. | F98: 1 | G98: =F98 -> 1
B99: Electricité - Electromagnétisme | C99: Electricité | E99: Expliquer le principe de l'électromagnétisme dans le contexte d'une bobine. | F99: 1 | G99: =F99 -> 1
B100: Electricité - Electromagnétisme | C100: Electricité | E100: Établir la fonction de transfert d'un système de type micro. | F100: 1 | G100: =F100 -> 1
B101: Electricité - Electromagnétisme | C101: Electricité | E101: Interpréter une courbe de réponse fréquentielle. | F101: 1 | G101: =F101 -> 1
B102: Electricité - Electromagnétisme | C102: Electricité | E102: Analyser la qualité de la transmission du signal en calculant le rapport signal/bruit. | F102: 1 | G102: =F102 -> 1
B103: Electricité - Electromagnétisme | C103: Electricité | D103: Electronique - montages | E103: Expliquer le comportement du condensateur dans un circuit (propriétés, charge/décharge, constante de temps). | F103: 1 | G103: =F103 -> 1
B104: Electricité - Electromagnétisme | C104: Electricité | E104: Expliquer le comportement d'une bobine dans un circuit (propriétés, résistance propre, inductance, constante de temps). | F104: 1 | G104: =F104 -> 1
B105: Electricité - Electromagnétisme | C105: Electricité | E105: Expérimenter différents filtres : RL, RC, RLC. | F105: 1 | G105: =F105 -> 1
B106: Electricité - Electromagnétisme | C106: Electricité | E106: Produire un diagramme de Bode. | F106: 1 | G106: =F106 -> 1
B107: Electricité - Electromagnétisme | C107: Electricité | E107: Reconnaître les filtres passe-bas/haut/bande. | F107: 1 | G107: =F107 -> 1
B108: Electricité - Electromagnétisme | C108: Electricité | D108: Electricité - courant continu | E108: Calculer un courant et une tension à partir de la loi d'Ohm et des lois de Kirchhoff. | F108: 5 | G108: =F108 -> 5
B109: Electricité - Electromagnétisme | C109: Electricité | E109: Calculer la puissance et l'énergie d'un récepteur ou d'un générateur alimenté en courant continu. | F109: 5 | G109: =F109 -> 5
B110: Electricité - Electromagnétisme | C110: Electricité | E110: Calculer un générateur équivalent à partir de générateurs en série et/ou en parallèle. | F110: 5 | G110: =F110 -> 5
B111: Electricité - Electromagnétisme | C111: Electricité | E111: Calculer une résistance équivalente à partir de résistances en série et/ou en parallèle. | F111: 5 | G111: =F111 -> 5 | I111: lien Moodle
B112: Electricité - Electromagnétisme | C112: Electricité | E112: Utiliser et modifier un langage de programmation de 1er niveau (Arduino). | F112: 5 | G112: =F112 -> 5
B113: Electricité - Electromagnétisme | C113: Electricité | D113: Electricité - courant alternatif | E113: Calculer les grandeurs instantanées et efficaces du courant alternatif sinusoïdal. | F113: 6 | G113: =F113 -> 6
B114: Electricité - Electromagnétisme | C114: Electricité | E114: Schématiser les grandeurs instantanées et efficaces du courant alternatif sinusoïdal dans un diagramme temporel et de Fresnel. | F114: 6 | G114: =F114 -> 6
B115: Electricité - Electromagnétisme | C115: Electricité | E115: Calculer l'impédance équivalente à partir d'impédances de récepteurs en parallèle ou série (résistance, bobine et self). | F115: 6 | G115: =F115 -> 6
B116: Electricité - Electromagnétisme | C116: Electricité | E116: Calculer la somme de courants ou tensions dans un circuit en régime alternatif sinusoïdal. | F116: 6 | G116: =F116 -> 6
...

Sheet Remédiation A3
A1: Aide :
A2: Vous retrouverez dans les onglets votre cursus
A3: Vous retrouverez les éléments évaluables de votre dossier de synthèse avec les chapitres et thèmes sur lesquels vous serez interrogé
A4: Vos révisions sont donc ciblées sur la base de ce référentiel et les AAVs des blocs
A5: Pour les A1 et A3 vous pouvez renseigner vos scores et voir votre progression par rapport au positionnement
A7: Une note supérieure à 10/20 au test de positionnement est attendu au minimum
A9: 2) Insérer vos résultats (nombre de bonnes réponses sur THEIA) dans les cases :
A10: 3) faites vos diagrammes de remédiation sur la base des scores en pourcentage
A11: Mécanique
A12: Compétences | C12: Calculer | D12: Modéliser | E12: Valider | F12: score
A13: Statique du point et du solide | B13: Calculer une action mécanique (force et moment)
B14: Appliquer le principe fondamental de la statique
B15: Utiliser les torseurs pour résoudre un problème de statique du solide
B16: Utiliser la loi de Coulomb
A17: Cinématique du solide | B17: Représenter les liaisons cinématiques
A18: Energétique | B18: Calculer le travail d’une force
B19: Calculer une énergie (cinétique, potentielle, mécanique)
B20: Utiliser les théorèmes énergétiques (théorème de l’énergie cinétique, théorème de l’énergie mécanique)
C21: score
A23: Electricité
A24: Compétences | C24: Calculer | D24: Modéliser | E24: Valider | F24: score
B25: Calculer un courant et une tension à partir de la loi d'Ohm et des lois de Kirchhoff
B26: Calculer la puissance et l'énergie d'un récepteur ou d'un générateur alimenté en courant continu
B27: Calculer une résistance équivalente à partir de résistances en série et/ou en parallèle
C28: score
A30: Energétique
A31: Compétences | C31: Calculer | D31: Modéliser | E31: Valider | F31: score
B32: Décrire un système thermodynamique fermé ou isolé en fonction de ses variables d’état (P, V, T)
B33: Utiliser la loi des GP
B34: Expliquer les différents type de transformations (réversible, isobare, isochore, isotherme, adiabatique)
B35: Utiliser la loi des GP et les lois de Laplace dans le cadre des transformations isobares, isothermes,isochores,adiabatiques réversibles pour trouver le travail d'une transformation
B36: Discuter d'un bilan énergétique en utilisant le 1er principe de la thermodynamique
B37: Décrire et situer les phénomènes de conduction, convection et rayonnement
C38: score

Sheet A1 CPI S1
A1: Objectifs d'apprentissage des sciences physiques | G1: Remédiation
A4: Notions à maîtriser en CPI A1 S1 | G4: lien Unisciel ou livre scolaire
A7: UE du DS | B7: Domaine | C7: Discipline | D7: Chapitres | E7: Thèmes | F7: Utilisation
A8: UE 1.3 : Mécanique | B8: =IF('Items sous domaines Sciences '!G10=1,'Items sous domaines Sciences '!B10,0) -> Mécanique | C8: =IF('Items sous domaines Sciences '!G10=1,'Items sous domaines Sciences '!C10,0) -> Point | D8: =IF('Items sous domaines Sciences '!G10=1,'Items sous domaines Sciences '!D10,0) -> Mécanique du point | E8: =IF('Items sous domaines Sciences '!G10=1,'Items sous domaines Sciences '!E10,0) -> Distinguer les différents types de force (poids, réaction, frottements (statique et cinétique), tension...). | F8: Bloc Mécanique | G8: https://uel.unisciel.fr/physique/meca/meca/co/meca.html
B9: =IF('Items sous domaines Sciences '!G11=1,'Items sous domaines Sciences '!B11,0) -> Mécanique | C9: =IF('Items sous domaines Sciences '!G11=1,'Items sous domaines Sciences '!C11,0) -> Point | D9: =IF('Items sous domaines Sciences '!G11=1,'Items sous domaines Sciences '!D11,0) -> 0 | E9: =IF('Items sous domaines Sciences '!G11=1,'Items sous domaines Sciences '!E11,0) -> Appliquer le PFD avec et sans frottements à un mouvement plan.
B10: =IF('Items sous domaines Sciences '!G12=1,'Items sous domaines Sciences '!B12,0) -> Mécanique | C10: =IF('Items sous domaines Sciences '!G12=1,'Items sous domaines Sciences '!C12,0) -> Point | D10: =IF('Items sous domaines Sciences '!G12=1,'Items sous domaines Sciences '!D12,0) -> 0 | E10: =IF('Items sous domaines Sciences '!G12=1,'Items sous domaines Sciences '!E12,0) -> Calculer le travail d'une force.
B11: =IF('Items sous domaines Sciences '!G13=1,'Items sous domaines Sciences '!B13,0) -> Mécanique | C11: =IF('Items sous domaines Sciences '!G13=1,'Items sous domaines Sciences '!C13,0) -> Point | D11: =IF('Items sous domaines Sciences '!G13=1,'Items sous domaines Sciences '!D13,0) -> 0 | E11: =IF('Items sous domaines Sciences '!G13=1,'Items sous domaines Sciences '!E13,0) -> Distinguer une force conservative et non conservative.
B12: =IF('Items sous domaines Sciences '!G14=1,'Items sous domaines Sciences '!B14,0) -> Mécanique | C12: =IF('Items sous domaines Sciences '!G14=1,'Items sous domaines Sciences '!C14,0) -> Point | D12: =IF('Items sous domaines Sciences '!G14=1,'Items sous domaines Sciences '!D14,0) -> 0 | E12: =IF('Items sous domaines Sciences '!G14=1,'Items sous domaines Sciences '!E14,0) -> Calculer une énergie mécanique, cinétique, potentielle.
B13: =IF('Items sous domaines Sciences '!G15=1,'Items sous domaines Sciences '!B15,0) -> Mécanique | C13: =IF('Items sous domaines Sciences '!G15=1,'Items sous domaines Sciences '!C15,0) -> Point | D13: =IF('Items sous domaines Sciences '!G15=1,'Items sous domaines Sciences '!D15,0) -> 0 | E13: =IF('Items sous domaines Sciences '!G15=1,'Items sous domaines Sciences '!E15,0) -> Appliquer le théorème de conservation de l'énergie mécanique.
B14: =IF('Items sous domaines Sciences '!G16=1,'Items sous domaines Sciences '!B16,0) -> Mécanique | C14: =IF('Items sous domaines Sciences '!G16=1,'Items sous domaines Sciences '!C16,0) -> Point | D14: =IF('Items sous domaines Sciences '!G16=1,'Items sous domaines Sciences '!D16,0) -> 0 | E14: =IF('Items sous domaines Sciences '!G16=1,'Items sous domaines Sciences '!E16,0) -> Appliquer le théorème de l'énergie cinétique.
B15: =IF('Items sous domaines Sciences '!G17=1,'Items sous domaines Sciences '!B17,0) -> Mécanique | C15: =IF('Items sous domaines Sciences '!G17=1,'Items sous domaines Sciences '!C17,0) -> Point | D15: =IF('Items sous domaines Sciences '!G17=1,'Items sous domaines Sciences '!D17,0) -> 0 | E15: =IF('Items sous domaines Sciences '!G17=1,'Items sous domaines Sciences '!E17,0) -> Établir les équations horaires (sans et avec frottements).
B16: =IF('Items sous domaines Sciences '!G18=1,'Items sous domaines Sciences '!B18,0) -> Mécanique | C16: =IF('Items sous domaines Sciences '!G18=1,'Items sous domaines Sciences '!C18,0) -> Point | D16: =IF('Items sous domaines Sciences '!G18=1,'Items sous domaines Sciences '!D18,0) -> 0 | E16: =IF('Items sous domaines Sciences '!G18=1,'Items sous domaines Sciences '!E18,0) -> Calculer le moment d’une force.
B17: =IF('Items sous domaines Sciences '!G19=1,'Items sous domaines Sciences '!B19,0) -> Mécanique | C17: =IF('Items sous domaines Sciences '!G19=1,'Items sous domaines Sciences '!C19,0) -> Point | D17: =IF('Items sous domaines Sciences '!G19=1,'Items sous domaines Sciences '!D19,0) -> 0 | E17: =IF('Items sous domaines Sciences '!G19=1,'Items sous domaines Sciences '!E19,0) -> Appliquer le PFD avec et sans frottements à un mouvement circulaire.
B18: =IF('Items sous domaines Sciences '!G20=1,'Items sous domaines Sciences '!B20,0) -> Mécanique | C18: =IF('Items sous domaines Sciences '!G20=1,'Items sous domaines Sciences '!C20,0) -> Point | D18: =IF('Items sous domaines Sciences '!G20=1,'Items sous domaines Sciences '!D20,0) -> 0 | E18: =IF('Items sous domaines Sciences '!G20=1,'Items sous domaines Sciences '!E20,0) -> Établir une équation différentielle du 1er et 2ème ordre.
B19: =IF('Items sous domaines Sciences '!G21=1,'Items sous domaines Sciences '!B21,0) -> 0 | C19: =IF('Items sous domaines Sciences '!G21=1,'Items sous domaines Sciences '!C21,0) -> 0 | D19: =IF('Items sous domaines Sciences '!G21=1,'Items sous domaines Sciences '!D21,0) -> 0 | E19: =IF('Items sous domaines Sciences '!G21=1,'Items sous domaines Sciences '!E21,0) -> 0
B20: =IF('Items sous domaines Sciences '!G22=1,'Items sous domaines Sciences '!B22,0) -> 0 | C20: =IF('Items sous domaines Sciences '!G22=1,'Items sous domaines Sciences '!C22,0) -> 0 | D20: =IF('Items sous domaines Sciences '!G22=1,'Items sous domaines Sciences '!D22,0) -> 0 | E20: =IF('Items sous domaines Sciences '!G22=1,'Items sous domaines Sciences '!E22,0) -> 0
... B23: =IF('Items sous domaines Sciences '!G25=1,'Items sous domaines Sciences '!B25,0) -> 0 | C23: =IF('Items sous domaines Sciences '!G25=1,'Items sous domaines Sciences '!C25,0) -> 0 | D23: =IF('Items sous domaines Sciences '!G25=1,'Items sous domaines Sciences '!D25,0) -> 0 | E23: =IF('Items sous domaines Sciences '!G25=1,'Items sous domaines Sciences '!E25,0) -> 0
B24: =IF('Items sous domaines Sciences '!G26=1,'Items sous domaines Sciences '!B26,0) -> 0 | C24: =IF('Items sous domaines Sciences '!G26=1,'Items sous domaines Sciences '!C26,0) -> 0 | D24: =IF('Items sous domaines Sciences '!G26=1,'Items sous domaines Sciences '!D26,0) -> 0 | E24: =IF('Items sous domaines Sciences '!G26=1,'Items sous domaines Sciences '!E26,0) -> 0 | F24: =IF('Items sous domaines Sciences '!#REF!=1,'Items sous domaines Sciences '!#REF!,0) -> #REF!
B25: =IF('Items sous domaines Sciences '!G27=1,'Items sous domaines Sciences '!B27,0) -> 0 | C25: =IF('Items sous domaines Sciences '!G27=1,'Items sous domaines Sciences '!C27,0) -> 0 | D25: =IF('Items sous domaines Sciences '!G27=1,'Items sous domaines Sciences '!D27,0) -> 0 | E25: =IF('Items sous domaines Sciences '!G27=1,'Items sous domaines Sciences '!E27,0) -> 0 | F25: =IF('Items sous domaines Sciences '!G78=1,'Items sous domaines Sciences '!#REF!,0) -> 0
A26: Algèbre de Boole | B26: =IF('Items sous domaines Sciences '!G28=1,'Items sous domaines Sciences '!B28,0) -> 0 | C26: =IF('Items sous domaines Sciences '!G28=1,'Items sous domaines Sciences '!C28,0) -> 0 | D26: =IF('Items sous domaines Sciences '!G28=1,'Items sous domaines Sciences '!D28,0) -> 0 | E26: =IF('Items sous domaines Sciences '!G28=1,'Items sous domaines Sciences '!E28,0) -> 0 | F26: Projet Strongbox-Electronique | G26: https://uel.unisciel.fr/mathematiques/logique1/logique1/co/logique1.html
B27: =IF('Items sous domaines Sciences '!G29=1,'Items sous domaines Sciences '!B29,0) -> 0 | C27: =IF('Items sous domaines Sciences '!G29=1,'Items sous domaines Sciences '!C29,0) -> 0 | D27: =IF('Items sous domaines Sciences '!G29=1,'Items sous domaines Sciences '!D29,0) -> 0 | E27: =IF('Items sous domaines Sciences '!G29=1,'Items sous domaines Sciences '!E29,0) -> 0
B28: =IF('Items sous domaines Sciences '!G30=1,'Items sous domaines Sciences '!B30,0) -> 0 | C28: =IF('Items sous domaines Sciences '!G30=1,'Items sous domaines Sciences '!C30,0) -> 0 | D28: =IF('Items sous domaines Sciences '!G30=1,'Items sous domaines Sciences '!D30,0) -> 0 | E28: =IF('Items sous domaines Sciences '!G30=1,'Items sous domaines Sciences '!E30,0) -> 0
B29: =IF('Items sous domaines Sciences '!G31=1,'Items sous domaines Sciences '!B31,0) -> 0 | C29: =IF('Items sous domaines Sciences '!G31=1,'Items sous domaines Sciences '!C31,0) -> 0 | D29: =IF('Items sous domaines Sciences '!G31=1,'Items sous domaines Sciences '!D31,0) -> 0 | E29: =IF('Items sous domaines Sciences '!G31=1,'Items sous domaines Sciences '!E31,0) -> 0
B30: =IF('Items sous domaines Sciences '!G32=1,'Items sous domaines Sciences '!B32,0) -> 0 | C30: =IF('Items sous domaines Sciences '!G32=1,'Items sous domaines Sciences '!C32,0) -> 0 | D30: =IF('Items sous domaines Sciences '!G32=1,'Items sous domaines Sciences '!D32,0) -> 0 | E30: =IF('Items sous domaines Sciences '!G32=1,'Items sous domaines Sciences '!E32,0) -> 0
B31: =IF('Items sous domaines Sciences '!G33=1,'Items sous domaines Sciences '!B33,0) -> 0 | C31: =IF('Items sous domaines Sciences '!G33=1,'Items sous domaines Sciences '!C33,0) -> 0 | D31: =IF('Items sous domaines Sciences '!G33=1,'Items sous domaines Sciences '!D33,0) -> 0 | E31: =IF('Items sous domaines Sciences '!G33=1,'Items sous domaines Sciences '!E33,0) -> 0
B32: =IF('Items sous domaines Sciences '!G34=1,'Items sous domaines Sciences '!B34,0) -> 0 | C32: =IF('Items sous domaines Sciences '!G34=1,'Items sous domaines Sciences '!C34,0) -> 0 | D32: =IF('Items sous domaines Sciences '!G34=1,'Items sous domaines Sciences '!D34,0) -> 0 | E32: =IF('Items sous domaines Sciences '!G34=1,'Items sous domaines Sciences '!E34,0) -> 0
B33: =IF('Items sous domaines Sciences '!G35=1,'Items sous domaines Sciences '!B35,0) -> 0 | C33: =IF('Items sous domaines Sciences '!G35=1,'Items sous domaines Sciences '!C35,0) -> 0 | D33: =IF('Items sous domaines Sciences '!G35=1,'Items sous domaines Sciences '!D35,0) -> 0 | E33: =IF('Items sous domaines Sciences '!G35=1,'Items sous domaines Sciences '!E35,0) -> 0
B34: =IF('Items sous domaines Sciences '!G36=1,'Items sous domaines Sciences '!B36,0) -> 0 | C34: =IF('Items sous domaines Sciences '!G36=1,'Items sous domaines Sciences '!C36,0) -> 0 | D34: =IF('Items sous domaines Sciences '!G36=1,'Items sous domaines Sciences '!D36,0) -> 0 | E34: =IF('Items sous domaines Sciences '!G36=1,'Items sous domaines Sciences '!E36,0) -> 0
B35: =IF('Items sous domaines Sciences '!G37=1,'Items sous domaines Sciences '!B37,0) -> 0 | C35: =IF('Items sous domaines Sciences '!G37=1,'Items sous domaines Sciences '!C37,0) -> 0 | D35: =IF('Items sous domaines Sciences '!G37=1,'Items sous domaines Sciences '!D37,0) -> 0 | E35: =IF('Items sous domaines Sciences '!G37=1,'Items sous domaines Sciences '!E37,0) -> 0
B36: =IF('Items sous domaines Sciences '!G38=1,'Items sous domaines Sciences '!B38,0) -> 0 | C36: =IF('Items sous domaines Sciences '!G38=1,'Items sous domaines Sciences '!C38,0) -> 0 | D36: =IF('Items sous domaines Sciences '!G38=1,'Items sous domaines Sciences '!D38,0) -> 0 | E36: =IF('Items sous domaines Sciences '!G38=1,'Items sous domaines Sciences '!E38,0) -> 0
B37: =IF('Items sous domaines Sciences '!G39=1,'Items sous domaines Sciences '!B39,0) -> 0 | C37: =IF('Items sous domaines Sciences '!G39=1,'Items sous domaines Sciences '!C39,0) -> 0 | D37: =IF('Items sous domaines Sciences '!G39=1,'Items sous domaines Sciences '!D39,0) -> 0 | E37: =IF('Items sous domaines Sciences '!G39=1,'Items sous domaines Sciences '!E39,0) -> 0
B38: =IF('Items sous domaines Sciences '!G40=1,'Items sous domaines Sciences '!B40,0) -> 0 | C38: =IF('Items sous domaines Sciences '!G40=1,'Items sous domaines Sciences '!C40,0) -> 0 | D38: =IF('Items sous domaines Sciences '!G40=1,'Items sous domaines Sciences '!D40,0) -> 0 | E38: =IF('Items sous domaines Sciences '!G40=1,'Items sous domaines Sciences '!E40,0) -> 0
B39: =IF('Items sous domaines Sciences '!G41=1,'Items sous domaines Sciences '!B41,0) -> 0 | C39: =IF('Items sous domaines Sciences '!G41=1,'Items sous domaines Sciences '!C41,0) -> 0 | D39: =IF('Items sous domaines Sciences '!G41=1,'Items sous domaines Sciences '!D41,0) -> 0 | E39: =IF('Items sous domaines Sciences '!G41=1,'Items sous domaines Sciences '!E41,0) -> 0 | F39: =IF('Items sous domaines Sciences '!G207=1,'Items sous domaines Sciences '!#REF!,0) -> 0
A40: Algèbre : Nombres complexes | B40: =IF('Items sous domaines Sciences '!G42=1,'Items sous domaines Sciences '!B42,0) -> 0 | C40: =IF('Items sous domaines Sciences '!G42=1,'Items sous domaines Sciences '!C42,0) -> 0 | D40: =IF('Items sous domaines Sciences '!G42=1,'Items sous domaines Sciences '!D42,0) -> 0 | E40: =IF('Items sous domaines Sciences '!G42=1,'Items sous domaines Sciences '!E42,0) -> 0 | F40: Projet Strongbox-Electronique et ETS | G40: https://uel.unisciel.fr/physique/outils_nancy/outils_nancy_ch04/co/apprendre_ch04.html
B41: =IF('Items sous domaines Sciences '!G43=1,'Items sous domaines Sciences '!B43,0) -> 0 | C41: =IF('Items sous domaines Sciences '!G43=1,'Items sous domaines Sciences '!C43,0) -> 0 | D41: =IF('Items sous domaines Sciences '!G43=1,'Items sous domaines Sciences '!D43,0) -> 0 | E41: =IF('Items sous domaines Sciences '!G43=1,'Items sous domaines Sciences '!E43,0) -> 0
B42: =IF('Items sous domaines Sciences '!G44=1,'Items sous domaines Sciences '!B44,0) -> 0 | C42: =IF('Items sous domaines Sciences '!G44=1,'Items sous domaines Sciences '!C44,0) -> 0 | D42: =IF('Items sous domaines Sciences '!G44=1,'Items sous domaines Sciences '!D44,0) -> 0 | E42: =IF('Items sous domaines Sciences '!G44=1,'Items sous domaines Sciences '!E44,0) -> 0
B43: =IF('Items sous domaines Sciences '!G45=1,'Items sous domaines Sciences '!B45,0) -> 0 | C43: =IF('Items sous domaines Sciences '!G45=1,'Items sous domaines Sciences '!C45,0) -> 0 | D43: =IF('Items sous domaines Sciences '!G45=1,'Items sous domaines Sciences '!D45,0) -> 0 | E43: =IF('Items sous domaines Sciences '!G45=1,'Items sous domaines Sciences '!E45,0) -> 0
B44: =IF('Items sous domaines Sciences '!G46=1,'Items sous domaines Sciences '!B46,0) -> 0 | C44: =IF('Items sous domaines Sciences '!G46=1,'Items sous domaines Sciences '!C46,0) -> 0 | D44: =IF('Items sous domaines Sciences '!G46=1,'Items sous domaines Sciences '!D46,0) -> 0 | E44: =IF('Items sous domaines Sciences '!G46=1,'Items sous domaines Sciences '!E46,0) -> 0
B45: =IF('Items sous domaines Sciences '!G47=1,'Items sous domaines Sciences '!B47,0) -> 0 | C45: =IF('Items sous domaines Sciences '!G47=1,'Items sous domaines Sciences '!C47,0) -> 0 | D45: =IF('Items sous domaines Sciences '!G47=1,'Items sous domaines Sciences '!D47,0) -> 0 | E45: =IF('Items sous domaines Sciences '!G47=1,'Items sous domaines Sciences '!E47,0) -> 0
B46: =IF('Items sous domaines Sciences '!G48=1,'Items sous domaines Sciences '!B48,0) -> 0 | C46: =IF('Items sous domaines Sciences '!G48=1,'Items sous domaines Sciences '!C48,0) -> 0 | D46: =IF('Items sous domaines Sciences '!G48=1,'Items sous domaines Sciences '!D48,0) -> 0 | E46: =IF('Items sous domaines Sciences '!G48=1,'Items sous domaines Sciences '!E48,0) -> 0
B47: =IF('Items sous domaines Sciences '!G49=1,'Items sous domaines Sciences '!B49,0) -> 0 | C47: =IF('Items sous domaines Sciences '!G49=1,'Items sous domaines Sciences '!C49,0) -> 0 | D47: =IF('Items sous domaines Sciences '!G49=1,'Items sous domaines Sciences '!D49,0) -> 0 | E47: =IF('Items sous domaines Sciences '!G49=1,'Items sous domaines Sciences '!E49,0) -> 0
B48: =IF('Items sous domaines Sciences '!G50=1,'Items sous domaines Sciences '!B50,0) -> 0 | C48: =IF('Items sous domaines Sciences '!G50=1,'Items sous domaines Sciences '!C50,0) -> 0 | D48: =IF('Items sous domaines Sciences '!G50=1,'Items sous domaines Sciences '!D50,0) -> 0 | E48: =IF('Items sous domaines Sciences '!G50=1,'Items sous domaines Sciences '!E50,0) -> 0
B49: =IF('Items sous domaines Sciences '!G51=1,'Items sous domaines Sciences '!B51,0) -> 0 | C49: =IF('Items sous domaines Sciences '!G51=1,'Items sous domaines Sciences '!C51,0) -> 0 | D49: =IF('Items sous domaines Sciences '!G51=1,'Items sous domaines Sciences '!D51,0) -> 0 | E49: =IF('Items sous domaines Sciences '!G51=1,'Items sous domaines Sciences '!E51,0) -> 0
B50: =IF('Items sous domaines Sciences '!G52=1,'Items sous domaines Sciences '!B52,0) -> 0 | C50: =IF('Items sous domaines Sciences '!G52=1,'Items sous domaines Sciences '!C52,0) -> 0 | D50: =IF('Items sous domaines Sciences '!G52=1,'Items sous domaines Sciences '!D52,0) -> 0 | E50: =IF('Items sous domaines Sciences '!G52=1,'Items sous domaines Sciences '!E52,0) -> 0
B51: =IF('Items sous domaines Sciences '!G53=1,'Items sous domaines Sciences '!B53,0) -> 0 | C51: =IF('Items sous domaines Sciences '!G53=1,'Items sous domaines Sciences '!C53,0) -> 0 | D51: =IF('Items sous domaines Sciences '!G53=1,'Items sous domaines Sciences '!D53,0) -> 0 | E51: =IF('Items sous domaines Sciences '!G53=1,'Items sous domaines Sciences '!E53,0) -> 0
B52: =IF('Items sous domaines Sciences '!G54=1,'Items sous domaines Sciences '!B54,0) -> 0 | C52: =IF('Items sous domaines Sciences '!G54=1,'Items sous domaines Sciences '!C54,0) -> 0 | D52: =IF('Items sous domaines Sciences '!G54=1,'Items sous domaines Sciences '!D54,0) -> 0 | E52: =IF('Items sous domaines Sciences '!G54=1,'Items sous domaines Sciences '!E54,0) -> 0
... B56: =IF('Items sous domaines Sciences '!G58=1,'Items sous domaines Sciences '!B58,0) -> 0 | C56: =IF('Items sous domaines Sciences '!G58=1,'Items sous domaines Sciences '!C58,0) -> 0 | D56: =IF('Items sous domaines Sciences '!G58=1,'Items sous domaines Sciences '!D58,0) -> 0 | E56: =IF('Items sous domaines Sciences '!G58=1,'Items sous domaines Sciences '!E58,0) -> 0
B57: =IF('Items sous domaines Sciences '!G59=1,'Items sous domaines Sciences '!B59,0) -> 0 | C57: =IF('Items sous domaines Sciences '!G59=1,'Items sous domaines Sciences '!C59,0) -> 0 | D57: =IF('Items sous domaines Sciences '!G59=1,'Items sous domaines Sciences '!D59,0) -> 0 | E57: =IF('Items sous domaines Sciences '!G59=1,'Items sous domaines Sciences '!E59,0) -> 0 | F57: =IF('Items sous domaines Sciences '!#REF!=1,'Items sous domaines Sciences '!#REF!,0) -> #REF!
B58: =IF('Items sous domaines Sciences '!G60=1,'Items sous domaines Sciences '!B60,0) -> 0 | C58: =IF('Items sous domaines Sciences '!G60=1,'Items sous domaines Sciences '!C60,0) -> 0 | D58: =IF('Items sous domaines Sciences '!G60=1,'Items sous domaines Sciences '!D60,0) -> 0 | E58: =IF('Items sous domaines Sciences '!G60=1,'Items sous domaines Sciences '!E60,0) -> 0 | F58: =IF('Items sous domaines Sciences '!#REF!=1,'Items sous domaines Sciences '!#REF!,0) -> #REF!
B59: =IF('Items sous domaines Sciences '!G61=1,'Items sous domaines Sciences '!B61,0) -> 0 | C59: =IF('Items sous domaines Sciences '!G61=1,'Items sous domaines Sciences '!C61,0) -> 0 | D59: =IF('Items sous domaines Sciences '!G61=1,'Items sous domaines Sciences '!D61,0) -> 0 | E59: =IF('Items sous domaines Sciences '!G61=1,'Items sous domaines Sciences '!E61,0) -> 0 | F59: =IF('Items sous domaines Sciences '!#REF!=1,'Items sous domaines Sciences '!#REF!,0) -> #REF!
B60: =IF('Items sous domaines Sciences '!G62=1,'Items sous domaines Sciences '!B62,0) -> 0 | C60: =IF('Items sous domaines Sciences '!G62=1,'Items sous domaines Sciences '!C62,0) -> 0 | D60: =IF('Items sous domaines Sciences '!G62=1,'Items sous domaines Sciences '!D62,0) -> 0 | E60: =IF('Items sous domaines Sciences '!G62=1,'Items sous domaines Sciences '!E62,0) -> 0 | F60: =IF('Items sous domaines Sciences '!#REF!=1,'Items sous domaines Sciences '!#REF!,0) -> #REF!
B61: =IF('Items sous domaines Sciences '!G63=1,'Items sous domaines Sciences '!B63,0) -> 0 | C61: =IF('Items sous domaines Sciences '!G63=1,'Items sous domaines Sciences '!C63,0) -> 0 | D61: =IF('Items sous domaines Sciences '!G63=1,'Items sous domaines Sciences '!D63,0) -> 0 | E61: =IF('Items sous domaines Sciences '!G63=1,'Items sous domaines Sciences '!E63,0) -> 0 | F61: =IF('Items sous domaines Sciences '!#REF!=1,'Items sous domaines Sciences '!#REF!,0) -> #REF!
B62: =IF('Items sous domaines Sciences '!G64=1,'Items sous domaines Sciences '!B64,0) -> 0 | C62: =IF('Items sous domaines Sciences '!G64=1,'Items sous domaines Sciences '!C64,0) -> 0 | D62: =IF('Items sous domaines Sciences '!G64=1,'Items sous domaines Sciences '!D64,0) -> 0 | E62: =IF('Items sous domaines Sciences '!G64=1,'Items sous domaines Sciences '!E64,0) -> 0 | F62: =IF('Items sous domaines Sciences '!G248=1,'Items sous domaines Sciences '!#REF!,0) -> 0
A63: Analyse : Interpolation, développement limité 0 | B63: =IF('Items sous domaines Sciences '!G65=1,'Items sous domaines Sciences '!B65,0) -> 0 | C63: =IF('Items sous domaines Sciences '!G65=1,'Items sous domaines Sciences '!C65,0) -> 0 | D63: =IF('Items sous domaines Sciences '!G65=1,'Items sous domaines Sciences '!D65,0) -> 0 | E63: =IF('Items sous domaines Sciences '!G65=1,'Items sous domaines Sciences '!E65,0) -> 0 | F63: ETS | G63: Développements limités (unisciel.fr)
B64: =IF('Items sous domaines Sciences '!G66=1,'Items sous domaines Sciences '!B66,0) -> 0 | C64: =IF('Items sous domaines Sciences '!G66=1,'Items sous domaines Sciences '!C66,0) -> 0 | D64: =IF('Items sous domaines Sciences '!G66=1,'Items sous domaines Sciences '!D66,0) -> 0 | E64: =IF('Items sous domaines Sciences '!G66=1,'Items sous domaines Sciences '!E66,0) -> 0
B65: =IF('Items sous domaines Sciences '!G67=1,'Items sous domaines Sciences '!B67,0) -> 0 | C65: =IF('Items sous domaines Sciences '!G67=1,'Items sous domaines Sciences '!C67,0) -> 0 | D65: =IF('Items sous domaines Sciences '!G67=1,'Items sous domaines Sciences '!D67,0) -> 0 | E65: =IF('Items sous domaines Sciences '!G67=1,'Items sous domaines Sciences '!E67,0) -> 0
B66: =IF('Items sous domaines Sciences '!G68=1,'Items sous domaines Sciences '!B68,0) -> 0 | C66: =IF('Items sous domaines Sciences '!G68=1,'Items sous domaines Sciences '!C68,0) -> 0 | D66: =IF('Items sous domaines Sciences '!G68=1,'Items sous domaines Sciences '!D68,0) -> 0 | E66: =IF('Items sous domaines Sciences '!G68=1,'Items sous domaines Sciences '!E68,0) -> 0
B67: =IF('Items sous domaines Sciences '!G69=1,'Items sous domaines Sciences '!B69,0) -> 0 | C67: =IF('Items sous domaines Sciences '!G69=1,'Items sous domaines Sciences '!C69,0) -> 0 | D67: =IF('Items sous domaines Sciences '!G69=1,'Items sous domaines Sciences '!D69,0) -> 0 | E67: =IF('Items sous domaines Sciences '!G69=1,'Items sous domaines Sciences '!E69,0) -> 0
B68: =IF('Items sous domaines Sciences '!G70=1,'Items sous domaines Sciences '!B70,0) -> 0 | C68: =IF('Items sous domaines Sciences '!G70=1,'Items sous domaines Sciences '!C70,0) -> 0 | D68: =IF('Items sous domaines Sciences '!G70=1,'Items sous domaines Sciences '!D70,0) -> 0 | E68: =IF('Items sous domaines Sciences '!G70=1,'Items sous domaines Sciences '!E70,0) -> 0
B69: =IF('Items sous domaines Sciences '!G71=1,'Items sous domaines Sciences '!B71,0) -> 0 | C69: =IF('Items sous domaines Sciences '!G71=1,'Items sous domaines Sciences '!C71,0) -> 0 | D69: =IF('Items sous domaines Sciences '!G71=1,'Items sous domaines Sciences '!D71,0) -> 0 | E69: =IF('Items sous domaines Sciences '!G71=1,'Items sous domaines Sciences '!E71,0) -> 0
B70: =IF('Items sous domaines Sciences '!G72=1,'Items sous domaines Sciences '!B72,0) -> 0 | C70: =IF('Items sous domaines Sciences '!G72=1,'Items sous domaines Sciences '!C72,0) -> 0 | D70: =IF('Items sous domaines Sciences '!G72=1,'Items sous domaines Sciences '!D72,0) -> 0 | E70: =IF('Items sous domaines Sciences '!G72=1,'Items sous domaines Sciences '!E72,0) -> 0
B71: =IF('Items sous domaines Sciences '!G73=1,'Items sous domaines Sciences '!B73,0) -> 0 | C71: =IF('Items sous domaines Sciences '!G73=1,'Items sous domaines Sciences '!C73,0) -> 0 | D71: =IF('Items sous domaines Sciences '!G73=1,'Items sous domaines Sciences '!D73,0) -> 0 | E71: =IF('Items sous domaines Sciences '!G73=1,'Items sous domaines Sciences '!E73,0) -> 0
B72: =IF('Items sous domaines Sciences '!G74=1,'Items sous domaines Sciences '!B74,0) -> 0 | C72: =IF('Items sous domaines Sciences '!G74=1,'Items sous domaines Sciences '!C74,0) -> 0 | D72: =IF('Items sous domaines Sciences '!G74=1,'Items sous domaines Sciences '!D74,0) -> 0 | E72: =IF('Items sous domaines Sciences '!G74=1,'Items sous domaines Sciences '!E74,0) -> 0
B73: =IF('Items sous domaines Sciences '!G75=1,'Items sous domaines Sciences '!B75,0) -> 0 | C73: =IF('Items sous domaines Sciences '!G75=1,'Items sous domaines Sciences '!C75,0) -> 0 | D73: =IF('Items sous domaines Sciences '!G75=1,'Items sous domaines Sciences '!D75,0) -> 0 | E73: =IF('Items sous domaines Sciences '!G75=1,'Items sous domaines Sciences '!E75,0) -> 0 | F73: =IF('Items sous domaines Sciences '!G308=1,'Items sous domaines Sciences '!#REF!,0) -> 0
B74: =IF('Items sous domaines Sciences '!G76=1,'Items sous domaines Sciences '!B76,0) -> 0 | C74: =IF('Items sous domaines Sciences '!G76=1,'Items sous domaines Sciences '!C76,0) -> 0 | D74: =IF('Items sous domaines Sciences '!G76=1,'Items sous domaines Sciences '!D76,0) -> 0 | E74: =IF('Items sous domaines Sciences '!G76=1,'Items sous domaines Sciences '!E76,0) -> 0 | F74: =IF('Items sous domaines Sciences '!G309=1,'Items sous domaines Sciences '!#REF!,0) -> 0
B75: =IF('Items sous domaines Sciences '!G77=1,'Items sous domaines Sciences '!B77,0) -> 0 | C75: =IF('Items sous domaines Sciences '!G77=1,'Items sous domaines Sciences '!C77,0) -> 0 | D75: =IF('Items sous domaines Sciences '!G77=1,'Items sous domaines Sciences '!D77,0) -> 0 | E75: =IF('Items sous domaines Sciences '!G77=1,'Items sous domaines Sciences '!E77,0) -> 0 | F75: =IF('Items sous domaines Sciences '!G310=1,'Items sous domaines Sciences '!#REF!,0) -> 0
B76: =IF('Items sous domaines Sciences '!G78=1,'Items sous domaines Sciences '!B78,0) -> 0 | C76: =IF('Items sous domaines Sciences '!G78=1,'Items sous domaines Sciences '!C78,0) -> 0 | D76: =IF('Items sous domaines Sciences '!G78=1,'Items sous domaines Sciences '!D78,0) -> 0 | E76: =IF('Items sous domaines Sciences '!G78=1,'Items sous domaines Sciences '!E78,0) -> 0 | F76: =IF('Items sous domaines Sciences '!#REF!=1,'Items sous domaines Sciences '!#REF!,0) -> #REF!
A77: UE 1.1 : Electricité et électronique fondamentale UE 1.2 : Traitement du signal | B77: =IF('Items sous domaines Sciences '!G79=1,'Items sous domaines Sciences '!B79,0) -> Electricité - Electromagnétisme | C77: =IF('Items sous domaines Sciences '!G79=1,'Items sous domaines Sciences '!C79,0) -> Electricité | D77: =IF('Items sous domaines Sciences '!G79=1,'Items sous domaines Sciences '!D79,0) -> Electricité - courant continu | E77: =IF('Items sous domaines Sciences '!G79=1,'Items sous domaines Sciences '!E79,0) -> Identifier les différents composants d'un circuit électrique (générateur, résistance, diode, transistor…) (prérequis). | F77: Bloc Electronique et signal | G77: https://uel.unisciel.fr/physique/continu/continu/co/continu.html
B78: =IF('Items sous domaines Sciences '!G80=1,'Items sous domaines Sciences '!B80,0) -> Electricité - Electromagnétisme | C78: =IF('Items sous domaines Sciences '!G80=1,'Items sous domaines Sciences '!C80,0) -> Electricité | D78: =IF('Items sous domaines Sciences '!G80=1,'Items sous domaines Sciences '!D80,0) -> 0 | E78: =IF('Items sous domaines Sciences '!G80=1,'Items sous domaines Sciences '!E80,0) -> Connaître les conventions (générateur et récepteur, sens du courant) (prérequis).
B79: =IF('Items sous domaines Sciences '!G81=1,'Items sous domaines Sciences '!B81,0) -> Electricité - Electromagnétisme | C79: =IF('Items sous domaines Sciences '!G81=1,'Items sous domaines Sciences '!C81,0) -> Electricité | D79: =IF('Items sous domaines Sciences '!G81=1,'Items sous domaines Sciences '!D81,0) -> 0 | E79: =IF('Items sous domaines Sciences '!G81=1,'Items sous domaines Sciences '!E81,0) -> Produire une mesure physique à l'aide de l'outil adapté (prérequis).
B80: =IF('Items sous domaines Sciences '!G82=1,'Items sous domaines Sciences '!B82,0) -> Electricité - Electromagnétisme | C80: =IF('Items sous domaines Sciences '!G82=1,'Items sous domaines Sciences '!C82,0) -> Electricité | D80: =IF('Items sous domaines Sciences '!G82=1,'Items sous domaines Sciences '!D82,0) -> 0 | E80: =IF('Items sous domaines Sciences '!G82=1,'Items sous domaines Sciences '!E82,0) -> Décrire la constitution et le fonctionnement d'une résistance.
B81: =IF('Items sous domaines Sciences '!G83=1,'Items sous domaines Sciences '!B83,0) -> Electricité - Electromagnétisme | C81: =IF('Items sous domaines Sciences '!G83=1,'Items sous domaines Sciences '!C83,0) -> Electricité | D81: =IF('Items sous domaines Sciences '!G83=1,'Items sous domaines Sciences '!D83,0) -> 0 | E81: =IF('Items sous domaines Sciences '!G83=1,'Items sous domaines Sciences '!E83,0) -> Expliquer la notion de différence de potentiel.
B82: =IF('Items sous domaines Sciences '!G84=1,'Items sous domaines Sciences '!B84,0) -> Electricité - Electromagnétisme | C82: =IF('Items sous domaines Sciences '!G84=1,'Items sous domaines Sciences '!C84,0) -> Electricité | D82: =IF('Items sous domaines Sciences '!G84=1,'Items sous domaines Sciences '!D84,0) -> 0 | E82: =IF('Items sous domaines Sciences '!G84=1,'Items sous domaines Sciences '!E84,0) -> Appliquer la loi d’Ohm.
B83: =IF('Items sous domaines Sciences '!G85=1,'Items sous domaines Sciences '!B85,0) -> Electricité - Electromagnétisme | C83: =IF('Items sous domaines Sciences '!G85=1,'Items sous domaines Sciences '!C85,0) -> Electricité | D83: =IF('Items sous domaines Sciences '!G85=1,'Items sous domaines Sciences '!D85,0) -> 0 | E83: =IF('Items sous domaines Sciences '!G85=1,'Items sous domaines Sciences '!E85,0) -> Appliquer les lois de Kirchhoff.
B84: =IF('Items sous domaines Sciences '!G86=1,'Items sous domaines Sciences '!B86,0) -> Electricité - Electromagnétisme | C84: =IF('Items sous domaines Sciences '!G86=1,'Items sous domaines Sciences '!C86,0) -> Electricité | D84: =IF('Items sous domaines Sciences '!G86=1,'Items sous domaines Sciences '!D86,0) -> 0 | E84: =IF('Items sous domaines Sciences '!G86=1,'Items sous domaines Sciences '!E86,0) -> Calculer une résistance équivalente.
B85: =IF('Items sous domaines Sciences '!G87=1,'Items sous domaines Sciences '!B87,0) -> Electricité - Electromagnétisme | C85: =IF('Items sous domaines Sciences '!G87=1,'Items sous domaines Sciences '!C87,0) -> Electricité | D85: =IF('Items sous domaines Sciences '!G87=1,'Items sous domaines Sciences '!D87,0) -> 0 | E85: =IF('Items sous domaines Sciences '!G87=1,'Items sous domaines Sciences '!E87,0) -> Appliquer le théorème de Thévenin.
B86: =IF('Items sous domaines Sciences '!G88=1,'Items sous domaines Sciences '!B88,0) -> Electricité - Electromagnétisme | C86: =IF('Items sous domaines Sciences '!G88=1,'Items sous domaines Sciences '!C88,0) -> Electricité | D86: =IF('Items sous domaines Sciences '!G88=1,'Items sous domaines Sciences '!D88,0) -> 0 | E86: =IF('Items sous domaines Sciences '!G88=1,'Items sous domaines Sciences '!E88,0) -> Appliquer le théorème du pont diviseur de tension.
B87: =IF('Items sous domaines Sciences '!G89=1,'Items sous domaines Sciences '!B89,0) -> Electricité - Electromagnétisme | C87: =IF('Items sous domaines Sciences '!G89=1,'Items sous domaines Sciences '!C89,0) -> Electricité | D87: =IF('Items sous domaines Sciences '!G89=1,'Items sous domaines Sciences '!D89,0) -> 0 | E87: =IF('Items sous domaines Sciences '!G89=1,'Items sous domaines Sciences '!E89,0) -> Décrire le fonctionnement d’une jonction PN.
B88: =IF('Items sous domaines Sciences '!G90=1,'Items sous domaines Sciences '!B90,0) -> Electricité - Electromagnétisme | C88: =IF('Items sous domaines Sciences '!G90=1,'Items sous domaines Sciences '!C90,0) -> Electricité | D88: =IF('Items sous domaines Sciences '!G90=1,'Items sous domaines Sciences '!D90,0) -> 0 | E88: =IF('Items sous domaines Sciences '!G90=1,'Items sous domaines Sciences '!E90,0) -> Décrire le fonctionnement d’une diode (caractéristique, polarisation directe et inverse).
B89: =IF('Items sous domaines Sciences '!G91=1,'Items sous domaines Sciences '!B91,0) -> Electricité - Electromagnétisme | C89: =IF('Items sous domaines Sciences '!G91=1,'Items sous domaines Sciences '!C91,0) -> Electricité | D89: =IF('Items sous domaines Sciences '!G91=1,'Items sous domaines Sciences '!D91,0) -> 0 | E89: =IF('Items sous domaines Sciences '!G91=1,'Items sous domaines Sciences '!E91,0) -> Décrire le fonctionnement d’un transistor (caractéristique, polarisations).
... B112: =IF('Items sous domaines Sciences '!G114=1,'Items sous domaines Sciences '!B114,0) -> 0 | C112: =IF('Items sous domaines Sciences '!G114=1,'Items sous domaines Sciences '!C114,0) -> 0 | D112: =IF('Items sous domaines Sciences '!G114=1,'Items sous domaines Sciences '!D114,0) -> 0 | E112: =IF('Items sous domaines Sciences '!G114=1,'Items sous domaines Sciences '!E114,0) -> 0
B113: =IF('Items sous domaines Sciences '!G115=1,'Items sous domaines Sciences '!B115,0) -> 0 | C113: =IF('Items sous domaines Sciences '!G115=1,'Items sous domaines Sciences '!C115,0) -> 0 | D113: =IF('Items sous domaines Sciences '!G115=1,'Items sous domaines Sciences '!D115,0) -> 0 | E113: =IF('Items sous domaines Sciences '!G115=1,'Items sous domaines Sciences '!E115,0) -> 0 | G113: 2. Les graphes | Lelivrescolaire.fr
B114: =IF('Items sous domaines Sciences '!G116=1,'Items sous domaines Sciences '!B116,0) -> 0 | C114: =IF('Items sous domaines Sciences '!G116=1,'Items sous domaines Sciences '!C116,0) -> 0 | D114: =IF('Items sous domaines Sciences '!G116=1,'Items sous domaines Sciences '!D116,0) -> 0 | E114: =IF('Items sous domaines Sciences '!G116=1,'Items sous domaines Sciences '!E116,0) -> 0
B115: =IF('Items sous domaines Sciences '!G117=1,'Items sous domaines Sciences '!B117,0) -> 0 | C115: =IF('Items sous domaines Sciences '!G117=1,'Items sous domaines Sciences '!C117,0) -> 0 | D115: =IF('Items sous domaines Sciences '!G117=1,'Items sous domaines Sciences '!D117,0) -> 0 | E115: =IF('Items sous domaines Sciences '!G117=1,'Items sous domaines Sciences '!E117,0) -> 0
B116: =IF('Items sous domaines Sciences '!G118=1,'Items sous domaines Sciences '!B118,0) -> 0 | C116: =IF('Items sous domaines Sciences '!G118=1,'Items sous domaines Sciences '!C118,0) -> 0 | D116: =IF('Items sous domaines Sciences '!G118=1,'Items sous domaines Sciences '!D118,0) -> 0 | E116: =IF('Items sous domaines Sciences '!G118=1,'Items sous domaines Sciences '!E118,0) -> 0
B117: =IF('Items sous domaines Sciences '!G119=1,'Items sous domaines Sciences '!B119,0) -> 0 | C117: =IF('Items sous domaines Sciences '!G119=1,'Items sous domaines Sciences '!C119,0) -> 0 | D117: =IF('Items sous domaines Sciences '!G119=1,'Items sous domaines Sciences '!D119,0) -> 0 | E117: =IF('Items sous domaines Sciences '!G119=1,'Items sous domaines Sciences '!E119,0) -> 0
B118: =IF('Items sous domaines Sciences '!G120=1,'Items sous domaines Sciences '!B120,0) -> 0 | C118: =IF('Items sous domaines Sciences '!G120=1,'Items sous domaines Sciences '!C120,0) -> 0 | D118: =IF('Items sous domaines Sciences '!G120=1,'Items sous domaines Sciences '!D120,0) -> 0 | E118: =IF('Items sous domaines Sciences '!G120=1,'Items sous domaines Sciences '!E120,0) -> 0
B119: =IF('Items sous domaines Sciences '!G121=1,'Items sous domaines Sciences '!B121,0) -> 0 | C119: =IF('Items sous domaines Sciences '!G121=1,'Items sous domaines Sciences '!C121,0) -> 0 | D119: =IF('Items sous domaines Sciences '!G121=1,'Items sous domaines Sciences '!D121,0) -> 0 | E119: =IF('Items sous domaines Sciences '!G121=1,'Items sous domaines Sciences '!E121,0) -> 0
B120: =IF('Items sous domaines Sciences '!G122=1,'Items sous domaines Sciences '!B122,0) -> 0 | C120: =IF('Items sous domaines Sciences '!G122=1,'Items sous domaines Sciences '!C122,0) -> 0 | D120: =IF('Items sous domaines Sciences '!G122=1,'Items sous domaines Sciences '!D122,0) -> 0 | E120: =IF('Items sous domaines Sciences '!G122=1,'Items sous domaines Sciences '!E122,0) -> 0
B121: =IF('Items sous domaines Sciences '!G123=1,'Items sous domaines Sciences '!B123,0) -> 0 | C121: =IF('Items sous domaines Sciences '!G123=1,'Items sous domaines Sciences '!C123,0) -> 0 | D121: =IF('Items sous domaines Sciences '!G123=1,'Items sous domaines Sciences '!D123,0) -> 0 | E121: =IF('Items sous domaines Sciences '!G123=1,'Items sous domaines Sciences '!E123,0) -> 0
B122: =IF('Items sous domaines Sciences '!G124=1,'Items sous domaines Sciences '!B124,0) -> 0 | C122: =IF('Items sous domaines Sciences '!G124=1,'Items sous domaines Sciences '!C124,0) -> 0 | D122: =IF('Items sous domaines Sciences '!G124=1,'Items sous domaines Sciences '!D124,0) -> 0 | E122: =IF('Items sous domaines Sciences '!G124=1,'Items sous domaines Sciences '!E124,0) -> 0
B123: =IF('Items sous domaines Sciences '!G125=1,'Items sous domaines Sciences '!B125,0) -> 0 | C123: =IF('Items sous domaines Sciences '!G125=1,'Items sous domaines Sciences '!C125,0) -> 0 | D123: =IF('Items sous domaines Sciences '!G125=1,'Items sous domaines Sciences '!D125,0) -> 0 | E123: =IF('Items sous domaines Sciences '!G125=1,'Items sous domaines Sciences '!E125,0) -> 0
B124: =IF('Items sous domaines Sciences '!G126=1,'Items sous domaines Sciences '!B126,0) -> 0 | C124: =IF('Items sous domaines Sciences '!G126=1,'Items sous domaines Sciences '!C126,0) -> 0 | D124: =IF('Items sous domaines Sciences '!G126=1,'Items sous domaines Sciences '!D126,0) -> 0 | E124: =IF('Items sous domaines Sciences '!G126=1,'Items sous domaines Sciences '!E126,0) -> 0
B125: =IF('Items sous domaines Sciences '!G127=1,'Items sous domaines Sciences '!B127,0) -> 0 | C125: =IF('Items sous domaines Sciences '!G127=1,'Items sous domaines Sciences '!C127,0) -> 0 | D125: =IF('Items sous domaines Sciences '!G127=1,'Items sous domaines Sciences '!D127,0) -> 0 | E125: =IF('Items sous domaines Sciences '!G127=1,'Items sous domaines Sciences '!E127,0) -> 0
... B133: =IF('Items sous domaines Sciences '!G135=1,'Items sous domaines Sciences '!B135,0) -> 0 | C133: =IF('Items sous domaines Sciences '!G135=1,'Items sous domaines Sciences '!C135,0) -> 0 | D133: =IF('Items sous domaines Sciences '!G135=1,'Items sous domaines Sciences '!D135,0) -> 0 | E133: =IF('Items sous domaines Sciences '!G135=1,'Items sous domaines Sciences '!E135,0) -> 0
B134: =IF('Items sous domaines Sciences '!G136=1,'Items sous domaines Sciences '!B136,0) -> Electricité - Electromagnétisme | C134: =IF('Items sous domaines Sciences '!G136=1,'Items sous domaines Sciences '!C136,0) -> Electromagnétisme | D134: =IF('Items sous domaines Sciences '!G136=1,'Items sous domaines Sciences '!D136,0) -> Signal | E134: =IF('Items sous domaines Sciences '!G136=1,'Items sous domaines Sciences '!E136,0) -> Décrire les caractéristiques physiques (période, fréquence, pulsation, amplitude, longueur d'onde, phase) d'une onde (grandeurs physiques et unités associées). | G134: https://uel.unisciel.fr/physique/vibrapropa/vibrapropa_ch02/co/vibrapropa_ch02.html
B135: =IF('Items sous domaines Sciences '!G137=1,'Items sous domaines Sciences '!B137,0) -> Electricité - Electromagnétisme | C135: =IF('Items sous domaines Sciences '!G137=1,'Items sous domaines Sciences '!C137,0) -> Electromagnétisme | D135: =IF('Items sous domaines Sciences '!G137=1,'Items sous domaines Sciences '!D137,0) -> 0 | E135: =IF('Items sous domaines Sciences '!G137=1,'Items sous domaines Sciences '!E137,0) -> Expliquer le phénomène de propagation d'une onde (atténuation, diffraction, réflexion).
B136: =IF('Items sous domaines Sciences '!G138=1,'Items sous domaines Sciences '!B138,0) -> Electricité - Electromagnétisme | C136: =IF('Items sous domaines Sciences '!G138=1,'Items sous domaines Sciences '!C138,0) -> Electromagnétisme | D136: =IF('Items sous domaines Sciences '!G138=1,'Items sous domaines Sciences '!D138,0) -> 0 | E136: =IF('Items sous domaines Sciences '!G138=1,'Items sous domaines Sciences '!E138,0) -> Représenter mathématiquement et graphiquement un signal périodique pur.
B137: =IF('Items sous domaines Sciences '!G139=1,'Items sous domaines Sciences '!B139,0) -> Electricité - Electromagnétisme | C137: =IF('Items sous domaines Sciences '!G139=1,'Items sous domaines Sciences '!C139,0) -> Electromagnétisme | D137: =IF('Items sous domaines Sciences '!G139=1,'Items sous domaines Sciences '!D139,0) -> 0 | E137: =IF('Items sous domaines Sciences '!G139=1,'Items sous domaines Sciences '!E139,0) -> Calculer la somme de plusieurs signaux périodiques purs.
B138: =IF('Items sous domaines Sciences '!G140=1,'Items sous domaines Sciences '!B140,0) -> Electricité - Electromagnétisme | C138: =IF('Items sous domaines Sciences '!G140=1,'Items sous domaines Sciences '!C140,0) -> Electromagnétisme | D138: =IF('Items sous domaines Sciences '!G140=1,'Items sous domaines Sciences '!D140,0) -> 0 | E138: =IF('Items sous domaines Sciences '!G140=1,'Items sous domaines Sciences '!E140,0) -> Rajouter son (bruit blanc, bruit rose, décibel,...) ?
...

Sheet A1 CPI S2
A1: Objectifs d'apprentissage des sciences physiques
G3: Remédiation
A4: Notions à maîtriser en CPI A1 S2 (+ onglet A1 CPI S1)
G6: lien Unisciel ou livre scolaire
A7: ='A1 CPI S1'!A7 -> UE du DS | B7: ='A1 CPI S1'!B7 -> Domaine | C7: ='A1 CPI S1'!C7 -> Discipline | D7: ='A1 CPI S1'!D7 -> Chapitres | E7: ='A1 CPI S1'!E7 -> Thèmes | F7: Utilisation
A8: Algèbre : Nombres complexes, arithmétique | B8: =IF('Items sous domaines Sciences '!G10=2,'Items sous domaines Sciences '!B10,0) -> 0 | C8: =IF('Items sous domaines Sciences '!G10=2,'Items sous domaines Sciences '!C10,0) -> 0 | D8: =IF('Items sous domaines Sciences '!G10=2,'Items sous domaines Sciences '!D10,0) -> 0 | E8: =IF('Items sous domaines Sciences '!G10=2,'Items sous domaines Sciences '!E10,0) -> 0 | F8: =IF('Items sous domaines Sciences '!#REF!=2,'Items sous domaines Sciences '!#REF!,0) -> #REF!
B9: =IF('Items sous domaines Sciences '!G11=2,'Items sous domaines Sciences '!B11,0) -> 0 | C9: =IF('Items sous domaines Sciences '!G11=2,'Items sous domaines Sciences '!C11,0) -> 0 | D9: =IF('Items sous domaines Sciences '!G11=2,'Items sous domaines Sciences '!D11,0) -> 0 | E9: =IF('Items sous domaines Sciences '!G11=2,'Items sous domaines Sciences '!E11,0) -> 0 | F9: =IF('Items sous domaines Sciences '!G22=2,'Items sous domaines Sciences '!#REF!,0) -> 0
B10: =IF('Items sous domaines Sciences '!G12=2,'Items sous domaines Sciences '!B12,0) -> 0 | C10: =IF('Items sous domaines Sciences '!G12=2,'Items sous domaines Sciences '!C12,0) -> 0 | D10: =IF('Items sous domaines Sciences '!G12=2,'Items sous domaines Sciences '!D12,0) -> 0 | E10: =IF('Items sous domaines Sciences '!G12=2,'Items sous domaines Sciences '!E12,0) -> 0 | F10: =IF('Items sous domaines Sciences '!G23=2,'Items sous domaines Sciences '!#REF!,0) -> 0
A11: Algèbre : arithmétique | B11: =IF('Items sous domaines Sciences '!G13=2,'Items sous domaines Sciences '!B13,0) -> 0 | C11: =IF('Items sous domaines Sciences '!G13=2,'Items sous domaines Sciences '!C13,0) -> 0 | D11: =IF('Items sous domaines Sciences '!G13=2,'Items sous domaines Sciences '!D13,0) -> 0 | E11: =IF('Items sous domaines Sciences '!G13=2,'Items sous domaines Sciences '!E13,0) -> 0 | F11: ETS | G11: https://uel.unisciel.fr/mathematiques/arithmetique/arithmetique/co/arithmetique.html
B12: =IF('Items sous domaines Sciences '!G14=2,'Items sous domaines Sciences '!B14,0) -> 0 | C12: =IF('Items sous domaines Sciences '!G14=2,'Items sous domaines Sciences '!C14,0) -> 0 | D12: =IF('Items sous domaines Sciences '!G14=2,'Items sous domaines Sciences '!D14,0) -> 0 | E12: =IF('Items sous domaines Sciences '!G14=2,'Items sous domaines Sciences '!E14,0) -> 0
B13: =IF('Items sous domaines Sciences '!G15=2,'Items sous domaines Sciences '!B15,0) -> 0 | C13: =IF('Items sous domaines Sciences '!G15=2,'Items sous domaines Sciences '!C15,0) -> 0 | D13: =IF('Items sous domaines Sciences '!G15=2,'Items sous domaines Sciences '!D15,0) -> 0 | E13: =IF('Items sous domaines Sciences '!G15=2,'Items sous domaines Sciences '!E15,0) -> 0
B14: =IF('Items sous domaines Sciences '!G16=2,'Items sous domaines Sciences '!B16,0) -> 0 | C14: =IF('Items sous domaines Sciences '!G16=2,'Items sous domaines Sciences '!C16,0) -> 0 | D14: =IF('Items sous domaines Sciences '!G16=2,'Items sous domaines Sciences '!D16,0) -> 0 | E14: =IF('Items sous domaines Sciences '!G16=2,'Items sous domaines Sciences '!E16,0) -> 0
B15: =IF('Items sous domaines Sciences '!G17=2,'Items sous domaines Sciences '!B17,0) -> 0 | C15: =IF('Items sous domaines Sciences '!G17=2,'Items sous domaines Sciences '!C17,0) -> 0 | D15: =IF('Items sous domaines Sciences '!G17=2,'Items sous domaines Sciences '!D17,0) -> 0 | E15: =IF('Items sous domaines Sciences '!G17=2,'Items sous domaines Sciences '!E17,0) -> 0 | F15: =IF('Items sous domaines Sciences '!G28=2,'Items sous domaines Sciences '!#REF!,0) -> 0
B16: =IF('Items sous domaines Sciences '!G18=2,'Items sous domaines Sciences '!B18,0) -> 0 | C16: =IF('Items sous domaines Sciences '!G18=2,'Items sous domaines Sciences '!C18,0) -> 0 | D16: =IF('Items sous domaines Sciences '!G18=2,'Items sous domaines Sciences '!D18,0) -> 0 | E16: =IF('Items sous domaines Sciences '!G18=2,'Items sous domaines Sciences '!E18,0) -> 0 | F16: =IF('Items sous domaines Sciences '!G29=2,'Items sous domaines Sciences '!#REF!,0) -> 0
B17: =IF('Items sous domaines Sciences '!G19=2,'Items sous domaines Sciences '!B19,0) -> 0 | C17: =IF('Items sous domaines Sciences '!G19=2,'Items sous domaines Sciences '!C19,0) -> 0 | D17: =IF('Items sous domaines Sciences '!G19=2,'Items sous domaines Sciences '!D19,0) -> 0 | E17: =IF('Items sous domaines Sciences '!G19=2,'Items sous domaines Sciences '!E19,0) -> 0 | F17: =IF('Items sous domaines Sciences '!G30=2,'Items sous domaines Sciences '!#REF!,0) -> 0
B18: =IF('Items sous domaines Sciences '!G20=2,'Items sous domaines Sciences '!B20,0) -> 0 | C18: =IF('Items sous domaines Sciences '!G20=2,'Items sous domaines Sciences '!C20,0) -> 0 | D18: =IF('Items sous domaines Sciences '!G20=2,'Items sous domaines Sciences '!D20,0) -> 0 | E18: =IF('Items sous domaines Sciences '!G20=2,'Items sous domaines Sciences '!E20,0) -> 0 | F18: =IF('Items sous domaines Sciences '!G31=2,'Items sous domaines Sciences '!#REF!,0) -> 0
B19: =IF('Items sous domaines Sciences '!G21=2,'Items sous domaines Sciences '!B21,0) -> 0 | C19: =IF('Items sous domaines Sciences '!G21=2,'Items sous domaines Sciences '!C21,0) -> 0 | D19: =IF('Items sous domaines Sciences '!G21=2,'Items sous domaines Sciences '!D21,0) -> 0 | E19: =IF('Items sous domaines Sciences '!G21=2,'Items sous domaines Sciences '!E21,0) -> 0 | F19: =IF('Items sous domaines Sciences '!G32=2,'Items sous domaines Sciences '!#REF!,0) -> 0
B20: =IF('Items sous domaines Sciences '!G22=2,'Items sous domaines Sciences '!B22,0) -> 0 | C20: =IF('Items sous domaines Sciences '!G22=2,'Items sous domaines Sciences '!C22,0) -> 0 | D20: =IF('Items sous domaines Sciences '!G22=2,'Items sous domaines Sciences '!D22,0) -> 0 | E20: =IF('Items sous domaines Sciences '!G22=2,'Items sous domaines Sciences '!E22,0) -> 0 | F20: =IF('Items sous domaines Sciences '!G33=2,'Items sous domaines Sciences '!#REF!,0) -> 0
B21: =IF('Items sous domaines Sciences '!G23=2,'Items sous domaines Sciences '!B23,0) -> 0 | C21: =IF('Items sous domaines Sciences '!G23=2,'Items sous domaines Sciences '!C23,0) -> 0 | D21: =IF('Items sous domaines Sciences '!G23=2,'Items sous domaines Sciences '!D23,0) -> 0 | E21: =IF('Items sous domaines Sciences '!G23=2,'Items sous domaines Sciences '!E23,0) -> 0 | F21: =IF('Items sous domaines Sciences '!G34=2,'Items sous domaines Sciences '!#REF!,0) -> 0
B22: =IF('Items sous domaines Sciences '!G24=2,'Items sous domaines Sciences '!B24,0) -> 0 | C22: =IF('Items sous domaines Sciences '!G24=2,'Items sous domaines Sciences '!C24,0) -> 0 | D22: =IF('Items sous domaines Sciences '!G24=2,'Items sous domaines Sciences '!D24,0) -> 0 | E22: =IF('Items sous domaines Sciences '!G24=2,'Items sous domaines Sciences '!E24,0) -> 0 | F22: =IF('Items sous domaines Sciences '!G35=2,'Items sous domaines Sciences '!#REF!,0) -> 0
B23: =IF('Items sous domaines Sciences '!G25=2,'Items sous domaines Sciences '!B25,0) -> 0 | C23: =IF('Items sous domaines Sciences '!G25=2,'Items sous domaines Sciences '!C25,0) -> 0 | D23: =IF('Items sous domaines Sciences '!G25=2,'Items sous domaines Sciences '!D25,0) -> 0 | E23: =IF('Items sous domaines Sciences '!G25=2,'Items sous domaines Sciences '!E25,0) -> 0 | F23: =IF('Items sous domaines Sciences '!#REF!=2,'Items sous domaines Sciences '!#REF!,0) -> #REF!
B24: =IF('Items sous domaines Sciences '!G26=2,'Items sous domaines Sciences '!B26,0) -> 0 | C24: =IF('Items sous domaines Sciences '!G26=2,'Items sous domaines Sciences '!C26,0) -> 0 | D24: =IF('Items sous domaines Sciences '!G26=2,'Items sous domaines Sciences '!D26,0) -> 0 | E24: =IF('Items sous domaines Sciences '!G26=2,'Items sous domaines Sciences '!E26,0) -> 0 | F24: =IF('Items sous domaines Sciences '!#REF!=2,'Items sous domaines Sciences '!#REF!,0) -> #REF!
B25: =IF('Items sous domaines Sciences '!G27=2,'Items sous domaines Sciences '!B27,0) -> 0 | C25: =IF('Items sous domaines Sciences '!G27=2,'Items sous domaines Sciences '!C27,0) -> 0 | D25: =IF('Items sous domaines Sciences '!G27=2,'Items sous domaines Sciences '!D27,0) -> 0 | E25: =IF('Items sous domaines Sciences '!G27=2,'Items sous domaines Sciences '!E27,0) -> 0 | F25: =IF('Items sous domaines Sciences '!G78=2,'Items sous domaines Sciences '!#REF!,0) -> 0
B26: =IF('Items sous domaines Sciences '!G28=2,'Items sous domaines Sciences '!B28,0) -> 0 | C26: =IF('Items sous domaines Sciences '!G28=2,'Items sous domaines Sciences '!C28,0) -> 0 | D26: =IF('Items sous domaines Sciences '!G28=2,'Items sous domaines Sciences '!D28,0) -> 0 | E26: =IF('Items sous domaines Sciences '!G28=2,'Items sous domaines Sciences '!E28,0) -> 0 | F26: =IF('Items sous domaines Sciences '!G108=2,'Items sous domaines Sciences '!#REF!,0) -> 0
B27: =IF('Items sous domaines Sciences '!G29=2,'Items sous domaines Sciences '!B29,0) -> 0 | C27: =IF('Items sous domaines Sciences '!G29=2,'Items sous domaines Sciences '!C29,0) -> 0 | D27: =IF('Items sous domaines Sciences '!G29=2,'Items sous domaines Sciences '!D29,0) -> 0 | E27: =IF('Items sous domaines Sciences '!G29=2,'Items sous domaines Sciences '!E29,0) -> 0 | F27: =IF('Items sous domaines Sciences '!G109=2,'Items sous domaines Sciences '!#REF!,0) -> 0
B28: =IF('Items sous domaines Sciences '!G30=2,'Items sous domaines Sciences '!B30,0) -> 0 | C28: =IF('Items sous domaines Sciences '!G30=2,'Items sous domaines Sciences '!C30,0) -> 0 | D28: =IF('Items sous domaines Sciences '!G30=2,'Items sous domaines Sciences '!D30,0) -> 0 | E28: =IF('Items sous domaines Sciences '!G30=2,'Items sous domaines Sciences '!E30,0) -> 0 | F28: =IF('Items sous domaines Sciences '!G110=2,'Items sous domaines Sciences '!#REF!,0) -> 0
B29: =IF('Items sous domaines Sciences '!G31=2,'Items sous domaines Sciences '!B31,0) -> 0 | C29: =IF('Items sous domaines Sciences '!G31=2,'Items sous domaines Sciences '!C31,0) -> 0 | D29: =IF('Items sous domaines Sciences '!G31=2,'Items sous domaines Sciences '!D31,0) -> 0 | E29: =IF('Items sous domaines Sciences '!G31=2,'Items sous domaines Sciences '!E31,0) -> 0 | F29: =IF('Items sous domaines Sciences '!G111=2,'Items sous domaines Sciences '!#REF!,0) -> 0
A30: Théorie des ensembles | B30: =IF('Items sous domaines Sciences '!G32=2,'Items sous domaines Sciences '!B32,0) -> 0 | C30: =IF('Items sous domaines Sciences '!G32=2,'Items sous domaines Sciences '!C32,0) -> 0 | D30: =IF('Items sous domaines Sciences '!G32=2,'Items sous domaines Sciences '!D32,0) -> 0 | E30: =IF('Items sous domaines Sciences '!G32=2,'Items sous domaines Sciences '!E32,0) -> 0 | F30: Projet BDD
B31: =IF('Items sous domaines Sciences '!G33=2,'Items sous domaines Sciences '!B33,0) -> 0 | C31: =IF('Items sous domaines Sciences '!G33=2,'Items sous domaines Sciences '!C33,0) -> 0 | D31: =IF('Items sous domaines Sciences '!G33=2,'Items sous domaines Sciences '!D33,0) -> 0 | E31: =IF('Items sous domaines Sciences '!G33=2,'Items sous domaines Sciences '!E33,0) -> 0
B32: =IF('Items sous domaines Sciences '!G34=2,'Items sous domaines Sciences '!B34,0) -> 0 | C32: =IF('Items sous domaines Sciences '!G34=2,'Items sous domaines Sciences '!C34,0) -> 0 | D32: =IF('Items sous domaines Sciences '!G34=2,'Items sous domaines Sciences '!D34,0) -> 0 | E32: =IF('Items sous domaines Sciences '!G34=2,'Items sous domaines Sciences '!E34,0) -> 0 | F32: =IF('Items sous domaines Sciences '!G130=2,'Items sous domaines Sciences '!#REF!,0) -> 0
B33: =IF('Items sous domaines Sciences '!G35=2,'Items sous domaines Sciences '!B35,0) -> 0 | C33: =IF('Items sous domaines Sciences '!G35=2,'Items sous domaines Sciences '!C35,0) -> 0 | D33: =IF('Items sous domaines Sciences '!G35=2,'Items sous domaines Sciences '!D35,0) -> 0 | E33: =IF('Items sous domaines Sciences '!G35=2,'Items sous domaines Sciences '!E35,0) -> 0 | F33: =IF('Items sous domaines Sciences '!G131=2,'Items sous domaines Sciences '!#REF!,0) -> 0
A34: UE 2.4 : Thermodynamique et thermique | B34: =IF('Items sous domaines Sciences '!G36=2,'Items sous domaines Sciences '!B36,0) -> Mécanique | C34: =IF('Items sous domaines Sciences '!G36=2,'Items sous domaines Sciences '!C36,0) -> RDM | D34: =IF('Items sous domaines Sciences '!G36=2,'Items sous domaines Sciences '!D36,0) -> RDM | E34: =IF('Items sous domaines Sciences '!G36=2,'Items sous domaines Sciences '!E36,0) -> Expliquer les notions "contrainte" et "déformation". | F34: Bloc BTP | G34: https://uel.unisciel.fr/physique/meca/meca/co/meca.html
B35: =IF('Items sous domaines Sciences '!G37=2,'Items sous domaines Sciences '!B37,0) -> Mécanique | C35: =IF('Items sous domaines Sciences '!G37=2,'Items sous domaines Sciences '!C37,0) -> RDM | D35: =IF('Items sous domaines Sciences '!G37=2,'Items sous domaines Sciences '!D37,0) -> 0 | E35: =IF('Items sous domaines Sciences '!G37=2,'Items sous domaines Sciences '!E37,0) -> Interpréter une courbe de traction (domaines élastique, plastique, striction, rupture) et ses données caractéristiques (résistance élastique, résistance max).
B36: =IF('Items sous domaines Sciences '!G38=2,'Items sous domaines Sciences '!B38,0) -> Mécanique | C36: =IF('Items sous domaines Sciences '!G38=2,'Items sous domaines Sciences '!C38,0) -> RDM | D36: =IF('Items sous domaines Sciences '!G38=2,'Items sous domaines Sciences '!D38,0) -> 0 | E36: =IF('Items sous domaines Sciences '!G38=2,'Items sous domaines Sciences '!E38,0) -> Calculer un module d’Young à partir d’une courbe de traction.
B37: =IF('Items sous domaines Sciences '!G39=2,'Items sous domaines Sciences '!B39,0) -> Mécanique | C37: =IF('Items sous domaines Sciences '!G39=2,'Items sous domaines Sciences '!C39,0) -> RDM | D37: =IF('Items sous domaines Sciences '!G39=2,'Items sous domaines Sciences '!D39,0) -> 0 | E37: =IF('Items sous domaines Sciences '!G39=2,'Items sous domaines Sciences '!E39,0) -> Calculer une contrainte et un allongement.
B38: =IF('Items sous domaines Sciences '!G40=2,'Items sous domaines Sciences '!B40,0) -> Mécanique | C38: =IF('Items sous domaines Sciences '!G40=2,'Items sous domaines Sciences '!C40,0) -> RDM | D38: =IF('Items sous domaines Sciences '!G40=2,'Items sous domaines Sciences '!D40,0) -> 0 | E38: =IF('Items sous domaines Sciences '!G40=2,'Items sous domaines Sciences '!E40,0) -> Utiliser la loi de Hooke.
B39: =IF('Items sous domaines Sciences '!G41=2,'Items sous domaines Sciences '!B41,0) -> Mécanique | C39: =IF('Items sous domaines Sciences '!G41=2,'Items sous domaines Sciences '!C41,0) -> RDM | D39: =IF('Items sous domaines Sciences '!G41=2,'Items sous domaines Sciences '!D41,0) -> 0 | E39: =IF('Items sous domaines Sciences '!G41=2,'Items sous domaines Sciences '!E41,0) -> Corréler les propriétés mécaniques et thermiques d’un matériau au type de liaison.
B40: =IF('Items sous domaines Sciences '!G42=2,'Items sous domaines Sciences '!B42,0) -> Mécanique | C40: =IF('Items sous domaines Sciences '!G42=2,'Items sous domaines Sciences '!C42,0) -> RDM | D40: =IF('Items sous domaines Sciences '!G42=2,'Items sous domaines Sciences '!D42,0) -> 0 | E40: =IF('Items sous domaines Sciences '!G42=2,'Items sous domaines Sciences '!E42,0) -> Discriminer un matériau pour une application.
B41: =IF('Items sous domaines Sciences '!G43=2,'Items sous domaines Sciences '!B43,0) -> Mécanique | C41: =IF('Items sous domaines Sciences '!G43=2,'Items sous domaines Sciences '!C43,0) -> RDM | D41: =IF('Items sous domaines Sciences '!G43=2,'Items sous domaines Sciences '!D43,0) -> 0 | E41: =IF('Items sous domaines Sciences '!G43=2,'Items sous domaines Sciences '!E43,0) -> Identifier les liaisons mécaniques (2D) entre solides, internes/externes (appui simple, articulation).
B42: =IF('Items sous domaines Sciences '!G44=2,'Items sous domaines Sciences '!B44,0) -> Mécanique | C42: =IF('Items sous domaines Sciences '!G44=2,'Items sous domaines Sciences '!C44,0) -> RDM | D42: =IF('Items sous domaines Sciences '!G44=2,'Items sous domaines Sciences '!D44,0) -> 0 | E42: =IF('Items sous domaines Sciences '!G44=2,'Items sous domaines Sciences '!E44,0) -> Identifier et appliquer les différents types de charges (force ponctuelle, charge linéique).
B43: =IF('Items sous domaines Sciences '!G45=2,'Items sous domaines Sciences '!B45,0) -> Mécanique | C43: =IF('Items sous domaines Sciences '!G45=2,'Items sous domaines Sciences '!C45,0) -> RDM | D43: =IF('Items sous domaines Sciences '!G45=2,'Items sous domaines Sciences '!D45,0) -> 0 | E43: =IF('Items sous domaines Sciences '!G45=2,'Items sous domaines Sciences '!E45,0) -> Déterminer le nombre de degrés de liberté d’un système articulé.
B44: =IF('Items sous domaines Sciences '!G46=2,'Items sous domaines Sciences '!B46,0) -> Mécanique | C44: =IF('Items sous domaines Sciences '!G46=2,'Items sous domaines Sciences '!C46,0) -> RDM | D44: =IF('Items sous domaines Sciences '!G46=2,'Items sous domaines Sciences '!D46,0) -> 0 | E44: =IF('Items sous domaines Sciences '!G46=2,'Items sous domaines Sciences '!E46,0) -> Utiliser le principe d’action/réaction pour appliquer le PFS.
B45: =IF('Items sous domaines Sciences '!G47=2,'Items sous domaines Sciences '!B47,0) -> Mécanique | C45: =IF('Items sous domaines Sciences '!G47=2,'Items sous domaines Sciences '!C47,0) -> RDM | D45: =IF('Items sous domaines Sciences '!G47=2,'Items sous domaines Sciences '!D47,0) -> 0 | E45: =IF('Items sous domaines Sciences '!G47=2,'Items sous domaines Sciences '!E47,0) -> Mettre en place une méthode de résolution d’un système isostatique.
B46: =IF('Items sous domaines Sciences '!G48=2,'Items sous domaines Sciences '!B48,0) -> Mécanique | C46: =IF('Items sous domaines Sciences '!G48=2,'Items sous domaines Sciences '!C48,0) -> RDM | D46: =IF('Items sous domaines Sciences '!G48=2,'Items sous domaines Sciences '!D48,0) -> 0 | E46: =IF('Items sous domaines Sciences '!G48=2,'Items sous domaines Sciences '!E48,0) -> Calculer une descente de charge.
... B56: =IF('Items sous domaines Sciences '!G58=2,'Items sous domaines Sciences '!B58,0) -> 0 | C56: =IF('Items sous domaines Sciences '!G58=2,'Items sous domaines Sciences '!C58,0) -> 0 | D56: =IF('Items sous domaines Sciences '!G58=2,'Items sous domaines Sciences '!D58,0) -> 0 | E56: =IF('Items sous domaines Sciences '!G58=2,'Items sous domaines Sciences '!E58,0) -> 0
A57: Algèbre : Nombres complexes | B57: =IF('Items sous domaines Sciences '!G59=2,'Items sous domaines Sciences '!B59,0) -> 0 | C57: =IF('Items sous domaines Sciences '!G59=2,'Items sous domaines Sciences '!C59,0) -> 0 | D57: =IF('Items sous domaines Sciences '!G59=2,'Items sous domaines Sciences '!D59,0) -> 0 | E57: =IF('Items sous domaines Sciences '!G59=2,'Items sous domaines Sciences '!E59,0) -> 0 | G57: https://uel.unisciel.fr/physique/outils_nancy/outils_nancy_ch04/co/apprendre_ch04.html | H57: lien2
B58: =IF('Items sous domaines Sciences '!G60=2,'Items sous domaines Sciences '!B60,0) -> 0 | C58: =IF('Items sous domaines Sciences '!G60=2,'Items sous domaines Sciences '!C60,0) -> 0 | D58: =IF('Items sous domaines Sciences '!G60=2,'Items sous domaines Sciences '!D60,0) -> 0 | E58: =IF('Items sous domaines Sciences '!G60=2,'Items sous domaines Sciences '!E60,0) -> 0 | H58: lien 3
B59: =IF('Items sous domaines Sciences '!G61=2,'Items sous domaines Sciences '!B61,0) -> 0 | C59: =IF('Items sous domaines Sciences '!G61=2,'Items sous domaines Sciences '!C61,0) -> 0 | D59: =IF('Items sous domaines Sciences '!G61=2,'Items sous domaines Sciences '!D61,0) -> 0 | E59: =IF('Items sous domaines Sciences '!G61=2,'Items sous domaines Sciences '!E61,0) -> 0 | H59: lien 4
B60: =IF('Items sous domaines Sciences '!G62=2,'Items sous domaines Sciences '!B62,0) -> 0 | C60: =IF('Items sous domaines Sciences '!G62=2,'Items sous domaines Sciences '!C62,0) -> 0 | D60: =IF('Items sous domaines Sciences '!G62=2,'Items sous domaines Sciences '!D62,0) -> 0 | E60: =IF('Items sous domaines Sciences '!G62=2,'Items sous domaines Sciences '!E62,0) -> 0
B61: =IF('Items sous domaines Sciences '!G63=2,'Items sous domaines Sciences '!B63,0) -> 0 | C61: =IF('Items sous domaines Sciences '!G63=2,'Items sous domaines Sciences '!C63,0) -> 0 | D61: =IF('Items sous domaines Sciences '!G63=2,'Items sous domaines Sciences '!D63,0) -> 0 | E61: =IF('Items sous domaines Sciences '!G63=2,'Items sous domaines Sciences '!E63,0) -> 0
B62: =IF('Items sous domaines Sciences '!G64=2,'Items sous domaines Sciences '!B64,0) -> 0 | C62: =IF('Items sous domaines Sciences '!G64=2,'Items sous domaines Sciences '!C64,0) -> 0 | D62: =IF('Items sous domaines Sciences '!G64=2,'Items sous domaines Sciences '!D64,0) -> 0 | E62: =IF('Items sous domaines Sciences '!G64=2,'Items sous domaines Sciences '!E64,0) -> 0
A63: Analyse : Interpolation, développement limité 0 | B63: =IF('Items sous domaines Sciences '!G65=2,'Items sous domaines Sciences '!B65,0) -> 0 | C63: =IF('Items sous domaines Sciences '!G65=2,'Items sous domaines Sciences '!C65,0) -> 0 | D63: =IF('Items sous domaines Sciences '!G65=2,'Items sous domaines Sciences '!D65,0) -> 0 | E63: =IF('Items sous domaines Sciences '!G65=2,'Items sous domaines Sciences '!E65,0) -> 0
B64: =IF('Items sous domaines Sciences '!G66=2,'Items sous domaines Sciences '!B66,0) -> 0 | C64: =IF('Items sous domaines Sciences '!G66=2,'Items sous domaines Sciences '!C66,0) -> 0 | D64: =IF('Items sous domaines Sciences '!G66=2,'Items sous domaines Sciences '!D66,0) -> 0 | E64: =IF('Items sous domaines Sciences '!G66=2,'Items sous domaines Sciences '!E66,0) -> 0
B65: =IF('Items sous domaines Sciences '!G67=2,'Items sous domaines Sciences '!B67,0) -> 0 | C65: =IF('Items sous domaines Sciences '!G67=2,'Items sous domaines Sciences '!C67,0) -> 0 | D65: =IF('Items sous domaines Sciences '!G67=2,'Items sous domaines Sciences '!D67,0) -> 0 | E65: =IF('Items sous domaines Sciences '!G67=2,'Items sous domaines Sciences '!E67,0) -> 0
B66: =IF('Items sous domaines Sciences '!G68=2,'Items sous domaines Sciences '!B68,0) -> 0 | C66: =IF('Items sous domaines Sciences '!G68=2,'Items sous domaines Sciences '!C68,0) -> 0 | D66: =IF('Items sous domaines Sciences '!G68=2,'Items sous domaines Sciences '!D68,0) -> 0 | E66: =IF('Items sous domaines Sciences '!G68=2,'Items sous domaines Sciences '!E68,0) -> 0
B67: =IF('Items sous domaines Sciences '!G69=2,'Items sous domaines Sciences '!B69,0) -> 0 | C67: =IF('Items sous domaines Sciences '!G69=2,'Items sous domaines Sciences '!C69,0) -> 0 | D67: =IF('Items sous domaines Sciences '!G69=2,'Items sous domaines Sciences '!D69,0) -> 0 | E67: =IF('Items sous domaines Sciences '!G69=2,'Items sous domaines Sciences '!E69,0) -> 0
B68: =IF('Items sous domaines Sciences '!G70=2,'Items sous domaines Sciences '!B70,0) -> 0 | C68: =IF('Items sous domaines Sciences '!G70=2,'Items sous domaines Sciences '!C70,0) -> 0 | D68: =IF('Items sous domaines Sciences '!G70=2,'Items sous domaines Sciences '!D70,0) -> 0 | E68: =IF('Items sous domaines Sciences '!G70=2,'Items sous domaines Sciences '!E70,0) -> 0
B69: =IF('Items sous domaines Sciences '!G71=2,'Items sous domaines Sciences '!B71,0) -> 0 | C69: =IF('Items sous domaines Sciences '!G71=2,'Items sous domaines Sciences '!C71,0) -> 0 | D69: =IF('Items sous domaines Sciences '!G71=2,'Items sous domaines Sciences '!D71,0) -> 0 | E69: =IF('Items sous domaines Sciences '!G71=2,'Items sous domaines Sciences '!E71,0) -> 0
B70: =IF('Items sous domaines Sciences '!G72=2,'Items sous domaines Sciences '!B72,0) -> 0 | C70: =IF('Items sous domaines Sciences '!G72=2,'Items sous domaines Sciences '!C72,0) -> 0 | D70: =IF('Items sous domaines Sciences '!G72=2,'Items sous domaines Sciences '!D72,0) -> 0 | E70: =IF('Items sous domaines Sciences '!G72=2,'Items sous domaines Sciences '!E72,0) -> 0
B71: =IF('Items sous domaines Sciences '!G73=2,'Items sous domaines Sciences '!B73,0) -> 0 | C71: =IF('Items sous domaines Sciences '!G73=2,'Items sous domaines Sciences '!C73,0) -> 0 | D71: =IF('Items sous domaines Sciences '!G73=2,'Items sous domaines Sciences '!D73,0) -> 0 | E71: =IF('Items sous domaines Sciences '!G73=2,'Items sous domaines Sciences '!E73,0) -> 0
B72: =IF('Items sous domaines Sciences '!G74=2,'Items sous domaines Sciences '!B74,0) -> 0 | C72: =IF('Items sous domaines Sciences '!G74=2,'Items sous domaines Sciences '!C74,0) -> 0 | D72: =IF('Items sous domaines Sciences '!G74=2,'Items sous domaines Sciences '!D74,0) -> 0 | E72: =IF('Items sous domaines Sciences '!G74=2,'Items sous domaines Sciences '!E74,0) -> 0
B73: =IF('Items sous domaines Sciences '!G75=2,'Items sous domaines Sciences '!B75,0) -> 0 | C73: =IF('Items sous domaines Sciences '!G75=2,'Items sous domaines Sciences '!C75,0) -> 0 | D73: =IF('Items sous domaines Sciences '!G75=2,'Items sous domaines Sciences '!D75,0) -> 0 | E73: =IF('Items sous domaines Sciences '!G75=2,'Items sous domaines Sciences '!E75,0) -> 0
B74: =IF('Items sous domaines Sciences '!G76=2,'Items sous domaines Sciences '!B76,0) -> 0 | C74: =IF('Items sous domaines Sciences '!G76=2,'Items sous domaines Sciences '!C76,0) -> 0 | D74: =IF('Items sous domaines Sciences '!G76=2,'Items sous domaines Sciences '!D76,0) -> 0 | E74: =IF('Items sous domaines Sciences '!G76=2,'Items sous domaines Sciences '!E76,0) -> 0
B75: =IF('Items sous domaines Sciences '!G77=2,'Items sous domaines Sciences '!B77,0) -> 0 | C75: =IF('Items sous domaines Sciences '!G77=2,'Items sous domaines Sciences '!C77,0) -> 0 | D75: =IF('Items sous domaines Sciences '!G77=2,'Items sous domaines Sciences '!D77,0) -> 0 | E75: =IF('Items sous domaines Sciences '!G77=2,'Items sous domaines Sciences '!E77,0) -> 0
... B88: =IF('Items sous domaines Sciences '!G90=2,'Items sous domaines Sciences '!B90,0) -> 0 | C88: =IF('Items sous domaines Sciences '!G90=2,'Items sous domaines Sciences '!C90,0) -> 0 | D88: =IF('Items sous domaines Sciences '!G90=2,'Items sous domaines Sciences '!D90,0) -> 0 | E88: =IF('Items sous domaines Sciences '!G90=2,'Items sous domaines Sciences '!E90,0) -> 0
A89: Algèbre : Matrices et système | B89: =IF('Items sous domaines Sciences '!G91=2,'Items sous domaines Sciences '!B91,0) -> 0 | C89: =IF('Items sous domaines Sciences '!G91=2,'Items sous domaines Sciences '!C91,0) -> 0 | D89: =IF('Items sous domaines Sciences '!G91=2,'Items sous domaines Sciences '!D91,0) -> 0 | E89: =IF('Items sous domaines Sciences '!G91=2,'Items sous domaines Sciences '!E91,0) -> 0
B90: =IF('Items sous domaines Sciences '!G92=2,'Items sous domaines Sciences '!B92,0) -> 0 | C90: =IF('Items sous domaines Sciences '!G92=2,'Items sous domaines Sciences '!C92,0) -> 0 | D90: =IF('Items sous domaines Sciences '!G92=2,'Items sous domaines Sciences '!D92,0) -> 0 | E90: =IF('Items sous domaines Sciences '!G92=2,'Items sous domaines Sciences '!E92,0) -> 0
B91: =IF('Items sous domaines Sciences '!G93=2,'Items sous domaines Sciences '!B93,0) -> 0 | C91: =IF('Items sous domaines Sciences '!G93=2,'Items sous domaines Sciences '!C93,0) -> 0 | D91: =IF('Items sous domaines Sciences '!G93=2,'Items sous domaines Sciences '!D93,0) -> 0 | E91: =IF('Items sous domaines Sciences '!G93=2,'Items sous domaines Sciences '!E93,0) -> 0
B92: =IF('Items sous domaines Sciences '!G94=2,'Items sous domaines Sciences '!B94,0) -> 0 | C92: =IF('Items sous domaines Sciences '!G94=2,'Items sous domaines Sciences '!C94,0) -> 0 | D92: =IF('Items sous domaines Sciences '!G94=2,'Items sous domaines Sciences '!D94,0) -> 0 | E92: =IF('Items sous domaines Sciences '!G94=2,'Items sous domaines Sciences '!E94,0) -> 0
B93: =IF('Items sous domaines Sciences '!G95=2,'Items sous domaines Sciences '!B95,0) -> 0 | C93: =IF('Items sous domaines Sciences '!G95=2,'Items sous domaines Sciences '!C95,0) -> 0 | D93: =IF('Items sous domaines Sciences '!G95=2,'Items sous domaines Sciences '!D95,0) -> 0 | E93: =IF('Items sous domaines Sciences '!G95=2,'Items sous domaines Sciences '!E95,0) -> 0
B94: =IF('Items sous domaines Sciences '!G96=2,'Items sous domaines Sciences '!B96,0) -> 0 | C94: =IF('Items sous domaines Sciences '!G96=2,'Items sous domaines Sciences '!C96,0) -> 0 | D94: =IF('Items sous domaines Sciences '!G96=2,'Items sous domaines Sciences '!D96,0) -> 0 | E94: =IF('Items sous domaines Sciences '!G96=2,'Items sous domaines Sciences '!E96,0) -> 0
B95: =IF('Items sous domaines Sciences '!G97=2,'Items sous domaines Sciences '!B97,0) -> 0 | C95: =IF('Items sous domaines Sciences '!G97=2,'Items sous domaines Sciences '!C97,0) -> 0 | D95: =IF('Items sous domaines Sciences '!G97=2,'Items sous domaines Sciences '!D97,0) -> 0 | E95: =IF('Items sous domaines Sciences '!G97=2,'Items sous domaines Sciences '!E97,0) -> 0 | G95: Cours [Calcul matriciel] (unisciel.fr)
B96: =IF('Items sous domaines Sciences '!G98=2,'Items sous domaines Sciences '!B98,0) -> 0 | C96: =IF('Items sous domaines Sciences '!G98=2,'Items sous domaines Sciences '!C98,0) -> 0 | D96: =IF('Items sous domaines Sciences '!G98=2,'Items sous domaines Sciences '!D98,0) -> 0 | E96: =IF('Items sous domaines Sciences '!G98=2,'Items sous domaines Sciences '!E98,0) -> 0
B97: =IF('Items sous domaines Sciences '!G99=2,'Items sous domaines Sciences '!B99,0) -> 0 | C97: =IF('Items sous domaines Sciences '!G99=2,'Items sous domaines Sciences '!C99,0) -> 0 | D97: =IF('Items sous domaines Sciences '!G99=2,'Items sous domaines Sciences '!D99,0) -> 0 | E97: =IF('Items sous domaines Sciences '!G99=2,'Items sous domaines Sciences '!E99,0) -> 0
B98: =IF('Items sous domaines Sciences '!G100=2,'Items sous domaines Sciences '!B100,0) -> 0 | C98: =IF('Items sous domaines Sciences '!G100=2,'Items sous domaines Sciences '!C100,0) -> 0 | D98: =IF('Items sous domaines Sciences '!G100=2,'Items sous domaines Sciences '!D100,0) -> 0 | E98: =IF('Items sous domaines Sciences '!G100=2,'Items sous domaines Sciences '!E100,0) -> 0
B99: =IF('Items sous domaines Sciences '!G101=2,'Items sous domaines Sciences '!B101,0) -> 0 | C99: =IF('Items sous domaines Sciences '!G101=2,'Items sous domaines Sciences '!C101,0) -> 0 | D99: =IF('Items sous domaines Sciences '!G101=2,'Items sous domaines Sciences '!D101,0) -> 0 | E99: =IF('Items sous domaines Sciences '!G101=2,'Items sous domaines Sciences '!E101,0) -> 0
B100: =IF('Items sous domaines Sciences '!G102=2,'Items sous domaines Sciences '!B102,0) -> 0 | C100: =IF('Items sous domaines Sciences '!G102=2,'Items sous domaines Sciences '!C102,0) -> 0 | D100: =IF('Items sous domaines Sciences '!G102=2,'Items sous domaines Sciences '!D102,0) -> 0 | E100: =IF('Items sous domaines Sciences '!G102=2,'Items sous domaines Sciences '!E102,0) -> 0
B101: =IF('Items sous domaines Sciences '!G103=2,'Items sous domaines Sciences '!B103,0) -> 0 | C101: =IF('Items sous domaines Sciences '!G103=2,'Items sous domaines Sciences '!C103,0) -> 0 | D101: =IF('Items sous domaines Sciences '!G103=2,'Items sous domaines Sciences '!D103,0) -> 0 | E101: =IF('Items sous domaines Sciences '!G103=2,'Items sous domaines Sciences '!E103,0) -> 0
B102: =IF('Items sous domaines Sciences '!G104=2,'Items sous domaines Sciences '!B104,0) -> 0 | C102: =IF('Items sous domaines Sciences '!G104=2,'Items sous domaines Sciences '!C104,0) -> 0 | D102: =IF('Items sous domaines Sciences '!G104=2,'Items sous domaines Sciences '!D104,0) -> 0 | E102: =IF('Items sous domaines Sciences '!G104=2,'Items sous domaines Sciences '!E104,0) -> 0
B103: =IF('Items sous domaines Sciences '!G105=2,'Items sous domaines Sciences '!B105,0) -> 0 | C103: =IF('Items sous domaines Sciences '!G105=2,'Items sous domaines Sciences '!C105,0) -> 0 | D103: =IF('Items sous domaines Sciences '!G105=2,'Items sous domaines Sciences '!D105,0) -> 0 | E103: =IF('Items sous domaines Sciences '!G105=2,'Items sous domaines Sciences '!E105,0) -> 0
B104: =IF('Items sous domaines Sciences '!G106=2,'Items sous domaines Sciences '!B106,0) -> 0 | C104: =IF('Items sous domaines Sciences '!G106=2,'Items sous domaines Sciences '!C106,0) -> 0 | D104: =IF('Items sous domaines Sciences '!G106=2,'Items sous domaines Sciences '!D106,0) -> 0 | E104: =IF('Items sous domaines Sciences '!G106=2,'Items sous domaines Sciences '!E106,0) -> 0
B105: =IF('Items sous domaines Sciences '!G107=2,'Items sous domaines Sciences '!B107,0) -> 0 | C105: =IF('Items sous domaines Sciences '!G107=2,'Items sous domaines Sciences '!C107,0) -> 0 | D105: =IF('Items sous domaines Sciences '!G107=2,'Items sous domaines Sciences '!D107,0) -> 0 | E105: =IF('Items sous domaines Sciences '!G107=2,'Items sous domaines Sciences '!E107,0) -> 0
B106: =IF('Items sous domaines Sciences '!G108=2,'Items sous domaines Sciences '!B108,0) -> 0 | C106: =IF('Items sous domaines Sciences '!G108=2,'Items sous domaines Sciences '!C108,0) -> 0 | D106: =IF('Items sous domaines Sciences '!G108=2,'Items sous domaines Sciences '!D108,0) -> 0 | E106: =IF('Items sous domaines Sciences '!G108=2,'Items sous domaines Sciences '!E108,0) -> 0
B107: =IF('Items sous domaines Sciences '!G109=2,'Items sous domaines Sciences '!B109,0) -> 0 | C107: =IF('Items sous domaines Sciences '!G109=2,'Items sous domaines Sciences '!C109,0) -> 0 | D107: =IF('Items sous domaines Sciences '!G109=2,'Items sous domaines Sciences '!D109,0) -> 0 | E107: =IF('Items sous domaines Sciences '!G109=2,'Items sous domaines Sciences '!E109,0) -> 0
... B112: =IF('Items sous domaines Sciences '!G114=2,'Items sous domaines Sciences '!B114,0) -> 0 | C112: =IF('Items sous domaines Sciences '!G114=2,'Items sous domaines Sciences '!C114,0) -> 0 | D112: =IF('Items sous domaines Sciences '!G114=2,'Items sous domaines Sciences '!D114,0) -> 0 | E112: =IF('Items sous domaines Sciences '!G114=2,'Items sous domaines Sciences '!E114,0) -> 0
A113: Algèbre : Graphes | B113: =IF('Items sous domaines Sciences '!G115=2,'Items sous domaines Sciences '!B115,0) -> 0 | C113: =IF('Items sous domaines Sciences '!G115=2,'Items sous domaines Sciences '!C115,0) -> 0 | D113: =IF('Items sous domaines Sciences '!G115=2,'Items sous domaines Sciences '!D115,0) -> 0 | E113: =IF('Items sous domaines Sciences '!G115=2,'Items sous domaines Sciences '!E115,0) -> 0
B114: =IF('Items sous domaines Sciences '!G116=2,'Items sous domaines Sciences '!B116,0) -> 0 | C114: =IF('Items sous domaines Sciences '!G116=2,'Items sous domaines Sciences '!C116,0) -> 0 | D114: =IF('Items sous domaines Sciences '!G116=2,'Items sous domaines Sciences '!D116,0) -> 0 | E114: =IF('Items sous domaines Sciences '!G116=2,'Items sous domaines Sciences '!E116,0) -> 0
B115: =IF('Items sous domaines Sciences '!G117=2,'Items sous domaines Sciences '!B117,0) -> 0 | C115: =IF('Items sous domaines Sciences '!G117=2,'Items sous domaines Sciences '!C117,0) -> 0 | D115: =IF('Items sous domaines Sciences '!G117=2,'Items sous domaines Sciences '!D117,0) -> 0 | E115: =IF('Items sous domaines Sciences '!G117=2,'Items sous domaines Sciences '!E117,0) -> 0
B116: =IF('Items sous domaines Sciences '!G118=2,'Items sous domaines Sciences '!B118,0) -> 0 | C116: =IF('Items sous domaines Sciences '!G118=2,'Items sous domaines Sciences '!C118,0) -> 0 | D116: =IF('Items sous domaines Sciences '!G118=2,'Items sous domaines Sciences '!D118,0) -> 0 | E116: =IF('Items sous domaines Sciences '!G118=2,'Items sous domaines Sciences '!E118,0) -> 0
B117: =IF('Items sous domaines Sciences '!G119=2,'Items sous domaines Sciences '!B119,0) -> 0 | C117: =IF('Items sous domaines Sciences '!G119=2,'Items sous domaines Sciences '!C119,0) -> 0 | D117: =IF('Items sous domaines Sciences '!G119=2,'Items sous domaines Sciences '!D119,0) -> 0 | E117: =IF('Items sous domaines Sciences '!G119=2,'Items sous domaines Sciences '!E119,0) -> 0
B118: =IF('Items sous domaines Sciences '!G120=2,'Items sous domaines Sciences '!B120,0) -> 0 | C118: =IF('Items sous domaines Sciences '!G120=2,'Items sous domaines Sciences '!C120,0) -> 0 | D118: =IF('Items sous domaines Sciences '!G120=2,'Items sous domaines Sciences '!D120,0) -> 0 | E118: =IF('Items sous domaines Sciences '!G120=2,'Items sous domaines Sciences '!E120,0) -> 0
B119: =IF('Items sous domaines Sciences '!G121=2,'Items sous domaines Sciences '!B121,0) -> 0 | C119: =IF('Items sous domaines Sciences '!G121=2,'Items sous domaines Sciences '!C121,0) -> 0 | D119: =IF('Items sous domaines Sciences '!G121=2,'Items sous domaines Sciences '!D121,0) -> 0 | E119: =IF('Items sous domaines Sciences '!G121=2,'Items sous domaines Sciences '!E121,0) -> 0
B120: =IF('Items sous domaines Sciences '!G122=2,'Items sous domaines Sciences '!B122,0) -> 0 | C120: =IF('Items sous domaines Sciences '!G122=2,'Items sous domaines Sciences '!C122,0) -> 0 | D120: =IF('Items sous domaines Sciences '!G122=2,'Items sous domaines Sciences '!D122,0) -> 0 | E120: =IF('Items sous domaines Sciences '!G122=2,'Items sous domaines Sciences '!E122,0) -> 0
B121: =IF('Items sous domaines Sciences '!G123=2,'Items sous domaines Sciences '!B123,0) -> 0 | C121: =IF('Items sous domaines Sciences '!G123=2,'Items sous domaines Sciences '!C123,0) -> 0 | D121: =IF('Items sous domaines Sciences '!G123=2,'Items sous domaines Sciences '!D123,0) -> 0 | E121: =IF('Items sous domaines Sciences '!G123=2,'Items sous domaines Sciences '!E123,0) -> 0
B122: =IF('Items sous domaines Sciences '!G124=2,'Items sous domaines Sciences '!B124,0) -> 0 | C122: =IF('Items sous domaines Sciences '!G124=2,'Items sous domaines Sciences '!C124,0) -> 0 | D122: =IF('Items sous domaines Sciences '!G124=2,'Items sous domaines Sciences '!D124,0) -> 0 | E122: =IF('Items sous domaines Sciences '!G124=2,'Items sous domaines Sciences '!E124,0) -> 0
B123: =IF('Items sous domaines Sciences '!G125=2,'Items sous domaines Sciences '!B125,0) -> 0 | C123: =IF('Items sous domaines Sciences '!G125=2,'Items sous domaines Sciences '!C125,0) -> 0 | D123: =IF('Items sous domaines Sciences '!G125=2,'Items sous domaines Sciences '!D125,0) -> 0 | E123: =IF('Items sous domaines Sciences '!G125=2,'Items sous domaines Sciences '!E125,0) -> 0
B124: =IF('Items sous domaines Sciences '!G126=2,'Items sous domaines Sciences '!B126,0) -> 0 | C124: =IF('Items sous domaines Sciences '!G126=2,'Items sous domaines Sciences '!C126,0) -> 0 | D124: =IF('Items sous domaines Sciences '!G126=2,'Items sous domaines Sciences '!D126,0) -> 0 | E124: =IF('Items sous domaines Sciences '!G126=2,'Items sous domaines Sciences '!E126,0) -> 0
B125: =IF('Items sous domaines Sciences '!G127=2,'Items sous domaines Sciences '!B127,0) -> 0 | C125: =IF('Items sous domaines Sciences '!G127=2,'Items sous domaines Sciences '!C127,0) -> 0 | D125: =IF('Items sous domaines Sciences '!G127=2,'Items sous domaines Sciences '!D127,0) -> 0 | E125: =IF('Items sous domaines Sciences '!G127=2,'Items sous domaines Sciences '!E127,0) -> 0
... B128: =IF('Items sous domaines Sciences '!G130=2,'Items sous domaines Sciences '!B130,0) -> 0 | C128: =IF('Items sous domaines Sciences '!G130=2,'Items sous domaines Sciences '!C130,0) -> 0 | D128: =IF('Items sous domaines Sciences '!G130=2,'Items sous domaines Sciences '!D130,0) -> 0 | E128: =IF('Items sous domaines Sciences '!G130=2,'Items sous domaines Sciences '!E130,0) -> 0
A129: Géométire vectorielle | B129: =IF('Items sous domaines Sciences '!G131=2,'Items sous domaines Sciences '!B131,0) -> 0 | C129: =IF('Items sous domaines Sciences '!G131=2,'Items sous domaines Sciences '!C131,0) -> 0 | D129: =IF('Items sous domaines Sciences '!G131=2,'Items sous domaines Sciences '!D131,0) -> 0 | E129: =IF('Items sous domaines Sciences '!G131=2,'Items sous domaines Sciences '!E131,0) -> 0 | G129: Géométrie analytique (unisciel.fr)
...

Sheet A2 CPI Géné  S3 
A1: Objectifs d'apprentissage des sciences physiques
G3: Remédiation
A4: Notions à maîtriser en A2 (en révisant le socle A1)
G6: lien Unisciel ou livre scolaire
A7: ='A1 CPI S1'!A7 -> UE du DS | B7: ='A1 CPI S1'!B7 -> Domaine | C7: ='A1 CPI S1'!C7 -> Discipline | D7: ='A1 CPI S1'!D7 -> Chapitres | E7: ='A1 CPI S1'!E7 -> Thèmes | F7: ='A1 CPI S1'!F7 -> Utilisation
A8: UE 3.3 : Thermique et Mécanique des fluides | B8: =IF('Items sous domaines Sciences '!G10=3,'Items sous domaines Sciences '!B10,0) -> 0 | C8: =IF('Items sous domaines Sciences '!G10=3,'Items sous domaines Sciences '!C10,0) -> 0 | D8: =IF('Items sous domaines Sciences '!G10=3,'Items sous domaines Sciences '!D10,0) -> 0 | E8: =IF('Items sous domaines Sciences '!G10=3,'Items sous domaines Sciences '!E10,0) -> 0 | F8: =IF('Items sous domaines Sciences '!#REF!=1,'Items sous domaines Sciences '!#REF!,0) -> #REF!
B9: =IF('Items sous domaines Sciences '!G11=3,'Items sous domaines Sciences '!B11,0) -> 0 | C9: =IF('Items sous domaines Sciences '!G11=3,'Items sous domaines Sciences '!C11,0) -> 0 | D9: =IF('Items sous domaines Sciences '!G11=3,'Items sous domaines Sciences '!D11,0) -> 0 | E9: =IF('Items sous domaines Sciences '!G11=3,'Items sous domaines Sciences '!E11,0) -> 0 | F9: =IF('Items sous domaines Sciences '!G22=1,'Items sous domaines Sciences '!#REF!,0) -> 0
B10: =IF('Items sous domaines Sciences '!G12=3,'Items sous domaines Sciences '!B12,0) -> 0 | C10: =IF('Items sous domaines Sciences '!G12=3,'Items sous domaines Sciences '!C12,0) -> 0 | D10: =IF('Items sous domaines Sciences '!G12=3,'Items sous domaines Sciences '!D12,0) -> 0 | E10: =IF('Items sous domaines Sciences '!G12=3,'Items sous domaines Sciences '!E12,0) -> 0 | F10: =IF('Items sous domaines Sciences '!G23=1,'Items sous domaines Sciences '!#REF!,0) -> 0
B11: =IF('Items sous domaines Sciences '!G13=3,'Items sous domaines Sciences '!B13,0) -> 0 | C11: =IF('Items sous domaines Sciences '!G13=3,'Items sous domaines Sciences '!C13,0) -> 0 | D11: =IF('Items sous domaines Sciences '!G13=3,'Items sous domaines Sciences '!D13,0) -> 0 | E11: =IF('Items sous domaines Sciences '!G13=3,'Items sous domaines Sciences '!E13,0) -> 0 | F11: =IF('Items sous domaines Sciences '!G24=1,'Items sous domaines Sciences '!#REF!,0) -> 0
B12: =IF('Items sous domaines Sciences '!G14=3,'Items sous domaines Sciences '!B14,0) -> 0 | C12: =IF('Items sous domaines Sciences '!G14=3,'Items sous domaines Sciences '!C14,0) -> 0 | D12: =IF('Items sous domaines Sciences '!G14=3,'Items sous domaines Sciences '!D14,0) -> 0 | E12: =IF('Items sous domaines Sciences '!G14=3,'Items sous domaines Sciences '!E14,0) -> 0 | F12: =IF('Items sous domaines Sciences '!G25=1,'Items sous domaines Sciences '!#REF!,0) -> 0
B13: =IF('Items sous domaines Sciences '!G15=3,'Items sous domaines Sciences '!B15,0) -> 0 | C13: =IF('Items sous domaines Sciences '!G15=3,'Items sous domaines Sciences '!C15,0) -> 0 | D13: =IF('Items sous domaines Sciences '!G15=3,'Items sous domaines Sciences '!D15,0) -> 0 | E13: =IF('Items sous domaines Sciences '!G15=3,'Items sous domaines Sciences '!E15,0) -> 0 | F13: =IF('Items sous domaines Sciences '!G26=1,'Items sous domaines Sciences '!#REF!,0) -> 0
B14: =IF('Items sous domaines Sciences '!G16=3,'Items sous domaines Sciences '!B16,0) -> 0 | C14: =IF('Items sous domaines Sciences '!G16=3,'Items sous domaines Sciences '!C16,0) -> 0 | D14: =IF('Items sous domaines Sciences '!G16=3,'Items sous domaines Sciences '!D16,0) -> 0 | E14: =IF('Items sous domaines Sciences '!G16=3,'Items sous domaines Sciences '!E16,0) -> 0 | F14: =IF('Items sous domaines Sciences '!G27=1,'Items sous domaines Sciences '!#REF!,0) -> 0
B15: =IF('Items sous domaines Sciences '!G17=3,'Items sous domaines Sciences '!B17,0) -> 0 | C15: =IF('Items sous domaines Sciences '!G17=3,'Items sous domaines Sciences '!C17,0) -> 0 | D15: =IF('Items sous domaines Sciences '!G17=3,'Items sous domaines Sciences '!D17,0) -> 0 | E15: =IF('Items sous domaines Sciences '!G17=3,'Items sous domaines Sciences '!E17,0) -> 0 | F15: =IF('Items sous domaines Sciences '!G28=1,'Items sous domaines Sciences '!#REF!,0) -> 0
B16: =IF('Items sous domaines Sciences '!G18=3,'Items sous domaines Sciences '!B18,0) -> 0 | C16: =IF('Items sous domaines Sciences '!G18=3,'Items sous domaines Sciences '!C18,0) -> 0 | D16: =IF('Items sous domaines Sciences '!G18=3,'Items sous domaines Sciences '!D18,0) -> 0 | E16: =IF('Items sous domaines Sciences '!G18=3,'Items sous domaines Sciences '!E18,0) -> 0 | F16: =IF('Items sous domaines Sciences '!G29=1,'Items sous domaines Sciences '!#REF!,0) -> 0
B17: =IF('Items sous domaines Sciences '!G19=3,'Items sous domaines Sciences '!B19,0) -> 0 | C17: =IF('Items sous domaines Sciences '!G19=3,'Items sous domaines Sciences '!C19,0) -> 0 | D17: =IF('Items sous domaines Sciences '!G19=3,'Items sous domaines Sciences '!D19,0) -> 0 | E17: =IF('Items sous domaines Sciences '!G19=3,'Items sous domaines Sciences '!E19,0) -> 0 | F17: =IF('Items sous domaines Sciences '!G30=1,'Items sous domaines Sciences '!#REF!,0) -> 0
B18: =IF('Items sous domaines Sciences '!G20=3,'Items sous domaines Sciences '!B20,0) -> 0 | C18: =IF('Items sous domaines Sciences '!G20=3,'Items sous domaines Sciences '!C20,0) -> 0 | D18: =IF('Items sous domaines Sciences '!G20=3,'Items sous domaines Sciences '!D20,0) -> 0 | E18: =IF('Items sous domaines Sciences '!G20=3,'Items sous domaines Sciences '!E20,0) -> 0 | F18: =IF('Items sous domaines Sciences '!G31=1,'Items sous domaines Sciences '!#REF!,0) -> 0
B19: =IF('Items sous domaines Sciences '!G21=3,'Items sous domaines Sciences '!B21,0) -> 0 | C19: =IF('Items sous domaines Sciences '!G21=3,'Items sous domaines Sciences '!C21,0) -> 0 | D19: =IF('Items sous domaines Sciences '!G21=3,'Items sous domaines Sciences '!D21,0) -> 0 | E19: =IF('Items sous domaines Sciences '!G21=3,'Items sous domaines Sciences '!E21,0) -> 0 | F19: =IF('Items sous domaines Sciences '!G32=1,'Items sous domaines Sciences '!#REF!,0) -> 0
B20: =IF('Items sous domaines Sciences '!G22=3,'Items sous domaines Sciences '!B22,0) -> 0 | C20: =IF('Items sous domaines Sciences '!G22=3,'Items sous domaines Sciences '!C22,0) -> 0 | D20: =IF('Items sous domaines Sciences '!G22=3,'Items sous domaines Sciences '!D22,0) -> 0 | E20: =IF('Items sous domaines Sciences '!G22=3,'Items sous domaines Sciences '!E22,0) -> 0 | F20: =IF('Items sous domaines Sciences '!G33=1,'Items sous domaines Sciences '!#REF!,0) -> 0
... B22: =IF('Items sous domaines Sciences '!G24=3,'Items sous domaines Sciences '!B24,0) -> 0 | C22: =IF('Items sous domaines Sciences '!G24=3,'Items sous domaines Sciences '!C24,0) -> 0 | D22: =IF('Items sous domaines Sciences '!G24=3,'Items sous domaines Sciences '!D24,0) -> 0 | E22: =IF('Items sous domaines Sciences '!G24=3,'Items sous domaines Sciences '!E24,0) -> 0 | F22: =IF('Items sous domaines Sciences '!G35=1,'Items sous domaines Sciences '!#REF!,0) -> 0
B23: =IF('Items sous domaines Sciences '!G25=3,'Items sous domaines Sciences '!B25,0) -> 0 | C23: =IF('Items sous domaines Sciences '!G25=3,'Items sous domaines Sciences '!C25,0) -> 0 | D23: =IF('Items sous domaines Sciences '!G25=3,'Items sous domaines Sciences '!D25,0) -> 0 | E23: =IF('Items sous domaines Sciences '!G25=3,'Items sous domaines Sciences '!E25,0) -> 0 | F23: =IF('Items sous domaines Sciences '!#REF!=1,'Items sous domaines Sciences '!#REF!,0) -> #REF!
B24: =IF('Items sous domaines Sciences '!G26=3,'Items sous domaines Sciences '!B26,0) -> 0 | C24: =IF('Items sous domaines Sciences '!G26=3,'Items sous domaines Sciences '!C26,0) -> 0 | D24: =IF('Items sous domaines Sciences '!G26=3,'Items sous domaines Sciences '!D26,0) -> 0 | E24: =IF('Items sous domaines Sciences '!G26=3,'Items sous domaines Sciences '!E26,0) -> 0 | F24: =IF('Items sous domaines Sciences '!#REF!=1,'Items sous domaines Sciences '!#REF!,0) -> #REF!
B25: =IF('Items sous domaines Sciences '!G27=3,'Items sous domaines Sciences '!B27,0) -> 0 | C25: =IF('Items sous domaines Sciences '!G27=3,'Items sous domaines Sciences '!C27,0) -> 0 | D25: =IF('Items sous domaines Sciences '!G27=3,'Items sous domaines Sciences '!D27,0) -> 0 | E25: =IF('Items sous domaines Sciences '!G27=3,'Items sous domaines Sciences '!E27,0) -> 0 | F25: =IF('Items sous domaines Sciences '!G78=1,'Items sous domaines Sciences '!#REF!,0) -> 0
B26: =IF('Items sous domaines Sciences '!G28=3,'Items sous domaines Sciences '!B28,0) -> 0 | C26: =IF('Items sous domaines Sciences '!G28=3,'Items sous domaines Sciences '!C28,0) -> 0 | D26: =IF('Items sous domaines Sciences '!G28=3,'Items sous domaines Sciences '!D28,0) -> 0 | E26: =IF('Items sous domaines Sciences '!G28=3,'Items sous domaines Sciences '!E28,0) -> 0 | F26: =IF('Items sous domaines Sciences '!G108=1,'Items sous domaines Sciences '!#REF!,0) -> 0
B27: =IF('Items sous domaines Sciences '!G29=3,'Items sous domaines Sciences '!B29,0) -> 0 | C27: =IF('Items sous domaines Sciences '!G29=3,'Items sous domaines Sciences '!C29,0) -> 0 | D27: =IF('Items sous domaines Sciences '!G29=3,'Items sous domaines Sciences '!D29,0) -> 0 | E27: =IF('Items sous domaines Sciences '!G29=3,'Items sous domaines Sciences '!E29,0) -> 0 | F27: =IF('Items sous domaines Sciences '!G109=1,'Items sous domaines Sciences '!#REF!,0) -> 0
B28: =IF('Items sous domaines Sciences '!G30=3,'Items sous domaines Sciences '!B30,0) -> 0 | C28: =IF('Items sous domaines Sciences '!G30=3,'Items sous domaines Sciences '!C30,0) -> 0 | D28: =IF('Items sous domaines Sciences '!G30=3,'Items sous domaines Sciences '!D30,0) -> 0 | E28: =IF('Items sous domaines Sciences '!G30=3,'Items sous domaines Sciences '!E30,0) -> 0 | F28: =IF('Items sous domaines Sciences '!G110=1,'Items sous domaines Sciences '!#REF!,0) -> 0
B29: =IF('Items sous domaines Sciences '!G31=3,'Items sous domaines Sciences '!B31,0) -> 0 | C29: =IF('Items sous domaines Sciences '!G31=3,'Items sous domaines Sciences '!C31,0) -> 0 | D29: =IF('Items sous domaines Sciences '!G31=3,'Items sous domaines Sciences '!D31,0) -> 0 | E29: =IF('Items sous domaines Sciences '!G31=3,'Items sous domaines Sciences '!E31,0) -> 0 | F29: =IF('Items sous domaines Sciences '!G111=1,'Items sous domaines Sciences '!#REF!,0) -> 0
B30: =IF('Items sous domaines Sciences '!G32=3,'Items sous domaines Sciences '!B32,0) -> 0 | C30: =IF('Items sous domaines Sciences '!G32=3,'Items sous domaines Sciences '!C32,0) -> 0 | D30: =IF('Items sous domaines Sciences '!G32=3,'Items sous domaines Sciences '!D32,0) -> 0 | E30: =IF('Items sous domaines Sciences '!G32=3,'Items sous domaines Sciences '!E32,0) -> 0 | F30: =IF('Items sous domaines Sciences '!G112=1,'Items sous domaines Sciences '!#REF!,0) -> 0
B31: =IF('Items sous domaines Sciences '!G33=3,'Items sous domaines Sciences '!B33,0) -> 0 | C31: =IF('Items sous domaines Sciences '!G33=3,'Items sous domaines Sciences '!C33,0) -> 0 | D31: =IF('Items sous domaines Sciences '!G33=3,'Items sous domaines Sciences '!D33,0) -> 0 | E31: =IF('Items sous domaines Sciences '!G33=3,'Items sous domaines Sciences '!E33,0) -> 0 | F31: =IF('Items sous domaines Sciences '!G129=1,'Items sous domaines Sciences '!#REF!,0) -> 0
B32: =IF('Items sous domaines Sciences '!G34=3,'Items sous domaines Sciences '!B34,0) -> 0 | C32: =IF('Items sous domaines Sciences '!G34=3,'Items sous domaines Sciences '!C34,0) -> 0 | D32: =IF('Items sous domaines Sciences '!G34=3,'Items sous domaines Sciences '!D34,0) -> 0 | E32: =IF('Items sous domaines Sciences '!G34=3,'Items sous domaines Sciences '!E34,0) -> 0 | F32: =IF('Items sous domaines Sciences '!G130=1,'Items sous domaines Sciences '!#REF!,0) -> 0
B33: =IF('Items sous domaines Sciences '!G35=3,'Items sous domaines Sciences '!B35,0) -> 0 | C33: =IF('Items sous domaines Sciences '!G35=3,'Items sous domaines Sciences '!C35,0) -> 0 | D33: =IF('Items sous domaines Sciences '!G35=3,'Items sous domaines Sciences '!D35,0) -> 0 | E33: =IF('Items sous domaines Sciences '!G35=3,'Items sous domaines Sciences '!E35,0) -> 0 | F33: =IF('Items sous domaines Sciences '!G131=1,'Items sous domaines Sciences '!#REF!,0) -> 0
B34: =IF('Items sous domaines Sciences '!G36=3,'Items sous domaines Sciences '!B36,0) -> 0 | C34: =IF('Items sous domaines Sciences '!G36=3,'Items sous domaines Sciences '!C36,0) -> 0 | D34: =IF('Items sous domaines Sciences '!G36=3,'Items sous domaines Sciences '!D36,0) -> 0 | E34: =IF('Items sous domaines Sciences '!G36=3,'Items sous domaines Sciences '!E36,0) -> 0 | F34: =IF('Items sous domaines Sciences '!G132=1,'Items sous domaines Sciences '!#REF!,0) -> 0
B35: =IF('Items sous domaines Sciences '!G37=3,'Items sous domaines Sciences '!B37,0) -> 0 | C35: =IF('Items sous domaines Sciences '!G37=3,'Items sous domaines Sciences '!C37,0) -> 0 | D35: =IF('Items sous domaines Sciences '!G37=3,'Items sous domaines Sciences '!D37,0) -> 0 | E35: =IF('Items sous domaines Sciences '!G37=3,'Items sous domaines Sciences '!E37,0) -> 0 | F35: =IF('Items sous domaines Sciences '!G182=1,'Items sous domaines Sciences '!#REF!,0) -> 0
B36: =IF('Items sous domaines Sciences '!G38=3,'Items sous domaines Sciences '!B38,0) -> 0 | C36: =IF('Items sous domaines Sciences '!G38=3,'Items sous domaines Sciences '!C38,0) -> 0 | D36: =IF('Items sous domaines Sciences '!G38=3,'Items sous domaines Sciences '!D38,0) -> 0 | E36: =IF('Items sous domaines Sciences '!G38=3,'Items sous domaines Sciences '!E38,0) -> 0 | F36: =IF('Items sous domaines Sciences '!G192=1,'Items sous domaines Sciences '!#REF!,0) -> 0
B37: =IF('Items sous domaines Sciences '!G39=3,'Items sous domaines Sciences '!B39,0) -> 0 | C37: =IF('Items sous domaines Sciences '!G39=3,'Items sous domaines Sciences '!C39,0) -> 0 | D37: =IF('Items sous domaines Sciences '!G39=3,'Items sous domaines Sciences '!D39,0) -> 0 | E37: =IF('Items sous domaines Sciences '!G39=3,'Items sous domaines Sciences '!E39,0) -> 0 | F37: =IF('Items sous domaines Sciences '!G193=1,'Items sous domaines Sciences '!#REF!,0) -> 0
B38: =IF('Items sous domaines Sciences '!G40=3,'Items sous domaines Sciences '!B40,0) -> 0 | C38: =IF('Items sous domaines Sciences '!G40=3,'Items sous domaines Sciences '!C40,0) -> 0 | D38: =IF('Items sous domaines Sciences '!G40=3,'Items sous domaines Sciences '!D40,0) -> 0 | E38: =IF('Items sous domaines Sciences '!G40=3,'Items sous domaines Sciences '!E40,0) -> 0 | F38: =IF('Items sous domaines Sciences '!G194=1,'Items sous domaines Sciences '!#REF!,0) -> 0
B39: =IF('Items sous domaines Sciences '!G41=3,'Items sous domaines Sciences '!B41,0) -> 0 | C39: =IF('Items sous domaines Sciences '!G41=3,'Items sous domaines Sciences '!C41,0) -> 0 | D39: =IF('Items sous domaines Sciences '!G41=3,'Items sous domaines Sciences '!D41,0) -> 0 | E39: =IF('Items sous domaines Sciences '!G41=3,'Items sous domaines Sciences '!E41,0) -> 0 | F39: =IF('Items sous domaines Sciences '!G207=1,'Items sous domaines Sciences '!#REF!,0) -> 0
B40: =IF('Items sous domaines Sciences '!G42=3,'Items sous domaines Sciences '!B42,0) -> 0 | C40: =IF('Items sous domaines Sciences '!G42=3,'Items sous domaines Sciences '!C42,0) -> 0 | D40: =IF('Items sous domaines Sciences '!G42=3,'Items sous domaines Sciences '!D42,0) -> 0 | E40: =IF('Items sous domaines Sciences '!G42=3,'Items sous domaines Sciences '!E42,0) -> 0 | F40: Projet Mécanique des fluides | G40: https://uel.unisciel.fr/physique/meca/meca/co/meca.html
B41: =IF('Items sous domaines Sciences '!G43=3,'Items sous domaines Sciences '!B43,0) -> 0 | C41: =IF('Items sous domaines Sciences '!G43=3,'Items sous domaines Sciences '!C43,0) -> 0 | D41: =IF('Items sous domaines Sciences '!G43=3,'Items sous domaines Sciences '!D43,0) -> 0 | E41: =IF('Items sous domaines Sciences '!G43=3,'Items sous domaines Sciences '!E43,0) -> 0
B42: =IF('Items sous domaines Sciences '!G44=3,'Items sous domaines Sciences '!B44,0) -> 0 | C42: =IF('Items sous domaines Sciences '!G44=3,'Items sous domaines Sciences '!C44,0) -> 0 | D42: =IF('Items sous domaines Sciences '!G44=3,'Items sous domaines Sciences '!D44,0) -> 0 | E42: =IF('Items sous domaines Sciences '!G44=3,'Items sous domaines Sciences '!E44,0) -> 0
B43: =IF('Items sous domaines Sciences '!G45=3,'Items sous domaines Sciences '!B45,0) -> 0 | C43: =IF('Items sous domaines Sciences '!G45=3,'Items sous domaines Sciences '!C45,0) -> 0 | D43: =IF('Items sous domaines Sciences '!G45=3,'Items sous domaines Sciences '!D45,0) -> 0 | E43: =IF('Items sous domaines Sciences '!G45=3,'Items sous domaines Sciences '!E45,0) -> 0
B44: =IF('Items sous domaines Sciences '!G46=3,'Items sous domaines Sciences '!B46,0) -> 0 | C44: =IF('Items sous domaines Sciences '!G46=3,'Items sous domaines Sciences '!C46,0) -> 0 | D44: =IF('Items sous domaines Sciences '!G46=3,'Items sous domaines Sciences '!D46,0) -> 0 | E44: =IF('Items sous domaines Sciences '!G46=3,'Items sous domaines Sciences '!E46,0) -> 0
B45: =IF('Items sous domaines Sciences '!G47=3,'Items sous domaines Sciences '!B47,0) -> 0 | C45: =IF('Items sous domaines Sciences '!G47=3,'Items sous domaines Sciences '!C47,0) -> 0 | D45: =IF('Items sous domaines Sciences '!G47=3,'Items sous domaines Sciences '!D47,0) -> 0 | E45: =IF('Items sous domaines Sciences '!G47=3,'Items sous domaines Sciences '!E47,0) -> 0
B46: =IF('Items sous domaines Sciences '!G48=3,'Items sous domaines Sciences '!B48,0) -> 0 | C46: =IF('Items sous domaines Sciences '!G48=3,'Items sous domaines Sciences '!C48,0) -> 0 | D46: =IF('Items sous domaines Sciences '!G48=3,'Items sous domaines Sciences '!D48,0) -> 0 | E46: =IF('Items sous domaines Sciences '!G48=3,'Items sous domaines Sciences '!E48,0) -> 0
B47: =IF('Items sous domaines Sciences '!G49=3,'Items sous domaines Sciences '!B49,0) -> 0 | C47: =IF('Items sous domaines Sciences '!G49=3,'Items sous domaines Sciences '!C49,0) -> 0 | D47: =IF('Items sous domaines Sciences '!G49=3,'Items sous domaines Sciences '!D49,0) -> 0 | E47: =IF('Items sous domaines Sciences '!G49=3,'Items sous domaines Sciences '!E49,0) -> 0
B48: =IF('Items sous domaines Sciences '!G50=3,'Items sous domaines Sciences '!B50,0) -> 0 | C48: =IF('Items sous domaines Sciences '!G50=3,'Items sous domaines Sciences '!C50,0) -> 0 | D48: =IF('Items sous domaines Sciences '!G50=3,'Items sous domaines Sciences '!D50,0) -> 0 | E48: =IF('Items sous domaines Sciences '!G50=3,'Items sous domaines Sciences '!E50,0) -> 0
B49: =IF('Items sous domaines Sciences '!G51=3,'Items sous domaines Sciences '!B51,0) -> 0 | C49: =IF('Items sous domaines Sciences '!G51=3,'Items sous domaines Sciences '!C51,0) -> 0 | D49: =IF('Items sous domaines Sciences '!G51=3,'Items sous domaines Sciences '!D51,0) -> 0 | E49: =IF('Items sous domaines Sciences '!G51=3,'Items sous domaines Sciences '!E51,0) -> 0
B50: =IF('Items sous domaines Sciences '!G52=3,'Items sous domaines Sciences '!B52,0) -> 0 | C50: =IF('Items sous domaines Sciences '!G52=3,'Items sous domaines Sciences '!C52,0) -> 0 | D50: =IF('Items sous domaines Sciences '!G52=3,'Items sous domaines Sciences '!D52,0) -> 0 | E50: =IF('Items sous domaines Sciences '!G52=3,'Items sous domaines Sciences '!E52,0) -> 0
B51: =IF('Items sous domaines Sciences '!G53=3,'Items sous domaines Sciences '!B53,0) -> 0 | C51: =IF('Items sous domaines Sciences '!G53=3,'Items sous domaines Sciences '!C53,0) -> 0 | D51: =IF('Items sous domaines Sciences '!G53=3,'Items sous domaines Sciences '!D53,0) -> 0 | E51: =IF('Items sous domaines Sciences '!G53=3,'Items sous domaines Sciences '!E53,0) -> 0
B52: =IF('Items sous domaines Sciences '!G54=3,'Items sous domaines Sciences '!B54,0) -> 0 | C52: =IF('Items sous domaines Sciences '!G54=3,'Items sous domaines Sciences '!C54,0) -> 0 | D52: =IF('Items sous domaines Sciences '!G54=3,'Items sous domaines Sciences '!D54,0) -> 0 | E52: =IF('Items sous domaines Sciences '!G54=3,'Items sous domaines Sciences '!E54,0) -> 0
... B101: =IF('Items sous domaines Sciences '!G103=3,'Items sous domaines Sciences '!B103,0) -> 0 | C101: =IF('Items sous domaines Sciences '!G103=3,'Items sous domaines Sciences '!C103,0) -> 0 | D101: =IF('Items sous domaines Sciences '!G103=3,'Items sous domaines Sciences '!D103,0) -> 0 | E101: =IF('Items sous domaines Sciences '!G103=3,'Items sous domaines Sciences '!E103,0) -> 0
B102: =IF('Items sous domaines Sciences '!G104=3,'Items sous domaines Sciences '!B104,0) -> 0 | C102: =IF('Items sous domaines Sciences '!G104=3,'Items sous domaines Sciences '!C104,0) -> 0 | D102: =IF('Items sous domaines Sciences '!G104=3,'Items sous domaines Sciences '!D104,0) -> 0 | E102: =IF('Items sous domaines Sciences '!G104=3,'Items sous domaines Sciences '!E104,0) -> 0 | F102: =IF('Items sous domaines Sciences '!#REF!=1,'Items sous domaines Sciences '!#REF!,0) -> #REF!
B103: =IF('Items sous domaines Sciences '!G105=3,'Items sous domaines Sciences '!B105,0) -> 0 | C103: =IF('Items sous domaines Sciences '!G105=3,'Items sous domaines Sciences '!C105,0) -> 0 | D103: =IF('Items sous domaines Sciences '!G105=3,'Items sous domaines Sciences '!D105,0) -> 0 | E103: =IF('Items sous domaines Sciences '!G105=3,'Items sous domaines Sciences '!E105,0) -> 0 | F103: =IF('Items sous domaines Sciences '!#REF!=1,'Items sous domaines Sciences '!#REF!,0) -> #REF!
B104: =IF('Items sous domaines Sciences '!G106=3,'Items sous domaines Sciences '!B106,0) -> 0 | C104: =IF('Items sous domaines Sciences '!G106=3,'Items sous domaines Sciences '!C106,0) -> 0 | D104: =IF('Items sous domaines Sciences '!G106=3,'Items sous domaines Sciences '!D106,0) -> 0 | E104: =IF('Items sous domaines Sciences '!G106=3,'Items sous domaines Sciences '!E106,0) -> 0 | F104: =IF('Items sous domaines Sciences '!#REF!=1,'Items sous domaines Sciences '!#REF!,0) -> #REF!
B105: =IF('Items sous domaines Sciences '!G107=3,'Items sous domaines Sciences '!B107,0) -> 0 | C105: =IF('Items sous domaines Sciences '!G107=3,'Items sous domaines Sciences '!C107,0) -> 0 | D105: =IF('Items sous domaines Sciences '!G107=3,'Items sous domaines Sciences '!D107,0) -> 0 | E105: =IF('Items sous domaines Sciences '!G107=3,'Items sous domaines Sciences '!E107,0) -> 0 | F105: =IF('Items sous domaines Sciences '!#REF!=1,'Items sous domaines Sciences '!#REF!,0) -> #REF!
B106: =IF('Items sous domaines Sciences '!G108=3,'Items sous domaines Sciences '!B108,0) -> 0 | C106: =IF('Items sous domaines Sciences '!G108=3,'Items sous domaines Sciences '!C108,0) -> 0 | D106: =IF('Items sous domaines Sciences '!G108=3,'Items sous domaines Sciences '!D108,0) -> 0 | E106: =IF('Items sous domaines Sciences '!G108=3,'Items sous domaines Sciences '!E108,0) -> 0 | F106: =IF('Items sous domaines Sciences '!#REF!=1,'Items sous domaines Sciences '!#REF!,0) -> #REF!
B107: =IF('Items sous domaines Sciences '!G109=3,'Items sous domaines Sciences '!B109,0) -> 0 | C107: =IF('Items sous domaines Sciences '!G109=3,'Items sous domaines Sciences '!C109,0) -> 0 | D107: =IF('Items sous domaines Sciences '!G109=3,'Items sous domaines Sciences '!D109,0) -> 0 | E107: =IF('Items sous domaines Sciences '!G109=3,'Items sous domaines Sciences '!E109,0) -> 0 | F107: =IF('Items sous domaines Sciences '!#REF!=1,'Items sous domaines Sciences '!#REF!,0) -> #REF!
B108: =IF('Items sous domaines Sciences '!G110=3,'Items sous domaines Sciences '!B110,0) -> 0 | C108: =IF('Items sous domaines Sciences '!G110=3,'Items sous domaines Sciences '!C110,0) -> 0 | D108: =IF('Items sous domaines Sciences '!G110=3,'Items sous domaines Sciences '!D110,0) -> 0 | E108: =IF('Items sous domaines Sciences '!G110=3,'Items sous domaines Sciences '!E110,0) -> 0 | F108: =IF('Items sous domaines Sciences '!#REF!=1,'Items sous domaines Sciences '!#REF!,0) -> #REF!
B109: =IF('Items sous domaines Sciences '!G111=3,'Items sous domaines Sciences '!B111,0) -> 0 | C109: =IF('Items sous domaines Sciences '!G111=3,'Items sous domaines Sciences '!C111,0) -> 0 | D109: =IF('Items sous domaines Sciences '!G111=3,'Items sous domaines Sciences '!D111,0) -> 0 | E109: =IF('Items sous domaines Sciences '!G111=3,'Items sous domaines Sciences '!E111,0) -> 0 | F109: =IF('Items sous domaines Sciences '!#REF!=1,'Items sous domaines Sciences '!#REF!,0) -> #REF!
B110: =IF('Items sous domaines Sciences '!G112=3,'Items sous domaines Sciences '!B112,0) -> 0 | C110: =IF('Items sous domaines Sciences '!G112=3,'Items sous domaines Sciences '!C112,0) -> 0 | D110: =IF('Items sous domaines Sciences '!G112=3,'Items sous domaines Sciences '!D112,0) -> 0 | E110: =IF('Items sous domaines Sciences '!G112=3,'Items sous domaines Sciences '!E112,0) -> 0 | F110: =IF('Items sous domaines Sciences '!#REF!=1,'Items sous domaines Sciences '!#REF!,0) -> #REF!
B111: =IF('Items sous domaines Sciences '!G113=3,'Items sous domaines Sciences '!B113,0) -> 0 | C111: =IF('Items sous domaines Sciences '!G113=3,'Items sous domaines Sciences '!C113,0) -> 0 | D111: =IF('Items sous domaines Sciences '!G113=3,'Items sous domaines Sciences '!D113,0) -> 0 | E111: =IF('Items sous domaines Sciences '!G113=3,'Items sous domaines Sciences '!E113,0) -> 0 | F111: =IF('Items sous domaines Sciences '!#REF!=1,'Items sous domaines Sciences '!#REF!,0) -> #REF!
B112: =IF('Items sous domaines Sciences '!G114=3,'Items sous domaines Sciences '!B114,0) -> 0 | C112: =IF('Items sous domaines Sciences '!G114=3,'Items sous domaines Sciences '!C114,0) -> 0 | D112: =IF('Items sous domaines Sciences '!G114=3,'Items sous domaines Sciences '!D114,0) -> 0 | E112: =IF('Items sous domaines Sciences '!G114=3,'Items sous domaines Sciences '!E114,0) -> 0 | F112: =IF('Items sous domaines Sciences '!#REF!=1,'Items sous domaines Sciences '!#REF!,0) -> #REF!
A113: Maths spécialité : graphes en FISE info FISA info | B113: =IF('Items sous domaines Sciences '!G115=3,'Items sous domaines Sciences '!B115,0) -> 0 | C113: =IF('Items sous domaines Sciences '!G115=3,'Items sous domaines Sciences '!C115,0) -> 0 | D113: =IF('Items sous domaines Sciences '!G115=3,'Items sous domaines Sciences '!D115,0) -> 0 | E113: =IF('Items sous domaines Sciences '!G115=3,'Items sous domaines Sciences '!E115,0) -> 0 | F113: =IF('Items sous domaines Sciences '!#REF!=1,'Items sous domaines Sciences '!#REF!,0) -> #REF!
B114: =IF('Items sous domaines Sciences '!G116=3,'Items sous domaines Sciences '!B116,0) -> 0 | C114: =IF('Items sous domaines Sciences '!G116=3,'Items sous domaines Sciences '!C116,0) -> 0 | D114: =IF('Items sous domaines Sciences '!G116=3,'Items sous domaines Sciences '!D116,0) -> 0 | E114: =IF('Items sous domaines Sciences '!G116=3,'Items sous domaines Sciences '!E116,0) -> 0 | F114: =IF('Items sous domaines Sciences '!#REF!=1,'Items sous domaines Sciences '!#REF!,0) -> #REF!
B115: =IF('Items sous domaines Sciences '!G117=3,'Items sous domaines Sciences '!B117,0) -> 0 | C115: =IF('Items sous domaines Sciences '!G117=3,'Items sous domaines Sciences '!C117,0) -> 0 | D115: =IF('Items sous domaines Sciences '!G117=3,'Items sous domaines Sciences '!D117,0) -> 0 | E115: =IF('Items sous domaines Sciences '!G117=3,'Items sous domaines Sciences '!E117,0) -> 0 | F115: =IF('Items sous domaines Sciences '!#REF!=1,'Items sous domaines Sciences '!#REF!,0) -> #REF!
B116: =IF('Items sous domaines Sciences '!G118=3,'Items sous domaines Sciences '!B118,0) -> 0 | C116: =IF('Items sous domaines Sciences '!G118=3,'Items sous domaines Sciences '!C118,0) -> 0 | D116: =IF('Items sous domaines Sciences '!G118=3,'Items sous domaines Sciences '!D118,0) -> 0 | E116: =IF('Items sous domaines Sciences '!G118=3,'Items sous domaines Sciences '!E118,0) -> 0 | F116: =IF('Items sous domaines Sciences '!#REF!=1,'Items sous domaines Sciences '!#REF!,0) -> #REF!
B117: =IF('Items sous domaines Sciences '!G119=3,'Items sous domaines Sciences '!B119,0) -> 0 | C117: =IF('Items sous domaines Sciences '!G119=3,'Items sous domaines Sciences '!C119,0) -> 0 | D117: =IF('Items sous domaines Sciences '!G119=3,'Items sous domaines Sciences '!D119,0) -> 0 | E117: =IF('Items sous domaines Sciences '!G119=3,'Items sous domaines Sciences '!E119,0) -> 0 | F117: =IF('Items sous domaines Sciences '!#REF!=1,'Items sous domaines Sciences '!#REF!,0) -> #REF!
B118: =IF('Items sous domaines Sciences '!G120=3,'Items sous domaines Sciences '!B120,0) -> 0 | C118: =IF('Items sous domaines Sciences '!G120=3,'Items sous domaines Sciences '!C120,0) -> 0 | D118: =IF('Items sous domaines Sciences '!G120=3,'Items sous domaines Sciences '!D120,0) -> 0 | E118: =IF('Items sous domaines Sciences '!G120=3,'Items sous domaines Sciences '!E120,0) -> 0 | F118: =IF('Items sous domaines Sciences '!#REF!=1,'Items sous domaines Sciences '!#REF!,0) -> #REF!
B119: =IF('Items sous domaines Sciences '!G121=3,'Items sous domaines Sciences '!B121,0) -> 0 | C119: =IF('Items sous domaines Sciences '!G121=3,'Items sous domaines Sciences '!C121,0) -> 0 | D119: =IF('Items sous domaines Sciences '!G121=3,'Items sous domaines Sciences '!D121,0) -> 0 | E119: =IF('Items sous domaines Sciences '!G121=3,'Items sous domaines Sciences '!E121,0) -> 0 | F119: =IF('Items sous domaines Sciences '!#REF!=1,'Items sous domaines Sciences '!#REF!,0) -> #REF!
B120: =IF('Items sous domaines Sciences '!G122=3,'Items sous domaines Sciences '!B122,0) -> 0 | C120: =IF('Items sous domaines Sciences '!G122=3,'Items sous domaines Sciences '!C122,0) -> 0 | D120: =IF('Items sous domaines Sciences '!G122=3,'Items sous domaines Sciences '!D122,0) -> 0 | E120: =IF('Items sous domaines Sciences '!G122=3,'Items sous domaines Sciences '!E122,0) -> 0 | F120: =IF('Items sous domaines Sciences '!#REF!=1,'Items sous domaines Sciences '!#REF!,0) -> #REF!
B121: =IF('Items sous domaines Sciences '!G123=3,'Items sous domaines Sciences '!B123,0) -> 0 | C121: =IF('Items sous domaines Sciences '!G123=3,'Items sous domaines Sciences '!C123,0) -> 0 | D121: =IF('Items sous domaines Sciences '!G123=3,'Items sous domaines Sciences '!D123,0) -> 0 | E121: =IF('Items sous domaines Sciences '!G123=3,'Items sous domaines Sciences '!E123,0) -> 0 | F121: =IF('Items sous domaines Sciences '!#REF!=1,'Items sous domaines Sciences '!#REF!,0) -> #REF!
B122: =IF('Items sous domaines Sciences '!G124=3,'Items sous domaines Sciences '!B124,0) -> 0 | C122: =IF('Items sous domaines Sciences '!G124=3,'Items sous domaines Sciences '!C124,0) -> 0 | D122: =IF('Items sous domaines Sciences '!G124=3,'Items sous domaines Sciences '!D124,0) -> 0 | E122: =IF('Items sous domaines Sciences '!G124=3,'Items sous domaines Sciences '!E124,0) -> 0 | F122: =IF('Items sous domaines Sciences '!#REF!=1,'Items sous domaines Sciences '!#REF!,0) -> #REF!
B123: =IF('Items sous domaines Sciences '!G125=3,'Items sous domaines Sciences '!B125,0) -> 0 | C123: =IF('Items sous domaines Sciences '!G125=3,'Items sous domaines Sciences '!C125,0) -> 0 | D123: =IF('Items sous domaines Sciences '!G125=3,'Items sous domaines Sciences '!D125,0) -> 0 | E123: =IF('Items sous domaines Sciences '!G125=3,'Items sous domaines Sciences '!E125,0) -> 0 | F123: =IF('Items sous domaines Sciences '!#REF!=1,'Items sous domaines Sciences '!#REF!,0) -> #REF!
B124: =IF('Items sous domaines Sciences '!G126=3,'Items sous domaines Sciences '!B126,0) -> 0 | C124: =IF('Items sous domaines Sciences '!G126=3,'Items sous domaines Sciences '!C126,0) -> 0 | D124: =IF('Items sous domaines Sciences '!G126=3,'Items sous domaines Sciences '!D126,0) -> 0 | E124: =IF('Items sous domaines Sciences '!G126=3,'Items sous domaines Sciences '!E126,0) -> 0 | F124: =IF('Items sous domaines Sciences '!#REF!=1,'Items sous domaines Sciences '!#REF!,0) -> #REF!
B125: =IF('Items sous domaines Sciences '!G127=3,'Items sous domaines Sciences '!B127,0) -> 0 | C125: =IF('Items sous domaines Sciences '!G127=3,'Items sous domaines Sciences '!C127,0) -> 0 | D125: =IF('Items sous domaines Sciences '!G127=3,'Items sous domaines Sciences '!D127,0) -> 0 | E125: =IF('Items sous domaines Sciences '!G127=3,'Items sous domaines Sciences '!E127,0) -> 0 | F125: =IF('Items sous domaines Sciences '!#REF!=1,'Items sous domaines Sciences '!#REF!,0) -> #REF!
... B128: =IF('Items sous domaines Sciences '!G130=3,'Items sous domaines Sciences '!B130,0) -> 0 | C128: =IF('Items sous domaines Sciences '!G130=3,'Items sous domaines Sciences '!C130,0) -> 0 | D128: =IF('Items sous domaines Sciences '!G130=3,'Items sous domaines Sciences '!D130,0) -> 0 | E128: =IF('Items sous domaines Sciences '!G130=3,'Items sous domaines Sciences '!E130,0) -> 0 | F128: =IF('Items sous domaines Sciences '!#REF!=1,'Items sous domaines Sciences '!#REF!,0) -> #REF!
A129: Maths élémentaires | B129: =IF('Items sous domaines Sciences '!G131=3,'Items sous domaines Sciences '!B131,0) -> 0 | C129: =IF('Items sous domaines Sciences '!G131=3,'Items sous domaines Sciences '!C131,0) -> 0 | D129: =IF('Items sous domaines Sciences '!G131=3,'Items sous domaines Sciences '!D131,0) -> 0 | E129: =IF('Items sous domaines Sciences '!G131=3,'Items sous domaines Sciences '!E131,0) -> 0 | F129: =IF('Items sous domaines Sciences '!#REF!=1,'Items sous domaines Sciences '!#REF!,0) -> #REF!
B130: =IF('Items sous domaines Sciences '!G132=3,'Items sous domaines Sciences '!B132,0) -> 0 | C130: =IF('Items sous domaines Sciences '!G132=3,'Items sous domaines Sciences '!C132,0) -> 0 | D130: =IF('Items sous domaines Sciences '!G132=3,'Items sous domaines Sciences '!D132,0) -> 0 | E130: =IF('Items sous domaines Sciences '!G132=3,'Items sous domaines Sciences '!E132,0) -> 0 | F130: =IF('Items sous domaines Sciences '!#REF!=1,'Items sous domaines Sciences '!#REF!,0) -> #REF!
B131: =IF('Items sous domaines Sciences '!G133=3,'Items sous domaines Sciences '!B133,0) -> 0 | C131: =IF('Items sous domaines Sciences '!G133=3,'Items sous domaines Sciences '!C133,0) -> 0 | D131: =IF('Items sous domaines Sciences '!G133=3,'Items sous domaines Sciences '!D133,0) -> 0 | E131: =IF('Items sous domaines Sciences '!G133=3,'Items sous domaines Sciences '!E133,0) -> 0 | F131: =IF('Items sous domaines Sciences '!#REF!=1,'Items sous domaines Sciences '!#REF!,0) -> #REF!
B132: =IF('Items sous domaines Sciences '!G134=3,'Items sous domaines Sciences '!B134,0) -> 0 | C132: =IF('Items sous domaines Sciences '!G134=3,'Items sous domaines Sciences '!C134,0) -> 0 | D132: =IF('Items sous domaines Sciences '!G134=3,'Items sous domaines Sciences '!D134,0) -> 0 | E132: =IF('Items sous domaines Sciences '!G134=3,'Items sous domaines Sciences '!E134,0) -> 0 | F132: =IF('Items sous domaines Sciences '!#REF!=1,'Items sous domaines Sciences '!#REF!,0) -> #REF!
B133: =IF('Items sous domaines Sciences '!G135=3,'Items sous domaines Sciences '!B135,0) -> 0 | C133: =IF('Items sous domaines Sciences '!G135=3,'Items sous domaines Sciences '!C135,0) -> 0 | D133: =IF('Items sous domaines Sciences '!G135=3,'Items sous domaines Sciences '!D135,0) -> 0 | E133: =IF('Items sous domaines Sciences '!G135=3,'Items sous domaines Sciences '!E135,0) -> 0 | F133: =IF('Items sous domaines Sciences '!#REF!=1,'Items sous domaines Sciences '!#REF!,0) -> #REF!
B134: =IF('Items sous domaines Sciences '!G136=3,'Items sous domaines Sciences '!B136,0) -> 0 | C134: =IF('Items sous domaines Sciences '!G136=3,'Items sous domaines Sciences '!C136,0) -> 0 | D134: =IF('Items sous domaines Sciences '!G136=3,'Items sous domaines Sciences '!D136,0) -> 0 | E134: =IF('Items sous domaines Sciences '!G136=3,'Items sous domaines Sciences '!E136,0) -> 0 | F134: =IF('Items sous domaines Sciences '!#REF!=1,'Items sous domaines Sciences '!#REF!,0) -> #REF!
B135: =IF('Items sous domaines Sciences '!G137=3,'Items sous domaines Sciences '!B137,0) -> 0 | C135: =IF('Items sous domaines Sciences '!G137=3,'Items sous domaines Sciences '!C137,0) -> 0 | D135: =IF('Items sous domaines Sciences '!G137=3,'Items sous domaines Sciences '!D137,0) -> 0 | E135: =IF('Items sous domaines Sciences '!G137=3,'Items sous domaines Sciences '!E137,0) -> 0 | F135: =IF('Items sous domaines Sciences '!#REF!=1,'Items sous domaines Sciences '!#REF!,0) -> #REF!
B136: =IF('Items sous domaines Sciences '!G138=3,'Items sous domaines Sciences '!B138,0) -> 0 | C136: =IF('Items sous domaines Sciences '!G138=3,'Items sous domaines Sciences '!C138,0) -> 0 | D136: =IF('Items sous domaines Sciences '!G138=3,'Items sous domaines Sciences '!D138,0) -> 0 | E136: =IF('Items sous domaines Sciences '!G138=3,'Items sous domaines Sciences '!E138,0) -> 0 | F136: =IF('Items sous domaines Sciences '!#REF!=1,'Items sous domaines Sciences '!#REF!,0) -> #REF!
B137: =IF('Items sous domaines Sciences '!G139=3,'Items sous domaines Sciences '!B139,0) -> 0 | C137: =IF('Items sous domaines Sciences '!G139=3,'Items sous domaines Sciences '!C139,0) -> 0 | D137: =IF('Items sous domaines Sciences '!G139=3,'Items sous domaines Sciences '!D139,0) -> 0 | E137: =IF('Items sous domaines Sciences '!G139=3,'Items sous domaines Sciences '!E139,0) -> 0 | F137: =IF('Items sous domaines Sciences '!#REF!=1,'Items sous domaines Sciences '!#REF!,0) -> #REF!
B138: =IF('Items sous domaines Sciences '!G140=3,'Items sous domaines Sciences '!B140,0) -> 0 | C138: =IF('Items sous domaines Sciences '!G140=3,'Items sous domaines Sciences '!C140,0) -> 0 | D138: =IF('Items sous domaines Sciences '!G140=3,'Items sous domaines Sciences '!D140,0) -> 0 | E138: =IF('Items sous domaines Sciences '!G140=3,'Items sous domaines Sciences '!E140,0) -> 0 | F138: =IF('Items sous domaines Sciences '!#REF!=1,'Items sous domaines Sciences '!#REF!,0) -> #REF!
B139: =IF('Items sous domaines Sciences '!G141=3,'Items sous domaines Sciences '!B141,0) -> 0 | C139: =IF('Items sous domaines Sciences '!G141=3,'Items sous domaines Sciences '!C141,0) -> 0 | D139: =IF('Items sous domaines Sciences '!G141=3,'Items sous domaines Sciences '!D141,0) -> 0 | E139: =IF('Items sous domaines Sciences '!G141=3,'Items sous domaines Sciences '!E141,0) -> 0 | F139: =IF('Items sous domaines Sciences '!#REF!=1,'Items sous domaines Sciences '!#REF!,0) -> #REF!
B140: =IF('Items sous domaines Sciences '!G142=3,'Items sous domaines Sciences '!B142,0) -> 0 | C140: =IF('Items sous domaines Sciences '!G142=3,'Items sous domaines Sciences '!C142,0) -> 0 | D140: =IF('Items sous domaines Sciences '!G142=3,'Items sous domaines Sciences '!D142,0) -> 0 | E140: =IF('Items sous domaines Sciences '!G142=3,'Items sous domaines Sciences '!E142,0) -> 0 | F140: =IF('Items sous domaines Sciences '!#REF!=1,'Items sous domaines Sciences '!#REF!,0) -> #REF!
B141: =IF('Items sous domaines Sciences '!G143=3,'Items sous domaines Sciences '!B143,0) -> 0 | C141: =IF('Items sous domaines Sciences '!G143=3,'Items sous domaines Sciences '!C143,0) -> 0 | D141: =IF('Items sous domaines Sciences '!G143=3,'Items sous domaines Sciences '!D143,0) -> 0 | E141: =IF('Items sous domaines Sciences '!G143=3,'Items sous domaines Sciences '!E143,0) -> 0 | F141: =IF('Items sous domaines Sciences '!#REF!=1,'Items sous domaines Sciences '!#REF!,0) -> #REF!
B142: =IF('Items sous domaines Sciences '!G144=3,'Items sous domaines Sciences '!B144,0) -> 0 | C142: =IF('Items sous domaines Sciences '!G144=3,'Items sous domaines Sciences '!C144,0) -> 0 | D142: =IF('Items sous domaines Sciences '!G144=3,'Items sous domaines Sciences '!D144,0) -> 0 | E142: =IF('Items sous domaines Sciences '!G144=3,'Items sous domaines Sciences '!E144,0) -> 0 | F142: =IF('Items sous domaines Sciences '!#REF!=1,'Items sous domaines Sciences '!#REF!,0) -> #REF!
A143: UE 4.2 : Mécanique / Electromagnétisme | B143: =IF('Items sous domaines Sciences '!G145=3,'Items sous domaines Sciences '!B145,0) -> Electricité - Electromagnétisme | C143: =IF('Items sous domaines Sciences '!G145=3,'Items sous domaines Sciences '!C145,0) -> Electromagnétisme | D143: =IF('Items sous domaines Sciences '!G145=3,'Items sous domaines Sciences '!D145,0) -> Electronique de puissance | E143: =IF('Items sous domaines Sciences '!G145=3,'Items sous domaines Sciences '!E145,0) -> Comprendre le fonctionnement des composants de base de l'électronique de puissance : diode, thrystor, transistor de puissance en commutation, triac | F143: Projet Mécanique
B144: =IF('Items sous domaines Sciences '!G146=3,'Items sous domaines Sciences '!B146,0) -> Electricité - Electromagnétisme | C144: =IF('Items sous domaines Sciences '!G146=3,'Items sous domaines Sciences '!C146,0) -> Electromagnétisme | D144: =IF('Items sous domaines Sciences '!G146=3,'Items sous domaines Sciences '!D146,0) -> 0 | E144: =IF('Items sous domaines Sciences '!G146=3,'Items sous domaines Sciences '!E146,0) -> Expliquer la forme d'onde de la tension de sortie d'un onduleur.
B145: =IF('Items sous domaines Sciences '!G147=3,'Items sous domaines Sciences '!B147,0) -> Electricité - Electromagnétisme | C145: =IF('Items sous domaines Sciences '!G147=3,'Items sous domaines Sciences '!C147,0) -> Electromagnétisme | D145: =IF('Items sous domaines Sciences '!G147=3,'Items sous domaines Sciences '!D147,0) -> 0 | E145: =IF('Items sous domaines Sciences '!G147=3,'Items sous domaines Sciences '!E147,0) -> Expliquer la forme d'onde de la tension de sortie d'un redresseur.
B146: =IF('Items sous domaines Sciences '!G148=3,'Items sous domaines Sciences '!B148,0) -> Electricité - Electromagnétisme | C146: =IF('Items sous domaines Sciences '!G148=3,'Items sous domaines Sciences '!C148,0) -> Electromagnétisme | D146: =IF('Items sous domaines Sciences '!G148=3,'Items sous domaines Sciences '!D148,0) -> 0 | E146: =IF('Items sous domaines Sciences '!G148=3,'Items sous domaines Sciences '!E148,0) -> Expliquer la forme d'onde de la tension de sortie d'un hacheur.
B147: =IF('Items sous domaines Sciences '!G149=3,'Items sous domaines Sciences '!B149,0) -> Electricité - Electromagnétisme | C147: =IF('Items sous domaines Sciences '!G149=3,'Items sous domaines Sciences '!C149,0) -> Electromagnétisme | D147: =IF('Items sous domaines Sciences '!G149=3,'Items sous domaines Sciences '!D149,0) -> 0 | E147: =IF('Items sous domaines Sciences '!G149=3,'Items sous domaines Sciences '!E149,0) -> Citer la structure des circuits de redressement et d'ondulation de base.
B148: =IF('Items sous domaines Sciences '!G150=3,'Items sous domaines Sciences '!B150,0) -> Electricité - Electromagnétisme | C148: =IF('Items sous domaines Sciences '!G150=3,'Items sous domaines Sciences '!C150,0) -> Electromagnétisme | D148: =IF('Items sous domaines Sciences '!G150=3,'Items sous domaines Sciences '!D150,0) -> Stockage de l'énergie électrique | E148: =IF('Items sous domaines Sciences '!G150=3,'Items sous domaines Sciences '!E150,0) -> Calculer l'énergie et la puissance d'un accumulateur.
B149: =IF('Items sous domaines Sciences '!G151=3,'Items sous domaines Sciences '!B151,0) -> Electricité - Electromagnétisme | C149: =IF('Items sous domaines Sciences '!G151=3,'Items sous domaines Sciences '!C151,0) -> Electromagnétisme | D149: =IF('Items sous domaines Sciences '!G151=3,'Items sous domaines Sciences '!D151,0) -> 0 | E149: =IF('Items sous domaines Sciences '!G151=3,'Items sous domaines Sciences '!E151,0) -> Citer les caractéristiques des accumulateurs en phase de charge et de décharge.
B150: =IF('Items sous domaines Sciences '!G152=3,'Items sous domaines Sciences '!B152,0) -> Electricité - Electromagnétisme | C150: =IF('Items sous domaines Sciences '!G152=3,'Items sous domaines Sciences '!C152,0) -> Electromagnétisme | D150: =IF('Items sous domaines Sciences '!G152=3,'Items sous domaines Sciences '!D152,0) -> 0 | E150: =IF('Items sous domaines Sciences '!G152=3,'Items sous domaines Sciences '!E152,0) -> Citer les différents principes et technologies d'accumulateurs d'énergie électrique.
B151: =IF('Items sous domaines Sciences '!G153=3,'Items sous domaines Sciences '!B153,0) -> Electricité - Electromagnétisme | C151: =IF('Items sous domaines Sciences '!G153=3,'Items sous domaines Sciences '!C153,0) -> Electromagnétisme | D151: =IF('Items sous domaines Sciences '!G153=3,'Items sous domaines Sciences '!D153,0) -> Transformateur | E151: =IF('Items sous domaines Sciences '!G153=3,'Items sous domaines Sciences '!E153,0) -> Utiliser un multimètre (ampèremètre, voltmètre, ohmmètre).
B152: =IF('Items sous domaines Sciences '!G154=3,'Items sous domaines Sciences '!B154,0) -> Electricité - Electromagnétisme | C152: =IF('Items sous domaines Sciences '!G154=3,'Items sous domaines Sciences '!C154,0) -> Electromagnétisme | D152: =IF('Items sous domaines Sciences '!G154=3,'Items sous domaines Sciences '!D154,0) -> 0 | E152: =IF('Items sous domaines Sciences '!G154=3,'Items sous domaines Sciences '!E154,0) -> Comprendre les principes de fonctionnement des composants électroniques de base.
B153: =IF('Items sous domaines Sciences '!G155=3,'Items sous domaines Sciences '!B155,0) -> Electricité - Electromagnétisme | C153: =IF('Items sous domaines Sciences '!G155=3,'Items sous domaines Sciences '!C155,0) -> Electromagnétisme | D153: =IF('Items sous domaines Sciences '!G155=3,'Items sous domaines Sciences '!D155,0) -> 0 | E153: =IF('Items sous domaines Sciences '!G155=3,'Items sous domaines Sciences '!E155,0) -> Citer les lois de base du courant.
...

Sheet A3 CI Géné S5
A1: Objectifs d'apprentissage des sciences physiques
G2: Remédiation
A4: Notions à maîtriser en cycle ingénieur S5
G5: lien Unisciel ou livre scolaire
A7: ='A1 CPI S1'!A7 -> UE du DS | B7: ='A1 CPI S1'!B7 -> Domaine | C7: ='A1 CPI S1'!C7 -> Discipline | D7: ='A1 CPI S1'!D7 -> Chapitres | E7: ='A1 CPI S1'!E7 -> Thèmes | F7: Utilisation
A8: UE 5.3 Sciences physiques | B8: =IF('Items sous domaines Sciences '!G10=5,'Items sous domaines Sciences '!B10,0) -> 0 | C8: =IF('Items sous domaines Sciences '!G10=5,'Items sous domaines Sciences '!C10,0) -> 0 | D8: =IF('Items sous domaines Sciences '!G10=5,'Items sous domaines Sciences '!D10,0) -> 0 | E8: =IF('Items sous domaines Sciences '!G10=5,'Items sous domaines Sciences '!E10,0) -> 0 | F8: SAS (P2 Vieux-pont) et Projet Energ'in box | G8: https://uel.unisciel.fr/physique/meca/meca/co/meca.html https://uel.unisciel.fr/physique/continu/continu/co/continu.html
B9: =IF('Items sous domaines Sciences '!G11=5,'Items sous domaines Sciences '!B11,0) -> 0 | C9: =IF('Items sous domaines Sciences '!G11=5,'Items sous domaines Sciences '!C11,0) -> 0 | D9: =IF('Items sous domaines Sciences '!G11=5,'Items sous domaines Sciences '!D11,0) -> 0 | E9: =IF('Items sous domaines Sciences '!G11=5,'Items sous domaines Sciences '!E11,0) -> 0
B10: =IF('Items sous domaines Sciences '!G12=5,'Items sous domaines Sciences '!B12,0) -> 0 | C10: =IF('Items sous domaines Sciences '!G12=5,'Items sous domaines Sciences '!C12,0) -> 0 | D10: =IF('Items sous domaines Sciences '!G12=5,'Items sous domaines Sciences '!D12,0) -> 0 | E10: =IF('Items sous domaines Sciences '!G12=5,'Items sous domaines Sciences '!E12,0) -> 0
B11: =IF('Items sous domaines Sciences '!G13=5,'Items sous domaines Sciences '!B13,0) -> 0 | C11: =IF('Items sous domaines Sciences '!G13=5,'Items sous domaines Sciences '!C13,0) -> 0 | D11: =IF('Items sous domaines Sciences '!G13=5,'Items sous domaines Sciences '!D13,0) -> 0 | E11: =IF('Items sous domaines Sciences '!G13=5,'Items sous domaines Sciences '!E13,0) -> 0
B12: =IF('Items sous domaines Sciences '!G14=5,'Items sous domaines Sciences '!B14,0) -> 0 | C12: =IF('Items sous domaines Sciences '!G14=5,'Items sous domaines Sciences '!C14,0) -> 0 | D12: =IF('Items sous domaines Sciences '!G14=5,'Items sous domaines Sciences '!D14,0) -> 0 | E12: =IF('Items sous domaines Sciences '!G14=5,'Items sous domaines Sciences '!E14,0) -> 0
B13: =IF('Items sous domaines Sciences '!G15=5,'Items sous domaines Sciences '!B15,0) -> 0 | C13: =IF('Items sous domaines Sciences '!G15=5,'Items sous domaines Sciences '!C15,0) -> 0 | D13: =IF('Items sous domaines Sciences '!G15=5,'Items sous domaines Sciences '!D15,0) -> 0 | E13: =IF('Items sous domaines Sciences '!G15=5,'Items sous domaines Sciences '!E15,0) -> 0
B14: =IF('Items sous domaines Sciences '!G16=5,'Items sous domaines Sciences '!B16,0) -> 0 | C14: =IF('Items sous domaines Sciences '!G16=5,'Items sous domaines Sciences '!C16,0) -> 0 | D14: =IF('Items sous domaines Sciences '!G16=5,'Items sous domaines Sciences '!D16,0) -> 0 | E14: =IF('Items sous domaines Sciences '!G16=5,'Items sous domaines Sciences '!E16,0) -> 0
B15: =IF('Items sous domaines Sciences '!G17=5,'Items sous domaines Sciences '!B17,0) -> 0 | C15: =IF('Items sous domaines Sciences '!G17=5,'Items sous domaines Sciences '!C17,0) -> 0 | D15: =IF('Items sous domaines Sciences '!G17=5,'Items sous domaines Sciences '!D17,0) -> 0 | E15: =IF('Items sous domaines Sciences '!G17=5,'Items sous domaines Sciences '!E17,0) -> 0
B16: =IF('Items sous domaines Sciences '!G18=5,'Items sous domaines Sciences '!B18,0) -> 0 | C16: =IF('Items sous domaines Sciences '!G18=5,'Items sous domaines Sciences '!C18,0) -> 0 | D16: =IF('Items sous domaines Sciences '!G18=5,'Items sous domaines Sciences '!D18,0) -> 0 | E16: =IF('Items sous domaines Sciences '!G18=5,'Items sous domaines Sciences '!E18,0) -> 0
B17: =IF('Items sous domaines Sciences '!G19=5,'Items sous domaines Sciences '!B19,0) -> 0 | C17: =IF('Items sous domaines Sciences '!G19=5,'Items sous domaines Sciences '!C19,0) -> 0 | D17: =IF('Items sous domaines Sciences '!G19=5,'Items sous domaines Sciences '!D19,0) -> 0 | E17: =IF('Items sous domaines Sciences '!G19=5,'Items sous domaines Sciences '!E19,0) -> 0
B18: =IF('Items sous domaines Sciences '!G20=5,'Items sous domaines Sciences '!B20,0) -> 0 | C18: =IF('Items sous domaines Sciences '!G20=5,'Items sous domaines Sciences '!C20,0) -> 0 | D18: =IF('Items sous domaines Sciences '!G20=5,'Items sous domaines Sciences '!D20,0) -> 0 | E18: =IF('Items sous domaines Sciences '!G20=5,'Items sous domaines Sciences '!E20,0) -> 0
B19: =IF('Items sous domaines Sciences '!G21=5,'Items sous domaines Sciences '!B21,0) -> Mécanique | C19: =IF('Items sous domaines Sciences '!G21=5,'Items sous domaines Sciences '!C21,0) -> Point | D19: =IF('Items sous domaines Sciences '!G21=5,'Items sous domaines Sciences '!D21,0) -> 0 | E19: =IF('Items sous domaines Sciences '!G21=5,'Items sous domaines Sciences '!E21,0) -> Calculer une force.
B20: =IF('Items sous domaines Sciences '!G22=5,'Items sous domaines Sciences '!B22,0) -> Mécanique | C20: =IF('Items sous domaines Sciences '!G22=5,'Items sous domaines Sciences '!C22,0) -> Point | D20: =IF('Items sous domaines Sciences '!G22=5,'Items sous domaines Sciences '!D22,0) -> 0 | E20: =IF('Items sous domaines Sciences '!G22=5,'Items sous domaines Sciences '!E22,0) -> Calculer un moment.
... B248: =IF('Items sous domaines Sciences '!G250=5,'Items sous domaines Sciences '!B250,0) -> 0 | C248: =IF('Items sous domaines Sciences '!G250=5,'Items sous domaines Sciences '!C250,0) -> 0 | D248: =IF('Items sous domaines Sciences '!G250=5,'Items sous domaines Sciences '!D250,0) -> 0 | E248: =IF('Items sous domaines Sciences '!G250=5,'Items sous domaines Sciences '!E250,0) -> 0
A249: Analyse : Intégrations 1 | B249: =IF('Items sous domaines Sciences '!G251=5,'Items sous domaines Sciences '!B251,0) -> 0 | C249: =IF('Items sous domaines Sciences '!G251=5,'Items sous domaines Sciences '!C251,0) -> 0 | D249: =IF('Items sous domaines Sciences '!G251=5,'Items sous domaines Sciences '!D251,0) -> 0 | E249: =IF('Items sous domaines Sciences '!G251=5,'Items sous domaines Sciences '!E251,0) -> 0
B250: =IF('Items sous domaines Sciences '!G252=5,'Items sous domaines Sciences '!B252,0) -> 0 | C250: =IF('Items sous domaines Sciences '!G252=5,'Items sous domaines Sciences '!C252,0) -> 0 | D250: =IF('Items sous domaines Sciences '!G252=5,'Items sous domaines Sciences '!D252,0) -> 0 | E250: =IF('Items sous domaines Sciences '!G252=5,'Items sous domaines Sciences '!E252,0) -> 0
B251: =IF('Items sous domaines Sciences '!G253=5,'Items sous domaines Sciences '!B253,0) -> 0 | C251: =IF('Items sous domaines Sciences '!G253=5,'Items sous domaines Sciences '!C253,0) -> 0 | D251: =IF('Items sous domaines Sciences '!G253=5,'Items sous domaines Sciences '!D253,0) -> 0 | E251: =IF('Items sous domaines Sciences '!G253=5,'Items sous domaines Sciences '!E253,0) -> 0
B252: =IF('Items sous domaines Sciences '!G254=5,'Items sous domaines Sciences '!B254,0) -> 0 | C252: =IF('Items sous domaines Sciences '!G254=5,'Items sous domaines Sciences '!C254,0) -> 0 | D252: =IF('Items sous domaines Sciences '!G254=5,'Items sous domaines Sciences '!D254,0) -> 0 | E252: =IF('Items sous domaines Sciences '!G254=5,'Items sous domaines Sciences '!E254,0) -> 0
B253: =IF('Items sous domaines Sciences '!G255=5,'Items sous domaines Sciences '!B255,0) -> 0 | C253: =IF('Items sous domaines Sciences '!G255=5,'Items sous domaines Sciences '!C255,0) -> 0 | D253: =IF('Items sous domaines Sciences '!G255=5,'Items sous domaines Sciences '!D255,0) -> 0 | E253: =IF('Items sous domaines Sciences '!G255=5,'Items sous domaines Sciences '!E255,0) -> 0
B254: =IF('Items sous domaines Sciences '!G256=5,'Items sous domaines Sciences '!B256,0) -> 0 | C254: =IF('Items sous domaines Sciences '!G256=5,'Items sous domaines Sciences '!C256,0) -> 0 | D254: =IF('Items sous domaines Sciences '!G256=5,'Items sous domaines Sciences '!D256,0) -> 0 | E254: =IF('Items sous domaines Sciences '!G256=5,'Items sous domaines Sciences '!E256,0) -> 0
B255: =IF('Items sous domaines Sciences '!G257=5,'Items sous domaines Sciences '!B257,0) -> 0 | C255: =IF('Items sous domaines Sciences '!G257=5,'Items sous domaines Sciences '!C257,0) -> 0 | D255: =IF('Items sous domaines Sciences '!G257=5,'Items sous domaines Sciences '!D257,0) -> 0 | E255: =IF('Items sous domaines Sciences '!G257=5,'Items sous domaines Sciences '!E257,0) -> 0
B256: =IF('Items sous domaines Sciences '!G258=5,'Items sous domaines Sciences '!B258,0) -> 0 | C256: =IF('Items sous domaines Sciences '!G258=5,'Items sous domaines Sciences '!C258,0) -> 0 | D256: =IF('Items sous domaines Sciences '!G258=5,'Items sous domaines Sciences '!D258,0) -> 0 | E256: =IF('Items sous domaines Sciences '!G258=5,'Items sous domaines Sciences '!E258,0) -> 0
B257: =IF('Items sous domaines Sciences '!G259=5,'Items sous domaines Sciences '!B259,0) -> 0 | C257: =IF('Items sous domaines Sciences '!G259=5,'Items sous domaines Sciences '!C259,0) -> 0 | D257: =IF('Items sous domaines Sciences '!G259=5,'Items sous domaines Sciences '!D259,0) -> 0 | E257: =IF('Items sous domaines Sciences '!G259=5,'Items sous domaines Sciences '!E259,0) -> 0
B258: =IF('Items sous domaines Sciences '!G260=5,'Items sous domaines Sciences '!B260,0) -> 0 | C258: =IF('Items sous domaines Sciences '!G260=5,'Items sous domaines Sciences '!C260,0) -> 0 | D258: =IF('Items sous domaines Sciences '!G260=5,'Items sous domaines Sciences '!D260,0) -> 0 | E258: =IF('Items sous domaines Sciences '!G260=5,'Items sous domaines Sciences '!E260,0) -> 0
B259: =IF('Items sous domaines Sciences '!G261=5,'Items sous domaines Sciences '!B261,0) -> 0 | C259: =IF('Items sous domaines Sciences '!G261=5,'Items sous domaines Sciences '!C261,0) -> 0 | D259: =IF('Items sous domaines Sciences '!G261=5,'Items sous domaines Sciences '!D261,0) -> 0 | E259: =IF('Items sous domaines Sciences '!G261=5,'Items sous domaines Sciences '!E261,0) -> 0
B260: =IF('Items sous domaines Sciences '!G262=5,'Items sous domaines Sciences '!B262,0) -> 0 | C260: =IF('Items sous domaines Sciences '!G262=5,'Items sous domaines Sciences '!C262,0) -> 0 | D260: =IF('Items sous domaines Sciences '!G262=5,'Items sous domaines Sciences '!D262,0) -> 0 | E260: =IF('Items sous domaines Sciences '!G262=5,'Items sous domaines Sciences '!E262,0) -> 0
B261: =IF('Items sous domaines Sciences '!G263=5,'Items sous domaines Sciences '!B263,0) -> 0 | C261: =IF('Items sous domaines Sciences '!G263=5,'Items sous domaines Sciences '!C263,0) -> 0 | D261: =IF('Items sous domaines Sciences '!G263=5,'Items sous domaines Sciences '!D263,0) -> 0 | E261: =IF('Items sous domaines Sciences '!G263=5,'Items sous domaines Sciences '!E263,0) -> 0
... B282: =IF('Items sous domaines Sciences '!G284=5,'Items sous domaines Sciences '!B284,0) -> 0 | C282: =IF('Items sous domaines Sciences '!G284=5,'Items sous domaines Sciences '!C284,0) -> 0 | D282: =IF('Items sous domaines Sciences '!G284=5,'Items sous domaines Sciences '!D284,0) -> 0 | E282: =IF('Items sous domaines Sciences '!G284=5,'Items sous domaines Sciences '!E284,0) -> 0
A283: UE 5.4 : Matériaux et Energies renouvelables | B283: =IF('Items sous domaines Sciences '!G285=5,'Items sous domaines Sciences '!B285,0) -> 0 | C283: =IF('Items sous domaines Sciences '!G285=5,'Items sous domaines Sciences '!C285,0) -> 0 | D283: =IF('Items sous domaines Sciences '!G285=5,'Items sous domaines Sciences '!D285,0) -> 0 | E283: =IF('Items sous domaines Sciences '!G285=5,'Items sous domaines Sciences '!E285,0) -> 0
B284: =IF('Items sous domaines Sciences '!G286=5,'Items sous domaines Sciences '!B286,0) -> 0 | C284: =IF('Items sous domaines Sciences '!G286=5,'Items sous domaines Sciences '!C286,0) -> 0 | D284: =IF('Items sous domaines Sciences '!G286=5,'Items sous domaines Sciences '!D286,0) -> 0 | E284: =IF('Items sous domaines Sciences '!G286=5,'Items sous domaines Sciences '!E286,0) -> 0
B285: =IF('Items sous domaines Sciences '!G287=5,'Items sous domaines Sciences '!B287,0) -> 0 | C285: =IF('Items sous domaines Sciences '!G287=5,'Items sous domaines Sciences '!C287,0) -> 0 | D285: =IF('Items sous domaines Sciences '!G287=5,'Items sous domaines Sciences '!D287,0) -> 0 | E285: =IF('Items sous domaines Sciences '!G287=5,'Items sous domaines Sciences '!E287,0) -> 0
B286: =IF('Items sous domaines Sciences '!G288=5,'Items sous domaines Sciences '!B288,0) -> 0 | C286: =IF('Items sous domaines Sciences '!G288=5,'Items sous domaines Sciences '!C288,0) -> 0 | D286: =IF('Items sous domaines Sciences '!G288=5,'Items sous domaines Sciences '!D288,0) -> 0 | E286: =IF('Items sous domaines Sciences '!G288=5,'Items sous domaines Sciences '!E288,0) -> 0
B287: =IF('Items sous domaines Sciences '!G289=5,'Items sous domaines Sciences '!B289,0) -> 0 | C287: =IF('Items sous domaines Sciences '!G289=5,'Items sous domaines Sciences '!C289,0) -> 0 | D287: =IF('Items sous domaines Sciences '!G289=5,'Items sous domaines Sciences '!D289,0) -> 0 | E287: =IF('Items sous domaines Sciences '!G289=5,'Items sous domaines Sciences '!E289,0) -> 0
B288: =IF('Items sous domaines Sciences '!G290=5,'Items sous domaines Sciences '!B290,0) -> 0 | C288: =IF('Items sous domaines Sciences '!G290=5,'Items sous domaines Sciences '!C290,0) -> 0 | D288: =IF('Items sous domaines Sciences '!G290=5,'Items sous domaines Sciences '!D290,0) -> 0 | E288: =IF('Items sous domaines Sciences '!G290=5,'Items sous domaines Sciences '!E290,0) -> 0
B289: =IF('Items sous domaines Sciences '!G291=5,'Items sous domaines Sciences '!B291,0) -> 0 | C289: =IF('Items sous domaines Sciences '!G291=5,'Items sous domaines Sciences '!C291,0) -> 0 | D289: =IF('Items sous domaines Sciences '!G291=5,'Items sous domaines Sciences '!D291,0) -> 0 | E289: =IF('Items sous domaines Sciences '!G291=5,'Items sous domaines Sciences '!E291,0) -> 0
B290: =IF('Items sous domaines Sciences '!G292=5,'Items sous domaines Sciences '!B292,0) -> 0 | C290: =IF('Items sous domaines Sciences '!G292=5,'Items sous domaines Sciences '!C292,0) -> 0 | D290: =IF('Items sous domaines Sciences '!G292=5,'Items sous domaines Sciences '!D292,0) -> 0 | E290: =IF('Items sous domaines Sciences '!G292=5,'Items sous domaines Sciences '!E292,0) -> 0
B291: =IF('Items sous domaines Sciences '!G293=5,'Items sous domaines Sciences '!B293,0) -> 0 | C291: =IF('Items sous domaines Sciences '!G293=5,'Items sous domaines Sciences '!C293,0) -> 0 | D291: =IF('Items sous domaines Sciences '!G293=5,'Items sous domaines Sciences '!D293,0) -> 0 | E291: =IF('Items sous domaines Sciences '!G293=5,'Items sous domaines Sciences '!E293,0) -> 0
B292: =IF('Items sous domaines Sciences '!G294=5,'Items sous domaines Sciences '!B294,0) -> 0 | C292: =IF('Items sous domaines Sciences '!G294=5,'Items sous domaines Sciences '!C294,0) -> 0 | D292: =IF('Items sous domaines Sciences '!G294=5,'Items sous domaines Sciences '!D294,0) -> 0 | E292: =IF('Items sous domaines Sciences '!G294=5,'Items sous domaines Sciences '!E294,0) -> 0
B293: =IF('Items sous domaines Sciences '!G295=5,'Items sous domaines Sciences '!B295,0) -> Chimie | C293: =IF('Items sous domaines Sciences '!G295=5,'Items sous domaines Sciences '!C295,0) -> Chimie | D293: =IF('Items sous domaines Sciences '!G295=5,'Items sous domaines Sciences '!D295,0) -> REDOX | E293: =IF('Items sous domaines Sciences '!G295=5,'Items sous domaines Sciences '!E295,0) -> Utiliser les principes chimiques de base de l'oxydo-réduction : électrochimie.
B294: =IF('Items sous domaines Sciences '!G296=5,'Items sous domaines Sciences '!B296,0) -> Chimie | C294: =IF('Items sous domaines Sciences '!G296=5,'Items sous domaines Sciences '!C296,0) -> Chimie | D294: =IF('Items sous domaines Sciences '!G296=5,'Items sous domaines Sciences '!D296,0) -> 0 | E294: =IF('Items sous domaines Sciences '!G296=5,'Items sous domaines Sciences '!E296,0) -> Déterminer le fonctionnement d'une batterie à partir des principes de l'oxydo-réduction.
B295: =IF('Items sous domaines Sciences '!G297=5,'Items sous domaines Sciences '!B297,0) -> Chimie | C295: =IF('Items sous domaines Sciences '!G297=5,'Items sous domaines Sciences '!C297,0) -> Chimie | D295: =IF('Items sous domaines Sciences '!G297=5,'Items sous domaines Sciences '!D297,0) -> 0 | E295: =IF('Items sous domaines Sciences '!G297=5,'Items sous domaines Sciences '!E297,0) -> Décrire le fonctionnement d'un accumulateur à partir des principes de l'électrolyse.
... B302: =IF('Items sous domaines Sciences '!G304=5,'Items sous domaines Sciences '!B304,0) -> Chimie | C302: =IF('Items sous domaines Sciences '!G304=5,'Items sous domaines Sciences '!C304,0) -> Chimie | D302: =IF('Items sous domaines Sciences '!G304=5,'Items sous domaines Sciences '!D304,0) -> 0 | E302: =IF('Items sous domaines Sciences '!G304=5,'Items sous domaines Sciences '!E304,0) -> Produire un schéma d'ingénierie et analyser les performances de l'implatation des panneaux.
B303: =IF('Items sous domaines Sciences '!G305=5,'Items sous domaines Sciences '!B305,0) -> 0 | C303: =IF('Items sous domaines Sciences '!G305=5,'Items sous domaines Sciences '!C305,0) -> 0 | D303: =IF('Items sous domaines Sciences '!G305=5,'Items sous domaines Sciences '!D305,0) -> 0 | E303: =IF('Items sous domaines Sciences '!G305=5,'Items sous domaines Sciences '!E305,0) -> 0 | G303: =IF(AND('Items sous domaines Sciences '!#REF!<=5, 'Items sous domaines Sciences '!#REF!>0),'Items sous domaines Sciences '!#REF!,0) -> #REF!
B304: =IF('Items sous domaines Sciences '!G306=5,'Items sous domaines Sciences '!B306,0) -> 0 | C304: =IF('Items sous domaines Sciences '!G306=5,'Items sous domaines Sciences '!C306,0) -> 0 | D304: =IF('Items sous domaines Sciences '!G306=5,'Items sous domaines Sciences '!D306,0) -> 0 | E304: =IF('Items sous domaines Sciences '!G306=5,'Items sous domaines Sciences '!E306,0) -> 0 | G304: =IF(AND('Items sous domaines Sciences '!#REF!<=5, 'Items sous domaines Sciences '!#REF!>0),'Items sous domaines Sciences '!#REF!,0) -> #REF!
B305: =IF('Items sous domaines Sciences '!G307=5,'Items sous domaines Sciences '!B307,0) -> 0 | C305: =IF('Items sous domaines Sciences '!G307=5,'Items sous domaines Sciences '!C307,0) -> 0 | D305: =IF('Items sous domaines Sciences '!G307=5,'Items sous domaines Sciences '!D307,0) -> 0 | E305: =IF('Items sous domaines Sciences '!G307=5,'Items sous domaines Sciences '!E307,0) -> 0 | G305: =IF(AND('Items sous domaines Sciences '!#REF!<=5, 'Items sous domaines Sciences '!#REF!>0),'Items sous domaines Sciences '!#REF!,0) -> #REF!
B306: =IF('Items sous domaines Sciences '!G308=5,'Items sous domaines Sciences '!B308,0) -> 0 | C306: =IF('Items sous domaines Sciences '!G308=5,'Items sous domaines Sciences '!C308,0) -> 0 | D306: =IF('Items sous domaines Sciences '!G308=5,'Items sous domaines Sciences '!D308,0) -> 0 | E306: =IF('Items sous domaines Sciences '!G308=5,'Items sous domaines Sciences '!E308,0) -> 0 | G306: =IF(AND('Items sous domaines Sciences '!#REF!<=5, 'Items sous domaines Sciences '!#REF!>0),'Items sous domaines Sciences '!#REF!,0) -> #REF!
B307: =IF('Items sous domaines Sciences '!G309=5,'Items sous domaines Sciences '!B309,0) -> 0 | C307: =IF('Items sous domaines Sciences '!G309=5,'Items sous domaines Sciences '!C309,0) -> 0 | D307: =IF('Items sous domaines Sciences '!G309=5,'Items sous domaines Sciences '!D309,0) -> 0 | E307: =IF('Items sous domaines Sciences '!G309=5,'Items sous domaines Sciences '!E309,0) -> 0 | G307: =IF(AND('Items sous domaines Sciences '!#REF!<=5, 'Items sous domaines Sciences '!#REF!>0),'Items sous domaines Sciences '!#REF!,0) -> #REF!
B308: =IF('Items sous domaines Sciences '!G310=5,'Items sous domaines Sciences '!B310,0) -> 0 | C308: =IF('Items sous domaines Sciences '!G310=5,'Items sous domaines Sciences '!C310,0) -> 0 | D308: =IF('Items sous domaines Sciences '!G310=5,'Items sous domaines Sciences '!D310,0) -> 0 | E308: =IF('Items sous domaines Sciences '!G310=5,'Items sous domaines Sciences '!E310,0) -> 0 | G308: =IF(AND('Items sous domaines Sciences '!#REF!<=5, 'Items sous domaines Sciences '!#REF!>0),'Items sous domaines Sciences '!#REF!,0) -> #REF!
B309: =IF('Items sous domaines Sciences '!G311=5,'Items sous domaines Sciences '!B311,0) -> 0 | C309: =IF('Items sous domaines Sciences '!G311=5,'Items sous domaines Sciences '!C311,0) -> 0 | D309: =IF('Items sous domaines Sciences '!G311=5,'Items sous domaines Sciences '!D311,0) -> 0 | E309: =IF('Items sous domaines Sciences '!G311=5,'Items sous domaines Sciences '!E311,0) -> 0 | G309: =IF(AND('Items sous domaines Sciences '!#REF!<=5, 'Items sous domaines Sciences '!#REF!>0),'Items sous domaines Sciences '!#REF!,0) -> #REF!
B310: =IF('Items sous domaines Sciences '!G312=5,'Items sous domaines Sciences '!B312,0) -> 0 | C310: =IF('Items sous domaines Sciences '!G312=5,'Items sous domaines Sciences '!C312,0) -> 0 | D310: =IF('Items sous domaines Sciences '!G312=5,'Items sous domaines Sciences '!D312,0) -> 0 | E310: =IF('Items sous domaines Sciences '!G312=5,'Items sous domaines Sciences '!E312,0) -> 0 | G310: =IF(AND('Items sous domaines Sciences '!#REF!<=5, 'Items sous domaines Sciences '!#REF!>0),'Items sous domaines Sciences '!#REF!,0) -> #REF!
A311: Analyse : Suites et Séries 1 | B311: =IF('Items sous domaines Sciences '!G313=5,'Items sous domaines Sciences '!B313,0) -> 0 | C311: =IF('Items sous domaines Sciences '!G313=5,'Items sous domaines Sciences '!C313,0) -> 0 | D311: =IF('Items sous domaines Sciences '!G313=5,'Items sous domaines Sciences '!D313,0) -> 0 | E311: =IF('Items sous domaines Sciences '!G313=5,'Items sous domaines Sciences '!E313,0) -> 0 | G311: Suites de nombres réels (unisciel.fr)
B312: =IF('Items sous domaines Sciences '!G314=5,'Items sous domaines Sciences '!B314,0) -> 0 | C312: =IF('Items sous domaines Sciences '!G314=5,'Items sous domaines Sciences '!C314,0) -> 0 | D312: =IF('Items sous domaines Sciences '!G314=5,'Items sous domaines Sciences '!D314,0) -> 0 | E312: =IF('Items sous domaines Sciences '!G314=5,'Items sous domaines Sciences '!E314,0) -> 0
B313: =IF('Items sous domaines Sciences '!G315=5,'Items sous domaines Sciences '!B315,0) -> 0 | C313: =IF('Items sous domaines Sciences '!G315=5,'Items sous domaines Sciences '!C315,0) -> 0 | D313: =IF('Items sous domaines Sciences '!G315=5,'Items sous domaines Sciences '!D315,0) -> 0 | E313: =IF('Items sous domaines Sciences '!G315=5,'Items sous domaines Sciences '!E315,0) -> 0
B314: =IF('Items sous domaines Sciences '!G316=5,'Items sous domaines Sciences '!B316,0) -> 0 | C314: =IF('Items sous domaines Sciences '!G316=5,'Items sous domaines Sciences '!C316,0) -> 0 | D314: =IF('Items sous domaines Sciences '!G316=5,'Items sous domaines Sciences '!D316,0) -> 0 | E314: =IF('Items sous domaines Sciences '!G316=5,'Items sous domaines Sciences '!E316,0) -> 0
B315: =IF('Items sous domaines Sciences '!G317=5,'Items sous domaines Sciences '!B317,0) -> 0 | C315: =IF('Items sous domaines Sciences '!G317=5,'Items sous domaines Sciences '!C317,0) -> 0 | D315: =IF('Items sous domaines Sciences '!G317=5,'Items sous domaines Sciences '!D317,0) -> 0 | E315: =IF('Items sous domaines Sciences '!G317=5,'Items sous domaines Sciences '!E317,0) -> 0
B316: =IF('Items sous domaines Sciences '!G318=5,'Items sous domaines Sciences '!B318,0) -> 0 | C316: =IF('Items sous domaines Sciences '!G318=5,'Items sous domaines Sciences '!C318,0) -> 0 | D316: =IF('Items sous domaines Sciences '!G318=5,'Items sous domaines Sciences '!D318,0) -> 0 | E316: =IF('Items sous domaines Sciences '!G318=5,'Items sous domaines Sciences '!E318,0) -> 0
B317: =IF('Items sous domaines Sciences '!G319=5,'Items sous domaines Sciences '!B319,0) -> 0 | C317: =IF('Items sous domaines Sciences '!G319=5,'Items sous domaines Sciences '!C319,0) -> 0 | D317: =IF('Items sous domaines Sciences '!G319=5,'Items sous domaines Sciences '!D319,0) -> 0 | E317: =IF('Items sous domaines Sciences '!G319=5,'Items sous domaines Sciences '!E319,0) -> 0
B318: =IF('Items sous domaines Sciences '!G320=5,'Items sous domaines Sciences '!B320,0) -> 0 | C318: =IF('Items sous domaines Sciences '!G320=5,'Items sous domaines Sciences '!C320,0) -> 0 | D318: =IF('Items sous domaines Sciences '!G320=5,'Items sous domaines Sciences '!D320,0) -> 0 | E318: =IF('Items sous domaines Sciences '!G320=5,'Items sous domaines Sciences '!E320,0) -> 0
B319: =IF('Items sous domaines Sciences '!G321=5,'Items sous domaines Sciences '!B321,0) -> 0 | C319: =IF('Items sous domaines Sciences '!G321=5,'Items sous domaines Sciences '!C321,0) -> 0 | D319: =IF('Items sous domaines Sciences '!G321=5,'Items sous domaines Sciences '!D321,0) -> 0 | E319: =IF('Items sous domaines Sciences '!G321=5,'Items sous domaines Sciences '!E321,0) -> 0
B320: =IF('Items sous domaines Sciences '!G322=5,'Items sous domaines Sciences '!B322,0) -> 0 | C320: =IF('Items sous domaines Sciences '!G322=5,'Items sous domaines Sciences '!C322,0) -> 0 | D320: =IF('Items sous domaines Sciences '!G322=5,'Items sous domaines Sciences '!D322,0) -> 0 | E320: =IF('Items sous domaines Sciences '!G322=5,'Items sous domaines Sciences '!E322,0) -> 0
B321: =IF('Items sous domaines Sciences '!G323=5,'Items sous domaines Sciences '!B323,0) -> 0 | C321: =IF('Items sous domaines Sciences '!G323=5,'Items sous domaines Sciences '!C323,0) -> 0 | D321: =IF('Items sous domaines Sciences '!G323=5,'Items sous domaines Sciences '!D323,0) -> 0 | E321: =IF('Items sous domaines Sciences '!G323=5,'Items sous domaines Sciences '!E323,0) -> 0
B322: =IF('Items sous domaines Sciences '!G324=5,'Items sous domaines Sciences '!B324,0) -> 0 | C322: =IF('Items sous domaines Sciences '!G324=5,'Items sous domaines Sciences '!C324,0) -> 0 | D322: =IF('Items sous domaines Sciences '!G324=5,'Items sous domaines Sciences '!D324,0) -> 0 | E322: =IF('Items sous domaines Sciences '!G324=5,'Items sous domaines Sciences '!E324,0) -> 0 | G322: =IF(AND('Items sous domaines Sciences '!#REF!<=5, 'Items sous domaines Sciences '!#REF!>0),'Items sous domaines Sciences '!#REF!,0) -> #REF!
B323: =IF('Items sous domaines Sciences '!G325=5,'Items sous domaines Sciences '!B325,0) -> 0 | C323: =IF('Items sous domaines Sciences '!G325=5,'Items sous domaines Sciences '!C325,0) -> 0 | D323: =IF('Items sous domaines Sciences '!G325=5,'Items sous domaines Sciences '!D325,0) -> 0 | E323: =IF('Items sous domaines Sciences '!G325=5,'Items sous domaines Sciences '!E325,0) -> 0 | G323: =IF(AND('Items sous domaines Sciences '!#REF!<=5, 'Items sous domaines Sciences '!#REF!>0),'Items sous domaines Sciences '!#REF!,0) -> #REF!
B324: =IF('Items sous domaines Sciences '!G326=5,'Items sous domaines Sciences '!B326,0) -> 0 | C324: =IF('Items sous domaines Sciences '!G326=5,'Items sous domaines Sciences '!C326,0) -> 0 | D324: =IF('Items sous domaines Sciences '!G326=5,'Items sous domaines Sciences '!D326,0) -> 0 | E324: =IF('Items sous domaines Sciences '!G326=5,'Items sous domaines Sciences '!E326,0) -> 0 | G324: =IF(AND('Items sous domaines Sciences '!#REF!<=5, 'Items sous domaines Sciences '!#REF!>0),'Items sous domaines Sciences '!#REF!,0) -> #REF!
B325: =IF('Items sous domaines Sciences '!G327=5,'Items sous domaines Sciences '!B327,0) -> 0 | C325: =IF('Items sous domaines Sciences '!G327=5,'Items sous domaines Sciences '!C327,0) -> 0 | D325: =IF('Items sous domaines Sciences '!G327=5,'Items sous domaines Sciences '!D327,0) -> 0 | E325: =IF('Items sous domaines Sciences '!G327=5,'Items sous domaines Sciences '!E327,0) -> 0 | G325: =IF(AND('Items sous domaines Sciences '!#REF!<=5, 'Items sous domaines Sciences '!#REF!>0),'Items sous domaines Sciences '!#REF!,0) -> #REF!
B326: =IF('Items sous domaines Sciences '!G328=5,'Items sous domaines Sciences '!B328,0) -> 0 | C326: =IF('Items sous domaines Sciences '!G328=5,'Items sous domaines Sciences '!C328,0) -> 0 | D326: =IF('Items sous domaines Sciences '!G328=5,'Items sous domaines Sciences '!D328,0) -> 0 | E326: =IF('Items sous domaines Sciences '!G328=5,'Items sous domaines Sciences '!E328,0) -> 0 | G326: =IF(AND('Items sous domaines Sciences '!#REF!<=5, 'Items sous domaines Sciences '!#REF!>0),'Items sous domaines Sciences '!#REF!,0) -> #REF!
B327: =IF('Items sous domaines Sciences '!G329=5,'Items sous domaines Sciences '!B329,0) -> 0 | C327: =IF('Items sous domaines Sciences '!G329=5,'Items sous domaines Sciences '!C329,0) -> 0 | D327: =IF('Items sous domaines Sciences '!G329=5,'Items sous domaines Sciences '!D329,0) -> 0 | E327: =IF('Items sous domaines Sciences '!G329=5,'Items sous domaines Sciences '!E329,0) -> 0 | G327: =IF(AND('Items sous domaines Sciences '!#REF!<=5, 'Items sous domaines Sciences '!#REF!>0),'Items sous domaines Sciences '!#REF!,0) -> #REF!
B328: =IF('Items sous domaines Sciences '!G330=5,'Items sous domaines Sciences '!B330,0) -> 0 | C328: =IF('Items sous domaines Sciences '!G330=5,'Items sous domaines Sciences '!C330,0) -> 0 | D328: =IF('Items sous domaines Sciences '!G330=5,'Items sous domaines Sciences '!D330,0) -> 0 | E328: =IF('Items sous domaines Sciences '!G330=5,'Items sous domaines Sciences '!E330,0) -> 0 | G328: =IF(AND('Items sous domaines Sciences '!#REF!<=5, 'Items sous domaines Sciences '!#REF!>0),'Items sous domaines Sciences '!#REF!,0) -> #REF!
B329: =IF('Items sous domaines Sciences '!G331=5,'Items sous domaines Sciences '!B331,0) -> 0 | C329: =IF('Items sous domaines Sciences '!G331=5,'Items sous domaines Sciences '!C331,0) -> 0 | D329: =IF('Items sous domaines Sciences '!G331=5,'Items sous domaines Sciences '!D331,0) -> 0 | E329: =IF('Items sous domaines Sciences '!G331=5,'Items sous domaines Sciences '!E331,0) -> 0 | G329: =IF(AND('Items sous domaines Sciences '!#REF!<=5, 'Items sous domaines Sciences '!#REF!>0),'Items sous domaines Sciences '!#REF!,0) -> #REF!
B330: =IF('Items sous domaines Sciences '!G332=5,'Items sous domaines Sciences '!B332,0) -> 0 | C330: =IF('Items sous domaines Sciences '!G332=5,'Items sous domaines Sciences '!C332,0) -> 0 | D330: =IF('Items sous domaines Sciences '!G332=5,'Items sous domaines Sciences '!D332,0) -> 0 | E330: =IF('Items sous domaines Sciences '!G332=5,'Items sous domaines Sciences '!E332,0) -> 0 | G330: =IF(AND('Items sous domaines Sciences '!#REF!<=5, 'Items sous domaines Sciences '!#REF!>0),'Items sous domaines Sciences '!#REF!,0) -> #REF!
B331: =IF('Items sous domaines Sciences '!G333=5,'Items sous domaines Sciences '!B333,0) -> 0 | C331: =IF('Items sous domaines Sciences '!G333=5,'Items sous domaines Sciences '!C333,0) -> 0 | D331: =IF('Items sous domaines Sciences '!G333=5,'Items sous domaines Sciences '!D333,0) -> 0 | E331: =IF('Items sous domaines Sciences '!G333=5,'Items sous domaines Sciences '!E333,0) -> 0 | G331: =IF(AND('Items sous domaines Sciences '!#REF!<=5, 'Items sous domaines Sciences '!#REF!>0),'Items sous domaines Sciences '!#REF!,0) -> #REF!
B332: =IF('Items sous domaines Sciences '!G334=5,'Items sous domaines Sciences '!B334,0) -> 0 | C332: =IF('Items sous domaines Sciences '!G334=5,'Items sous domaines Sciences '!C334,0) -> 0 | D332: =IF('Items sous domaines Sciences '!G334=5,'Items sous domaines Sciences '!D334,0) -> 0 | E332: =IF('Items sous domaines Sciences '!G334=5,'Items sous domaines Sciences '!E334,0) -> 0 | G332: =IF(AND('Items sous domaines Sciences '!#REF!<=5, 'Items sous domaines Sciences '!#REF!>0),'Items sous domaines Sciences '!#REF!,0) -> #REF!
B333: =IF('Items sous domaines Sciences '!G335=5,'Items sous domaines Sciences '!B335,0) -> 0 | C333: =IF('Items sous domaines Sciences '!G335=5,'Items sous domaines Sciences '!C335,0) -> 0 | D333: =IF('Items sous domaines Sciences '!G335=5,'Items sous domaines Sciences '!D335,0) -> 0 | E333: =IF('Items sous domaines Sciences '!G335=5,'Items sous domaines Sciences '!E335,0) -> 0 | G333: =IF(AND('Items sous domaines Sciences '!#REF!<=5, 'Items sous domaines Sciences '!#REF!>0),'Items sous domaines Sciences '!#REF!,0) -> #REF!
... B342: =IF('Items sous domaines Sciences '!G344=5,'Items sous domaines Sciences '!B344,0) -> 0 | C342: =IF('Items sous domaines Sciences '!G344=5,'Items sous domaines Sciences '!C344,0) -> 0 | D342: =IF('Items sous domaines Sciences '!G344=5,'Items sous domaines Sciences '!D344,0) -> 0 | E342: =IF('Items sous domaines Sciences '!G344=5,'Items sous domaines Sciences '!E344,0) -> 0 | G342: =IF(AND('Items sous domaines Sciences '!#REF!<=5, 'Items sous domaines Sciences '!#REF!>0),'Items sous domaines Sciences '!#REF!,0) -> #REF!
A343: Mathématiques : élémentaire | B343: =IF('Items sous domaines Sciences '!G345=5,'Items sous domaines Sciences '!B345,0) -> 0 | C343: =IF('Items sous domaines Sciences '!G345=5,'Items sous domaines Sciences '!C345,0) -> 0 | D343: =IF('Items sous domaines Sciences '!G345=5,'Items sous domaines Sciences '!D345,0) -> 0 | E343: =IF('Items sous domaines Sciences '!G345=5,'Items sous domaines Sciences '!E345,0) -> 0 | G343: https://ressources.unisciel.fr/ramses/519-21_probabilites/co/fa901_5.html
B344: =IF('Items sous domaines Sciences '!G346=5,'Items sous domaines Sciences '!B346,0) -> 0 | C344: =IF('Items sous domaines Sciences '!G346=5,'Items sous domaines Sciences '!C346,0) -> 0 | D344: =IF('Items sous domaines Sciences '!G346=5,'Items sous domaines Sciences '!D346,0) -> 0 | E344: =IF('Items sous domaines Sciences '!G346=5,'Items sous domaines Sciences '!E346,0) -> 0
B345: =IF('Items sous domaines Sciences '!G347=5,'Items sous domaines Sciences '!B347,0) -> 0 | C345: =IF('Items sous domaines Sciences '!G347=5,'Items sous domaines Sciences '!C347,0) -> 0 | D345: =IF('Items sous domaines Sciences '!G347=5,'Items sous domaines Sciences '!D347,0) -> 0 | E345: =IF('Items sous domaines Sciences '!G347=5,'Items sous domaines Sciences '!E347,0) -> 0
B346: =IF('Items sous domaines Sciences '!G348=5,'Items sous domaines Sciences '!B348,0) -> 0 | C346: =IF('Items sous domaines Sciences '!G348=5,'Items sous domaines Sciences '!C348,0) -> 0 | D346: =IF('Items sous domaines Sciences '!G348=5,'Items sous domaines Sciences '!D348,0) -> 0 | E346: =IF('Items sous domaines Sciences '!G348=5,'Items sous domaines Sciences '!E348,0) -> 0
B347: =IF('Items sous domaines Sciences '!G349=5,'Items sous domaines Sciences '!B349,0) -> 0 | C347: =IF('Items sous domaines Sciences '!G349=5,'Items sous domaines Sciences '!C349,0) -> 0 | D347: =IF('Items sous domaines Sciences '!G349=5,'Items sous domaines Sciences '!D349,0) -> 0 | E347: =IF('Items sous domaines Sciences '!G349=5,'Items sous domaines Sciences '!E349,0) -> 0
B348: =IF('Items sous domaines Sciences '!G350=5,'Items sous domaines Sciences '!B350,0) -> 0 | C348: =IF('Items sous domaines Sciences '!G350=5,'Items sous domaines Sciences '!C350,0) -> 0 | D348: =IF('Items sous domaines Sciences '!G350=5,'Items sous domaines Sciences '!D350,0) -> 0 | E348: =IF('Items sous domaines Sciences '!G350=5,'Items sous domaines Sciences '!E350,0) -> 0
B349: =IF('Items sous domaines Sciences '!G351=5,'Items sous domaines Sciences '!B351,0) -> 0 | C349: =IF('Items sous domaines Sciences '!G351=5,'Items sous domaines Sciences '!C351,0) -> 0 | D349: =IF('Items sous domaines Sciences '!G351=5,'Items sous domaines Sciences '!D351,0) -> 0 | E349: =IF('Items sous domaines Sciences '!G351=5,'Items sous domaines Sciences '!E351,0) -> 0
B350: =IF('Items sous domaines Sciences '!G352=5,'Items sous domaines Sciences '!B352,0) -> 0 | C350: =IF('Items sous domaines Sciences '!G352=5,'Items sous domaines Sciences '!C352,0) -> 0 | D350: =IF('Items sous domaines Sciences '!G352=5,'Items sous domaines Sciences '!D352,0) -> 0 | E350: =IF('Items sous domaines Sciences '!G352=5,'Items sous domaines Sciences '!E352,0) -> 0
B351: =IF('Items sous domaines Sciences '!G353=5,'Items sous domaines Sciences '!B353,0) -> 0 | C351: =IF('Items sous domaines Sciences '!G353=5,'Items sous domaines Sciences '!C353,0) -> 0 | D351: =IF('Items sous domaines Sciences '!G353=5,'Items sous domaines Sciences '!D353,0) -> 0 | E351: =IF('Items sous domaines Sciences '!G353=5,'Items sous domaines Sciences '!E353,0) -> 0
B352: =IF('Items sous domaines Sciences '!G354=5,'Items sous domaines Sciences '!B354,0) -> 0 | C352: =IF('Items sous domaines Sciences '!G354=5,'Items sous domaines Sciences '!C354,0) -> 0 | D352: =IF('Items sous domaines Sciences '!G354=5,'Items sous domaines Sciences '!D354,0) -> 0 | E352: =IF('Items sous domaines Sciences '!G354=5,'Items sous domaines Sciences '!E354,0) -> 0
B353: =IF('Items sous domaines Sciences '!G355=5,'Items sous domaines Sciences '!B355,0) -> 0 | C353: =IF('Items sous domaines Sciences '!G355=5,'Items sous domaines Sciences '!C355,0) -> 0 | D353: =IF('Items sous domaines Sciences '!G355=5,'Items sous domaines Sciences '!D355,0) -> 0 | E353: =IF('Items sous domaines Sciences '!G355=5,'Items sous domaines Sciences '!E355,0) -> 0
B354: =IF('Items sous domaines Sciences '!G356=5,'Items sous domaines Sciences '!B356,0) -> 0 | C354: =IF('Items sous domaines Sciences '!G356=5,'Items sous domaines Sciences '!C356,0) -> 0 | D354: =IF('Items sous domaines Sciences '!G356=5,'Items sous domaines Sciences '!D356,0) -> 0 | E354: =IF('Items sous domaines Sciences '!G356=5,'Items sous domaines Sciences '!E356,0) -> 0
B355: =IF('Items sous domaines Sciences '!G357=5,'Items sous domaines Sciences '!B357,0) -> 0 | C355: =IF('Items sous domaines Sciences '!G357=5,'Items sous domaines Sciences '!C357,0) -> 0 | D355: =IF('Items sous domaines Sciences '!G357=5,'Items sous domaines Sciences '!D357,0) -> 0 | E355: =IF('Items sous domaines Sciences '!G357=5,'Items sous domaines Sciences '!E357,0) -> 0
... B379: =IF('Items sous domaines Sciences '!G381=5,'Items sous domaines Sciences '!B381,0) -> 0 | C379: =IF('Items sous domaines Sciences '!G381=5,'Items sous domaines Sciences '!C381,0) -> 0 | D379: =IF('Items sous domaines Sciences '!G381=5,'Items sous domaines Sciences '!D381,0) -> 0 | E379: =IF('Items sous domaines Sciences '!G381=5,'Items sous domaines Sciences '!E381,0) -> 0
B380: =IF('Items sous domaines Sciences '!G382=5,'Items sous domaines Sciences '!B382,0) -> 0 | C380: =IF('Items sous domaines Sciences '!G382=5,'Items sous domaines Sciences '!C382,0) -> 0 | D380: =IF('Items sous domaines Sciences '!G382=5,'Items sous domaines Sciences '!D382,0) -> 0 | E380: =IF('Items sous domaines Sciences '!G382=5,'Items sous domaines Sciences '!E382,0) -> 0 | F380: =IF('Items sous domaines Sciences '!#REF!<4,'Items sous domaines Sciences '!#REF!,0) -> #REF! | G380: =IF(AND('Items sous domaines Sciences '!#REF!<=5, 'Items sous domaines Sciences '!#REF!>0),'Items sous domaines Sciences '!#REF!,0) -> #REF!
B381: =IF('Items sous domaines Sciences '!G383=5,'Items sous domaines Sciences '!B383,0) -> 0 | C381: =IF('Items sous domaines Sciences '!G383=5,'Items sous domaines Sciences '!C383,0) -> 0 | D381: =IF('Items sous domaines Sciences '!G383=5,'Items sous domaines Sciences '!D383,0) -> 0 | E381: =IF('Items sous domaines Sciences '!G383=5,'Items sous domaines Sciences '!E383,0) -> 0 | F381: =IF('Items sous domaines Sciences '!#REF!<4,'Items sous domaines Sciences '!#REF!,0) -> #REF! | G381: =IF(AND('Items sous domaines Sciences '!#REF!<=5, 'Items sous domaines Sciences '!#REF!>0),'Items sous domaines Sciences '!#REF!,0) -> #REF!
B382: =IF('Items sous domaines Sciences '!G384=5,'Items sous domaines Sciences '!B384,0) -> 0 | C382: =IF('Items sous domaines Sciences '!G384=5,'Items sous domaines Sciences '!C384,0) -> 0 | D382: =IF('Items sous domaines Sciences '!G384=5,'Items sous domaines Sciences '!D384,0) -> 0 | E382: =IF('Items sous domaines Sciences '!G384=5,'Items sous domaines Sciences '!E384,0) -> 0 | F382: =IF('Items sous domaines Sciences '!#REF!<4,'Items sous domaines Sciences '!#REF!,0) -> #REF! | G382: =IF(AND('Items sous domaines Sciences '!#REF!<=5, 'Items sous domaines Sciences '!#REF!>0),'Items sous domaines Sciences '!#REF!,0) -> #REF!
B383: =IF('Items sous domaines Sciences '!G385=5,'Items sous domaines Sciences '!B385,0) -> 0 | C383: =IF('Items sous domaines Sciences '!G385=5,'Items sous domaines Sciences '!C385,0) -> 0 | D383: =IF('Items sous domaines Sciences '!G385=5,'Items sous domaines Sciences '!D385,0) -> 0 | E383: =IF('Items sous domaines Sciences '!G385=5,'Items sous domaines Sciences '!E385,0) -> 0 | F383: =IF('Items sous domaines Sciences '!#REF!<4,'Items sous domaines Sciences '!#REF!,0) -> #REF! | G383: =IF(AND('Items sous domaines Sciences '!#REF!<=5, 'Items sous domaines Sciences '!#REF!>0),'Items sous domaines Sciences '!#REF!,0) -> #REF!
B384: =IF('Items sous domaines Sciences '!G386=5,'Items sous domaines Sciences '!B386,0) -> 0 | C384: =IF('Items sous domaines Sciences '!G386=5,'Items sous domaines Sciences '!C386,0) -> 0 | D384: =IF('Items sous domaines Sciences '!G386=5,'Items sous domaines Sciences '!D386,0) -> 0 | E384: =IF('Items sous domaines Sciences '!G386=5,'Items sous domaines Sciences '!E386,0) -> 0 | F384: =IF('Items sous domaines Sciences '!#REF!<4,'Items sous domaines Sciences '!#REF!,0) -> #REF! | G384: =IF(AND('Items sous domaines Sciences '!#REF!<=5, 'Items sous domaines Sciences '!#REF!>0),'Items sous domaines Sciences '!#REF!,0) -> #REF!
B385: =IF('Items sous domaines Sciences '!G387=5,'Items sous domaines Sciences '!B387,0) -> 0 | C385: =IF('Items sous domaines Sciences '!G387=5,'Items sous domaines Sciences '!C387,0) -> 0 | D385: =IF('Items sous domaines Sciences '!G387=5,'Items sous domaines Sciences '!D387,0) -> 0 | E385: =IF('Items sous domaines Sciences '!G387=5,'Items sous domaines Sciences '!E387,0) -> 0 | F385: =IF('Items sous domaines Sciences '!#REF!<4,'Items sous domaines Sciences '!#REF!,0) -> #REF! | G385: =IF(AND('Items sous domaines Sciences '!#REF!<=5, 'Items sous domaines Sciences '!#REF!>0),'Items sous domaines Sciences '!#REF!,0) -> #REF!
B386: =IF('Items sous domaines Sciences '!G388=5,'Items sous domaines Sciences '!B388,0) -> 0 | C386: =IF('Items sous domaines Sciences '!G388=5,'Items sous domaines Sciences '!C388,0) -> 0 | D386: =IF('Items sous domaines Sciences '!G388=5,'Items sous domaines Sciences '!D388,0) -> 0 | E386: =IF('Items sous domaines Sciences '!G388=5,'Items sous domaines Sciences '!E388,0) -> 0 | F386: =IF('Items sous domaines Sciences '!#REF!<4,'Items sous domaines Sciences '!#REF!,0) -> #REF! | G386: =IF(AND('Items sous domaines Sciences '!#REF!<=5, 'Items sous domaines Sciences '!#REF!>0),'Items sous domaines Sciences '!#REF!,0) -> #REF!
...

Sheet A3 CI Géné S6
A1: Objectifs d'apprentissage des sciences physiques
G3: Remédiation
A4: Notions à maîtriser en cycle ingénieur en S6 (+ onglet A3 CI S5)
G6: lien Unisciel ou livre scolaire
A7: ='A1 CPI S1'!A7 -> UE du DS | B7: ='A1 CPI S1'!B7 -> Domaine | C7: ='A1 CPI S1'!C7 -> Discipline | D7: ='A1 CPI S1'!D7 -> Chapitres | E7: ='A1 CPI S1'!E7 -> Thèmes | F7: Utilisation
A8: UE 6.2 - Sciences physiques | B8: =IF('Items sous domaines Sciences '!G10=6,'Items sous domaines Sciences '!B10,0) -> 0 | C8: =IF('Items sous domaines Sciences '!G10=6,'Items sous domaines Sciences '!C10,0) -> 0 | D8: =IF('Items sous domaines Sciences '!G10=6,'Items sous domaines Sciences '!D10,0) -> 0 | E8: =IF('Items sous domaines Sciences '!G10=6,'Items sous domaines Sciences '!E10,0) -> 0 | F8: =IF(AND('Items sous domaines Sciences '!#REF!=6, 'Items sous domaines Sciences '!#REF!>0),'Items sous domaines Sciences '!#REF!,0) -> #REF!
B9: =IF('Items sous domaines Sciences '!G11=6,'Items sous domaines Sciences '!B11,0) -> 0 | C9: =IF('Items sous domaines Sciences '!G11=6,'Items sous domaines Sciences '!C11,0) -> 0 | D9: =IF('Items sous domaines Sciences '!G11=6,'Items sous domaines Sciences '!D11,0) -> 0 | E9: =IF('Items sous domaines Sciences '!G11=6,'Items sous domaines Sciences '!E11,0) -> 0 | F9: =IF('Items sous domaines Sciences '!#REF!=6,'Items sous domaines Sciences '!#REF!,0) -> #REF!
B10: =IF('Items sous domaines Sciences '!G12=6,'Items sous domaines Sciences '!B12,0) -> 0 | C10: =IF('Items sous domaines Sciences '!G12=6,'Items sous domaines Sciences '!C12,0) -> 0 | D10: =IF('Items sous domaines Sciences '!G12=6,'Items sous domaines Sciences '!D12,0) -> 0 | E10: =IF('Items sous domaines Sciences '!G12=6,'Items sous domaines Sciences '!E12,0) -> 0 | F10: =IF('Items sous domaines Sciences '!#REF!=6,'Items sous domaines Sciences '!#REF!,0) -> #REF!
B11: =IF('Items sous domaines Sciences '!G13=6,'Items sous domaines Sciences '!B13,0) -> 0 | C11: =IF('Items sous domaines Sciences '!G13=6,'Items sous domaines Sciences '!C13,0) -> 0 | D11: =IF('Items sous domaines Sciences '!G13=6,'Items sous domaines Sciences '!D13,0) -> 0 | E11: =IF('Items sous domaines Sciences '!G13=6,'Items sous domaines Sciences '!E13,0) -> 0 | F11: Projet Electrotechnique
B12: =IF('Items sous domaines Sciences '!G14=6,'Items sous domaines Sciences '!B14,0) -> 0 | C12: =IF('Items sous domaines Sciences '!G14=6,'Items sous domaines Sciences '!C14,0) -> 0 | D12: =IF('Items sous domaines Sciences '!G14=6,'Items sous domaines Sciences '!D14,0) -> 0 | E12: =IF('Items sous domaines Sciences '!G14=6,'Items sous domaines Sciences '!E14,0) -> 0 | G12: https://uel.unisciel.fr/mathematiques/arithmetique/arithmetique/co/arithmetique.html
B13: =IF('Items sous domaines Sciences '!G15=6,'Items sous domaines Sciences '!B15,0) -> 0 | C13: =IF('Items sous domaines Sciences '!G15=6,'Items sous domaines Sciences '!C15,0) -> 0 | D13: =IF('Items sous domaines Sciences '!G15=6,'Items sous domaines Sciences '!D15,0) -> 0 | E13: =IF('Items sous domaines Sciences '!G15=6,'Items sous domaines Sciences '!E15,0) -> 0
B14: =IF('Items sous domaines Sciences '!G16=6,'Items sous domaines Sciences '!B16,0) -> 0 | C14: =IF('Items sous domaines Sciences '!G16=6,'Items sous domaines Sciences '!C16,0) -> 0 | D14: =IF('Items sous domaines Sciences '!G16=6,'Items sous domaines Sciences '!D16,0) -> 0 | E14: =IF('Items sous domaines Sciences '!G16=6,'Items sous domaines Sciences '!E16,0) -> 0
B15: =IF('Items sous domaines Sciences '!G17=6,'Items sous domaines Sciences '!B17,0) -> 0 | C15: =IF('Items sous domaines Sciences '!G17=6,'Items sous domaines Sciences '!C17,0) -> 0 | D15: =IF('Items sous domaines Sciences '!G17=6,'Items sous domaines Sciences '!D17,0) -> 0 | E15: =IF('Items sous domaines Sciences '!G17=6,'Items sous domaines Sciences '!E17,0) -> 0
B16: =IF('Items sous domaines Sciences '!G18=6,'Items sous domaines Sciences '!B18,0) -> 0 | C16: =IF('Items sous domaines Sciences '!G18=6,'Items sous domaines Sciences '!C18,0) -> 0 | D16: =IF('Items sous domaines Sciences '!G18=6,'Items sous domaines Sciences '!D18,0) -> 0 | E16: =IF('Items sous domaines Sciences '!G18=6,'Items sous domaines Sciences '!E18,0) -> 0
B17: =IF('Items sous domaines Sciences '!G19=6,'Items sous domaines Sciences '!B19,0) -> 0 | C17: =IF('Items sous domaines Sciences '!G19=6,'Items sous domaines Sciences '!C19,0) -> 0 | D17: =IF('Items sous domaines Sciences '!G19=6,'Items sous domaines Sciences '!D19,0) -> 0 | E17: =IF('Items sous domaines Sciences '!G19=6,'Items sous domaines Sciences '!E19,0) -> 0
B18: =IF('Items sous domaines Sciences '!G20=6,'Items sous domaines Sciences '!B20,0) -> 0 | C18: =IF('Items sous domaines Sciences '!G20=6,'Items sous domaines Sciences '!C20,0) -> 0 | D18: =IF('Items sous domaines Sciences '!G20=6,'Items sous domaines Sciences '!D20,0) -> 0 | E18: =IF('Items sous domaines Sciences '!G20=6,'Items sous domaines Sciences '!E20,0) -> 0
B19: =IF('Items sous domaines Sciences '!G21=6,'Items sous domaines Sciences '!B21,0) -> 0 | C19: =IF('Items sous domaines Sciences '!G21=6,'Items sous domaines Sciences '!C21,0) -> 0 | D19: =IF('Items sous domaines Sciences '!G21=6,'Items sous domaines Sciences '!D21,0) -> 0 | E19: =IF('Items sous domaines Sciences '!G21=6,'Items sous domaines Sciences '!E21,0) -> 0
B20: =IF('Items sous domaines Sciences '!G22=6,'Items sous domaines Sciences '!B22,0) -> 0 | C20: =IF('Items sous domaines Sciences '!G22=6,'Items sous domaines Sciences '!C22,0) -> 0 | D20: =IF('Items sous domaines Sciences '!G22=6,'Items sous domaines Sciences '!D22,0) -> 0 | E20: =IF('Items sous domaines Sciences '!G22=6,'Items sous domaines Sciences '!E22,0) -> 0
B21: =IF('Items sous domaines Sciences '!G23=6,'Items sous domaines Sciences '!B23,0) -> 0 | C21: =IF('Items sous domaines Sciences '!G23=6,'Items sous domaines Sciences '!C23,0) -> 0 | D21: =IF('Items sous domaines Sciences '!G23=6,'Items sous domaines Sciences '!D23,0) -> 0 | E21: =IF('Items sous domaines Sciences '!G23=6,'Items sous domaines Sciences '!E23,0) -> 0
B22: =IF('Items sous domaines Sciences '!G24=6,'Items sous domaines Sciences '!B24,0) -> 0 | C22: =IF('Items sous domaines Sciences '!G24=6,'Items sous domaines Sciences '!C24,0) -> 0 | D22: =IF('Items sous domaines Sciences '!G24=6,'Items sous domaines Sciences '!D24,0) -> 0 | E22: =IF('Items sous domaines Sciences '!G24=6,'Items sous domaines Sciences '!E24,0) -> 0
B23: =IF('Items sous domaines Sciences '!G25=6,'Items sous domaines Sciences '!B25,0) -> 0 | C23: =IF('Items sous domaines Sciences '!G25=6,'Items sous domaines Sciences '!C25,0) -> 0 | D23: =IF('Items sous domaines Sciences '!G25=6,'Items sous domaines Sciences '!D25,0) -> 0 | E23: =IF('Items sous domaines Sciences '!G25=6,'Items sous domaines Sciences '!E25,0) -> 0
B24: =IF('Items sous domaines Sciences '!G26=6,'Items sous domaines Sciences '!B26,0) -> 0 | C24: =IF('Items sous domaines Sciences '!G26=6,'Items sous domaines Sciences '!C26,0) -> 0 | D24: =IF('Items sous domaines Sciences '!G26=6,'Items sous domaines Sciences '!D26,0) -> 0 | E24: =IF('Items sous domaines Sciences '!G26=6,'Items sous domaines Sciences '!E26,0) -> 0
... B28: =IF('Items sous domaines Sciences '!G30=6,'Items sous domaines Sciences '!B30,0) -> 0 | C28: =IF('Items sous domaines Sciences '!G30=6,'Items sous domaines Sciences '!C30,0) -> 0 | D28: =IF('Items sous domaines Sciences '!G30=6,'Items sous domaines Sciences '!D30,0) -> 0 | E28: =IF('Items sous domaines Sciences '!G30=6,'Items sous domaines Sciences '!E30,0) -> 0
B29: =IF('Items sous domaines Sciences '!G31=6,'Items sous domaines Sciences '!B31,0) -> Mécanique | C29: =IF('Items sous domaines Sciences '!G31=6,'Items sous domaines Sciences '!C31,0) -> Solide | D29: =IF('Items sous domaines Sciences '!G31=6,'Items sous domaines Sciences '!D31,0) -> 0 | E29: =IF('Items sous domaines Sciences '!G31=6,'Items sous domaines Sciences '!E31,0) -> Appliquer le principe fondamental de la dynamique. | G29: https://uel.unisciel.fr/physique/meca/meca/co/meca.html
B30: =IF('Items sous domaines Sciences '!G32=6,'Items sous domaines Sciences '!B32,0) -> Mécanique | C30: =IF('Items sous domaines Sciences '!G32=6,'Items sous domaines Sciences '!C32,0) -> Solide | D30: =IF('Items sous domaines Sciences '!G32=6,'Items sous domaines Sciences '!D32,0) -> 0 | E30: =IF('Items sous domaines Sciences '!G32=6,'Items sous domaines Sciences '!E32,0) -> Schématiser les actions mécaniques.
B31: =IF('Items sous domaines Sciences '!G33=6,'Items sous domaines Sciences '!B33,0) -> Mécanique | C31: =IF('Items sous domaines Sciences '!G33=6,'Items sous domaines Sciences '!C33,0) -> Solide | D31: =IF('Items sous domaines Sciences '!G33=6,'Items sous domaines Sciences '!D33,0) -> 0 | E31: =IF('Items sous domaines Sciences '!G33=6,'Items sous domaines Sciences '!E33,0) -> Calculer une puissance mécanique.
B32: =IF('Items sous domaines Sciences '!G34=6,'Items sous domaines Sciences '!B34,0) -> Mécanique | C32: =IF('Items sous domaines Sciences '!G34=6,'Items sous domaines Sciences '!C34,0) -> Solide | D32: =IF('Items sous domaines Sciences '!G34=6,'Items sous domaines Sciences '!D34,0) -> 0 | E32: =IF('Items sous domaines Sciences '!G34=6,'Items sous domaines Sciences '!E34,0) -> Appliquer le théorème de l'énergie cinétique.
B33: =IF('Items sous domaines Sciences '!G35=6,'Items sous domaines Sciences '!B35,0) -> Mécanique | C33: =IF('Items sous domaines Sciences '!G35=6,'Items sous domaines Sciences '!C35,0) -> Solide | D33: =IF('Items sous domaines Sciences '!G35=6,'Items sous domaines Sciences '!D35,0) -> 0 | E33: =IF('Items sous domaines Sciences '!G35=6,'Items sous domaines Sciences '!E35,0) -> Utiliser les moments d'inertie équivalents.
B34: =IF('Items sous domaines Sciences '!G36=6,'Items sous domaines Sciences '!B36,0) -> 0 | C34: =IF('Items sous domaines Sciences '!G36=6,'Items sous domaines Sciences '!C36,0) -> 0 | D34: =IF('Items sous domaines Sciences '!G36=6,'Items sous domaines Sciences '!D36,0) -> 0 | E34: =IF('Items sous domaines Sciences '!G36=6,'Items sous domaines Sciences '!E36,0) -> 0
B35: =IF('Items sous domaines Sciences '!G37=6,'Items sous domaines Sciences '!B37,0) -> 0 | C35: =IF('Items sous domaines Sciences '!G37=6,'Items sous domaines Sciences '!C37,0) -> 0 | D35: =IF('Items sous domaines Sciences '!G37=6,'Items sous domaines Sciences '!D37,0) -> 0 | E35: =IF('Items sous domaines Sciences '!G37=6,'Items sous domaines Sciences '!E37,0) -> 0
B36: =IF('Items sous domaines Sciences '!G38=6,'Items sous domaines Sciences '!B38,0) -> 0 | C36: =IF('Items sous domaines Sciences '!G38=6,'Items sous domaines Sciences '!C38,0) -> 0 | D36: =IF('Items sous domaines Sciences '!G38=6,'Items sous domaines Sciences '!D38,0) -> 0 | E36: =IF('Items sous domaines Sciences '!G38=6,'Items sous domaines Sciences '!E38,0) -> 0
B37: =IF('Items sous domaines Sciences '!G39=6,'Items sous domaines Sciences '!B39,0) -> 0 | C37: =IF('Items sous domaines Sciences '!G39=6,'Items sous domaines Sciences '!C39,0) -> 0 | D37: =IF('Items sous domaines Sciences '!G39=6,'Items sous domaines Sciences '!D39,0) -> 0 | E37: =IF('Items sous domaines Sciences '!G39=6,'Items sous domaines Sciences '!E39,0) -> 0
B38: =IF('Items sous domaines Sciences '!G40=6,'Items sous domaines Sciences '!B40,0) -> 0 | C38: =IF('Items sous domaines Sciences '!G40=6,'Items sous domaines Sciences '!C40,0) -> 0 | D38: =IF('Items sous domaines Sciences '!G40=6,'Items sous domaines Sciences '!D40,0) -> 0 | E38: =IF('Items sous domaines Sciences '!G40=6,'Items sous domaines Sciences '!E40,0) -> 0
B39: =IF('Items sous domaines Sciences '!G41=6,'Items sous domaines Sciences '!B41,0) -> 0 | C39: =IF('Items sous domaines Sciences '!G41=6,'Items sous domaines Sciences '!C41,0) -> 0 | D39: =IF('Items sous domaines Sciences '!G41=6,'Items sous domaines Sciences '!D41,0) -> 0 | E39: =IF('Items sous domaines Sciences '!G41=6,'Items sous domaines Sciences '!E41,0) -> 0
B40: =IF('Items sous domaines Sciences '!G42=6,'Items sous domaines Sciences '!B42,0) -> 0 | C40: =IF('Items sous domaines Sciences '!G42=6,'Items sous domaines Sciences '!C42,0) -> 0 | D40: =IF('Items sous domaines Sciences '!G42=6,'Items sous domaines Sciences '!D42,0) -> 0 | E40: =IF('Items sous domaines Sciences '!G42=6,'Items sous domaines Sciences '!E42,0) -> 0
B41: =IF('Items sous domaines Sciences '!G43=6,'Items sous domaines Sciences '!B43,0) -> 0 | C41: =IF('Items sous domaines Sciences '!G43=6,'Items sous domaines Sciences '!C43,0) -> 0 | D41: =IF('Items sous domaines Sciences '!G43=6,'Items sous domaines Sciences '!D43,0) -> 0 | E41: =IF('Items sous domaines Sciences '!G43=6,'Items sous domaines Sciences '!E43,0) -> 0
... B59: =IF('Items sous domaines Sciences '!G61=6,'Items sous domaines Sciences '!B61,0) -> 0 | C59: =IF('Items sous domaines Sciences '!G61=6,'Items sous domaines Sciences '!C61,0) -> 0 | D59: =IF('Items sous domaines Sciences '!G61=6,'Items sous domaines Sciences '!D61,0) -> 0 | E59: =IF('Items sous domaines Sciences '!G61=6,'Items sous domaines Sciences '!E61,0) -> 0
B60: =IF('Items sous domaines Sciences '!G62=6,'Items sous domaines Sciences '!B62,0) -> 0 | C60: =IF('Items sous domaines Sciences '!G62=6,'Items sous domaines Sciences '!C62,0) -> 0 | D60: =IF('Items sous domaines Sciences '!G62=6,'Items sous domaines Sciences '!D62,0) -> 0 | E60: =IF('Items sous domaines Sciences '!G62=6,'Items sous domaines Sciences '!E62,0) -> 0 | G60: https://uel.unisciel.fr/physique/outils_nancy/outils_nancy_ch04/co/apprendre_ch04.html
B61: =IF('Items sous domaines Sciences '!G63=6,'Items sous domaines Sciences '!B63,0) -> 0 | C61: =IF('Items sous domaines Sciences '!G63=6,'Items sous domaines Sciences '!C63,0) -> 0 | D61: =IF('Items sous domaines Sciences '!G63=6,'Items sous domaines Sciences '!D63,0) -> 0 | E61: =IF('Items sous domaines Sciences '!G63=6,'Items sous domaines Sciences '!E63,0) -> 0
B62: =IF('Items sous domaines Sciences '!G64=6,'Items sous domaines Sciences '!B64,0) -> 0 | C62: =IF('Items sous domaines Sciences '!G64=6,'Items sous domaines Sciences '!C64,0) -> 0 | D62: =IF('Items sous domaines Sciences '!G64=6,'Items sous domaines Sciences '!D64,0) -> 0 | E62: =IF('Items sous domaines Sciences '!G64=6,'Items sous domaines Sciences '!E64,0) -> 0
B63: =IF('Items sous domaines Sciences '!G65=6,'Items sous domaines Sciences '!B65,0) -> 0 | C63: =IF('Items sous domaines Sciences '!G65=6,'Items sous domaines Sciences '!C65,0) -> 0 | D63: =IF('Items sous domaines Sciences '!G65=6,'Items sous domaines Sciences '!D65,0) -> 0 | E63: =IF('Items sous domaines Sciences '!G65=6,'Items sous domaines Sciences '!E65,0) -> 0
